Workbook

Sheet Summary
I4: Cumulative Extraction Summary by Method
I5: (time measured in seconds)
J6: Excel (Advanced) | K6: LLM API | L6: Python | V6: Standardization Goal
I7: Ticker | J7: Manual | K7: Presentation (exc build) | L7: Script (exc build)
B8: =K8/$J8-1 -> -0.29276316 | C8: =L8/$J8-1 -> 0.22368421 | I8: BAC | J8: =L30 -> 304 | K8: =Y30 -> 215 | L8: =AD30 -> 372
B9: =K9/$J9-1 -> -0.1807598 | C9: =L9/$J9-1 -> 0.62198529 | I9: WFC | J9: =L43 -> 544 | K9: =Y43 -> 445.66667 | L9: =AD43 -> 882.36
B10: =K10/$J10-1 -> -0.20121951 | C10: =L10/$J10-1 -> -0.67886179 | I10: JPM | J10: =L58 -> 492 | K10: =Y58 -> 393 | L10: =AD58 -> 158 | AH10: Scroll
B11: =K11/$J11-1 -> -0.31923077 | C11: =L11/$J11-1 -> -0.35128205 | I11: PNC | J11: =L75 -> 260 | K11: =Y75 -> 177 | L11: =AD75 -> 168.66667 | AH11: Right
B12: =K12/$J12-1 -> -0.60123043 | C12: =L12/$J12-1 -> -0.71029083 | I12: KEY | J12: =L91 -> 596 | K12: =Y91 -> 237.66667 | L12: =AD91 -> 172.66667 | AH12: for
B13: =K13/$J13-1 -> -0.55357143 | C13: =L13/$J13-1 -> 0.31994048 | I13: HBAN | J13: =L109 -> 224 | K13: =Y109 -> 100 | L13: =AD109 -> 295.66667 | AH13: Charts
B14: =K14/$J14-1 -> -0.75707547 | C14: =L14/$J14-1 -> -0.66273585 | I14: CFG | J14: =L127 -> 424 | K14: =Y127 -> 103 | L14: =AD127 -> 143
B15: =K15/$J15-1 -> -0.68465909 | C15: =L15/$J15-1 -> -0.58617424 | I15: FCNCA | J15: =L143 -> 352 | K15: =Y143 -> 111 | L15: =AD143 -> 145.66667
B16: =K16/$J16-1 -> -0.75 | C16: =L16/$J16-1 -> 0.011299435 | I16: SNV | J16: =L163 -> 472 | K16: =Y163 -> 118 | L16: =AD163 -> 477.33333
B17: =K17/$J17-1 -> -0.45661157 | C17: =L17/$J17-1 -> -0.2977135 | I17: RF | J17: =L184 -> 484 | K17: =Y184 -> 263 | L17: =AD184 -> 339.90667
B19: =K19/$J19-1 -> -0.47896596 | C19: =L19/$J19-1 -> -0.24006101 | G19: =AVERAGE(G30,G43,G58,G75,G91,G109,G127,G143,G163,G184) -> 640.8 | I19: Average | J19: =AVERAGE(J8:J17) -> 415.2 | K19: =AVERAGE(K8:K17) -> 216.33333 | L19: =AVERAGE(L8:L17) -> 315.52667
I20: Efficency | K20: =($J$19-K19)/$J$19 -> 0.47896596 | L20: =($J$19-L19)/$J$19 -> 0.24006101
AU22: Cumulative Time (10-Q) | BI22: Cumulative Time (10-Q)
D23: Excel (Manual - Presentation / 10-Q) | I23: Advanced Excel Manual Benchmark (10-Q) | N23: LLM Interface (Presentation) | U23: LLM API (Presentation) | AA23: Python Modules (10-Q) | AG23: Time Savings | AU23: (Python Modules vs Advanced Excel) | BI23: LLM API vs Advanced Excel | BW23: Script Construct | BZ23: LLM API Construct
I24: (time measured in seconds) | N24: Convert Prompt | P24: Correct Prompt | Q24: Standardization Prompt | R24: Clean Prompts | U24: (time measured in seconds) | AA24: (time measured in seconds) | BW24: Breakeven | BZ24: Breakeven
B25: Ticker | C25: Quarter | D25: Extraction | E25: Standardization | F25: Database Format | G25: Total Excel | I25: Extraction | J25: Standardization | K25: Database Format | L25: Total | N25: Extraction | O25: Accuracy | P25: Correction | Q25: Standardization | R25: Database Format | S25: Total LLM | U25: Construct Extraction | V25: Adjustment | W25: Execute | X25: Accuracy | Y25: Total | AA25: Construct Extraction | AB25: Adjustment | AC25: Execute | AD25: Total | AF25: Date | AG25: LLM API | AH25: Python Modules | AU25: Advanced Excel | AV25: Python Modules | AX25: Delta | AY25: Efficiency % | BI25: Advanced Excel | BJ25: LLM API | BL25: Delta | BM25: Efficiency %
B26: BAC | C26: 4Q24 | D26: 33 | E26: 0 | F26: 59 | G26: =SUM(D26:F26) -> 92 | I26: 30 | J26: 0 | K26: 46 | L26: =SUM(I26:K26) -> 76 | N26: =42+39 -> 81 | O26: ='BAC LLM Interface'!T23 -> 0.9 | P26: =N26+52+20 -> 153 | Q26: 0 | R26: =66+32+57+38+37+33+55+12 -> 330 | S26: =SUM(N26,P26,Q26,R26) -> 564 | V26: 37 | W26: 19 | X26: ='BAC LLM API'!F42 -> 0.7 | Y26: =SUM(U26:W26) -> 56 | AB26: 62 | AC26: 28 | AD26: =SUM(AA26:AC26) -> 90 | AF26: 45657 | AG26: =L26-Y26 -> 20 | AH26: =L26-AD26 -> -14 | AT26: 45657 | AU26: =L26+L27+L28+L29 -> 304 | AV26: =AD26+AD27+AD28+AD29 -> 372 | AX26: =AV26-AU26 -> 68 | AY26: =(-AX26/AU26) -> -0.22368421 | BH26: 45657 | BI26: =AU26 -> 304 | BJ26: =Y27+Y28+Y26+Y29 -> 215 | BL26: =BJ26-BI26 -> -89 | BM26: =(-BL26/BI26) -> 0.29276316 | BU26: =B26 -> BAC | BV26: 45657 | BW26: =L26-AD26 -> -14 | BZ26: =L26-Y26 -> 20
A27: Base | B27: BAC | C27: 3Q24 | D27: 33 | E27: 0 | F27: 59 | G27: =SUM(D27:F27) -> 92 | I27: 30 | J27: 0 | K27: 46 | L27: =SUM(I27:K27) -> 76 | N27: =42+26 -> 68 | O27: ='BAC LLM Interface'!T52 -> 0.9 | P27: =N27+52+15 -> 135 | Q27: 0 | R27: =66+17+57+15+37+28+55+9 -> 284 | S27: =SUM(N27,P27,Q27,R27) -> 487 | U27: =2727/250*60 -> 654.48 | V27: 0 | W27: 20 | X27: ='BAC LLM API'!F83 -> 0.9 | Y27: =W27+AVERAGE(V26,V28:V29) -> 55 | AA27: =1680/250*60 -> 403.2 | AB27: 0 | AC27: 32 | AD27: =AC27+AVERAGE(AB26,AB28:AB29) -> 97 | AF27: 45565 | AG27: =L27-Y27 -> 21 | AH27: =L27-AD27 -> -21 | AT27: 45565 | AU27: =L27+L28+L29 -> 228 | AV27: =AD27+AD28+AD29 -> 282 | AX27: =AV27-AU27 -> 54 | AY27: =(-AX27/AU27) -> -0.23684211 | BH27: 45565 | BI27: =AU27 -> 228 | BJ27: =Y28+Y29+Y27 -> 159 | BL27: =BJ27-BI27 -> -69 | BM27: =(-BL27/BI27) -> 0.30263158 | BU27: =B27 -> BAC | BV27: 45565 | BW27: =L27-(AC27+AVERAGE(AB26,AB28:AB29)) -> -21 | BZ27: =L27-(W27+AVERAGE(V26,V28:V29)) -> 21
B28: BAC | C28: 2Q24 | D28: 33 | E28: 0 | F28: 59 | G28: =SUM(D28:F28) -> 92 | I28: 30 | J28: 0 | K28: 46 | L28: =SUM(I28:K28) -> 76 | N28: =42+27 -> 69 | O28: ='BAC LLM Interface'!T83 -> 1 | P28: 0 | Q28: 0 | R28: =66+14+57+20+37+30+55+11 -> 290 | S28: =SUM(N28,P28,Q28,R28) -> 359 | V28: 34 | W28: 19 | X28: ='BAC LLM API'!F120 -> 1 | Y28: =SUM(U28:W28) -> 53 | AB28: 49 | AC28: 25 | AD28: =SUM(AA28:AC28) -> 74 | AF28: 45473 | AG28: =L28-Y28 -> 23 | AH28: =L28-AD28 -> 2 | AT28: 45473 | AU28: =L28+L29 -> 152 | AV28: =AD28+AD29 -> 185 | AX28: =AV28-AU28 -> 33 | AY28: =(-AX28/AU28) -> -0.21710526 | BH28: 45473 | BI28: =AU28 -> 152 | BJ28: =Y28+Y29 -> 104 | BL28: =BJ28-BI28 -> -48 | BM28: =(-BL28/BI28) -> 0.31578947 | BU28: =B28 -> BAC | BV28: 45473 | BW28: =L28-AD28 -> 2 | BZ28: =L28-Y28 -> 23
B29: BAC | C29: 1Q24 | D29: 33 | E29: 0 | F29: 59 | G29: =SUM(D29:F29) -> 92 | I29: 30 | J29: 0 | K29: 46 | L29: =SUM(I29:K29) -> 76 | N29: =42+42 -> 84 | O29: ='BAC LLM Interface'!T109 -> 1 | P29: 0 | Q29: 0 | R29: =66+11+57+20+37+29+55+26 -> 301 | S29: =SUM(N29,P29,Q29,R29) -> 385 | V29: 34 | W29: 17 | X29: ='BAC LLM API'!F158 -> 1 | Y29: =SUM(U29:W29) -> 51 | AB29: 84 | AC29: 27 | AD29: =SUM(AA29:AC29) -> 111 | AF29: 45382 | AG29: =L29-Y29 -> 25 | AH29: =L29-AD29 -> -35 | AT29: 45382 | AU29: =L29 -> 76 | AV29: =AD29 -> 111 | AX29: =AV29-AU29 -> 35 | AY29: =(-AX29/AU29) -> -0.46052632 | BH29: 45382 | BI29: =AU29 -> 76 | BJ29: =Y29 -> 51 | BL29: =BJ29-BI29 -> -25 | BM29: =(-BL29/BI29) -> 0.32894737 | BU29: =B29 -> BAC | BV29: 45382 | BW29: =L29-AD29 -> -35 | BZ29: =L29-Y29 -> 25
B30: Total | G30: =SUM(G26:G29) -> 368 | K30: Cumulative Total | L30: =SUM(L26:L29) -> 304 | S30: =SUM(S26:S29) -> 1795 | W30: Cumulative Total | Y30: =SUM(Y26:Y29) -> 215 | AC30: Cumulative Total | AD30: =SUM(AD26:AD29) -> 372 | AF30: Total | AG30: =SUM(AG26:AG29) -> 89 | AH30: =SUM(AH26:AH29) -> -68 | BV30: Quarter Breakeven | BW30: =AA27/AVERAGE(BW26:BX29) -> -23.717647 | BZ30: =U27/AVERAGE(BZ26:CA29) -> 29.414831
R31: Cumulative Efficiency % | S31: =(($L30-S30)/$L30)*1 -> -4.9046053 | W31: Cumulative Efficiency % | Y31: =($L30-Y30)/$L30*100% -> 0.29276316 | AC31: Cumulative Efficiency % | AD31: =($L30-AD30)/$L30*100% -> -0.22368421
W32: Average Accuracy | X32: =AVERAGE(X26:X29) -> 0.9
AB33: =AVERAGE(AB28:AB29,AB26) -> 65 | AC33: =AVERAGE(AC26:AC29) -> 28
D36: Excel (Manual - Presentation / 10-Q) | I36: Advanced Excel Manual Benchmark (10-Q) | N36: LLM (10-Q) | U36: LLM API (Presentation) | AA36: Python Modules (10-Q)
I37: (time measured in seconds) | N37: Convert Prompt | P37: Correct Prompt | Q37: Standardization Prompt | R37: Clean Prompts | U37: (time measured in seconds) | AA37: (time measured in seconds)
B38: Ticker | C38: Quarter | D38: Extraction | E38: Standardization | F38: Database Format | G38: Total Excel | I38: Extraction | J38: Standardization | K38: Database Format | L38: Total | N38: Extraction | O38: Accuracy | P38: Correction | Q38: Standardization | R38: Database Format | S38: Total LLM | U38: Construct Extraction | V38: Adjustment | W38: Execute | X38: Accuracy | Y38: Total | AA38: Construct Extraction | AB38: Adjustment | AC38: Execute | AD38: Total | AF38: Date | AG38: LLM API | AH38: Python Modules | AU38: Advanced Excel | AV38: Python Modules | AX38: Delta | AY38: Efficiency % | BI38: Advanced Excel | BJ38: LLM API | BL38: Delta | BM38: Efficiency %
B39: WFC | C39: 4Q24 | D39: 138 | E39: 52 | F39: 60 | G39: =SUM(D39:F39) -> 250 | I39: 52 | J39: 54 | K39: 30 | L39: =SUM(I39:K39) -> 136 | N39: =49+17 -> 66 | O39: ='WFC LLM Interface'!M27 -> 0.92307692 | P39: =52+12 -> 64 | Q39: =41+11 -> 52 | R39: =87+12+54+15+56+11 -> 235 | S39: =SUM(N39,P39,Q39,R39) -> 417 | V39: 85 | W39: 24 | X39: ='WFC LLM API'!F46 -> 0.83333333 | Y39: =SUM(U39:W39) -> 109 | AB39: =666/250*60+40 -> 199.84 | AC39: 25 | AD39: =SUM(AA39:AC39) -> 224.84 | AF39: 45657 | AG39: =L39-Y39 -> 27 | AH39: =L39-AD39 -> -88.84 | AT39: 45657 | AU39: =L39+L40+L41+L42 -> 544 | AV39: =AD39+AD40+AD41+AD42 -> 882.36 | AX39: =AV39-AU39 -> 338.36 | AY39: =(-AX39/AU39) -> -0.62198529 | BH39: 45657 | BI39: =AU39 -> 544 | BJ39: =Y40+Y41+Y39+Y42 -> 445.66667 | BL39: =BJ39-BI39 -> -98.333333 | BM39: =(-BL39/BI39) -> 0.1807598 | BU39: =B39 -> WFC | BV39: 45657 | BW39: =L39-AD39 -> -88.84 | BZ39: =L39-Y39 -> 27
A40: Base | B40: WFC | C40: 3Q24 | D40: 138 | E40: 52 | F40: 60 | G40: =SUM(D40:F40) -> 250 | I40: 52 | J40: 54 | K40: 30 | L40: =SUM(I40:K40) -> 136 | N40: =49+20 -> 69 | O40: ='WFC LLM Interface'!M59 -> 0.96153846 | P40: =29+16 -> 45 | Q40: =34+28 -> 62 | R40: =87+9+54+10+56+15 -> 231 | S40: =SUM(N40,P40,Q40,R40) -> 407 | U40: =2921/250*60 -> 701.04 | V40: 0 | W40: 33 | X40: ='WFC LLM API'!F95 -> 0.85 | Y40: =W40+AVERAGE(V39,V41:V42) -> 112.66667 | AA40: =(2334/250)*60+(1686/250)*60 -> 964.8 | AB40: 0 | AC40: 40 | AD40: =AC40+AVERAGE(AB39,AB41:AB42) -> 232.84 | AF40: 45565 | AG40: =L40-Y40 -> 23.333333 | AH40: =L40-AD40 -> -96.84 | AT40: 45565 | AU40: =L40+L41+L42 -> 408 | AV40: =AD40+AD41+AD42 -> 657.52 | AX40: =AV40-AU40 -> 249.52 | AY40: =(-AX40/AU40) -> -0.61156863 | BH40: 45565 | BI40: =AU40 -> 408 | BJ40: =Y41+Y42+Y40 -> 336.66667 | BL40: =BJ40-BI40 -> -71.333333 | BM40: =(-BL40/BI40) -> 0.1748366 | BU40: =B40 -> WFC | BV40: 45565 | BW40: =L40-(AC40+AVERAGE(AB39,AB41:AB42)) -> -96.84 | BZ40: =L40-(W40+AVERAGE(V39,V41:V42)) -> 23.333333
B41: WFC | C41: 2Q24 | D41: 138 | E41: 52 | F41: 60 | G41: =SUM(D41:F41) -> 250 | I41: 52 | J41: 54 | K41: 30 | L41: =SUM(I41:K41) -> 136 | N41: =49+20 -> 69 | O41: ='WFC LLM Interface'!M91 -> 0.92307692 | P41: =50+11 -> 61 | Q41: =34+10 -> 44 | R41: =87+10+54+19+56+13 -> 239 | S41: =SUM(N41,P41,Q41,R41) -> 413 | V41: 74 | W41: 31 | X41: ='WFC LLM API'!F142 -> 0.8 | Y41: =SUM(U41:W41) -> 105 | AB41: =666/250*60+29 -> 188.84 | AC41: 25 | AD41: =SUM(AA41:AC41) -> 213.84 | AF41: 45473 | AG41: =L41-Y41 -> 31 | AH41: =L41-AD41 -> -77.84 | AT41: 45473 | AU41: =L41+L42 -> 272 | AV41: =AD41+AD42 -> 424.68 | AX41: =AV41-AU41 -> 152.68 | AY41: =(-AX41/AU41) -> -0.56132353 | BH41: 45473 | BI41: =AU41 -> 272 | BJ41: =Y41+Y42 -> 224 | BL41: =BJ41-BI41 -> -48 | BM41: =(-BL41/BI41) -> 0.17647059 | BU41: =B41 -> WFC | BV41: 45473 | BW41: =L41-AD41 -> -77.84 | BZ41: =L41-Y41 -> 31
B42: WFC | C42: 1Q24 | D42: 138 | E42: 52 | F42: 60 | G42: =SUM(D42:F42) -> 250 | I42: 52 | J42: 54 | K42: 30 | L42: =SUM(I42:K42) -> 136 | N42: =49+13 -> 62 | O42: ='WFC LLM Interface'!M118 -> 0.92307692 | P42: =48+15 -> 63 | Q42: =34+12 -> 46 | R42: =87+14+54+14+56+13 -> 238 | S42: =SUM(N42,P42,Q42,R42) -> 409 | V42: 80 | W42: 39 | X42: ='WFC LLM API'!F188 -> 0.85 | Y42: =SUM(U42:W42) -> 119 | AB42: =666/250*60+30 -> 189.84 | AC42: 21 | AD42: =SUM(AA42:AC42) -> 210.84 | AF42: 45382 | AG42: =L42-Y42 -> 17 | AH42: =L42-AD42 -> -74.84 | AT42: 45382 | AU42: =L42 -> 136 | AV42: =AD42 -> 210.84 | AX42: =AV42-AU42 -> 74.84 | AY42: =(-AX42/AU42) -> -0.55029412 | BH42: 45382 | BI42: =AU42 -> 136 | BJ42: =Y42 -> 119 | BL42: =BJ42-BI42 -> -17 | BM42: =(-BL42/BI42) -> 0.125 | BU42: =B42 -> WFC | BV42: 45382 | BW42: =L42-AD42 -> -74.84 | BZ42: =L42-Y42 -> 17
G43: =SUM(G39:G42) -> 1000 | K43: Cumulative Total | L43: =SUM(L39:L42) -> 544 | S43: =SUM(S39:S42) -> 1646 | W43: Cumulative Total | Y43: =SUM(Y39:Y42) -> 445.66667 | AC43: Cumulative Total | AD43: =SUM(AD39:AD42) -> 882.36 | AF43: Total | AG43: =SUM(AG39:AG42) -> 98.333333 | AH43: =SUM(AH39:AH42) -> -338.36 | BV43: Quarter Breakeven | BW43: =AA40/AVERAGE(BW39:BX42) -> -11.405603 | BZ43: =U40/AVERAGE(BZ39:CA42) -> 28.516881
R44: Cumulative Efficiency % | S44: =(($L43-S43)/$L43)*1 -> -2.0257353 | W44: Cumulative Efficiency % | Y44: =(($L43-Y43)/$L43)*1 -> 0.1807598 | AC44: Cumulative Efficiency % | AD44: =(($L43-AD43)/$L43)*1 -> -0.62198529
W45: Average Accuracy | X45: =AVERAGE(X39:X42) -> 0.83333333
AB46: =AVERAGE(AB41:AB42,AB39) -> 192.84 | AC46: =AVERAGE(AC39:AC42) -> 27.75
D51: Excel (Manual - Presentation / 10-Q) | I51: Advanced Excel Manual Benchmark (10-Q) | N51: LLM (10-Q) | U51: LLM API (Presentation) | AA51: Python Modules (10-Q)
I52: (time measured in seconds) | N52: Convert Prompt | P52: Correct Prompt | Q52: Standardization Prompt | R52: Clean Prompts | U52: (time measured in seconds) | AA52: (time measured in seconds)
B53: Ticker | C53: Quarter | D53: Extraction | E53: Standardization | F53: Database Format | G53: Total Excel | I53: Extraction | J53: Standardization | K53: Database Format | L53: Total | N53: Extraction | O53: Accuracy | P53: Correction | Q53: Standardization | R53: Database Format | S53: Total LLM | U53: Construct Extraction | V53: Adjustment | W53: Execute | X53: Accuracy | Y53: Total | AA53: Construct Extraction | AB53: Adjustment | AC53: Execute | AD53: Total | AF53: Date | AG53: LLM API | AH53: Python Modules | AU53: Advanced Excel | AV53: Python Modules | AX53: Delta | AY53: Efficiency % | BI53: Advanced Excel | BJ53: LLM API | BL53: Delta | BM53: Efficiency %
B54: JPM | C54: 4Q24 | D54: 88 | E54: 50 | F54: 62 | G54: =SUM(D54:F54) -> 200 | I54: 49 | J54: 39 | K54: 35 | L54: =SUM(I54:K54) -> 123 | N54: =48+10 -> 58 | O54: ='JPM LLM Interface'!G236 -> 1 | P54: 0 | Q54: =54+18+40+19 -> 131 | R54: =54+12+56+12+26+11 -> 171 | S54: =SUM(N54,P54,Q54,R54) -> 360 | V54: 65 | W54: 34 | X54: ='JPM LLM API'!F48 -> 0.8125 | Y54: =SUM(U54:W54) -> 99 | AB54: 20 | AC54: 18 | AD54: =SUM(AA54:AC54) -> 38 | AF54: 45657 | AG54: =L54-Y54 -> 24 | AH54: =L54-AD54 -> 85 | AT54: 45657 | AU54: =L54+L55+L56+L57 -> 492 | AV54: =AD54+AD55+AD56+AD57 -> 158 | AX54: =AV54-AU54 -> -334 | AY54: =(-AX54/AU54) -> 0.67886179 | BH54: 45657 | BI54: =AU54 -> 492 | BJ54: =Y55+Y56+Y54+Y57 -> 393 | BL54: =BJ54-BI54 -> -99 | BM54: =(-BL54/BI54) -> 0.20121951 | BU54: =B54 -> JPM | BV54: 45657 | BW54: =L54-AD54 -> 85 | BZ54: =L54-Y54 -> 24
A55: Base | B55: JPM | C55: 3Q24 | D55: 88 | E55: 50 | F55: 62 | G55: =SUM(D55:F55) -> 200 | I55: 49 | J55: 39 | K55: 35 | L55: =SUM(I55:K55) -> 123 | N55: =48+14 -> 62 | O55: ='JPM LLM Interface'!G24 -> 1 | P55: 0 | Q55: =54+18+40+17 -> 129 | R55: =54+12+56+15+26+11 -> 174 | S55: =SUM(N55,P55,Q55,R55) -> 365 | U55: =3190/250*60 -> 765.6 | V55: 0 | W55: 35 | X55: ='JPM LLM API'!F107 -> 0.75 | Y55: =W55+AVERAGE(V54,V56:V57) -> 96 | AA55: =3417/250*60 -> 820.08 | AB55: 0 | AC55: 29 | AD55: =AC55+AVERAGE(AB54,AB56:AB57) -> 49 | AF55: 45565 | AG55: =L55-Y55 -> 27 | AH55: =L55-AD55 -> 74 | AT55: 45565 | AU55: =L55+L56+L57 -> 369 | AV55: =AD55+AD56+AD57 -> 120 | AX55: =AV55-AU55 -> -249 | AY55: =(-AX55/AU55) -> 0.67479675 | BH55: 45565 | BI55: =AU55 -> 369 | BJ55: =Y56+Y57+Y55 -> 294 | BL55: =BJ55-BI55 -> -75 | BM55: =(-BL55/BI55) -> 0.20325203 | BU55: =B55 -> JPM | BV55: 45565 | BW55: =L55-(AC55+AVERAGE(AB54,AB56:AB57)) -> 74 | BZ55: =L55-(W55+AVERAGE(V54,V56:V57)) -> 27
B56: JPM | C56: 2Q24 | D56: 88 | E56: 50 | F56: 62 | G56: =SUM(D56:F56) -> 200 | I56: 49 | J56: 39 | K56: 35 | L56: =SUM(I56:K56) -> 123 | N56: =48+12 -> 60 | O56: ='JPM LLM Interface'!G96 -> 1 | P56: 0 | Q56: =54+18+40+17 -> 129 | R56: =54+13+56+14+26+13 -> 176 | S56: =SUM(N56,P56,Q56,R56) -> 365 | V56: 60 | W56: 43 | X56: ='JPM LLM API'!F164 -> 0.8125 | Y56: =SUM(U56:W56) -> 103 | AB56: 18 | AC56: 14 | AD56: =SUM(AA56:AC56) -> 32 | AF56: 45473 | AG56: =L56-Y56 -> 20 | AH56: =L56-AD56 -> 91 | AT56: 45473 | AU56: =L56+L57 -> 246 | AV56: =AD56+AD57 -> 71 | AX56: =AV56-AU56 -> -175 | AY56: =(-AX56/AU56) -> 0.71138211 | BH56: 45473 | BI56: =AU56 -> 246 | BJ56: =Y56+Y57 -> 198 | BL56: =BJ56-BI56 -> -48 | BM56: =(-BL56/BI56) -> 0.19512195 | BU56: =B56 -> JPM | BV56: 45473 | BW56: =L56-AD56 -> 91 | BZ56: =L56-Y56 -> 20
B57: JPM | C57: 1Q24 | D57: 88 | E57: 50 | F57: 62 | G57: =SUM(D57:F57) -> 200 | I57: 49 | J57: 39 | K57: 35 | L57: =SUM(I57:K57) -> 123 | N57: =48+11 -> 59 | O57: ='JPM LLM Interface'!G167 -> 1 | P57: 0 | Q57: =54+19+40+16 -> 129 | R57: =54+13+56+22+26+15 -> 186 | S57: =SUM(N57,P57,Q57,R57) -> 374 | V57: 58 | W57: 37 | X57: ='JPM LLM API'!F221 -> 0.75 | Y57: =SUM(U57:W57) -> 95 | AB57: 22 | AC57: 17 | AD57: =SUM(AA57:AC57) -> 39 | AF57: 45382 | AG57: =L57-Y57 -> 28 | AH57: =L57-AD57 -> 84 | AT57: 45382 | AU57: =L57 -> 123 | AV57: =AD57 -> 39 | AX57: =AV57-AU57 -> -84 | AY57: =(-AX57/AU57) -> 0.68292683 | BH57: 45382 | BI57: =AU57 -> 123 | BJ57: =Y57 -> 95 | BL57: =BJ57-BI57 -> -28 | BM57: =(-BL57/BI57) -> 0.22764228 | BU57: =B57 -> JPM | BV57: 45382 | BW57: =L57-AD57 -> 84 | BZ57: =L57-Y57 -> 28
G58: =SUM(G54:G57) -> 800 | K58: Cumulative Total | L58: =SUM(L54:L57) -> 492 | S58: =SUM(S54:S57) -> 1464 | W58: Cumulative Total | Y58: =SUM(Y54:Y57) -> 393 | AC58: Cumulative Total | AD58: =SUM(AD54:AD57) -> 158 | AF58: Total | AG58: =SUM(AG54:AG57) -> 99 | AH58: =SUM(AH54:AH57) -> 334 | BV58: Quarter Breakeven | BW58: =AA55/AVERAGE(BW54:BX57) -> 9.8213174 | BZ58: =U55/AVERAGE(BZ54:CA57) -> 30.933333
R59: Cumulative Efficiency % | S59: =(($L58-S58)/$L58)*1 -> -1.9756098 | W59: Cumulative Efficiency % | Y59: =(($L58-Y58)/$L58)*1 -> 0.20121951 | AC59: Cumulative Efficiency % | AD59: =(($L58-AD58)/$L58)*1 -> 0.67886179
W60: Average Accuracy | X60: =AVERAGE(X54:X57) -> 0.78125
AB61: =AVERAGE(AB56:AB57,AB54) -> 20 | AC61: =AVERAGE(AC54:AC57) -> 19.5
D68: Excel (Manual - Presentation / 10-Q) | I68: Advanced Excel Manual Benchmark (10-Q) | N68: LLM (Presentation) | U68: LLM API (Presentation) | AA68: Python Modules (10-Q)
I69: (time measured in seconds) | N69: Convert Prompt | P69: Correct Prompt | Q69: Standardization Prompt | R69: Clean Prompts | U69: (time measured in seconds) | AA69: (time measured in seconds)
B70: Ticker | C70: Quarter | D70: Extraction | E70: Standardization | F70: Database Format | G70: Total Excel | I70: Extraction | J70: Standardization | K70: Database Format | L70: Total | N70: Extraction | O70: Accuracy | P70: Correction | Q70: Standardization | R70: Database Format | S70: Total LLM | U70: Construct Extraction | V70: Adjustment | W70: Execute | X70: Accuracy | Y70: Total | AA70: Construct Extraction | AB70: Adjustment | AC70: Execute | AD70: Total | AF70: Date | AG70: LLM API | AH70: Python Modules | AU70: Advanced Excel | AV70: Python Modules | AX70: Delta | AY70: Efficiency % | BI70: Advanced Excel | BJ70: LLM API | BL70: Delta | BM70: Efficiency %
B71: PNC | C71: 4Q24 | D71: 48 | E71: 17 | F71: 39 | G71: =SUM(D71:F71) -> 104 | I71: 22 | J71: 12 | K71: 31 | L71: =SUM(I71:K71) -> 65 | N71: =49+10 -> 59 | O71: ='PNC LLM Interface'!F24 -> 1 | P71: 0 | Q71: =34+6 -> 40 | R71: =34+8+54+12+56+16 -> 180 | S71: =SUM(N71,P71,Q71,R71) -> 279 | V71: 27 | W71: 26 | X71: ='PNC LLM API'!F33 -> 0.92857143 | Y71: =SUM(U71:W71) -> 53 | AB71: 30 | AC71: 15 | AD71: =SUM(AA71:AC71) -> 45 | AF71: 45657 | AG71: =L71-Y71 -> 12 | AH71: =L71-AD71 -> 20 | AT71: 45657 | AU71: =L71+L72+L73+L74 -> 260 | AV71: =AD71+AD72+AD73+AD74 -> 168.66667 | AX71: =AV71-AU71 -> -91.333333 | AY71: =(-AX71/AU71) -> 0.35128205 | BH71: 45657 | BI71: =AU71 -> 260 | BJ71: =Y72+Y73+Y71+Y74 -> 177 | BL71: =BJ71-BI71 -> -83 | BM71: =(-BL71/BI71) -> 0.31923077 | BU71: =B71 -> PNC | BV71: 45657 | BW71: =L71-AD71 -> 20 | BZ71: =L71-Y71 -> 12
A72: Base | B72: PNC | C72: 3Q24 | D72: 48 | E72: 17 | F72: 39 | G72: =SUM(D72:F72) -> 104 | I72: 22 | J72: 12 | K72: 31 | L72: =SUM(I72:K72) -> 65 | N72: =49+20 -> 69 | O72: ='PNC LLM Interface'!F65 -> 1 | P72: 0 | Q72: =34+18 -> 52 | R72: =34+12+54+23+56+24 -> 203 | S72: =SUM(N72,P72,Q72,R72) -> 324 | U72: =2720/250*60 -> 652.8 | V72: 0 | W72: 25 | X72: ='PNC LLM API'!F58 -> 1 | Y72: =W72+AVERAGE(V71,V73:V74) -> 44 | AA72: =3015/250*60 -> 723.6 | AB72: 0 | AC72: 32 | AD72: =AC72+AVERAGE(AB71,AB73:AB74) -> 55.666667 | AF72: 45565 | AG72: =L72-Y72 -> 21 | AH72: =L72-AD72 -> 9.3333333 | AT72: 45565 | AU72: =L72+L73+L74 -> 195 | AV72: =AD72+AD73+AD74 -> 123.66667 | AX72: =AV72-AU72 -> -71.333333 | AY72: =(-AX72/AU72) -> 0.36581197 | BH72: 45565 | BI72: =AU72 -> 195 | BJ72: =Y73+Y74+Y72 -> 124 | BL72: =BJ72-BI72 -> -71 | BM72: =(-BL72/BI72) -> 0.36410256 | BU72: =B72 -> PNC | BV72: 45565 | BW72: =L72-(AC72+AVERAGE(AB71,AB73:AB74)) -> 9.3333333 | BZ72: =L72-(W72+AVERAGE(V71,V73:V74)) -> 21
B73: PNC | C73: 2Q24 | D73: 48 | E73: 17 | F73: 39 | G73: =SUM(D73:F73) -> 104 | I73: 22 | J73: 12 | K73: 31 | L73: =SUM(I73:K73) -> 65 | N73: =49+10 -> 59 | O73: ='PNC LLM Interface'!F105 -> 1 | P73: 0 | Q73: =34+15 -> 49 | R73: =34+8+54+11+56+12 -> 175 | S73: =SUM(N73,P73,Q73,R73) -> 283 | V73: 2 | W73: 24 | X73: ='PNC LLM API'!F83 -> 1 | Y73: =SUM(U73:W73) -> 26 | AB73: 20 | AC73: 15 | AD73: =SUM(AA73:AC73) -> 35 | AF73: 45473 | AG73: =L73-Y73 -> 39 | AH73: =L73-AD73 -> 30 | AT73: 45473 | AU73: =L73+L74 -> 130 | AV73: =AD73+AD74 -> 68 | AX73: =AV73-AU73 -> -62 | AY73: =(-AX73/AU73) -> 0.47692308 | BH73: 45473 | BI73: =AU73 -> 130 | BJ73: =Y73+Y74 -> 80 | BL73: =BJ73-BI73 -> -50 | BM73: =(-BL73/BI73) -> 0.38461538 | BU73: =B73 -> PNC | BV73: 45473 | BW73: =L73-AD73 -> 30 | BZ73: =L73-Y73 -> 39
B74: PNC | C74: 1Q24 | D74: 48 | E74: 17 | F74: 39 | G74: =SUM(D74:F74) -> 104 | I74: 22 | J74: 12 | K74: 31 | L74: =SUM(I74:K74) -> 65 | N74: =49+10 -> 59 | O74: ='PNC LLM Interface'!F145 -> 1 | P74: 0 | Q74: =34+10 -> 44 | R74: =34+10+54+8+56+17 -> 179 | S74: =SUM(N74,P74,Q74,R74) -> 282 | V74: 28 | W74: 26 | X74: ='PNC LLM API'!F119 -> 0.92857143 | Y74: =SUM(U74:W74) -> 54 | AB74: 21 | AC74: 12 | AD74: =SUM(AA74:AC74) -> 33 | AF74: 45382 | AG74: =L74-Y74 -> 11 | AH74: =L74-AD74 -> 32 | AT74: 45382 | AU74: =L74 -> 65 | AV74: =AD74 -> 33 | AX74: =AV74-AU74 -> -32 | AY74: =(-AX74/AU74) -> 0.49230769 | BH74: 45382 | BI74: =AU74 -> 65 | BJ74: =Y74 -> 54 | BL74: =BJ74-BI74 -> -11 | BM74: =(-BL74/BI74) -> 0.16923077 | BU74: =B74 -> PNC | BV74: 45382 | BW74: =L74-AD74 -> 32 | BZ74: =L74-Y74 -> 11
G75: =SUM(G71:G74) -> 416 | K75: Cumulative Total | L75: =SUM(L71:L74) -> 260 | S75: =SUM(S71:S74) -> 1168 | W75: Cumulative Total | Y75: =SUM(Y71:Y74) -> 177 | AC75: Cumulative Total | AD75: =SUM(AD71:AD74) -> 168.66667 | AF75: Total | AG75: =SUM(AG71:AG74) -> 83 | AH75: =SUM(AH71:AH74) -> 91.333333 | BV75: Quarter Breakeven | BW75: =AA72/AVERAGE(BW71:BX74) -> 31.690511 | BZ75: =U72/AVERAGE(BZ71:CA74) -> 31.460241
R76: Cumulative Efficiency % | S76: =(($L75-S75)/$L75)*1 -> -3.4923077 | W76: Cumulative Efficiency % | Y76: =(($L75-Y75)/$L75)*1 -> 0.31923077 | AC76: Cumulative Efficiency % | AD76: =(($L75-AD75)/$L75)*1 -> 0.35128205
W77: Average Accuracy | X77: =AVERAGE(X71:X74) -> 0.96428571
AB78: =AVERAGE(AB73:AB74,AB71) -> 23.666667 | AC78: =AVERAGE(AC71:AC74) -> 18.5
D84: Excel (Manual - Presentation / 10-Q) | I84: Advanced Excel Manual Benchmark (10-Q) | N84: LLM (Presentation) | U84: LLM API (Presentation) | AA84: Python Modules (10-Q)
I85: (time measured in seconds) | N85: Convert Prompt | P85: Correct Prompt | Q85: Standardization Prompt | R85: Clean Prompts | U85: (time measured in seconds) | AA85: (time measured in seconds)
B86: Ticker | C86: Quarter | D86: Extraction | E86: Standardization | F86: Database Format | G86: Total Excel | I86: Extraction | J86: Standardization | K86: Database Format | L86: Total | N86: Extraction | O86: Accuracy | P86: Correction | Q86: Standardization | R86: Database Format | S86: Total LLM | U86: Construct Extraction | V86: Adjustment | W86: Execute | X86: Accuracy | Y86: Total | AA86: Construct Extraction | AB86: Adjustment | AC86: Execute | AD86: Total | AF86: Date | AG86: LLM API | AH86: Python Modules | AU86: Advanced Excel | AV86: Python Modules | AX86: Delta | AY86: Efficiency % | BI86: Advanced Excel | BJ86: LLM API | BL86: Delta | BM86: Efficiency %
B87: KEY | C87: 4Q24 | D87: 99 | E87: 89 | F87: 44 | G87: =SUM(D87:F87) -> 232 | I87: 47 | J87: 60 | K87: 42 | L87: =SUM(I87:K87) -> 149 | N87: =52+10 -> 62 | O87: ='KEY LLM Interface'!F28 -> 1 | P87: 0 | Q87: =73+5 -> 78 | R87: =54+5+56+7+27+7 -> 156 | S87: =SUM(N87,P87,Q87,R87) -> 296 | V87: 31 | W87: 28 | X87: ='KEY LLM API'!F43 -> 1 | Y87: =SUM(U87:W87) -> 59 | AB87: 48 | AC87: 12 | AD87: =SUM(AA87:AC87) -> 60 | AF87: 45657 | AG87: =L87-Y87 -> 90 | AH87: =L87-AD87 -> 89 | AT87: 45657 | AU87: =L87+L88+L89+L90 -> 596 | AV87: =AD87+AD88+AD89+AD90 -> 172.66667 | AX87: =AV87-AU87 -> -423.33333 | AY87: =(-AX87/AU87) -> 0.71029083 | BH87: 45657 | BI87: =AU87 -> 596 | BJ87: =Y88+Y89+Y87+Y90 -> 237.66667 | BL87: =BJ87-BI87 -> -358.33333 | BM87: =(-BL87/BI87) -> 0.60123043 | BU87: =B87 -> KEY | BV87: 45657 | BW87: =L87-AD87 -> 89 | BZ87: =L87-Y87 -> 90
A88: Base | B88: KEY | C88: 3Q24 | D88: 99 | E88: 89 | F88: 44 | G88: =SUM(D88:F88) -> 232 | I88: 47 | J88: 60 | K88: 42 | L88: =SUM(I88:K88) -> 149 | N88: =52+9 -> 61 | O88: ='KEY LLM Interface'!F71 -> 0.93333333 | P88: =19+5 -> 24 | Q88: =66+6 -> 72 | R88: =54+7+56+7+64+6 -> 194 | S88: =SUM(N88,P88,Q88,R88) -> 351 | U88: =2999/250*60 -> 719.76 | V88: 0 | W88: 24 | X88: ='KEY LLM API'!F88 -> 1 | Y88: =W88+AVERAGE(V87,V89:V90) -> 55.666667 | AA88: =2987/250*60 -> 716.88 | AB88: 0 | AC88: 23 | AD88: =AC88+AVERAGE(AB87,AB89:AB90) -> 49.666667 | AF88: 45565 | AG88: =L88-Y88 -> 93.333333 | AH88: =L88-AD88 -> 99.333333 | AT88: 45565 | AU88: =L88+L89+L90 -> 447 | AV88: =AD88+AD89+AD90 -> 112.66667 | AX88: =AV88-AU88 -> -334.33333 | AY88: =(-AX88/AU88) -> 0.74794929 | BH88: 45565 | BI88: =AU88 -> 447 | BJ88: =Y89+Y90+Y88 -> 178.66667 | BL88: =BJ88-BI88 -> -268.33333 | BM88: =(-BL88/BI88) -> 0.60029828 | BU88: =B88 -> KEY | BV88: 45565 | BW88: =L88-(AC88+AVERAGE(AB87,AB89:AB90)) -> 99.333333 | BZ88: =L88-(W88+AVERAGE(V87,V89:V90)) -> 93.333333
B89: KEY | C89: 2Q24 | D89: 99 | E89: 89 | F89: 44 | G89: =SUM(D89:F89) -> 232 | I89: 47 | J89: 60 | K89: 42 | L89: =SUM(I89:K89) -> 149 | N89: =52+9 -> 61 | O89: ='KEY LLM Interface'!F113 -> 1 | P89: 0 | Q89: =66+7 -> 73 | R89: =54+7+56+6+27+7 -> 157 | S89: =SUM(N89,P89,Q89,R89) -> 291 | V89: 36 | W89: 32 | X89: ='KEY LLM API'!F139 -> 0.875 | Y89: =SUM(U89:W89) -> 68 | AB89: 17 | AC89: 17 | AD89: =SUM(AA89:AC89) -> 34 | AF89: 45473 | AG89: =L89-Y89 -> 81 | AH89: =L89-AD89 -> 115 | AT89: 45473 | AU89: =L89+L90 -> 298 | AV89: =AD89+AD90 -> 63 | AX89: =AV89-AU89 -> -235 | AY89: =(-AX89/AU89) -> 0.7885906 | BH89: 45473 | BI89: =AU89 -> 298 | BJ89: =Y89+Y90 -> 123 | BL89: =BJ89-BI89 -> -175 | BM89: =(-BL89/BI89) -> 0.58724832 | BU89: =B89 -> KEY | BV89: 45473 | BW89: =L89-AD89 -> 115 | BZ89: =L89-Y89 -> 81
B90: KEY | C90: 1Q24 | D90: 99 | E90: 89 | F90: 44 | G90: =SUM(D90:F90) -> 232 | I90: 47 | J90: 60 | K90: 42 | L90: =SUM(I90:K90) -> 149 | N90: =52+9 -> 61 | O90: ='KEY LLM Interface'!F155 -> 1 | P90: 0 | Q90: =66+6 -> 72 | R90: =54+6+56+8+27+7 -> 158 | S90: =SUM(N90,P90,Q90,R90) -> 291 | V90: 28 | W90: 27 | X90: ='KEY LLM API'!F190 -> 0.75 | Y90: =SUM(U90:W90) -> 55 | AB90: 15 | AC90: 14 | AD90: =SUM(AA90:AC90) -> 29 | AF90: 45382 | AG90: =L90-Y90 -> 94 | AH90: =L90-AD90 -> 120 | AT90: 45382 | AU90: =L90 -> 149 | AV90: =AD90 -> 29 | AX90: =AV90-AU90 -> -120 | AY90: =(-AX90/AU90) -> 0.80536913 | BH90: 45382 | BI90: =AU90 -> 149 | BJ90: =Y90 -> 55 | BL90: =BJ90-BI90 -> -94 | BM90: =(-BL90/BI90) -> 0.63087248 | BU90: =B90 -> KEY | BV90: 45382 | BW90: =L90-AD90 -> 120 | BZ90: =L90-Y90 -> 94
G91: =SUM(G87:G90) -> 928 | K91: Cumulative Total | L91: =SUM(L87:L90) -> 596 | S91: =SUM(S87:S90) -> 1229 | W91: Cumulative Total | Y91: =SUM(Y87:Y90) -> 237.66667 | AC91: Cumulative Total | AD91: =SUM(AD87:AD90) -> 172.66667 | AF91: Total | AG91: =SUM(AG87:AG90) -> 358.33333 | AH91: =SUM(AH87:AH90) -> 423.33333 | BV91: Quarter Breakeven | BW91: =AA88/AVERAGE(BW87:BX90) -> 6.7736693 | BZ91: =U88/AVERAGE(BZ87:CA90) -> 8.0345302
R92: Cumulative Efficiency % | S92: =(($L91-S91)/$L91)*1 -> -1.0620805 | W92: Cumulative Efficiency % | Y92: =(($L91-Y91)/$L91)*1 -> 0.60123043 | AC92: Cumulative Efficiency % | AD92: =(($L91-AD91)/$L91)*1 -> 0.71029083
W93: Average Accuracy | X93: =AVERAGE(X87:X90) -> 0.90625
AB94: =AVERAGE(AB89:AB90,AB87) -> 26.666667 | AC94: =AVERAGE(AC87:AC90) -> 16.5
D102: Excel (Manual - Presentation / 10-Q) | I102: Advanced Excel Manual Benchmark (10-Q) | N102: LLM (Presentation) | U102: LLM API (Presentation) | AA102: Python Modules (10-Q)
I103: (time measured in seconds) | N103: Convert Prompt | P103: Correct Prompt | Q103: Standardization Prompt | R103: Clean Prompts | U103: (time measured in seconds) | AA103: (time measured in seconds)
B104: Ticker | C104: Quarter | D104: Extraction | E104: Standardization | F104: Database Format | G104: Total Excel | I104: Extraction | J104: Standardization | K104: Database Format | L104: Total | N104: Extraction | O104: Accuracy | P104: Correction | Q104: Standardization | R104: Database Format | S104: Total LLM | U104: Construct Extraction | V104: Adjustment | W104: Execute | X104: Accuracy | Y104: Total | AA104: Construct Extraction | AB104: Adjustment | AC104: Execute | AD104: Total | AF104: Date | AG104: LLM API | AH104: Python Modules | AU104: Advanced Excel | AV104: Python Modules | AX104: Delta | AY104: Efficiency % | BI104: Advanced Excel | BJ104: LLM API | BL104: Delta | BM104: Efficiency %
B105: HBAN | C105: 4Q24 | D105: 38 | E105: 0 | F105: 44 | G105: =SUM(D105:F105) -> 82 | I105: 24 | J105: 0 | K105: 32 | L105: =SUM(I105:K105) -> 56 | N105: =49+7 -> 56 | O105: ='HBAN LLM Interface'!G19 -> 1 | P105: 0 | Q105: 0 | R105: =54+9+56+14+37+12 -> 182 | S105: =SUM(N105,P105,Q105,R105) -> 238 | V105: 2 | W105: 22 | X105: ='HBAN LLM API'!F25 -> 1 | Y105: =SUM(U105:W105) -> 24 | AB105: =525/250*60+19 -> 145 | AC105: 15 | AD105: =SUM(AA105:AC105) -> 160 | AF105: 45657 | AG105: =L105-Y105 -> 32 | AH105: =L105-AD105 -> -104 | AT105: 45657 | AU105: =L105+L106+L107+L108 -> 224 | AV105: =AD105+AD106+AD107+AD108 -> 295.66667 | AX105: =AV105-AU105 -> 71.666667 | AY105: =(-AX105/AU105) -> -0.31994048 | BH105: 45657 | BI105: =AU105 -> 224 | BJ105: =Y106+Y107+Y105+Y108 -> 100 | BL105: =BJ105-BI105 -> -124 | BM105: =(-BL105/BI105) -> 0.55357143 | BU105: =B105 -> HBAN | BV105: 45657 | BW105: =L105-AD105 -> -104 | BZ105: =L105-Y105 -> 32
A106: Base | B106: HBAN | C106: 3Q24 | D106: 38 | E106: 0 | F106: 44 | G106: =SUM(D106:F106) -> 82 | I106: 24 | J106: 0 | K106: 32 | L106: =SUM(I106:K106) -> 56 | N106: =49+19 -> 68 | O106: ='HBAN LLM Interface'!G41 -> 1 | P106: 0 | Q106: 0 | R106: =54+10+56+15+37+5 -> 177 | S106: =SUM(N106,P106,Q106,R106) -> 245 | U106: =1641/250*60 -> 393.84 | V106: 0 | W106: 24 | X106: ='HBAN LLM API'!F51 -> 1 | Y106: =W106+AVERAGE(V105,V107:V108) -> 26 | AA106: =1788/250*60 -> 429.12 | AB106: 0 | AC106: 17 | AD106: =AC106+AVERAGE(AB105,AB107:AB108) -> 74.666667 | AF106: 45565 | AG106: =L106-Y106 -> 30 | AH106: =L106-AD106 -> -18.666667 | AT106: 45565 | AU106: =L106+L107+L108 -> 168 | AV106: =AD106+AD107+AD108 -> 135.66667 | AX106: =AV106-AU106 -> -32.333333 | AY106: =(-AX106/AU106) -> 0.19246032 | BH106: 45565 | BI106: =AU106 -> 168 | BJ106: =Y107+Y108+Y106 -> 76 | BL106: =BJ106-BI106 -> -92 | BM106: =(-BL106/BI106) -> 0.54761905 | BU106: =B106 -> HBAN | BV106: 45565 | BW106: =L106-(AC106+AVERAGE(AB105,AB107:AB108)) -> -18.666667 | BZ106: =L106-(W106+AVERAGE(V105,V107:V108)) -> 30
B107: HBAN | C107: 2Q24 | D107: 38 | E107: 0 | F107: 44 | G107: =SUM(D107:F107) -> 82 | I107: 24 | J107: 0 | K107: 32 | L107: =SUM(I107:K107) -> 56 | N107: =49+10 -> 59 | O107: ='HBAN LLM Interface'!G64 -> 1 | P107: 0 | Q107: 0 | R107: =54+9+56+10+37+14 -> 180 | S107: =SUM(N107,P107,Q107,R107) -> 239 | V107: 2 | W107: 21 | X107: ='HBAN LLM API'!F76 -> 1 | Y107: =SUM(U107:W107) -> 23 | AB107: 14 | AC107: 15 | AD107: =SUM(AA107:AC107) -> 29 | AF107: 45473 | AG107: =L107-Y107 -> 33 | AH107: =L107-AD107 -> 27 | AT107: 45473 | AU107: =L107+L108 -> 112 | AV107: =AD107+AD108 -> 61 | AX107: =AV107-AU107 -> -51 | AY107: =(-AX107/AU107) -> 0.45535714 | BH107: 45473 | BI107: =AU107 -> 112 | BJ107: =Y107+Y108 -> 50 | BL107: =BJ107-BI107 -> -62 | BM107: =(-BL107/BI107) -> 0.55357143 | BU107: =B107 -> HBAN | BV107: 45473 | BW107: =L107-AD107 -> 27 | BZ107: =L107-Y107 -> 33
B108: HBAN | C108: 1Q24 | D108: 38 | E108: 0 | F108: 44 | G108: =SUM(D108:F108) -> 82 | I108: 24 | J108: 0 | K108: 32 | L108: =SUM(I108:K108) -> 56 | N108: =49+10 -> 59 | O108: ='HBAN LLM Interface'!G85 -> 1 | P108: 0 | Q108: 0 | R108: =54+8+56+16+37+12 -> 183 | S108: =SUM(N108,P108,Q108,R108) -> 242 | V108: 2 | W108: 25 | X108: ='HBAN LLM API'!F102 -> 1 | Y108: =SUM(U108:W108) -> 27 | AB108: 14 | AC108: 18 | AD108: =SUM(AA108:AC108) -> 32 | AF108: 45382 | AG108: =L108-Y108 -> 29 | AH108: =L108-AD108 -> 24 | AT108: 45382 | AU108: =L108 -> 56 | AV108: =AD108 -> 32 | AX108: =AV108-AU108 -> -24 | AY108: =(-AX108/AU108) -> 0.42857143 | BH108: 45382 | BI108: =AU108 -> 56 | BJ108: =Y108 -> 27 | BL108: =BJ108-BI108 -> -29 | BM108: =(-BL108/BI108) -> 0.51785714 | BU108: =B108 -> HBAN | BV108: 45382 | BW108: =L108-AD108 -> 24 | BZ108: =L108-Y108 -> 29
G109: =SUM(G105:G108) -> 328 | K109: Cumulative Total | L109: =SUM(L105:L108) -> 224 | S109: =SUM(S105:S108) -> 964 | W109: Cumulative Total | Y109: =SUM(Y105:Y108) -> 100 | AC109: Cumulative Total | AD109: =SUM(AD105:AD108) -> 295.66667 | AF109: Total | AG109: =SUM(AG105:AG108) -> 124 | AH109: =SUM(AH105:AH108) -> -71.666667 | BV109: Quarter Breakeven | BW109: =AA106/AVERAGE(BW105:BX108) -> -23.950884 | BZ109: =U106/AVERAGE(BZ105:CA108) -> 12.704516
R110: Cumulative Efficiency % | S110: =(($L109-S109)/$L109)*1 -> -3.3035714 | W110: Cumulative Efficiency % | Y110: =(($L109-Y109)/$L109)*1 -> 0.55357143 | AC110: Cumulative Efficiency % | AD110: =(($L109-AD109)/$L109)*1 -> -0.31994048
W111: Average Accuracy | X111: =AVERAGE(X105:X108) -> 1
AB112: =AVERAGE(AB107:AB108,AB105) -> 57.666667 | AC112: =AVERAGE(AC105:AC108) -> 16.25
D120: Excel (Manual - Presentation / 10-Q) | I120: Advanced Excel Manual Benchmark (10-Q) | N120: LLM (Presentation) | U120: LLM API (Presentation) | AA120: Python Modules (10-Q)
I121: (time measured in seconds) | N121: Convert Prompt | P121: Correct Prompt | Q121: Standardization Prompt | R121: Clean Prompts | U121: (time measured in seconds) | AA121: (time measured in seconds)
B122: Ticker | C122: Quarter | D122: Extraction | E122: Standardization | F122: Database Format | G122: Total Excel | I122: Extraction | J122: Standardization | K122: Database Format | L122: Total | N122: Extraction | O122: Accuracy | P122: Correction | Q122: Standardization | R122: Database Format | S122: Total LLM | U122: Construct Extraction | V122: Adjustment | W122: Execute | X122: Accuracy | Y122: Total | AA122: Construct Extraction | AB122: Adjustment | AC122: Execute | AD122: Total | AF122: Date | AG122: LLM API | AH122: Python Modules | AU122: Advanced Excel | AV122: Python Modules | AX122: Delta | AY122: Efficiency % | BI122: Advanced Excel | BJ122: LLM API | BL122: Delta | BM122: Efficiency %
B123: CFG | C123: 4Q24 | D123: 54 | E123: 50 | F123: 48 | G123: =SUM(D123:F123) -> 152 | I123: 32 | J123: 42 | K123: 32 | L123: =SUM(I123:K123) -> 106 | N123: =49+8 -> 57 | O123: ='CFG LLM Interface'!F25 -> 1 | P123: 0 | Q123: =40+8 -> 48 | R123: =54+9+56+12+33+12 -> 176 | S123: =SUM(N123,P123,Q123,R123) -> 281 | V123: 2 | W123: 23 | X123: ='CFG LLM API'!F24 -> 1 | Y123: =SUM(U123:W123) -> 25 | AB123: 22 | AC123: 18 | AD123: =SUM(AA123:AC123) -> 40 | AF123: 45657 | AG123: =L123-Y123 -> 81 | AH123: =L123-AD123 -> 66 | AT123: 45657 | AU123: =L123+L124+L125+L126 -> 424 | AV123: =AD123+AD124+AD125+AD126 -> 143 | AX123: =AV123-AU123 -> -281 | AY123: =(-AX123/AU123) -> 0.66273585 | BH123: 45657 | BI123: =AU123 -> 424 | BJ123: =Y124+Y125+Y123+Y126 -> 103 | BL123: =BJ123-BI123 -> -321 | BM123: =(-BL123/BI123) -> 0.75707547 | BU123: =B123 -> CFG | BV123: 45657 | BW123: =L123-AD123 -> 66 | BZ123: =L123-Y123 -> 81
A124: Base | B124: CFG | C124: 3Q24 | D124: 54 | E124: 50 | F124: 48 | G124: =SUM(D124:F124) -> 152 | I124: 32 | J124: 42 | K124: 32 | L124: =SUM(I124:K124) -> 106 | N124: =49+9 -> 58 | O124: ='CFG LLM Interface'!F50 -> 1 | P124: 0 | Q124: =40+7 -> 47 | R124: =54+11+56+10+33+14 -> 178 | S124: =SUM(N124,P124,Q124,R124) -> 283 | U124: =1879/250*60 -> 450.96 | V124: 0 | W124: 23 | X124: ='CFG LLM API'!F50 -> 1 | Y124: =W124+AVERAGE(V123,V125:V126) -> 25 | AA124: =2694/250*60 -> 646.56 | AB124: 0 | AC124: 16 | AD124: =AC124+AVERAGE(AB123,AB125:AB126) -> 36 | AF124: 45565 | AG124: =L124-Y124 -> 81 | AH124: =L124-AD124 -> 70 | AT124: 45565 | AU124: =L124+L125+L126 -> 318 | AV124: =AD124+AD125+AD126 -> 103 | AX124: =AV124-AU124 -> -215 | AY124: =(-AX124/AU124) -> 0.67610063 | BH124: 45565 | BI124: =AU124 -> 318 | BJ124: =Y125+Y126+Y124 -> 78 | BL124: =BJ124-BI124 -> -240 | BM124: =(-BL124/BI124) -> 0.75471698 | BU124: =B124 -> CFG | BV124: 45565 | BW124: =L124-(AC124+AVERAGE(AB123,AB125:AB126)) -> 70 | BZ124: =L124-(W124+AVERAGE(V123,V125:V126)) -> 81
B125: CFG | C125: 2Q24 | D125: 54 | E125: 50 | F125: 48 | G125: =SUM(D125:F125) -> 152 | I125: 32 | J125: 42 | K125: 32 | L125: =SUM(I125:K125) -> 106 | N125: =49+8 -> 57 | O125: ='CFG LLM Interface'!F77 -> 1 | P125: 0 | Q125: =40+5 -> 45 | R125: =54+7+56+10+33+12 -> 172 | S125: =SUM(N125,P125,Q125,R125) -> 274 | V125: 2 | W125: 24 | X125: ='CFG LLM API'!F75 -> 1 | Y125: =SUM(U125:W125) -> 26 | AB125: 20 | AC125: 14 | AD125: =SUM(AA125:AC125) -> 34 | AF125: 45473 | AG125: =L125-Y125 -> 80 | AH125: =L125-AD125 -> 72 | AT125: 45473 | AU125: =L125+L126 -> 212 | AV125: =AD125+AD126 -> 67 | AX125: =AV125-AU125 -> -145 | AY125: =(-AX125/AU125) -> 0.68396226 | BH125: 45473 | BI125: =AU125 -> 212 | BJ125: =Y125+Y126 -> 53 | BL125: =BJ125-BI125 -> -159 | BM125: =(-BL125/BI125) -> 0.75 | BU125: =B125 -> CFG | BV125: 45473 | BW125: =L125-AD125 -> 72 | BZ125: =L125-Y125 -> 80
B126: CFG | C126: 1Q24 | D126: 54 | E126: 50 | F126: 48 | G126: =SUM(D126:F126) -> 152 | I126: 32 | J126: 42 | K126: 32 | L126: =SUM(I126:K126) -> 106 | N126: =49+11 -> 60 | O126: ='CFG LLM Interface'!F102 -> 1 | P126: 0 | Q126: =40+6 -> 46 | R126: =54+7+56+11+33+10 -> 171 | S126: =SUM(N126,P126,Q126,R126) -> 277 | V126: 2 | W126: 25 | X126: ='CFG LLM API'!F100 -> 1 | Y126: =SUM(U126:W126) -> 27 | AB126: 18 | AC126: 15 | AD126: =SUM(AA126:AC126) -> 33 | AF126: 45382 | AG126: =L126-Y126 -> 79 | AH126: =L126-AD126 -> 73 | AT126: 45382 | AU126: =L126 -> 106 | AV126: =AD126 -> 33 | AX126: =AV126-AU126 -> -73 | AY126: =(-AX126/AU126) -> 0.68867925 | BH126: 45382 | BI126: =AU126 -> 106 | BJ126: =Y126 -> 27 | BL126: =BJ126-BI126 -> -79 | BM126: =(-BL126/BI126) -> 0.74528302 | BU126: =B126 -> CFG | BV126: 45382 | BW126: =L126-AD126 -> 73 | BZ126: =L126-Y126 -> 79
G127: =SUM(G123:G126) -> 608 | K127: Cumulative Total | L127: =SUM(L123:L126) -> 424 | S127: =SUM(S123:S126) -> 1115 | W127: Cumulative Total | Y127: =SUM(Y123:Y126) -> 103 | AC127: Cumulative Total | AD127: =SUM(AD123:AD126) -> 143 | AF127: Total | AG127: =SUM(AG123:AG126) -> 321 | AH127: =SUM(AH123:AH126) -> 281 | BV127: Quarter Breakeven | BW127: =AA124/AVERAGE(BW123:BX126) -> 9.2037011 | BZ127: =U124/AVERAGE(BZ123:CA126) -> 5.6194393
R128: Cumulative Efficiency % | S128: =(($L127-S127)/$L127)*1 -> -1.629717 | W128: Cumulative Efficiency % | Y128: =(($L127-Y127)/$L127)*1 -> 0.75707547 | AC128: Cumulative Efficiency % | AD128: =(($L127-AD127)/$L127)*1 -> 0.66273585
W129: Average Accuracy | X129: =AVERAGE(X123:X126) -> 1
AB130: =AVERAGE(AB125:AB126,AB123) -> 20 | AC130: =AVERAGE(AC123:AC126) -> 15.75
D136: Excel (Manual - Presentation / 10-Q) | I136: Advanced Excel Manual Benchmark (10-Q) | N136: LLM (Presentation) | U136: LLM API (Presentation) | AA136: Python Modules (10-Q)
I137: (time measured in seconds) | N137: Convert Prompt | P137: Correct Prompt | Q137: Standardization Prompt | R137: Clean Prompts | U137: (time measured in seconds) | AA137: (time measured in seconds)
B138: Ticker | C138: Quarter | D138: Extraction | E138: Standardization | F138: Database Format | G138: Total Excel | I138: Extraction | J138: Standardization | K138: Database Format | L138: Total | N138: Extraction | O138: Accuracy | P138: Correction | Q138: Standardization | R138: Database Format | S138: Total LLM | U138: Construct Extraction | V138: Adjustment | W138: Execute | X138: Accuracy | Y138: Total | AA138: Construct Extraction | AB138: Adjustment | AC138: Execute | AD138: Total | AF138: Date | AG138: LLM API | AH138: Python Modules | AU138: Advanced Excel | AV138: Python Modules | AX138: Delta | AY138: Efficiency % | BI138: Advanced Excel | BJ138: LLM API | BL138: Delta | BM138: Efficiency %
B139: FCNCA | C139: 4Q24 | D139: 47 | E139: 27 | F139: 57 | G139: =SUM(D139:F139) -> 131 | I139: 27 | J139: 21 | K139: 40 | L139: =SUM(I139:K139) -> 88 | N139: =49+6 -> 55 | O139: ='FCNCA LLM Interface'!F21 -> 1 | P139: 0 | Q139: =25+6 -> 31 | R139: =34+6+56+8+44+6 -> 154 | S139: =SUM(N139,P139,Q139,R139) -> 240 | V139: 2 | W139: 26 | X139: ='FCNCA LLM API'!F25 -> 1 | Y139: =SUM(U139:W139) -> 28 | AB139: 24 | AC139: 16 | AD139: =SUM(AA139:AC139) -> 40 | AF139: 45657 | AG139: =L139-Y139 -> 60 | AH139: =L139-AD139 -> 48 | AT139: 45657 | AU139: =L139+L140+L141+L142 -> 352 | AV139: =AD139+AD140+AD141+AD142 -> 145.66667 | AX139: =AV139-AU139 -> -206.33333 | AY139: =(-AX139/AU139) -> 0.58617424 | BH139: 45657 | BI139: =AU139 -> 352 | BJ139: =Y140+Y141+Y139+Y142 -> 111 | BL139: =BJ139-BI139 -> -241 | BM139: =(-BL139/BI139) -> 0.68465909 | BU139: =B139 -> FCNCA | BV139: 45657 | BW139: =L139-AD139 -> 48 | BZ139: =L139-Y139 -> 60
A140: Base | B140: FCNCA | C140: 3Q24 | D140: 47 | E140: 27 | F140: 57 | G140: =SUM(D140:F140) -> 131 | I140: 27 | J140: 21 | K140: 40 | L140: =SUM(I140:K140) -> 88 | N140: =49+6 -> 55 | O140: ='FCNCA LLM Interface'!F45 -> 1 | P140: 0 | Q140: =25+7 -> 32 | R140: =34+7+56+10+45+11 -> 163 | S140: =SUM(N140,P140,Q140,R140) -> 250 | U140: =1788/250*60 -> 429.12 | V140: 0 | W140: 26 | X140: ='FCNCA LLM API'!F49 -> 1 | Y140: =W140+AVERAGE(V139,V141:V142) -> 28 | AA140: =1967/250*60 -> 472.08 | AB140: 0 | AC140: 18 | AD140: =AC140+AVERAGE(AB139,AB141:AB142) -> 37.666667 | AF140: 45565 | AG140: =L140-Y140 -> 60 | AH140: =L140-AD140 -> 50.333333 | AT140: 45565 | AU140: =L140+L141+L142 -> 264 | AV140: =AD140+AD141+AD142 -> 105.66667 | AX140: =AV140-AU140 -> -158.33333 | AY140: =(-AX140/AU140) -> 0.59974747 | BH140: 45565 | BI140: =AU140 -> 264 | BJ140: =Y141+Y142+Y140 -> 83 | BL140: =BJ140-BI140 -> -181 | BM140: =(-BL140/BI140) -> 0.68560606 | BU140: =B140 -> FCNCA | BV140: 45565 | BW140: =L140-(AC140+AVERAGE(AB139,AB141:AB142)) -> 50.333333 | BZ140: =L140-(W140+AVERAGE(V139,V141:V142)) -> 60
B141: FCNCA | C141: 2Q24 | D141: 47 | E141: 27 | F141: 57 | G141: =SUM(D141:F141) -> 131 | I141: 27 | J141: 21 | K141: 40 | L141: =SUM(I141:K141) -> 88 | N141: =49+6 -> 55 | O141: ='FCNCA LLM Interface'!$F$68 -> 1 | P141: 0 | Q141: =25+4 -> 29 | R141: =34+7+56+7+44+7 -> 155 | S141: =SUM(N141,P141,Q141,R141) -> 239 | V141: 2 | W141: 25 | X141: ='FCNCA LLM API'!F75 -> 1 | Y141: =SUM(U141:W141) -> 27 | AB141: 18 | AC141: 18 | AD141: =SUM(AA141:AC141) -> 36 | AF141: 45473 | AG141: =L141-Y141 -> 61 | AH141: =L141-AD141 -> 52 | AT141: 45473 | AU141: =L141+L142 -> 176 | AV141: =AD141+AD142 -> 68 | AX141: =AV141-AU141 -> -108 | AY141: =(-AX141/AU141) -> 0.61363636 | BH141: 45473 | BI141: =AU141 -> 176 | BJ141: =Y141+Y142 -> 55 | BL141: =BJ141-BI141 -> -121 | BM141: =(-BL141/BI141) -> 0.6875 | BU141: =B141 -> FCNCA | BV141: 45473 | BW141: =L141-AD141 -> 52 | BZ141: =L141-Y141 -> 61
...

Sheet Application

Sheet Single Generic Prompt
B2: Prompt (v1)
B29: CMA 4Q24 | D29: CRE Total: | E29: 9.4 | Q29: LLM Generic Prompt Application Feature (4Q24 Presentation) | W29: Time Delta | X29: Accuracy Delta | Z29: LLM Ticker Specific Prompt (4Q24 Presentation) | AF29: Time Delta | AG29: Accuracy Delta | AI29: Python Script (4Q24 Presentation) | AO29: Time Delta | AP29: Accuracy Delta | AR29: Manual (4Q24 Presentation)
Q30: (time measured in seconds) | Z30: (time measured in seconds) | AI30: (time measured in seconds) | AR30: (time measured in seconds)
D31: Correct | Q31: Ticker | R31: Execution | S31: Override | T31: Total | U31: Accuracy | Z31: Ticker | AA31: Execution | AB31: Override | AC31: Total | AD31: Accuracy | AI31: Ticker | AJ31: Execution | AK31: Adjustment | AL31: Total | AM31: Accuracy | AR31: Ticker | AS31: Execution | AT31: Adjustment | AU31: Total | AV31: Accuracy
Q32: BAC | R32: 30 | S32: 32 | T32: =SUM(R32:S32) -> 62 | U32: =H232 -> 0.55555556 | W32: =T32-AC32 -> 6 | X32: =U32-AD32 -> -0.14444444 | Z32: BAC | AA32: =Summary!W26 -> 19 | AB32: =Summary!V26 -> 37 | AC32: =SUM(AA32:AB32) -> 56 | AD32: =Summary!X26 -> 0.7 | AF32: =T32-AL32 -> -28 | AG32: =U32-AM32 -> -0.44444444 | AI32: BAC | AJ32: =Summary!AC26 -> 28 | AK32: =Summary!AB26 -> 62 | AL32: =SUM(AJ32:AK32) -> 90 | AM32: 1 | AO32: =T32-AU32 -> -14 | AP32: =U32-AV32 -> -0.44444444 | AR32: BAC | AS32: =Summary!I26 -> 30 | AT32: =SUM(Summary!J26:K26) -> 46 | AU32: =SUM(AS32:AT32) -> 76 | AV32: 1
D33: CRE Property Types | E33: Percentage | F33: Loan Amount ($bn) | G33: Loan Amount ($mn) | Q33: FCNCA | R33: 24 | S33: 13 | T33: =SUM(R33:S33) -> 37 | U33: =H261 -> 0.92857143 | W33: =T33-AC33 -> 9 | X33: =U33-AD33 -> -0.071428571 | Z33: FCNCA | AA33: =Summary!W139 -> 26 | AB33: =Summary!V139 -> 2 | AC33: =SUM(AA33:AB33) -> 28 | AD33: =Summary!X139 -> 1 | AF33: =T33-AL33 -> -3 | AG33: =U33-AM33 -> -0.071428571 | AI33: FCNCA | AJ33: =Summary!AC139 -> 16 | AK33: =Summary!AB139 -> 24 | AL33: =SUM(AJ33:AK33) -> 40 | AM33: 1 | AO33: =T33-AU33 -> -51 | AP33: =U33-AV33 -> -0.071428571 | AR33: FCNCA | AS33: =Summary!I139 -> 27 | AT33: =SUM(Summary!J139:K139) -> 61 | AU33: =SUM(AS33:AT33) -> 88 | AV33: 1
D34: Industrial | E34: 0.29 | F34: =$E$29*E34 -> 2.726 | G34: =F34*1000 -> 2726 | Q34: CFG | R34: 21 | S34: 19 | T34: =SUM(R34:S34) -> 40 | U34: =H289 -> 0.85714286 | W34: =T34-AC34 -> 15 | X34: =U34-AD34 -> -0.14285714 | Z34: CFG | AA34: =Summary!W123 -> 23 | AB34: =Summary!V123 -> 2 | AC34: =SUM(AA34:AB34) -> 25 | AD34: =Summary!X123 -> 1 | AF34: =T34-AL34 -> 0 | AG34: =U34-AM34 -> -0.14285714 | AI34: CFG | AJ34: =Summary!AC123 -> 18 | AK34: =Summary!AB123 -> 22 | AL34: =SUM(AJ34:AK34) -> 40 | AM34: 1 | AO34: =T34-AU34 -> -66 | AP34: =U34-AV34 -> -0.14285714 | AR34: CFG | AS34: =Summary!I123 -> 32 | AT34: =SUM(Summary!J123:K123) -> 74 | AU34: =SUM(AS34:AT34) -> 106 | AV34: 1
D35: Multi-family | E35: 0.48 | F35: =$E$29*E35 -> 4.512 | G35: =F35*1000 -> 4512 | Q35: HBAN | R35: 21 | S35: 0 | T35: =SUM(R35:S35) -> 21 | U35: =H316 -> 1 | W35: =T35-AC35 -> -3 | X35: =U35-AD35 -> 0 | Z35: HBAN | AA35: =Summary!W105 -> 22 | AB35: =Summary!V105 -> 2 | AC35: =SUM(AA35:AB35) -> 24 | AD35: =Summary!X105 -> 1 | AF35: =T35-AL35 -> -139 | AG35: =U35-AM35 -> 0 | AI35: HBAN | AJ35: =Summary!AC105 -> 15 | AK35: =Summary!AB105 -> 145 | AL35: =SUM(AJ35:AK35) -> 160 | AM35: 1 | AO35: =T35-AU35 -> -35 | AP35: =U35-AV35 -> 0 | AR35: HBAN | AS35: =Summary!I105 -> 24 | AT35: =SUM(Summary!J105:K105) -> 32 | AU35: =SUM(AS35:AT35) -> 56 | AV35: 1
D36: Self-Storage | E36: 0.05 | F36: =$E$29*E36 -> 0.47 | G36: =F36*1000 -> 470 | Q36: RF | R36: 21 | S36: 20 | T36: =SUM(R36:S36) -> 41 | U36: =H364 -> 0.8125 | W36: =T36-AC36 -> -25 | X36: =U36-AD36 -> -0.1875 | Z36: RF | AA36: =Summary!W180 -> 31 | AB36: =Summary!V180 -> 35 | AC36: =SUM(AA36:AB36) -> 66 | AD36: =Summary!X180 -> 1 | AF36: =T36-AL36 -> -131.68 | AG36: =U36-AM36 -> -0.1875 | AI36: RF | AJ36: =Summary!AC180 -> 20 | AK36: =Summary!AB180 -> 152.68 | AL36: =SUM(AJ36:AK36) -> 172.68 | AM36: 1 | AO36: =T36-AU36 -> -80 | AP36: =U36-AV36 -> -0.1875 | AR36: RF | AS36: =Summary!I180 -> 24 | AT36: =SUM(Summary!J180:K180) -> 97 | AU36: =SUM(AS36:AT36) -> 121 | AV36: 1
D37: Retail | E37: 0.04 | F37: =$E$29*E37 -> 0.376 | G37: =F37*1000 -> 376 | Q37: PNC | R37: 27 | S37: 0 | T37: =SUM(R37:S37) -> 27 | U37: =H393 -> 1 | W37: =T37-AC37 -> -26 | X37: =U37-AD37 -> 0.071428571 | Z37: PNC | AA37: =Summary!W71 -> 26 | AB37: =Summary!V71 -> 27 | AC37: =SUM(AA37:AB37) -> 53 | AD37: =Summary!X71 -> 0.92857143 | AF37: =T37-AL37 -> -18 | AG37: =U37-AM37 -> 0 | AI37: PNC | AJ37: =Summary!AC71 -> 15 | AK37: =Summary!AB71 -> 30 | AL37: =SUM(AJ37:AK37) -> 45 | AM37: 1 | AO37: =T37-AU37 -> -38 | AP37: =U37-AV37 -> 0 | AR37: PNC | AS37: =Summary!I71 -> 22 | AT37: =SUM(Summary!J71:K71) -> 43 | AU37: =SUM(AS37:AT37) -> 65 | AV37: 1
D38: Office | E38: 0.04 | F38: =$E$29*E38 -> 0.376 | G38: =F38*1000 -> 376 | Q38: SNV | R38: 23 | S38: 18 | T38: =SUM(R38:S38) -> 41 | U38: =H420 -> 0.9375 | W38: =T38-AC38 -> 15 | X38: =U38-AD38 -> -0.0625 | Z38: SNV | AA38: =Summary!W159 -> 24 | AB38: =Summary!V159 -> 2 | AC38: =SUM(AA38:AB38) -> 26 | AD38: =Summary!X159 -> 1 | AF38: =T38-AL38 -> -115 | AG38: =U38-AM38 -> -0.0625 | AI38: SNV | AJ38: =Summary!AC159 -> 30 | AK38: =Summary!AB159 -> 126 | AL38: =SUM(AJ38:AK38) -> 156 | AM38: 1 | AO38: =T38-AU38 -> -77 | AP38: =U38-AV38 -> -0.0625 | AR38: SNV | AS38: =Summary!I159 -> 47 | AT38: =SUM(Summary!J159:K159) -> 71 | AU38: =SUM(AS38:AT38) -> 118 | AV38: 1
D39: Single Family / Land Development | E39: 0.03 | F39: =$E$29*E39 -> 0.282 | G39: =F39*1000 -> 282 | Q39: KEY | R39: 22 | S39: 14 | T39: =SUM(R39:S39) -> 36 | U39: =H467 -> 0.85714286 | W39: =T39-AC39 -> -23 | X39: =U39-AD39 -> -0.14285714 | Z39: KEY | AA39: =Summary!W87 -> 28 | AB39: =Summary!V87 -> 31 | AC39: =SUM(AA39:AB39) -> 59 | AD39: =Summary!X87 -> 1 | AF39: =T39-AL39 -> -24 | AG39: =U39-AM39 -> -0.14285714 | AI39: KEY | AJ39: =Summary!AC87 -> 12 | AK39: =Summary!AB87 -> 48 | AL39: =SUM(AJ39:AK39) -> 60 | AM39: 1 | AO39: =T39-AU39 -> -113 | AP39: =U39-AV39 -> -0.14285714 | AR39: KEY | AS39: =Summary!I87 -> 47 | AT39: =SUM(Summary!J87:K87) -> 102 | AU39: =SUM(AS39:AT39) -> 149 | AV39: 1
D40: Land Carry | E40: 0.03 | F40: =$E$29*E40 -> 0.282 | G40: =F40*1000 -> 282 | Q40: WFC | R40: 24 | S40: 29 | T40: =SUM(R40:S40) -> 53 | U40: =H509 -> 0.75 | W40: =T40-AC40 -> -56 | X40: =U40-AD40 -> -0.083333333 | Z40: WFC | AA40: =Summary!W39 -> 24 | AB40: =Summary!V39 -> 85 | AC40: =SUM(AA40:AB40) -> 109 | AD40: =Summary!X39 -> 0.83333333 | AF40: =T40-AL40 -> -171.84 | AG40: =U40-AM40 -> -0.25 | AI40: WFC | AJ40: =Summary!AC39 -> 25 | AK40: =Summary!AB39 -> 199.84 | AL40: =SUM(AJ40:AK40) -> 224.84 | AM40: 1 | AO40: =T40-AU40 -> -83 | AP40: =U40-AV40 -> -0.25 | AR40: WFC | AS40: =Summary!I39 -> 52 | AT40: =SUM(Summary!J39:K39) -> 84 | AU40: =SUM(AS40:AT40) -> 136 | AV40: 1
D41: Multi-use | E41: 0.02 | F41: =$E$29*E41 -> 0.188 | G41: =F41*1000 -> 188 | Q41: JPM | R41: 25 | S41: 15 | T41: =SUM(R41:S41) -> 40 | U41: =H549 -> 0.78571429 | W41: =T41-AC41 -> -59 | X41: =U41-AD41 -> -0.026785714 | Z41: JPM | AA41: =Summary!W54 -> 34 | AB41: =Summary!V54 -> 65 | AC41: =SUM(AA41:AB41) -> 99 | AD41: =Summary!X54 -> 0.8125 | AF41: =T41-AL41 -> 2 | AG41: =U41-AM41 -> -0.21428571 | AI41: JPM | AJ41: =Summary!AC54 -> 18 | AK41: =Summary!AB54 -> 20 | AL41: =SUM(AJ41:AK41) -> 38 | AM41: 1 | AO41: =T41-AU41 -> -83 | AP41: =U41-AV41 -> -0.21428571 | AR41: JPM | AS41: =Summary!I54 -> 49 | AT41: =SUM(Summary!J54:K54) -> 74 | AU41: =SUM(AS41:AT41) -> 123 | AV41: 1
D42: Other | E42: 0.02 | F42: =$E$29*E42 -> 0.188 | G42: =F42*1000 -> 188 | Q42: Total | R42: =SUM(R32:R41) -> 238 | S42: =SUM(S32:S41) -> 160 | T42: =SUM(T32:T41) -> 398 | U42: =AVERAGE(U32:U41) -> 0.8484127 | W42: =T42-AC42 -> -147 | X42: =U42-AD42 -> -0.079027778 | Z42: Total | AA42: =SUM(AA32:AA41) -> 257 | AB42: =SUM(AB32:AB41) -> 288 | AC42: =SUM(AC32:AC41) -> 545 | AD42: =AVERAGE(AD32:AD41) -> 0.92744048 | AF42: =T42-AL42 -> -628.52 | AG42: =U42-AM42 -> -0.1515873 | AI42: Total | AJ42: =SUM(AJ32:AJ41) -> 197 | AK42: =SUM(AK32:AK41) -> 829.52 | AL42: =SUM(AL32:AL41) -> 1026.52 | AM42: =AVERAGE(AM32:AM41) -> 1 | AO42: =T42-AU42 -> -640 | AP42: =U42-AV42 -> -0.1515873 | AR42: Total | AS42: =SUM(AS32:AS41) -> 354 | AT42: =SUM(AT32:AT41) -> 684 | AU42: =SUM(AU32:AU41) -> 1038 | AV42: =AVERAGE(AV32:AV41) -> 1
E43: =SUM(E34:E42) -> 1 | F43: =SUM(F34:F42) -> 9.4 | G43: =SUM(G34:G42) -> 9400 | T43: =T42/AC42-1 -> -0.26972477
Q44: CMA | R44: 35 | S44: 0 | T44: =SUM(R44:S44) -> 35 | U44: =H57 -> 1
D45: Standardized | G45: LLM | Q45: VLY | R45: 22 | S45: 20 | T45: =SUM(R45:S45) -> 42 | U45: =H100 -> 0.92857143
Q46: TD | R46: 21 | S46: 0 | T46: =SUM(R46:S46) -> 21 | U46: =H127 -> 1
D47: Property Type | E47: Amount | G47: Property Type | H47: Amount | Q47: CIBC | R47: 23 | S47: 22 | T47: =SUM(R47:S47) -> 45 | U47: =H197 -> 0.9375
D48: Industrial | E48: =G34 -> 2726 | G48: Industrial | H48: 2726 | J48: =D48=G48 -> TRUE | K48: =E48=H48 -> TRUE | Q48: BKU | R48: 28 | S48: 0 | T48: =SUM(R48:S48) -> 28 | U48: =H154 -> 1
D49: Multi-family | E49: =G35 -> 4512 | G49: Multi-family | H49: 4512 | J49: =D49=G49 -> TRUE | K49: =E49=H49 -> TRUE | Q49: Total | R49: =SUM(R44:R48) -> 129 | S49: =SUM(S44:S48) -> 42 | T49: =SUM(T44:T48) -> 171 | U49: =AVERAGE(U44:U48) -> 0.97321429
D50: Retail | E50: =G37 -> 376 | G50: Retail | H50: 376 | J50: =D50=G50 -> TRUE | K50: =E50=H50 -> TRUE
D51: Office | E51: =G38 -> 376 | G51: Office | H51: 376 | J51: =D51=G51 -> TRUE | K51: =E51=H51 -> TRUE
D52: Residential | E52: =G39 -> 282 | G52: Residential | H52: 282 | J52: =D52=G52 -> TRUE | K52: =E52=H52 -> TRUE
D53: Mixed-use | E53: =G41 -> 188 | G53: Mixed-use | H53: 188 | J53: =D53=G53 -> TRUE | K53: =E53=H53 -> TRUE
D54: Other | E54: =G42+G36+G40 -> 940 | G54: Other | H54: 941 | J54: =D54=G54 -> TRUE | K54: TRUE
D55: Total CRE | E55: =SUM(E48:E54) -> 9400 | G55: Total CRE | H55: =SUM(H48:H54) -> 9401 | J55: =D55=G55 -> TRUE | K55: TRUE
G57: Accuracy | H57: =16/16 -> 1
B74: VLY 4Q24 | D74: CRE Total: | E74: 26.5
D76: Correct
D78: CRE Property Types | E78: Percentage | F78: Loan Amount ($bn) | G78: Loan Amount ($mn)
D79: Retail | E79: 0.17 | F79: =$E$74*E79 -> 4.505 | G79: =F79*1000 -> 4505
D80: Mixed-Use | E80: 0.1 | F80: =$E$74*E80 -> 2.65 | G80: =F80*1000 -> 2650
D81: Office | E81: 0.1 | F81: =$E$74*E81 -> 2.65 | G81: =F81*1000 -> 2650
D82: Healthcare Office | E82: 0.02 | F82: =$E$74*E82 -> 0.53 | G82: =F82*1000 -> 530
D83: Industrial | E83: 0.11 | F83: =$E$74*E83 -> 2.915 | G83: =F83*1000 -> 2915
D84: Healthcare | E84: 0.09 | F84: =$E$74*E84 -> 2.385 | G84: =F84*1000 -> 2385
D85: Specialty & Other | E85: 0.11 | F85: =$E$74*E85 -> 2.915 | G85: =F85*1000 -> 2915
D86: Apartment & Residential | E86: 0.3 | F86: =$E$74*E86 -> 7.95 | G86: =F86*1000 -> 7950
E87: =SUM(E79:E86) -> 1 | F87: =SUM(F79:F86) -> 26.5 | G87: =SUM(G79:G86) -> 26500
D89: Standardized | G89: LLM
D91: Property Type | E91: Amount | G91: Property Type | H91: Amount
D92: Industrial | E92: =G83 -> 2915 | G92: Industrial | H92: 2915 | J92: =D92=G92 -> TRUE | K92: =E92=H92 -> TRUE
D93: Multi-family | E93: =G86 -> 7950 | G93: Multi-family | H93: 7950 | J93: =D93=G93 -> TRUE | K93: =E93=H93 -> TRUE
D94: Retail | E94: =G79 -> 4505 | G94: Retail | H94: 4505 | J94: =D94=G94 -> TRUE | K94: =E94=H94 -> TRUE
D95: Office | E95: =G81+G82 -> 3180 | G95: Office | H95: 3180 | J95: =D95=G95 -> TRUE | K95: =E95=H95 -> TRUE
D96: Mixed-use | E96: =G80 -> 2650 | G96: Mixed-use | H96: 2650 | J96: =D96=G96 -> TRUE | K96: =E96=H96 -> TRUE
D97: Other | E97: =G85+G84 -> 5300 | G97: Other | H97: 4805 | J97: =D97=G97 -> TRUE | K97: =E97=H97 -> FALSE
D98: Total CRE | E98: =SUM(E92:E97) -> 26500 | G98: Total CRE | H98: 26500 | J98: =D98=G98 -> TRUE | K98: =E98=H98 -> TRUE
G100: Accuracy | H100: =13/14 -> 0.92857143
B115: TD 4Q24 | D115: Correct | G115: LLM
D117: Property Type | E117: Amount | G117: Property Type | H117: Amount
D118: Office | E118: 4100 | G118: Office | H118: 4100 | J118: =D118=G118 -> TRUE | K118: =E118=H118 -> TRUE
D119: Retail | E119: 5800 | G119: Retail | H119: 5800 | J119: =D119=G119 -> TRUE | K119: =E119=H119 -> TRUE
D120: Multifamily | E120: 8900 | G120: Multifamily | H120: 8900 | J120: =D120=G120 -> TRUE | K120: =E120=H120 -> TRUE
D121: Residential | E121: 100 | G121: Residential | H121: 100 | J121: =D121=G121 -> TRUE | K121: =E121=H121 -> TRUE
D122: Industrial | E122: 2400 | G122: Industrial | H122: 2400 | J122: =D122=G122 -> TRUE | K122: =E122=H122 -> TRUE
D123: Hotel | E123: 500 | G123: Hotel | H123: 500 | J123: =D123=G123 -> TRUE | K123: =E123=H123 -> TRUE
D124: Other | E124: =7100+100 -> 7200 | G124: Other | H124: 7200 | J124: =D124=G124 -> TRUE | K124: =E124=H124 -> TRUE
D125: Total CRE | E125: =SUM(E118:E124) -> 29000 | G125: Total CRE | H125: 29000 | J125: =D125=G125 -> TRUE | K125: =E125=H125 -> TRUE
G127: Accuracy | H127: =16/16 -> 1
B143: BKU 4Q24 | D143: Correct | G143: LLM
D145: Property Type | E145: Amount | G145: Property Type | H145: Amount
D146: Office | E146: 1769 | G146: Office | H146: 1769 | J146: =D146=G146 -> TRUE | K146: =E146=H146 -> TRUE
D147: Retail | E147: 1098 | G147: Retail | H147: 1098 | J147: =D147=G147 -> TRUE | K147: =E147=H147 -> TRUE
D148: Multifamily | E148: 838 | G148: Multifamily | H148: 838 | J148: =D148=G148 -> TRUE | K148: =E148=H148 -> TRUE
D149: Industrial | E149: 1375 | G149: Industrial | H149: 1375 | J149: =D149=G149 -> TRUE | K149: =E149=H149 -> TRUE
D150: Hotel | E150: 483 | G150: Hotel | H150: 483 | J150: =D150=G150 -> TRUE | K150: =E150=H150 -> TRUE
D151: Other | E151: =89+562 -> 651 | G151: Other | H151: 651 | J151: =D151=G151 -> TRUE | K151: =E151=H151 -> TRUE
D152: Total CRE | E152: =SUM(E146:E151) -> 6214 | G152: Total CRE | H152: 6214 | J152: =D152=G152 -> TRUE | K152: =E152=H152 -> TRUE
G154: Accuracy | H154: =14/14 -> 1
B170: CIBC 4Q24 | D170: CRE Total: | E170: 17.8
D172: Correct
D174: CRE Property Types | E174: Percentage | F174: Loan Amount ($bn) | G174: Loan Amount ($mn)
D175: Multi-family | E175: 0.3 | F175: =$E$170*E175 -> 5.34 | G175: =F175*1000 -> 5340
D176: Retail | E176: 0.08 | F176: =$E$170*E176 -> 1.424 | G176: =F176*1000 -> 1424
D177: Healthcare | E177: 0.04 | F177: =$E$170*E177 -> 0.712 | G177: =F177*1000 -> 712
D178: Hotel | E178: 0.02 | F178: =$E$170*E178 -> 0.356 | G178: =F178*1000 -> 356
D179: Industrial | E179: 0.22 | F179: =$E$170*E179 -> 3.916 | G179: =F179*1000 -> 3916
D180: Office | E180: 0.16 | F180: =$E$170*E180 -> 2.848 | G180: =F180*1000 -> 2848
D181: Other | E181: 0.17 | F181: =$E$170*E181 -> 3.026 | G181: =F181*1000 -> 3026
D182: Residential | E182: 0.01 | F182: =$E$170*E182 -> 0.178 | G182: =F182*1000 -> 178
E183: =SUM(E175:E182) -> 1 | F183: =SUM(F175:F182) -> 17.8 | G183: =SUM(G175:G182) -> 17800
E184: =G183*E181 -> 3026
D185: Standardized | G185: LLM
D187: Property Type | E187: Amount | G187: Property Type | H187: Amount
D188: Industrial | E188: =G179 -> 3916 | G188: Industrial | H188: 3916 | J188: =D188=G188 -> TRUE | K188: =E188=H188 -> TRUE
D189: Multi-family | E189: =G175 -> 5340 | G189: Multi-family | H189: 5340 | J189: =D189=G189 -> TRUE | K189: =E189=H189 -> TRUE
D190: Retail | E190: =G176 -> 1424 | G190: Retail | H190: 1424 | J190: =D190=G190 -> TRUE | K190: =E190=H190 -> TRUE
D191: Office | E191: =G180 -> 2848 | G191: Office | H191: 2848 | J191: =D191=G191 -> TRUE | K191: =E191=H191 -> TRUE
D192: Hotel | E192: =G178 -> 356 | G192: Hotel | H192: 356 | J192: =D192=G192 -> TRUE | K192: =E192=H192 -> TRUE
D193: Residential | E193: =G182 -> 178 | G193: Residential | H193: 178 | J193: =D193=G193 -> TRUE | K193: =E193=H193 -> TRUE
D194: Other | E194: =G181+G177 -> 3738 | G194: Other | H194: 3026 | J194: =D194=G194 -> TRUE | K194: =E194=H194 -> FALSE
D195: Total CRE | E195: =SUM(E188:E194) -> 17800 | G195: Total CRE | H195: 17800 | J195: =D195=G195 -> TRUE | K195: =E195=H195 -> TRUE
G197: Accuracy | H197: =15/16 -> 0.9375
D215: Generic Prompt Test on Database Tickers
B219: BAC 4Q24 | D219: Correct | G219: LLM
D221: Property Type | E221: Amount | G221: Property Type | H221: Amount
D222: Office | E222: 15100 | G222: Office | H222: 15100 | J222: =D222=G222 -> TRUE | K222: =E222=H222 -> TRUE
...

Sheet Two Generic Prompts
D2: Value Table Prompt | L2: Pie Chart Prompt
B3: Prompt (v2)
B29: CMA 4Q24 | D29: CRE Total: | E29: 9.4 | Q29: LLM Generic Prompt Application Feature (4Q24 Presentation) | W29: Time Delta vs V1 | X29: Accuracy Delta | Y29: Time Delta | Z29: Accuracy Delta | AB29: LLM Ticker Specific Prompt (4Q24 Presentation) | AH29: Time Delta | AI29: Accuracy Delta | AK29: Python Script (4Q24 Presentation) | AQ29: Time Delta | AR29: Accuracy Delta | AT29: Manual (4Q24 Presentation)
Q30: (time measured in seconds) | AB30: (time measured in seconds) | AK30: (time measured in seconds) | AT30: (time measured in seconds)
D31: Correct | Q31: Ticker | R31: Execution | S31: Override | T31: Total | U31: Accuracy | AB31: Ticker | AC31: Execution | AD31: Override | AE31: Total | AF31: Accuracy | AK31: Ticker | AL31: Execution | AM31: Adjustment | AN31: Total | AO31: Accuracy | AT31: Ticker | AU31: Execution | AV31: Adjustment | AW31: Total | AX31: Accuracy
Q32: BAC | R32: 35 | S32: 33 | T32: =SUM(R32:S32) -> 68 | U32: =H232 -> 0.55555556 | W32: =T32-'Single Generic Prompt'!T32 -> 6 | X32: =U32-'Single Generic Prompt'!U32 -> 0 | Y32: =T32-AE32 -> 12 | Z32: =U32-AF32 -> -0.14444444 | AB32: BAC | AC32: =Summary!W26 -> 19 | AD32: =Summary!V26 -> 37 | AE32: =SUM(AC32:AD32) -> 56 | AF32: =Summary!X26 -> 0.7 | AH32: =T32-AN32 -> -22 | AI32: =U32-AO32 -> -0.44444444 | AK32: BAC | AL32: =Summary!AC26 -> 28 | AM32: =Summary!AB26 -> 62 | AN32: =SUM(AL32:AM32) -> 90 | AO32: 1 | AQ32: =T32-AW32 -> -8 | AR32: =U32-AX32 -> -0.44444444 | AT32: BAC | AU32: =Summary!I26 -> 30 | AV32: =SUM(Summary!J26:K26) -> 46 | AW32: =SUM(AU32:AV32) -> 76 | AX32: 1
D33: CRE Property Types | E33: Percentage | F33: Loan Amount ($bn) | G33: Loan Amount ($mn) | Q33: FCNCA | R33: 32 | S33: 0 | T33: =SUM(R33:S33) -> 32 | U33: =H261 -> 1 | W33: =T33-'Single Generic Prompt'!T33 -> -5 | X33: =U33-'Single Generic Prompt'!U33 -> 0.071428571 | Y33: =T33-AE33 -> 4 | Z33: =U33-AF33 -> 0 | AB33: FCNCA | AC33: =Summary!W139 -> 26 | AD33: =Summary!V139 -> 2 | AE33: =SUM(AC33:AD33) -> 28 | AF33: =Summary!X139 -> 1 | AH33: =T33-AN33 -> -8 | AI33: =U33-AO33 -> 0 | AK33: FCNCA | AL33: =Summary!AC139 -> 16 | AM33: =Summary!AB139 -> 24 | AN33: =SUM(AL33:AM33) -> 40 | AO33: 1 | AQ33: =T33-AW33 -> -56 | AR33: =U33-AX33 -> 0 | AT33: FCNCA | AU33: =Summary!I139 -> 27 | AV33: =SUM(Summary!J139:K139) -> 61 | AW33: =SUM(AU33:AV33) -> 88 | AX33: 1
D34: Industrial | E34: 0.29 | F34: =$E$29*E34 -> 2.726 | G34: =F34*1000 -> 2726 | Q34: CFG | R34: 29 | S34: 0 | T34: =SUM(R34:S34) -> 29 | U34: =H289 -> 1 | W34: =T34-'Single Generic Prompt'!T34 -> -11 | X34: =U34-'Single Generic Prompt'!U34 -> 0.14285714 | Y34: =T34-AE34 -> 4 | Z34: =U34-AF34 -> 0 | AB34: CFG | AC34: =Summary!W123 -> 23 | AD34: =Summary!V123 -> 2 | AE34: =SUM(AC34:AD34) -> 25 | AF34: =Summary!X123 -> 1 | AH34: =T34-AN34 -> -11 | AI34: =U34-AO34 -> 0 | AK34: CFG | AL34: =Summary!AC123 -> 18 | AM34: =Summary!AB123 -> 22 | AN34: =SUM(AL34:AM34) -> 40 | AO34: 1 | AQ34: =T34-AW34 -> -77 | AR34: =U34-AX34 -> 0 | AT34: CFG | AU34: =Summary!I123 -> 32 | AV34: =SUM(Summary!J123:K123) -> 74 | AW34: =SUM(AU34:AV34) -> 106 | AX34: 1
D35: Multi-family | E35: 0.48 | F35: =$E$29*E35 -> 4.512 | G35: =F35*1000 -> 4512 | Q35: HBAN | R35: 33 | S35: 0 | T35: =SUM(R35:S35) -> 33 | U35: =H316 -> 1 | W35: =T35-'Single Generic Prompt'!T35 -> 12 | X35: =U35-'Single Generic Prompt'!U35 -> 0 | Y35: =T35-AE35 -> 9 | Z35: =U35-AF35 -> 0 | AB35: HBAN | AC35: =Summary!W105 -> 22 | AD35: =Summary!V105 -> 2 | AE35: =SUM(AC35:AD35) -> 24 | AF35: =Summary!X105 -> 1 | AH35: =T35-AN35 -> -127 | AI35: =U35-AO35 -> 0 | AK35: HBAN | AL35: =Summary!AC105 -> 15 | AM35: =Summary!AB105 -> 145 | AN35: =SUM(AL35:AM35) -> 160 | AO35: 1 | AQ35: =T35-AW35 -> -23 | AR35: =U35-AX35 -> 0 | AT35: HBAN | AU35: =Summary!I105 -> 24 | AV35: =SUM(Summary!J105:K105) -> 32 | AW35: =SUM(AU35:AV35) -> 56 | AX35: 1
D36: Self-Storage | E36: 0.05 | F36: =$E$29*E36 -> 0.47 | G36: =F36*1000 -> 470 | Q36: RF | R36: 43 | S36: 6 | T36: =SUM(R36:S36) -> 49 | U36: =H364 -> 0.875 | W36: =T36-'Single Generic Prompt'!T36 -> 8 | X36: =U36-'Single Generic Prompt'!U36 -> 0.0625 | Y36: =T36-AE36 -> -17 | Z36: =U36-AF36 -> -0.125 | AB36: RF | AC36: =Summary!W180 -> 31 | AD36: =Summary!V180 -> 35 | AE36: =SUM(AC36:AD36) -> 66 | AF36: =Summary!X180 -> 1 | AH36: =T36-AN36 -> -123.68 | AI36: =U36-AO36 -> -0.125 | AK36: RF | AL36: =Summary!AC180 -> 20 | AM36: =Summary!AB180 -> 152.68 | AN36: =SUM(AL36:AM36) -> 172.68 | AO36: 1 | AQ36: =T36-AW36 -> -72 | AR36: =U36-AX36 -> -0.125 | AT36: RF | AU36: =Summary!I180 -> 24 | AV36: =SUM(Summary!J180:K180) -> 97 | AW36: =SUM(AU36:AV36) -> 121 | AX36: 1
D37: Retail | E37: 0.04 | F37: =$E$29*E37 -> 0.376 | G37: =F37*1000 -> 376 | Q37: PNC | R37: 28 | S37: 0 | T37: =SUM(R37:S37) -> 28 | U37: =H393 -> 1 | W37: =T37-'Single Generic Prompt'!T37 -> 1 | X37: =U37-'Single Generic Prompt'!U37 -> 0 | Y37: =T37-AE37 -> -25 | Z37: =U37-AF37 -> 0.071428571 | AB37: PNC | AC37: =Summary!W71 -> 26 | AD37: =Summary!V71 -> 27 | AE37: =SUM(AC37:AD37) -> 53 | AF37: =Summary!X71 -> 0.92857143 | AH37: =T37-AN37 -> -17 | AI37: =U37-AO37 -> 0 | AK37: PNC | AL37: =Summary!AC71 -> 15 | AM37: =Summary!AB71 -> 30 | AN37: =SUM(AL37:AM37) -> 45 | AO37: 1 | AQ37: =T37-AW37 -> -37 | AR37: =U37-AX37 -> 0 | AT37: PNC | AU37: =Summary!I71 -> 22 | AV37: =SUM(Summary!J71:K71) -> 43 | AW37: =SUM(AU37:AV37) -> 65 | AX37: 1
D38: Office | E38: 0.04 | F38: =$E$29*E38 -> 0.376 | G38: =F38*1000 -> 376 | Q38: SNV | R38: 32 | S38: 0 | T38: =SUM(R38:S38) -> 32 | U38: =H420 -> 1 | W38: =T38-'Single Generic Prompt'!T38 -> -9 | X38: =U38-'Single Generic Prompt'!U38 -> 0.0625 | Y38: =T38-AE38 -> 6 | Z38: =U38-AF38 -> 0 | AB38: SNV | AC38: =Summary!W159 -> 24 | AD38: =Summary!V159 -> 2 | AE38: =SUM(AC38:AD38) -> 26 | AF38: =Summary!X159 -> 1 | AH38: =T38-AN38 -> -124 | AI38: =U38-AO38 -> 0 | AK38: SNV | AL38: =Summary!AC159 -> 30 | AM38: =Summary!AB159 -> 126 | AN38: =SUM(AL38:AM38) -> 156 | AO38: 1 | AQ38: =T38-AW38 -> -86 | AR38: =U38-AX38 -> 0 | AT38: SNV | AU38: =Summary!I159 -> 47 | AV38: =SUM(Summary!J159:K159) -> 71 | AW38: =SUM(AU38:AV38) -> 118 | AX38: 1
D39: Single Family / Land Development | E39: 0.03 | F39: =$E$29*E39 -> 0.282 | G39: =F39*1000 -> 282 | Q39: KEY | R39: 37 | S39: 0 | T39: =SUM(R39:S39) -> 37 | U39: =H468 -> 1 | W39: =T39-'Single Generic Prompt'!T39 -> 1 | X39: =U39-'Single Generic Prompt'!U39 -> 0.14285714 | Y39: =T39-AE39 -> -22 | Z39: =U39-AF39 -> 0 | AB39: KEY | AC39: =Summary!W87 -> 28 | AD39: =Summary!V87 -> 31 | AE39: =SUM(AC39:AD39) -> 59 | AF39: =Summary!X87 -> 1 | AH39: =T39-AN39 -> -23 | AI39: =U39-AO39 -> 0 | AK39: KEY | AL39: =Summary!AC87 -> 12 | AM39: =Summary!AB87 -> 48 | AN39: =SUM(AL39:AM39) -> 60 | AO39: 1 | AQ39: =T39-AW39 -> -112 | AR39: =U39-AX39 -> 0 | AT39: KEY | AU39: =Summary!I87 -> 47 | AV39: =SUM(Summary!J87:K87) -> 102 | AW39: =SUM(AU39:AV39) -> 149 | AX39: 1
D40: Land Carry | E40: 0.03 | F40: =$E$29*E40 -> 0.282 | G40: =F40*1000 -> 282 | Q40: WFC | R40: 33 | S40: 8 | T40: =SUM(R40:S40) -> 41 | U40: =H510 -> 0.875 | W40: =T40-'Single Generic Prompt'!T40 -> -12 | X40: =U40-'Single Generic Prompt'!U40 -> 0.125 | Y40: =T40-AE40 -> -68 | Z40: =U40-AF40 -> 0.041666667 | AB40: WFC | AC40: =Summary!W39 -> 24 | AD40: =Summary!V39 -> 85 | AE40: =SUM(AC40:AD40) -> 109 | AF40: =Summary!X39 -> 0.83333333 | AH40: =T40-AN40 -> -183.84 | AI40: =U40-AO40 -> -0.125 | AK40: WFC | AL40: =Summary!AC39 -> 25 | AM40: =Summary!AB39 -> 199.84 | AN40: =SUM(AL40:AM40) -> 224.84 | AO40: 1 | AQ40: =T40-AW40 -> -95 | AR40: =U40-AX40 -> -0.125 | AT40: WFC | AU40: =Summary!I39 -> 52 | AV40: =SUM(Summary!J39:K39) -> 84 | AW40: =SUM(AU40:AV40) -> 136 | AX40: 1
D41: Multi-use | E41: 0.02 | F41: =$E$29*E41 -> 0.188 | G41: =F41*1000 -> 188 | Q41: JPM | R41: 30 | S41: 8 | T41: =SUM(R41:S41) -> 38 | U41: =H550 -> 0.85714286 | W41: =T41-'Single Generic Prompt'!T41 -> -2 | X41: =U41-'Single Generic Prompt'!U41 -> 0.071428571 | Y41: =T41-AE41 -> -61 | Z41: =U41-AF41 -> 0.044642857 | AB41: JPM | AC41: =Summary!W54 -> 34 | AD41: =Summary!V54 -> 65 | AE41: =SUM(AC41:AD41) -> 99 | AF41: =Summary!X54 -> 0.8125 | AH41: =T41-AN41 -> 0 | AI41: =U41-AO41 -> -0.14285714 | AK41: JPM | AL41: =Summary!AC54 -> 18 | AM41: =Summary!AB54 -> 20 | AN41: =SUM(AL41:AM41) -> 38 | AO41: 1 | AQ41: =T41-AW41 -> -85 | AR41: =U41-AX41 -> -0.14285714 | AT41: JPM | AU41: =Summary!I54 -> 49 | AV41: =SUM(Summary!J54:K54) -> 74 | AW41: =SUM(AU41:AV41) -> 123 | AX41: 1
D42: Other | E42: 0.02 | F42: =$E$29*E42 -> 0.188 | G42: =F42*1000 -> 188 | Q42: Total | R42: =SUM(R32:R41) -> 332 | S42: =SUM(S32:S41) -> 55 | T42: =SUM(T32:T41) -> 387 | U42: =AVERAGE(U32:U41) -> 0.91626984 | W42: =T42-'Single Generic Prompt'!T42 -> -11 | X42: =U42-'Single Generic Prompt'!U42 -> 0.067857143 | Y42: =T42-AE42 -> -158 | Z42: =U42-AF42 -> -0.011170635 | AB42: Total | AC42: =SUM(AC32:AC41) -> 257 | AD42: =SUM(AD32:AD41) -> 288 | AE42: =SUM(AE32:AE41) -> 545 | AF42: =AVERAGE(AF32:AF41) -> 0.92744048 | AH42: =T42-AN42 -> -639.52 | AI42: =U42-AO42 -> -0.083730159 | AK42: Total | AL42: =SUM(AL32:AL41) -> 197 | AM42: =SUM(AM32:AM41) -> 829.52 | AN42: =SUM(AN32:AN41) -> 1026.52 | AO42: =AVERAGE(AO32:AO41) -> 1 | AQ42: =T42-AW42 -> -651 | AR42: =U42-AX42 -> -0.083730159 | AT42: Total | AU42: =SUM(AU32:AU41) -> 354 | AV42: =SUM(AV32:AV41) -> 684 | AW42: =SUM(AW32:AW41) -> 1038 | AX42: =AVERAGE(AX32:AX41) -> 1
E43: =SUM(E34:E42) -> 1 | F43: =SUM(F34:F42) -> 9.4 | G43: =SUM(G34:G42) -> 9400 | R43: =R42/'Single Generic Prompt'!R42-1 -> 0.39495798 | S43: =S42/'Single Generic Prompt'!S42-1 -> -0.65625 | T43: =T42/'Single Generic Prompt'!T42-1 -> -0.027638191 | U43: =T42/AE42-1 -> -0.28990826
Q44: CMA | R44: 36 | S44: 0 | T44: =SUM(R44:S44) -> 36 | U44: =H57 -> 1 | W44: =T44-'Single Generic Prompt'!T44 -> 1 | X44: =U44-'Single Generic Prompt'!U44 -> 0
D45: Standardized | G45: LLM | Q45: VLY | R45: 36 | S45: 0 | T45: =SUM(R45:S45) -> 36 | U45: =H100 -> 1 | W45: =T45-'Single Generic Prompt'!T45 -> -6 | X45: =U45-'Single Generic Prompt'!U45 -> 0.071428571
Q46: TD | R46: 29 | S46: 0 | T46: =SUM(R46:S46) -> 29 | U46: =H127 -> 1 | W46: =T46-'Single Generic Prompt'!T46 -> 8 | X46: =U46-'Single Generic Prompt'!U46 -> 0
D47: Property Type | E47: Amount | G47: Property Type | H47: Amount | Q47: CIBC | R47: 38 | S47: 0 | T47: =SUM(R47:S47) -> 38 | U47: =H197 -> 1 | W47: =T47-'Single Generic Prompt'!T47 -> -7 | X47: =U47-'Single Generic Prompt'!U47 -> 0.0625
D48: Industrial | E48: =G34 -> 2726 | G48: Industrial | H48: 2726 | J48: =D48=G48 -> TRUE | K48: =E48=H48 -> TRUE | Q48: BKU | R48: 25 | S48: 0 | T48: =SUM(R48:S48) -> 25 | U48: =H154 -> 1 | W48: =T48-'Single Generic Prompt'!T48 -> -3 | X48: =U48-'Single Generic Prompt'!U48 -> 0
D49: Multi-family | E49: =G35 -> 4512 | G49: Multi-family | H49: 4512 | J49: =D49=G49 -> TRUE | K49: =E49=H49 -> TRUE | Q49: Total | R49: =SUM(R44:R48) -> 164 | S49: =SUM(S44:S48) -> 0 | T49: =SUM(T44:T48) -> 164 | U49: =AVERAGE(U44:U48) -> 1 | W49: =T49-'Single Generic Prompt'!T49 -> -7 | X49: =U49-'Single Generic Prompt'!U49 -> 0.026785714
D50: Retail | E50: =G37 -> 376 | G50: Retail | H50: 376 | J50: =D50=G50 -> TRUE | K50: =E50=H50 -> TRUE | R50: =R49/'Single Generic Prompt'!R49-1 -> 0.27131783 | S50: =S49/'Single Generic Prompt'!S49-1 -> -1 | T50: =T49/'Single Generic Prompt'!T49-1 -> -0.040935673
D51: Office | E51: =G38 -> 376 | G51: Office | H51: 376 | J51: =D51=G51 -> TRUE | K51: =E51=H51 -> TRUE
D52: Residential | E52: =G39 -> 282 | G52: Residential | H52: 282 | J52: =D52=G52 -> TRUE | K52: =E52=H52 -> TRUE
D53: Mixed-use | E53: =G41 -> 188 | G53: Mixed-use | H53: 188 | J53: =D53=G53 -> TRUE | K53: =E53=H53 -> TRUE
D54: Other | E54: =G42+G36+G40 -> 940 | G54: Other | H54: 940 | J54: =D54=G54 -> TRUE | K54: =E54=H54 -> TRUE
D55: Total CRE | E55: =SUM(E48:E54) -> 9400 | G55: Total CRE | H55: 9400 | J55: =D55=G55 -> TRUE | K55: =E55=H55 -> TRUE
G57: Accuracy | H57: 1
B74: VLY 4Q24 | D74: CRE Total: | E74: 26.5
D76: Correct
D78: CRE Property Types | E78: Percentage | F78: Loan Amount ($bn) | G78: Loan Amount ($mn)
D79: Retail | E79: 0.17 | F79: =$E$74*E79 -> 4.505 | G79: =F79*1000 -> 4505
D80: Mixed-Use | E80: 0.1 | F80: =$E$74*E80 -> 2.65 | G80: =F80*1000 -> 2650
D81: Office | E81: 0.1 | F81: =$E$74*E81 -> 2.65 | G81: =F81*1000 -> 2650
D82: Healthcare Office | E82: 0.02 | F82: =$E$74*E82 -> 0.53 | G82: =F82*1000 -> 530
D83: Industrial | E83: 0.11 | F83: =$E$74*E83 -> 2.915 | G83: =F83*1000 -> 2915
D84: Healthcare | E84: 0.09 | F84: =$E$74*E84 -> 2.385 | G84: =F84*1000 -> 2385
D85: Specialty & Other | E85: 0.11 | F85: =$E$74*E85 -> 2.915 | G85: =F85*1000 -> 2915
D86: Apartment & Residential | E86: 0.3 | F86: =$E$74*E86 -> 7.95 | G86: =F86*1000 -> 7950
E87: =SUM(E79:E86) -> 1 | F87: =SUM(F79:F86) -> 26.5 | G87: =SUM(G79:G86) -> 26500
D89: Standardized | G89: LLM
D91: Property Type | E91: Amount | G91: Property Type | H91: Amount
D92: Industrial | E92: =G83 -> 2915 | G92: Industrial | H92: 2915 | J92: =D92=G92 -> TRUE | K92: =E92=H92 -> TRUE
D93: Multi-family | E93: =G86 -> 7950 | G93: Multi-family | H93: 7950 | J93: =D93=G93 -> TRUE | K93: =E93=H93 -> TRUE
D94: Retail | E94: =G79 -> 4505 | G94: Retail | H94: 4505 | J94: =D94=G94 -> TRUE | K94: =E94=H94 -> TRUE
D95: Office | E95: =G81+G82 -> 3180 | G95: Office | H95: 3180 | J95: =D95=G95 -> TRUE | K95: =E95=H95 -> TRUE
D96: Mixed-use | E96: =G80 -> 2650 | G96: Mixed-use | H96: 2650 | J96: =D96=G96 -> TRUE | K96: =E96=H96 -> TRUE
D97: Other | E97: =G85+G84 -> 5300 | G97: Other | H97: 5300 | J97: =D97=G97 -> TRUE | K97: =E97=H97 -> TRUE
D98: Total CRE | E98: =SUM(E92:E97) -> 26500 | G98: Total CRE | H98: 26500 | J98: =D98=G98 -> TRUE | K98: =E98=H98 -> TRUE
G100: Accuracy | H100: 1
B115: TD 4Q24 | D115: Correct | G115: LLM
D117: Property Type | E117: Amount | G117: Property Type | H117: Amount
D118: Office | E118: 4100 | G118: Office | H118: 4100 | J118: =D118=G118 -> TRUE | K118: =E118=H118 -> TRUE
D119: Retail | E119: 5800 | G119: Retail | H119: 5800 | J119: =D119=G119 -> TRUE | K119: =E119=H119 -> TRUE
D120: Multifamily | E120: 8900 | G120: Multifamily | H120: 8900 | J120: =D120=G120 -> TRUE | K120: =E120=H120 -> TRUE
D121: Residential | E121: 100 | G121: Residential | H121: 100 | J121: =D121=G121 -> TRUE | K121: =E121=H121 -> TRUE
D122: Industrial | E122: 2400 | G122: Industrial | H122: 2400 | J122: =D122=G122 -> TRUE | K122: =E122=H122 -> TRUE
D123: Lodging | E123: 500 | G123: Lodging | H123: 500 | J123: =D123=G123 -> TRUE | K123: =E123=H123 -> TRUE
D124: Other | E124: =7100+100 -> 7200 | G124: Other | H124: 7200 | J124: =D124=G124 -> TRUE | K124: =E124=H124 -> TRUE
D125: Total CRE | E125: =SUM(E118:E124) -> 29000 | G125: Total CRE | H125: 29000 | J125: =D125=G125 -> TRUE | K125: =E125=H125 -> TRUE
G127: Accuracy | H127: 1
B143: BKU 4Q24 | D143: Correct | G143: LLM
D145: Property Type | E145: Amount | G145: Property Type | H145: Amount
D146: Office | E146: 1769 | G146: Office | H146: 1769 | J146: =D146=G146 -> TRUE | K146: =E146=H146 -> TRUE
D147: Retail | E147: 1098 | G147: Retail | H147: 1098 | J147: =D147=G147 -> TRUE | K147: =E147=H147 -> TRUE
D148: Multifamily | E148: 838 | G148: Multifamily | H148: 838 | J148: =D148=G148 -> TRUE | K148: =E148=H148 -> TRUE
D149: Industrial | E149: 1375 | G149: Industrial | H149: 1375 | J149: =D149=G149 -> TRUE | K149: =E149=H149 -> TRUE
D150: Lodging | E150: 483 | G150: Lodging | H150: 483 | J150: =D150=G150 -> TRUE | K150: =E150=H150 -> TRUE
D151: Other | E151: =89+562 -> 651 | G151: Other | H151: 651 | J151: =D151=G151 -> TRUE | K151: =E151=H151 -> TRUE
D152: Total CRE | E152: =SUM(E146:E151) -> 6214 | G152: Total CRE | H152: 6214 | J152: =D152=G152 -> TRUE | K152: =E152=H152 -> TRUE
G154: Accuracy | H154: 1
B170: CIBC 4Q24 | D170: CRE Total: | E170: 17.8
D172: Correct
D174: CRE Property Types | E174: Percentage | F174: Loan Amount ($bn) | G174: Loan Amount ($mn)
D175: Multi-family | E175: 0.3 | F175: =$E$170*E175 -> 5.34 | G175: =F175*1000 -> 5340
D176: Retail | E176: 0.08 | F176: =$E$170*E176 -> 1.424 | G176: =F176*1000 -> 1424
D177: Healthcare | E177: 0.04 | F177: =$E$170*E177 -> 0.712 | G177: =F177*1000 -> 712
D178: Hotel | E178: 0.02 | F178: =$E$170*E178 -> 0.356 | G178: =F178*1000 -> 356
D179: Industrial | E179: 0.22 | F179: =$E$170*E179 -> 3.916 | G179: =F179*1000 -> 3916
D180: Office | E180: 0.16 | F180: =$E$170*E180 -> 2.848 | G180: =F180*1000 -> 2848
D181: Other | E181: 0.17 | F181: =$E$170*E181 -> 3.026 | G181: =F181*1000 -> 3026
D182: Residential | E182: 0.01 | F182: =$E$170*E182 -> 0.178 | G182: =F182*1000 -> 178
E183: =SUM(E175:E182) -> 1 | F183: =SUM(F175:F182) -> 17.8 | G183: =SUM(G175:G182) -> 17800
E184: =G183*E181 -> 3026
D185: Standardized | G185: LLM
D187: Property Type | E187: Amount | G187: Property Type | H187: Amount
D188: Industrial | E188: =G179 -> 3916 | G188: Industrial | H188: 3916 | J188: =D188=G188 -> TRUE | K188: =E188=H188 -> TRUE
D189: Multi-family | E189: =G175 -> 5340 | G189: Multi-family | H189: 5340 | J189: =D189=G189 -> TRUE | K189: =E189=H189 -> TRUE
D190: Retail | E190: =G176 -> 1424 | G190: Retail | H190: 1424 | J190: =D190=G190 -> TRUE | K190: =E190=H190 -> TRUE
D191: Office | E191: =G180 -> 2848 | G191: Office | H191: 2848 | J191: =D191=G191 -> TRUE | K191: =E191=H191 -> TRUE
D192: Hotel | E192: =G178 -> 356 | G192: Hotel | H192: 356 | J192: =D192=G192 -> TRUE | K192: =E192=H192 -> TRUE
D193: Residential | E193: =G182 -> 178 | G193: Residential | H193: 178 | J193: =D193=G193 -> TRUE | K193: =E193=H193 -> TRUE
D194: Other | E194: =G181+G177 -> 3738 | G194: Other | H194: 3738 | J194: =D194=G194 -> TRUE | K194: =E194=H194 -> TRUE
D195: Total CRE | E195: =SUM(E188:E194) -> 17800 | G195: Total CRE | H195: 17800 | J195: =D195=G195 -> TRUE | K195: =E195=H195 -> TRUE
G197: Accuracy | H197: 1
D215: Generic Prompt Test on Database Tickers
B219: BAC 4Q24 | D219: Correct | G219: LLM
D221: Property Type | E221: Amount | G221: Property Type | H221: Amount
...

Sheet BAC

Sheet BAC Manual
A2: 4Q24 | B2: Manual 4Q24 (10-Q)
B4: CRE Property Type | C4: Amount ($bn) | E4: Ticker | F4: Quarter | G4: CRE Property Type | H4: Amount ($bn) | I4: Unit | J4: Currency | K4: Category
B5: Office | C5: 15061 | E5: BAC | F5: 4Q24 | G5: Office | H5: 15061 | I5: mn | J5: USD | K5: CRE
B6: Industrial / Warehouse | C6: 13166 | E6: BAC | F6: 4Q24 | G6: Industrial | H6: 13166 | I6: mn | J6: USD | K6: CRE
B7: Multi-family rental | C7: 11022 | E7: BAC | F7: 4Q24 | G7: Multi-family | H7: 11022 | I7: mn | J7: USD | K7: CRE
B8: Shopping centers / Retail | C8: 5603 | E8: BAC | F8: 4Q24 | G8: Retail | H8: 5603 | I8: mn | J8: USD | K8: CRE
B9: Hotel / Motels | C9: 4680 | E9: BAC | F9: 4Q24 | G9: Lodging | H9: 4680 | I9: mn | J9: USD | K9: CRE
B10: Multi-use | C10: 2162 | E10: BAC | F10: 4Q24 | G10: Mixed-use | H10: 2162 | I10: mn | J10: USD | K10: CRE
B11: Other | C11: 13179 | E11: BAC | F11: 4Q24 | G11: Other | H11: 13179 | I11: mn | J11: USD | K11: CRE
B12: Residential | C12: 857 | E12: BAC | F12: 4Q24 | G12: Residential | H12: 857 | I12: mn | J12: USD | K12: CRE
B13: Total CRE | C13: =SUM(C5:C12) -> 65730 | E13: BAC | F13: 4Q24 | G13: Total CRE | H13: =SUM(H5:H12) -> 65730 | I13: mn | J13: USD | K13: CRE
A15: 3Q24 | B15: Manual 3Q24 (10-Q)
B17: CRE Property Type | C17: Amount ($bn) | E17: Ticker | F17: Quarter | G17: CRE Property Type | H17: Amount ($bn) | I17: Unit | J17: Currency | K17: Category
B18: Office | C18: 15768 | E18: BAC | F18: 3Q24 | G18: Office | H18: 15768 | I18: mn | J18: USD | K18: CRE
B19: Industrial / Warehouse | C19: 13912 | E19: BAC | F19: 3Q24 | G19: Industrial | H19: 13912 | I19: mn | J19: USD | K19: CRE
B20: Multi-family rental | C20: 11670 | E20: BAC | F20: 3Q24 | G20: Multi-family | H20: 11670 | I20: mn | J20: USD | K20: CRE
B21: Shopping centers / Retail | C21: 5423 | E21: BAC | F21: 3Q24 | G21: Retail | H21: 5423 | I21: mn | J21: USD | K21: CRE
B22: Hotel / Motels | C22: 4717 | E22: BAC | F22: 3Q24 | G22: Lodging | H22: 4717 | I22: mn | J22: USD | K22: CRE
B23: Multi-use | C23: 2073 | E23: BAC | F23: 3Q24 | G23: Mixed-use | H23: 2073 | I23: mn | J23: USD | K23: CRE
B24: Other | C24: 14159 | E24: BAC | F24: 3Q24 | G24: Other | H24: 14159 | I24: mn | J24: USD | K24: CRE
B25: Residential | C25: 698 | E25: BAC | F25: 3Q24 | G25: Residential | H25: 698 | I25: mn | J25: USD | K25: CRE
B26: Total CRE | C26: =SUM(C18:C25) -> 68420 | E26: BAC | F26: 3Q24 | G26: Total CRE | H26: 68420 | I26: mn | J26: USD | K26: CRE
A29: 2Q24 | B29: Manual 2Q24 (10-Q)
B31: CRE Property Type | C31: Amount ($bn) | E31: Ticker | F31: Quarter | G31: CRE Property Type | H31: Amount ($bn) | I31: Unit | J31: Currency | K31: Category
B32: Office | C32: 16314 | E32: BAC | F32: 2Q24 | G32: Office | H32: 16314 | I32: mn | J32: USD | K32: CRE
B33: Industrial / Warehouse | C33: 14675 | E33: BAC | F33: 2Q24 | G33: Industrial | H33: 14675 | I33: mn | J33: USD | K33: CRE
B34: Multi-family rental | C34: 11561 | E34: BAC | F34: 2Q24 | G34: Multi-family | H34: 11561 | I34: mn | J34: USD | K34: CRE
B35: Shopping centers / Retail | C35: 5640 | E35: BAC | F35: 2Q24 | G35: Retail | H35: 5640 | I35: mn | J35: USD | K35: CRE
B36: Hotel / Motels | C36: 5051 | E36: BAC | F36: 2Q24 | G36: Lodging | H36: 5051 | I36: mn | J36: USD | K36: CRE
B37: Multi-use | C37: 2131 | E37: BAC | F37: 2Q24 | G37: Mixed-use | H37: 2131 | I37: mn | J37: USD | K37: CRE
B38: Other | C38: 14080 | E38: BAC | F38: 2Q24 | G38: Other | H38: 14080 | I38: mn | J38: USD | K38: CRE
B39: Residential | C39: 832 | E39: BAC | F39: 2Q24 | G39: Residential | H39: 832 | I39: mn | J39: USD | K39: CRE
B40: Total CRE | C40: =SUM(C32:C39) -> 70284 | E40: BAC | F40: 2Q24 | G40: Total CRE | H40: =SUM(H32:H39) -> 70284 | I40: mn | J40: USD | K40: CRE
A43: 1Q24 | B43: Manual 1Q24 (10-Q)
B45: CRE Property Type | C45: Amount ($bn) | E45: Ticker | F45: Quarter | G45: CRE Property Type | H45: Amount ($bn) | I45: Unit | J45: Currency | K45: Category
B46: Office | C46: 17442 | E46: BAC | F46: 1Q24 | G46: Office | H46: 17442 | I46: mn | J46: USD | K46: CRE
B47: Industrial / Warehouse | C47: 14635 | E47: BAC | F47: 1Q24 | G47: Industrial | H47: 14635 | I47: mn | J47: USD | K47: CRE
B48: Multi-family rental | C48: 11414 | E48: BAC | F48: 1Q24 | G48: Multi-family | H48: 11414 | I48: mn | J48: USD | K48: CRE
B49: Shopping centers / Retail | C49: 5682 | E49: BAC | F49: 1Q24 | G49: Retail | H49: 5682 | I49: mn | J49: USD | K49: CRE
B50: Hotel / Motels | C50: 5434 | E50: BAC | F50: 1Q24 | G50: Lodging | H50: 5434 | I50: mn | J50: USD | K50: CRE
B51: Multi-use | C51: 2491 | E51: BAC | F51: 1Q24 | G51: Mixed-use | H51: 2491 | I51: mn | J51: USD | K51: CRE
B52: Other | C52: 13835 | E52: BAC | F52: 1Q24 | G52: Other | H52: 13835 | I52: mn | J52: USD | K52: CRE
B53: Residential | C53: 719 | E53: BAC | F53: 1Q24 | G53: Residential | H53: 719 | I53: mn | J53: USD | K53: CRE
B54: Total CRE | C54: =SUM(C46:C53) -> 71652 | E54: BAC | F54: 1Q24 | G54: Total CRE | H54: =SUM(H46:H53) -> 71652 | I54: mn | J54: USD | K54: CRE

Sheet BAC LLM API
B2: 4Q24 AI API Script
B29: Correct | E29: LLM
B31: CRE Property Type | C31: Loan Amount | E31: CRE Property Type | F31: Loan Amount | H31: =B31=E31 -> TRUE | I31: =C31=F31 -> TRUE
B32: Office | C32: 15.1 | E32: Office | F32: 15.1 | H32: =B32=E32 -> TRUE | I32: =C32=F32 -> TRUE
B33: Industrial | C33: 13.2 | E33: Industrial | F33: 5.6 | H33: =B33=E33 -> TRUE | I33: =C33=F33 -> FALSE
B34: Multi-family | C34: 11 | E34: Multi-family | F34: 13.2 | H34: =B34=E34 -> TRUE | I34: =C34=F34 -> FALSE
B35: Retail | C35: 5.6 | E35: Retail | F35: 4.7 | H35: =B35=E35 -> TRUE | I35: =C35=F35 -> FALSE
B36: Lodging | C36: 4.7 | E36: Lodging | F36: 11 | H36: =B36=E36 -> TRUE | I36: =C36=F36 -> FALSE
B37: Mixed-use | C37: 2.2 | E37: Mixed-use | F37: 2.2 | H37: =B37=E37 -> TRUE | I37: =C37=F37 -> TRUE
B38: Residential | C38: 0.9 | E38: Residential | F38: 13.2 | H38: =B38=E38 -> TRUE | I38: =C38=F38 -> FALSE
B39: Other | C39: 13.2 | E39: Other | F39: 0.9 | H39: =B39=E39 -> TRUE | I39: =C39=F39 -> FALSE
B40: Total | C40: 66 | E40: Total | F40: =SUM(F32:F39) -> 65.9 | H40: =B40=E40 -> TRUE | I40: TRUE
E42: Accuracy | F42: =14/20 -> 0.7
B45: 3Q24 AI API Script
B70: Correct | E70: LLM
B72: CRE Property Type | C72: Loan Amount | E72: CRE Property Type | F72: Loan Amount | H72: =B72=E72 -> TRUE | I72: =C72=F72 -> TRUE
B73: Office | C73: 15.8 | E73: Office | F73: 15.8 | H73: =B73=E73 -> TRUE | I73: =C73=F73 -> TRUE
B74: Industrial | C74: 13.9 | E74: Industrial | F74: 13.9 | H74: =B74=E74 -> TRUE | I74: =C74=F74 -> TRUE
B75: Multi-family | C75: 11.7 | E75: Multi-family | F75: 11.7 | H75: =B75=E75 -> TRUE | I75: =C75=F75 -> TRUE
B76: Retail | C76: 5.4 | E76: Retail | F76: 5.4 | H76: =B76=E76 -> TRUE | I76: =C76=F76 -> TRUE
B77: Lodging | C77: 4.7 | E77: Lodging | F77: 4.7 | H77: =B77=E77 -> TRUE | I77: =C77=F77 -> TRUE
B78: Multi-use | C78: 2.1 | E78: Multi-use | F78: 2.1 | H78: =B78=E78 -> TRUE | I78: =C78=F78 -> TRUE
B79: Residential | C79: 0.7 | E79: Residential | F79: 14.2 | H79: =B79=E79 -> TRUE | I79: =C79=F79 -> FALSE
B80: Other | C80: 14.2 | E80: Other | F80: 0.7 | H80: =B80=E80 -> TRUE | I80: =C80=F80 -> FALSE
B81: Total | C81: 68 | E81: Total | F81: =SUM(F73:F80) -> 68.5 | H81: =B81=E81 -> TRUE | I81: TRUE
E83: Accuracy | F83: =18/20 -> 0.9
B86: 2Q24 AI API Script
B107: Correct | E107: LLM
B109: CRE Property Type | C109: Loan Amount | E109: CRE Property Type | F109: Loan Amount
B110: Office | C110: 16.3 | E110: Office | F110: 16.3 | H110: =B110=E110 -> TRUE | I110: =C110=F110 -> TRUE
B111: Industrial | C111: 14.7 | E111: Industrial | F111: 14.7 | H111: =B111=E111 -> TRUE | I111: =C111=F111 -> TRUE
B112: Multi-family | C112: 11.6 | E112: Multi-family | F112: 11.6 | H112: =B112=E112 -> TRUE | I112: =C112=F112 -> TRUE
B113: Retail | C113: 5.6 | E113: Retail | F113: 5.6 | H113: =B113=E113 -> TRUE | I113: =C113=F113 -> TRUE
B114: Lodging | C114: 5.1 | E114: Lodging | F114: 5.1 | H114: =B114=E114 -> TRUE | I114: =C114=F114 -> TRUE
B115: Mixed-use | C115: 2.1 | E115: Mixed-use | F115: 2.1 | H115: =B115=E115 -> TRUE | I115: =C115=F115 -> TRUE
B116: Residential | C116: 0.8 | E116: Residential | F116: 0.8 | H116: =B116=E116 -> TRUE | I116: =C116=F116 -> TRUE
B117: Other | C117: 14.1 | E117: Other | F117: 14.1 | H117: =B117=E117 -> TRUE | I117: =C117=F117 -> TRUE
B118: Total | C118: =SUM(C110:C117) -> 70.3 | E118: Total | F118: =SUM(F110:F117) -> 70.3 | H118: =B118=E118 -> TRUE | I118: =C118=F118 -> TRUE
E120: Accuracy | F120: =30/30 -> 1
B122: 1Q24 AI API Script
B145: Correct | E145: LLM
B147: CRE Property Type | C147: Loan Amount | E147: CRE Property Type | F147: Loan Amount
B148: Office | C148: 17.4 | E148: Office | F148: 17.4 | H148: =B148=E148 -> TRUE | I148: =C148=F148 -> TRUE
B149: Industrial | C149: 14.6 | E149: Industrial | F149: 14.6 | H149: =B149=E149 -> TRUE | I149: =C149=F149 -> TRUE
B150: Multi-family | C150: 11.4 | E150: Multi-family | F150: 11.4 | H150: =B150=E150 -> TRUE | I150: =C150=F150 -> TRUE
B151: Retail | C151: 5.7 | E151: Retail | F151: 5.7 | H151: =B151=E151 -> TRUE | I151: =C151=F151 -> TRUE
B152: Lodging | C152: 5.4 | E152: Lodging | F152: 5.4 | H152: =B152=E152 -> TRUE | I152: =C152=F152 -> TRUE
B153: Mixed-use | C153: 2.5 | E153: Mixed-use | F153: 2.5 | H153: =B153=E153 -> TRUE | I153: =C153=F153 -> TRUE
B154: Residential | C154: 0.7 | E154: Residential | F154: 0.7 | H154: =B154=E154 -> TRUE | I154: =C154=F154 -> TRUE
B155: Other | C155: 13.8 | E155: Other | F155: 13.8 | H155: =B155=E155 -> TRUE | I155: =C155=F155 -> TRUE
B156: Total | C156: =SUM(C148:C155) -> 71.5 | E156: Total | F156: =SUM(F148:F155) -> 71.5 | H156: =B156=E156 -> TRUE | I156: =C156=F156 -> TRUE
E158: Accuracy | F158: =30/30 -> 1

Sheet BAC Script
B2: Script 4Q24 (10-Q) | L2: Script 3Q24 (10-Q)
B14: Script 1Q24 (10-Q) | L14: Script 2Q24 (10-Q)

Sheet JPM

Sheet JPM Manual
A2: 4Q24 | B2: Manual 4Q24 (10-Q)
B4: CRE Property Type | C4: Credit Exposure | D4: % Drawn | E4: Outstanding | H4: CRE Property Type | I4: Outstanding
B5: Multifamily | C5: 124081 | D5: 0.92 | E5: =D5*C5 -> 114154.52 | H5: Multi-family | I5: =E5 -> 114154.52
B6: Industrial | C6: 19109 | D6: 0.72 | E6: =D6*C6 -> 13758.48 | H6: Industrial | I6: =E6 -> 13758.48
B7: Other Income Producing Properties | C7: 16569 | D7: 0.63 | E7: =D7*C7 -> 10438.47 | H7: Office | I7: =E8 -> 13251.6
B8: Office | C8: 16360 | D8: 0.81 | E8: =D8*C8 -> 13251.6 | H8: Retail | I8: =E10 -> 9189.75
B9: Services and Non Income Producing | C9: 14104 | D9: 0.46 | E9: =D9*C9 -> 6487.84 | H9: Lodging | I9: =E11 -> 2424.22
B10: Retail | C10: 12253 | D10: 0.75 | E10: =D10*C10 -> 9189.75 | H10: Other | I10: =SUM(E9,E7) -> 16926.31
B11: Lodging | C11: 4574 | D11: 0.53 | E11: =D11*C11 -> 2424.22 | H11: Total CRE | I11: =SUM(I5:I10) -> 169704.88
B12: Total CRE | C12: =SUM(C5:C11) -> 207050 | D12: =E12/C12 -> 0.81963236 | E12: =SUM(E5:E11) -> 169704.88
A27: 3Q24 | B27: Manual 3Q24 (10-Q)
B29: CRE Property Type | C29: Credit Exposure | D29: % Drawn | E29: Outstanding | H29: CRE Property Type | I29: Outstanding | L29: Ticker | M29: Quarter | N29: CRE Property Type | O29: Loan Amount | P29: Unit | Q29: Currency | R29: Category
B30: Multi-family | C30: 125410 | D30: 0.91 | E30: =D30*C30 -> 114123.1 | H30: Multi-family | I30: 114123.1 | L30: JPM | M30: 3Q24 | N30: Multi-family | O30: 114123.1 | P30: mn | Q30: USD | R30: CRE
B31: Industrial | C31: 19282 | D31: 0.74 | E31: =D31*C31 -> 14268.68 | H31: Industrial | I31: 14268.68 | L31: JPM | M31: 3Q24 | N31: Industrial | O31: 14268.68 | P31: mn | Q31: USD | R31: CRE
B32: Office | C32: 16926 | D32: 0.81 | E32: =D32*C32 -> 13710.06 | H32: Office | I32: 13710.06 | L32: JPM | M32: 3Q24 | N32: Office | O32: 13710.06 | P32: mn | Q32: USD | R32: CRE
B33: Other Income Producing Properties | C33: 15011 | D33: 0.67 | E33: =D33*C33 -> 10057.37 | H33: Retail | I33: 8860.29 | L33: JPM | M33: 3Q24 | N33: Retail | O33: 8860.29 | P33: mn | Q33: USD | R33: CRE
B34: Services and Non Income Producing | C34: 14557 | D34: 0.51 | E34: =D34*C34 -> 7424.07 | H34: Lodging | I34: 2509.65 | L34: JPM | M34: 3Q24 | N34: Lodging | O34: 2509.65 | P34: mn | Q34: USD | R34: CRE
B35: Retail | C35: 12841 | D35: 0.69 | E35: =D35*C35 -> 8860.29 | H35: Other | I35: =SUM(E33:E34) -> 17481.44 | L35: JPM | M35: 3Q24 | N35: Other | O35: 17481.44 | P35: mn | Q35: USD | R35: CRE
B36: Lodging | C36: 4563 | D36: 0.55 | E36: =D36*C36 -> 2509.65 | H36: Total CRE | I36: =SUM(I30:I35) -> 170953.22 | L36: JPM | M36: 3Q24 | N36: Total CRE | O36: =SUM(O30:O35) -> 170953.22 | P36: mn | Q36: USD | R36: CRE
B37: Total CRE | C37: =SUM(C30:C36) -> 208590 | D37: =E37/C37 -> 0.81956575 | E37: =SUM(E30:E36) -> 170953.22
A54: 2Q24 | B54: Manual 2Q24 (10-Q)
B56: CRE Property Type | C56: Credit Exposure | D56: % Drawn | E56: Outstanding | H56: CRE Property Type | I56: Outstanding
B57: Multifamily | C57: 122991 | D57: 0.91 | E57: =D57*C57 -> 111921.81 | H57: Multi-family | I57: =E57 -> 111921.81
B58: Industrial | C58: 20871 | D58: 0.7 | E58: =D58*C58 -> 14609.7 | H58: Industrial | I58: =E58 -> 14609.7
B59: Office | C59: 16460 | D59: 0.84 | E59: =D59*C59 -> 13826.4 | H59: Office | I59: =E59 -> 13826.4
B60: Other Income Producing Properties | C60: 14813 | D60: 0.64 | E60: =D60*C60 -> 9480.32 | H60: Retail | I60: =E62 -> 8877.78
B61: Services and Non Income Producing | C61: 14613 | D61: 0.51 | E61: =D61*C61 -> 7452.63 | H61: Lodging | I61: =E63 -> 2380.86
B62: Retail | C62: 11997 | D62: 0.74 | E62: =D62*C62 -> 8877.78 | H62: Other | I62: =SUM(E60:E61) -> 16932.95
B63: Lodging | C63: 4409 | D63: 0.54 | E63: =D63*C63 -> 2380.86 | H63: Total CRE | I63: =SUM(I57:I62) -> 168549.5
B64: Total CRE | C64: =SUM(C57:C63) -> 206154 | D64: =E64/C64 -> 0.81759025 | E64: =SUM(E57:E63) -> 168549.5
A80: 1Q24 | B80: Manual 1Q24 (10-Q)
B82: CRE Property Type | C82: Credit Exposure | D82: % Drawn | E82: Outstanding | H82: CRE Property Type | I82: Outstanding
B83: Multifamily | C83: 122811 | D83: 0.9 | E83: =D83*C83 -> 110529.9 | H83: Multi-family | I83: =E83 -> 110529.9
B84: Industrial | C84: 20058 | D84: 0.71 | E84: =D84*C84 -> 14241.18 | H84: Industrial | I84: =E84 -> 14241.18
B85: Office | C85: 16300 | D85: 0.82 | E85: =D85*C85 -> 13366 | H85: Office | I85: =E85 -> 13366
B86: Services and Non Income Producing | C86: 15106 | D86: 0.51 | E86: =D86*C86 -> 7704.06 | H86: Retail | I86: =E88 -> 9057.6
B87: Other Income Producing Properties | C87: 14793 | D87: 0.65 | E87: =D87*C87 -> 9615.45 | H87: Lodging | I87: =E89 -> 2405.7
B88: Retail | C88: 12240 | D88: 0.74 | E88: =D88*C88 -> 9057.6 | H88: Other | I88: =SUM(E86:E87) -> 17319.51
B89: Lodging | C89: 4455 | D89: 0.54 | E89: =D89*C89 -> 2405.7 | H89: Total CRE | I89: =SUM(I83:I88) -> 166919.89
B90: Total CRE | C90: =SUM(C83:C89) -> 205763 | D90: =E90/C90 -> 0.81122403 | E90: =SUM(E83:E89) -> 166919.89

Sheet JPM LLM API
B2: 4Q24 AI API Script
B15: Correct
B17: CRE Property Type | C17: Credit Exposure | D17: Percentage Drawn
B18: Multi-family | C18: 124081 | D18: 0.92
B19: Industrial | C19: 19109 | D19: 0.72
B20: Office | C20: 16360 | D20: 0.81
B21: Other Income Producing Properties | C21: 16569 | D21: 0.63
B22: Services and Non Income Producing | C22: 14104 | D22: 0.46
B23: Retail | C23: 12253 | D23: 0.75
B24: Lodging | C24: 4574 | D24: 0.53
B25: Total CRE | C25: =SUM(C18:C24) -> 207050 | D25: 0.82
B37: Correct | E37: LLM
B39: CRE Property Type | C39: Loan Amount | E39: CRE Property Type | F39: Loan Amount | H39: =B39=E39 -> TRUE | I39: =C39=F39 -> TRUE
B40: Multi-family | C40: =C18*D18 -> 114154.52 | E40: Multi-family | F40: 114156 | H40: =B40=E40 -> TRUE | I40: TRUE
B41: Industrial | C41: =C19*D19 -> 13758.48 | E41: Industrial | F41: 13758.48 | H41: =B41=E41 -> TRUE | I41: =C41=F41 -> TRUE
B42: Office | C42: =C20*D20 -> 13251.6 | E42: Office | F42: 13256 | H42: =B42=E42 -> TRUE | I42: =C42=F42 -> FALSE
B43: Other | C43: =C21*D21+C22*D22 -> 16926.31 | E43: Other | F43: 14722 | H43: =B43=E43 -> TRUE | I43: =C43=F43 -> FALSE
B44: Retail | C44: =C23*D23 -> 9189.75 | E44: Retail | F44: 9189.75 | H44: =B44=E44 -> TRUE | I44: =C44=F44 -> TRUE
B45: Lodging | C45: =C24*D24 -> 2424.22 | E45: Lodging | F45: 2424.22 | H45: =B45=E45 -> TRUE | I45: =C45=F45 -> TRUE
B46: Total CRE | C46: =SUM(C40:C45) -> 169704.88 | E46: Total CRE | F46: 167506 | H46: =B46=E46 -> TRUE | I46: =C46=F46 -> FALSE
E48: Accuracy | F48: =13/16 -> 0.8125
B49: Override Table
B60: 3Q24 AI API Script
B74: Correct
B76: CRE Property Type | C76: Credit Exposure | D76: Percentage Drawn
B77: Multi-family | C77: 125410 | D77: 0.91
B78: Industrial | C78: 19282 | D78: 0.74
B79: Office | C79: 16926 | D79: 0.81
B80: Other Income Producing Properties | C80: 15011 | D80: 0.67
B81: Services and Non Income Producing | C81: 14557 | D81: 0.51
B82: Retail | C82: 12841 | D82: 0.69
B83: Lodging | C83: 4563 | D83: 0.55
B84: Total CRE | C84: =SUM(C77:C83) -> 208590 | D84: 0.82
B96: Correct | E96: LLM
B98: CRE Property Type | C98: Loan Amount | E98: CRE Property Type | F98: Loan Amount | H98: =B98=E98 -> TRUE | I98: =C98=F98 -> TRUE
B99: Multi-family | C99: =C77*D77 -> 114123.1 | E99: Multi-family | F99: 114122 | H99: =B99=E99 -> TRUE | I99: TRUE
B100: Industrial | C100: =C78*D78 -> 14268.68 | E100: Industrial | F100: 14272 | H100: =B100=E100 -> TRUE | I100: =C100=F100 -> FALSE
B101: Office | C101: =C79*D79 -> 13710.06 | E101: Office | F101: 13712 | H101: =B101=E101 -> TRUE | I101: =C101=F101 -> FALSE
B102: Other | C102: =C80*D80+C81*D81 -> 17481.44 | E102: Other | F102: 19621 | H102: =B102=E102 -> TRUE | I102: =C102=F102 -> FALSE
B103: Retail | C103: =C82*D82 -> 8860.29 | E103: Retail | F103: 8859 | H103: =B103=E103 -> TRUE | I103: TRUE
B104: Lodging | C104: =C83*D83 -> 2509.65 | E104: Lodging | F104: 2510 | H104: =B104=E104 -> TRUE | I104: TRUE
B105: Total CRE | C105: =SUM(C99:C104) -> 170953.22 | E105: Total CRE | F105: 173096 | H105: =B105=E105 -> TRUE | I105: =C105=F105 -> FALSE
B107: Override Table | E107: Accuracy | F107: =12/16 -> 0.75
B118: 2Q24 AI API Script
B131: Correct
B133: CRE Property Type | C133: Credit Exposure | D133: Percentage Drawn
B134: Multi-family | C134: 122991 | D134: 0.91
B135: Industrial | C135: 20871 | D135: 0.7
B136: Office | C136: 16460 | D136: 0.84
B137: Other Income Producing Properties | C137: 14813 | D137: 0.64
B138: Services and Non Income Producing | C138: 14613 | D138: 0.51
B139: Retail | C139: 11997 | D139: 0.74
B140: Lodging | C140: 4409 | D140: 0.54
B141: Total CRE | C141: =SUM(C134:C140) -> 206154 | D141: 0.81
B153: Correct | E153: LLM
B155: CRE Property Type | C155: Loan Amount | E155: CRE Property Type | F155: Loan Amount | H155: =B155=E155 -> TRUE | I155: =C155=F155 -> TRUE
B156: Multi-family | C156: =C134*D134 -> 111921.81 | E156: Multi-family | F156: 111921 | H156: =B156=E156 -> TRUE | I156: TRUE
B157: Industrial | C157: =C135*D135 -> 14609.7 | E157: Industrial | F157: 14610 | H157: =B157=E157 -> TRUE | I157: TRUE
B158: Office | C158: =C136*D136 -> 13826.4 | E158: Office | F158: 13794 | H158: =B158=E158 -> TRUE | I158: =C158=F158 -> FALSE
B159: Other | C159: =C137*D137+C138*D138 -> 16932.95 | E159: Other | F159: 18863 | H159: =B159=E159 -> TRUE | I159: =C159=F159 -> FALSE
B160: Retail | C160: =C139*D139 -> 8877.78 | E160: Retail | F160: 8878 | H160: =B160=E160 -> TRUE | I160: TRUE
B161: Lodging | C161: =C140*D140 -> 2380.86 | E161: Lodging | F161: 2381 | H161: =B161=E161 -> TRUE | I161: TRUE
B162: Total CRE | C162: =SUM(C156:C161) -> 168549.5 | E162: Total CRE | F162: 170447 | H162: =B162=E162 -> TRUE | I162: =C162=F162 -> FALSE
B164: Override Table | E164: Accuracy | F164: =13/16 -> 0.8125
B175: 1Q24 AI API Script
B188: Correct
B190: CRE Property Type | C190: Credit Exposure | D190: Percentage Drawn
B191: Multi-family | C191: 122811 | D191: 0.9
B192: Industrial | C192: 20058 | D192: 0.71
B193: Office | C193: 16300 | D193: 0.82
B194: Other Income Producing Properties | C194: 14793 | D194: 0.65
B195: Services and Non Income Producing | C195: 15106 | D195: 0.51
B196: Retail | C196: 12240 | D196: 0.74
B197: Lodging | C197: 4455 | D197: 0.54
B198: Total CRE | C198: =SUM(C191:C197) -> 205763 | D198: 0.81
B210: Correct | E210: LLM
B212: CRE Property Type | C212: Loan Amount | E212: CRE Property Type | F212: Loan Amount | H212: =B212=E212 -> TRUE | I212: =C212=F212 -> TRUE
B213: Multi-family | C213: =C191*D191 -> 110529.9 | E213: Multi-family | F213: 110529.9 | H213: =B213=E213 -> TRUE | I213: =C213=F213 -> TRUE
B214: Industrial | C214: =C192*D192 -> 14241.18 | E214: Industrial | F214: 14441 | H214: =B214=E214 -> TRUE | I214: =C214=F214 -> FALSE
B215: Office | C215: =C193*D193 -> 13366 | E215: Office | F215: 13366 | H215: =B215=E215 -> TRUE | I215: =C215=F215 -> TRUE
B216: Other | C216: =C194*D194+C195*D195 -> 17319.51 | E216: Other | F216: 15520 | H216: =B216=E216 -> TRUE | I216: =C216=F216 -> FALSE
B217: Retail | C217: =C196*D196 -> 9057.6 | E217: Retail | F217: 9058 | H217: =B217=E217 -> TRUE | I217: =C217=F217 -> FALSE
B218: Lodging | C218: =C197*D197 -> 2405.7 | E218: Lodging | F218: 2405 | H218: =B218=E218 -> TRUE | I218: TRUE
B219: Total CRE | C219: =SUM(C213:C218) -> 166919.89 | E219: Total CRE | F219: 165320 | H219: =B219=E219 -> TRUE | I219: =C219=F219 -> FALSE
B221: Override Table | E221: Accuracy | F221: =12/16 -> 0.75

Sheet JPM Script
B2: Script 4Q24 (10-Q) | K2: Script 3Q24 (10-Q)
B13: Script 2Q24 (10-Q) | K13: Script 1Q24 (10-Q)

Sheet WFC

Sheet WFC Manual
A2: 4Q24 | B2: CRE Property Type | C2: CRE Mortgage | D2: CRE Construction | E2: Total | G2: Ticker | H2: Quarter | I2: CRE Property Type | J2: Loan Amount | K2: Unit | L2: Currency | M2: Category
B3: Apartments | C3: 28359 | D3: 11399 | E3: =SUM(C3:D3) -> 39758 | G3: WFC | H3: 4Q24 | I3: Multi-family | J3: =E3 -> 39758 | K3: mn | L3: USD | M3: CRE
B4: Office | C4: 24818 | D4: 2562 | E4: =SUM(C4:D4) -> 27380 | G4: WFC | H4: 4Q24 | I4: Office | J4: =E4 -> 27380 | K4: mn | L4: USD | M4: CRE
B5: Industrial/warehouse | C5: 20987 | D5: 3051 | E5: =SUM(C5:D5) -> 24038 | G5: WFC | H5: 4Q24 | I5: Industrial | J5: =E5 -> 24038 | K5: mn | L5: USD | M5: CRE
B6: Hotel/motel | C6: 10853 | D6: 653 | E6: =SUM(C6:D6) -> 11506 | G6: WFC | H6: 4Q24 | I6: Retail | J6: =E7+E8 -> 19458 | K6: mn | L6: USD | M6: CRE
B7: Retail (excl shoppingcenter) | C7: 11260 | D7: 85 | E7: =SUM(C7:D7) -> 11345 | G7: WFC | H7: 4Q24 | I7: Lodging | J7: =E6 -> 11506 | K7: mn | L7: USD | M7: CRE
B8: Shopping center | C8: 7860 | D8: 253 | E8: =SUM(C8:D8) -> 8113 | G8: WFC | H8: 4Q24 | I8: Mixed-use | J8: =E10 -> 2316 | K8: mn | L8: USD | M8: CRE
B9: Institutional | C9: 4048 | D9: 1138 | E9: =SUM(C9:D9) -> 5186 | G9: WFC | H9: 4Q24 | I9: Other | J9: =SUM(E11:E12,E9,E13) -> 12049 | K9: mn | L9: USD | M9: CRE
B10: Mixed use properties | C10: 2303 | D10: 13 | E10: =SUM(C10:D10) -> 2316 | G10: WFC | H10: 4Q24 | I10: Total CRE | J10: =SUM(J3:J9) -> 136505 | K10: mn | L10: USD | M10: CRE
B11: Mobile home park | C11: 2273 | D11: — | E11: =SUM(C11:D11) -> 2273
B12: Storage facility | C12: 2040 | D12: 48 | E12: =SUM(C12:D12) -> 2088
B13: Other | C13: 1058 | D13: 1444 | E13: =SUM(C13:D13) -> 2502
B14: Total CRE | C14: =SUM(C3:C13) -> 115859 | D14: =SUM(D3:D13) -> 20646 | E14: =SUM(E3:E13) -> 136505
A16: 3Q24 | B16: CRE Property Type | C16: CRE Mortgage | D16: CRE Construction | E16: Total | G16: Ticker | H16: Quarter | I16: CRE Property Type | J16: Loan Amount | K16: Unit | L16: Currency | M16: Category
B17: Apartments | C17: 29374 | D17: 11975 | E17: =SUM(C17:D17) -> 41349 | G17: WFC | H17: 3Q24 | I17: Multi-family | J17: =E17 -> 41349 | K17: mn | L17: USD | M17: CRE
B18: Office | C18: 25946 | D18: 3050 | E18: =SUM(C18:D18) -> 28996 | G18: WFC | H18: 3Q24 | I18: Office | J18: =E18 -> 28996 | K18: mn | L18: USD | M18: CRE
B19: Industrial/warehouse | C19: 21147 | D19: 3456 | E19: =SUM(C19:D19) -> 24603 | G19: WFC | H19: 3Q24 | I19: Industrial | J19: =E19 -> 24603 | K19: mn | L19: USD | M19: CRE
B20: Retail (exc shopping center) | C20: 11303 | D20: 73 | E20: =SUM(C20:D20) -> 11376 | G20: WFC | H20: 3Q24 | I20: Retail | J20: =E20+E22 -> 19961 | K20: mn | L20: USD | M20: CRE
B21: Hotel/motel | C21: 10682 | D21: 783 | E21: =SUM(C21:D21) -> 11465 | G21: WFC | H21: 3Q24 | I21: Lodging | J21: =E21 -> 11465 | K21: mn | L21: USD | M21: CRE
B22: Shopping center | C22: 8311 | D22: 274 | E22: =SUM(C22:D22) -> 8585 | G22: WFC | H22: 3Q24 | I22: Mixed-use | J22: =E24 -> 2575 | K22: mn | L22: USD | M22: CRE
B23: Institutional | C23: 4245 | D23: 1148 | E23: =SUM(C23:D23) -> 5393 | G23: WFC | H23: 3Q24 | I23: Residential | J23: =E25 -> 1190 | K23: mn | L23: USD | M23: CRE
B24: Mixed use properties | C24: 2492 | D24: 83 | E24: =SUM(C24:D24) -> 2575 | G24: WFC | H24: 3Q24 | I24: Other | J24: =SUM(E26:E27,E23) -> 11271 | K24: mn | L24: USD | M24: CRE
B25: 1-4 family structure | C25: 0 | D25: 1190 | E25: =SUM(C25:D25) -> 1190 | G25: WFC | H25: 3Q24 | I25: Total CRE | J25: =SUM(J17:J24) -> 141410 | K25: mn | L25: USD | M25: CRE
B26: Storage facility | C26: 2038 | D26: 159 | E26: =SUM(C26:D26) -> 2197
B27: Other | C27: 3238 | D27: 443 | E27: =SUM(C27:D27) -> 3681
B28: Total CRE | C28: =SUM(C17:C27) -> 118776 | D28: =SUM(D17:D27) -> 22634 | E28: =SUM(E17:E27) -> 141410
A30: 2Q24 | B30: CRE Property Type | C30: CRE Mortgage | D30: CRE Construction | E30: Total | G30: Ticker | H30: Quarter | I30: CRE Property Type | J30: Loan Amount | K30: Unit | L30: Currency | M30: Category
B31: Apartments | C31: 31249 | D31: 11799 | E31: =SUM(C31:D31) -> 43048 | G31: WFC | H31: 2Q24 | I31: Multi-family | J31: =E31 -> 43048 | K31: mn | L31: USD | M31: CRE
B32: Office | C32: 26714 | D32: 2990 | E32: =SUM(C32:D32) -> 29704 | G32: WFC | H32: 2Q24 | I32: Office | J32: =E32 -> 29704 | K32: mn | L32: USD | M32: CRE
B33: Industrial/warehouse | C33: 21024 | D33: 3853 | E33: =SUM(C33:D33) -> 24877 | G33: WFC | H33: 2Q24 | I33: Industrial | J33: =E33 -> 24877 | K33: mn | L33: USD | M33: CRE
B34: Retail (excl shoppingcenter) | C34: 11193 | D34: 80 | E34: =SUM(C34:D34) -> 11273 | G34: WFC | H34: 2Q24 | I34: Retail | J34: =E34+E36 -> 19991 | K34: mn | L34: USD | M34: CRE
B35: Hotel/motel | C35: 10839 | D35: 762 | E35: =SUM(C35:D35) -> 11601 | G35: WFC | H35: 2Q24 | I35: Lodging | J35: =E35 -> 11601 | K35: mn | L35: USD | M35: CRE
B36: Shopping center | C36: 8402 | D36: 316 | E36: =SUM(C36:D36) -> 8718 | G36: WFC | H36: 2Q24 | I36: Mixed-use | J36: =E38 -> 2923 | K36: mn | L36: USD | M36: CRE
B37: Institutional | C37: 4323 | D37: 1232 | E37: =SUM(C37:D37) -> 5555 | G37: WFC | H37: 2Q24 | I37: Residential | J37: =E40 -> 1143 | K37: mn | L37: USD | M37: CRE
B38: Mixed use properties | C38: 2877 | D38: 46 | E38: =SUM(C38:D38) -> 2923 | G38: WFC | H38: 2Q24 | I38: Other | J38: =SUM(E39,E37,E41) -> 12031 | K38: mn | L38: USD | M38: CRE
B39: Storage facility | C39: 2194 | D39: 151 | E39: =SUM(C39:D39) -> 2345 | G39: WFC | H39: 2Q24 | I39: Total CRE | J39: =SUM(J31:J38) -> 145318 | K39: mn | L39: USD | M39: CRE
B40: 1-4 family structure | C40: — | D40: 1143 | E40: =SUM(C40:D40) -> 1143
B41: Other | C41: 3718 | D41: 413 | E41: =SUM(C41:D41) -> 4131
B42: Total CRE | C42: =SUM(C31:C41) -> 122533 | D42: =SUM(D31:D41) -> 22785 | E42: =SUM(E31:E41) -> 145318
A44: 1Q24 | B44: CRE Property Type | C44: CRE Mortgage | D44: CRE Construction | E44: Total | G44: Ticker | H44: Quarter | I44: CRE Property Type | J44: Loan Amount | K44: Unit | L44: Currency | M44: Category
B45: Apartments | C45: 30966 | D45: 11714 | E45: =SUM(C45:D45) -> 42680 | G45: WFC | H45: 1Q24 | I45: Multi-family | J45: =E45 -> 42680 | K45: mn | L45: USD | M45: CRE
B46: Office | C46: 27546 | D46: 2931 | E46: =SUM(C46:D46) -> 30477 | G46: WFC | H46: 1Q24 | I46: Office | J46: =E46 -> 30477 | K46: mn | L46: USD | M46: CRE
B47: Industrial/warehouse | C47: 21380 | D47: 4354 | E47: =SUM(C47:D47) -> 25734 | G47: WFC | H47: 1Q24 | I47: Industrial | J47: =E47 -> 25734 | K47: mn | L47: USD | M47: CRE
B48: Hotel/motel | C48: 11849 | D48: 674 | E48: =SUM(C48:D48) -> 12523 | G48: WFC | H48: 1Q24 | I48: Retail | J48: =E49+E50 -> 20141 | K48: mn | L48: USD | M48: CRE
B49: Retail (excl shoppingcenter) | C49: 11402 | D49: 78 | E49: =SUM(C49:D49) -> 11480 | G49: WFC | H49: 1Q24 | I49: Lodging | J49: =E48 -> 12523 | K49: mn | L49: USD | M49: CRE
B50: Shopping center | C50: 8313 | D50: 348 | E50: =SUM(C50:D50) -> 8661 | G50: WFC | H50: 1Q24 | I50: Mixed-use | J50: =E52 -> 2971 | K50: mn | L50: USD | M50: CRE
B51: Institutional | C51: 4420 | D51: 1375 | E51: =SUM(C51:D51) -> 5795 | G51: WFC | H51: 1Q24 | I51: Residential | J51: =E54 -> 1397 | K51: mn | L51: USD | M51: CRE
B52: Mixed use properties | C52: 2921 | D52: 50 | E52: =SUM(C52:D52) -> 2971 | G52: WFC | H52: 1Q24 | I52: Other | J52: =SUM(E53,E51,E55) -> 12863 | K52: mn | L52: USD | M52: CRE
B53: Storage facility | C53: 2593 | D53: 151 | E53: =SUM(C53:D53) -> 2744 | G53: WFC | H53: 1Q24 | I53: Total CRE | J53: =SUM(J45:J52) -> 148786 | K53: mn | L53: USD | M53: CRE
B54: 1-4 family structure | C54: 7 | D54: 1390 | E54: =SUM(C54:D54) -> 1397
B55: Other | C55: 3779 | D55: 545 | E55: =SUM(C55:D55) -> 4324
B56: Total CRE | C56: =SUM(C45:C55) -> 125176 | D56: =SUM(D45:D55) -> 23610 | E56: =SUM(E45:E55) -> 148786

Sheet WFC LLM API
B2: 4Q24 AI API Script
B18: Correct
B20: CRE Property Type | C20: Total
B21: Apartments | C21: 39758
B22: Office | C22: 27380
B23: Industrial/warehouse | C23: 24038
B24: Hotel/motel | C24: 11506
B25: Retail (excl shoppingcenter) | C25: 11345
B26: Shopping center | C26: 8113
B27: Institutional | C27: 5186
B28: Mixed use properties | C28: 2316
B29: Mobile home park | C29: 2273
B30: Storage facility | C30: 2088
B31: Other | C31: 2502
B32: Total CRE | C32: 136505
B34: Correct | E34: LLM
B36: CRE Property Type | C36: Loan Amount | E36: CRE Property Type | F36: Loan Amount | H36: =B36=E36 -> TRUE | I36: =C36=F36 -> TRUE
B37: Multi-family | C37: =C21 -> 39758 | E37: Multi-family | F37: 39758 | H37: =B37=E37 -> TRUE | I37: =C37=F37 -> TRUE
B38: Office | C38: =C22 -> 27380 | E38: Office | F38: 27380 | H38: =B38=E38 -> TRUE | I38: =C38=F38 -> TRUE
B39: Industrial | C39: =C23 -> 24038 | E39: Industrial | F39: 24038 | H39: =B39=E39 -> TRUE | I39: =C39=F39 -> TRUE
B40: Retail | C40: =C25+C26 -> 19458 | E40: Retail | F40: 18115 | H40: =B40=E40 -> TRUE | I40: =C40=F40 -> FALSE
B41: Lodging | C41: =C24 -> 11506 | E41: Lodging | F41: 11506 | H41: =B41=E41 -> TRUE | I41: =C41=F41 -> TRUE
B42: Mixed-use | C42: =C28 -> 2316 | E42: Mixed-use | F42: 2303 | H42: =B42=E42 -> TRUE | I42: =C42=F42 -> FALSE
B43: Other | C43: =SUM(C27,C30,C31,C29) -> 12049 | E43: Other | F43: 13405 | H43: =B43=E43 -> TRUE | I43: =C43=F43 -> FALSE
B44: Total CRE | C44: =SUM(C37:C43) -> 136505 | E44: Total CRE | F44: 136505 | H44: =B44=E44 -> TRUE | I44: =C44=F44 -> TRUE
E46: Accuracy | F46: =15/18 -> 0.83333333
B48: 3Q24 AI API Script
B66: Correct
B68: CRE Property Type | C68: Total
B69: Apartments | C69: 41349
B70: Office | C70: 28996
B71: Industrial/warehouse | C71: 24603
B72: Retail (exc shopping center) | C72: 11376
B73: Hotel/motel | C73: 11465
B74: Shopping center | C74: 8585
B75: Institutional | C75: 5393
B76: Mixed use properties | C76: 2575
B77: 1-4 family structure | C77: 1190
B78: Storage facility | C78: 2197
B79: Other | C79: 3681
B80: Total CRE | C80: 141410
B82: Correct | E82: LLM
B84: CRE Property Type | C84: Loan Amount | E84: CRE Property Type | F84: Loan Amount | H84: =B84=E84 -> TRUE | I84: =C84=F84 -> TRUE
B85: Multi-family | C85: =C69 -> 41349 | E85: Multi-family | F85: 41349 | H85: =B85=E85 -> TRUE | I85: =C85=F85 -> TRUE
B86: Office | C86: =C70 -> 28996 | E86: Office | F86: 28996 | H86: =B86=E86 -> TRUE | I86: =C86=F86 -> TRUE
B87: Industrial | C87: =C71 -> 24603 | E87: Industrial | F87: 24603 | H87: =B87=E87 -> TRUE | I87: =C87=F87 -> TRUE
B88: Retail | C88: =C72+C74 -> 19961 | E88: Retail | F88: 20423 | H88: =B88=E88 -> TRUE | I88: =C88=F88 -> FALSE
B89: Lodging | C89: =C73 -> 11465 | E89: Lodging | F89: 11465 | H89: =B89=E89 -> TRUE | I89: =C89=F89 -> TRUE
B90: Mixed-use | C90: =C76 -> 2575 | E90: Mixed-use | F90: 2575 | H90: =B90=E90 -> TRUE | I90: =C90=F90 -> TRUE
B91: Residential | C91: =C77 -> 1190 | E91: Residential | F91: 2197 | H91: =B91=E91 -> TRUE | I91: =C91=F91 -> FALSE
B92: Other | C92: =SUM(C75,C78,C79) -> 11271 | E92: Other | F92: 9252 | H92: =B92=E92 -> TRUE | I92: =C92=F92 -> FALSE
B93: Total CRE | C93: =SUM(C85:C92) -> 141410 | E93: Total CRE | F93: 141410 | H93: =B93=E93 -> TRUE | I93: =C93=F93 -> TRUE
E95: Accuracy | F95: =17/20 -> 0.85
B97: 2Q24 AI API Script
B113: Correct
B115: CRE Property Type | C115: Total
B116: Apartments | C116: 43048
B117: Office | C117: 29704
B118: Industrial/warehouse | C118: 24877
B119: Retail (excl shoppingcenter) | C119: 11273
B120: Hotel/motel | C120: 11601
B121: Shopping center | C121: 8718
B122: Institutional | C122: 5555
B123: Mixed use properties | C123: 2923
B124: Storage facility | C124: 2345
B125: 1-4 family structure | C125: 1143
B126: Other | C126: 4131
B127: Total CRE | C127: 145318
B129: Correct | E129: LLM
B131: CRE Property Type | C131: Loan Amount | E131: CRE Property Type | F131: Loan Amount | H131: =B131=E131 -> TRUE | I131: =C131=F131 -> TRUE
B132: Multi-family | C132: =C116 -> 43048 | E132: Multi-family | F132: 43048 | H132: =B132=E132 -> TRUE | I132: =C132=F132 -> TRUE
B133: Office | C133: =C117 -> 29704 | E133: Office | F133: 29704 | H133: =B133=E133 -> TRUE | I133: =C133=F133 -> TRUE
B134: Industrial | C134: =C118 -> 24877 | E134: Industrial | F134: 24877 | H134: =B134=E134 -> TRUE | I134: =C134=F134 -> TRUE
B135: Retail | C135: =C119+C121 -> 19991 | E135: Retail | F135: 20691 | H135: =B135=E135 -> TRUE | I135: =C135=F135 -> FALSE
B136: Lodging | C136: =C120 -> 11601 | E136: Lodging | F136: 11601 | H136: =B136=E136 -> TRUE | I136: =C136=F136 -> TRUE
B137: Mixed-use | C137: =C123 -> 2923 | E137: Mixed-use | F137: 2455 | H137: =B137=E137 -> TRUE | I137: =C137=F137 -> FALSE
B138: Residential | C138: =C125 -> 1143 | E138: Residential | F138: 4131 | H138: =B138=E138 -> TRUE | I138: =C138=F138 -> FALSE
B139: Other | C139: =SUM(C122,C124,C126) -> 12031 | E139: Other | F139: 8925 | H139: =B139=E139 -> TRUE | I139: =C139=F139 -> FALSE
B140: Total CRE | C140: =SUM(C132:C139) -> 145318 | E140: Total CRE | F140: 145318 | H140: =B140=E140 -> TRUE | I140: =C140=F140 -> TRUE
E142: Accuracy | F142: =16/20 -> 0.8
B144: 1Q24 AI API Script
B159: Correct
B161: CRE Property Type | C161: Total
B162: Apartments | C162: 42680
B163: Office | C163: 30477
B164: Industrial/warehouse | C164: 25734
B165: Hotel/motel | C165: 12523
B166: Retail (excl shoppingcenter) | C166: 11480
B167: Shopping center | C167: 8661
B168: Institutional | C168: 5795
B169: Mixed use properties | C169: 2971
B170: Storage facility | C170: 2744
B171: 1-4 family structure | C171: 1397
B172: Other | C172: 4324
B173: Total CRE | C173: 148786
B175: Correct | E175: LLM
B177: CRE Property Type | C177: Loan Amount | E177: CRE Property Type | F177: Loan Amount | H177: =B177=E177 -> TRUE | I177: =C177=F177 -> TRUE
B178: Multi-family | C178: =C162 -> 42680 | E178: Multi-family | F178: 42680 | H178: =B178=E178 -> TRUE | I178: =C178=F178 -> TRUE
B179: Office | C179: =C163 -> 30477 | E179: Office | F179: 30477 | H179: =B179=E179 -> TRUE | I179: =C179=F179 -> TRUE
B180: Industrial | C180: =C164 -> 25734 | E180: Industrial | F180: 25734 | H180: =B180=E180 -> TRUE | I180: =C180=F180 -> TRUE
...

Sheet WFC Script
B2: Script 4Q24 (10-Q) | K2: Script 3Q24 (10-Q)
B14: Script 2Q24 (10-Q) | K14: Script 1Q24 (10-Q)

Sheet KEY

Sheet KEY Manual
A3: 4Q24 | B3: CRE Property Type | C3: Construction | D3: Mortgage | E3: Loan Amount | G3: CRE Property Type | H3: Loan Amount
B4: Data Center | C4: — | D4: 152 | E4: =SUM(C4:D4) -> 152 | G4: Industrial | H4: =E6 -> 733
B5: Diversified | C5: — | D5: 135 | E5: =SUM(C5:D5) -> 135 | G5: Lodging | H5: =E8 -> 234
B6: Industrial | C6: 54 | D6: 679 | E6: =SUM(C6:D6) -> 733 | G6: Multi-family | H6: =E10 -> 8010
B7: Land & Residential | C7: 28 | D7: 20 | E7: =SUM(C7:D7) -> 48 | G7: Office | H7: =E11+E9 -> 1009
B8: Lodging | C8: — | D8: 234 | E8: =SUM(C8:D8) -> 234 | G8: Retail | H8: =E12 -> 880
B9: Medical Office | C9: — | D9: 271 | E9: =SUM(C9:D9) -> 271 | G9: Other | H9: =SUM(E4:E5,E7,E13:E17) -> 2138
B10: Multifamily | C10: 2405 | D10: 5605 | E10: =SUM(C10:D10) -> 8010 | G10: Total CRE | H10: =SUM(H4:H9) -> 13004
B11: Office | C11: — | D11: 738 | E11: =SUM(C11:D11) -> 738
B12: Retail | C12: 43 | D12: 837 | E12: =SUM(C12:D12) -> 880
B13: Self Storage | C13: 14 | D13: 346 | E13: =SUM(C13:D13) -> 360
B14: Senior Housing | C14: 154 | D14: 439 | E14: =SUM(C14:D14) -> 593
B15: Skilled Nursing | C15: — | D15: 392 | E15: =SUM(C15:D15) -> 392
B16: Student Housing | C16: 50 | D16: 190 | E16: =SUM(C16:D16) -> 240
B17: Other | C17: — | D17: 218 | E17: =SUM(C17:D17) -> 218
B18: Total CRE | C18: =SUM(C4:C17) -> 2748 | D18: =SUM(D4:D17) -> 10256 | E18: =SUM(E4:E17) -> 13004
A24: 3Q24 | B24: CRE Property Type | C24: Construction | D24: Mortgage | E24: Loan Amount | G24: CRE Property Type | H24: Loan Amount
B25: Diversified | C25: — | D25: 136 | E25: =SUM(C25:D25) -> 136 | G25: Industrial | H25: 763
B26: Industrial | C26: 141 | D26: 622 | E26: =SUM(C26:D26) -> 763 | G26: Lodging | H26: 226
B27: Land & Residential | C27: 18 | D27: 23 | E27: =SUM(C27:D27) -> 41 | G27: Multifamily | H27: 8387
B28: Lodging | C28: — | D28: 226 | E28: =SUM(C28:D28) -> 226 | G28: Office | H28: =E31+E29 -> 1030
B29: Medical Office | C29: — | D29: 278 | E29: =SUM(C29:D29) -> 278 | G29: Retail | H29: 889
B30: Multifamily | C30: 2492 | D30: 5895 | E30: =SUM(C30:D30) -> 8387 | G30: Other | H30: =SUM(E33:E37,E25,E27) -> 2027
B31: Office | C31: — | D31: 752 | E31: =SUM(C31:D31) -> 752 | G31: Total CRE | H31: =SUM(H25:H30) -> 13322
B32: Retail | C32: 43 | D32: 846 | E32: =SUM(C32:D32) -> 889
B33: Self Storage | C33: 12 | D33: 374 | E33: =SUM(C33:D33) -> 386
B34: Senior Housing | C34: 152 | D34: 492 | E34: =SUM(C34:D34) -> 644
B35: Skilled Nursing | C35: — | D35: 338 | E35: =SUM(C35:D35) -> 338
B36: Student Housing | C36: 50 | D36: 155 | E36: =SUM(C36:D36) -> 205
B37: Other | C37: — | D37: 277 | E37: =SUM(C37:D37) -> 277
B38: Total CRE | C38: =SUM(C25:C37) -> 2908 | D38: =SUM(D25:D37) -> 10414 | E38: =SUM(C38:D38) -> 13322
A46: 2Q24 | B46: CRE Property Type | C46: Construction | D46: Mortgage | E46: Loan Amount | G46: CRE Property Type | H46: Loan Amount
B47: Diversified | C47: — | D47: 143 | E47: =SUM(C47:D47) -> 143 | G47: Industrial | H47: =E48 -> 779
B48: Industrial | C48: 140 | D48: 639 | E48: =SUM(C48:D48) -> 779 | G48: Lodging | H48: =E50 -> 214
B49: Land & Residential | C49: 15 | D49: 23 | E49: =SUM(C49:D49) -> 38 | G49: Multi-family | H49: =E52 -> 8576
B50: Lodging | C50: — | D50: 214 | E50: =SUM(C50:D50) -> 214 | G50: Office | H50: =SUM(E53,E51) -> 1048
B51: Medical Office | C51: — | D51: 275 | E51: =SUM(C51:D51) -> 275 | G51: Retail | H51: =E54 -> 902
B52: Multifamily | C52: 2475 | D52: 6101 | E52: =SUM(C52:D52) -> 8576 | G52: Other | H52: =SUM(E55:E59,E49,E47) -> 2196
B53: Office | C53: — | D53: 773 | E53: =SUM(C53:D53) -> 773 | G53: Total CRE | H53: =SUM(H47:H52) -> 13715
B54: Retail | C54: 46 | D54: 856 | E54: =SUM(C54:D54) -> 902
B55: Self Storage | C55: 11 | D55: 371 | E55: =SUM(C55:D55) -> 382
B56: Senior Housing | C56: 145 | D56: 522 | E56: =SUM(C56:D56) -> 667
B57: Skilled Nursing | C57: — | D57: 483 | E57: =SUM(C57:D57) -> 483
B58: Student Housing | C58: 50 | D58: 135 | E58: =SUM(C58:D58) -> 185
B59: Other | C59: — | D59: 298 | E59: =SUM(C59:D59) -> 298
B60: Total CRE | C60: =SUM(C47:C59) -> 2882 | D60: =SUM(D47:D59) -> 10833 | E60: =SUM(E47:E59) -> 13715
A68: 1Q24 | B68: CRE Property Type | C68: Construction | D68: Mortgage | E68: Loan Amount | G68: CRE Property Type | H68: Loan Amount
B69: Diversified | C69: — | D69: 142 | E69: =SUM(C69:D69) -> 142 | G69: Industrial | H69: =E70 -> 791
B70: Industrial | C70: 131 | D70: 660 | E70: =SUM(C70:D70) -> 791 | G70: Lodging | H70: =E72 -> 222
B71: Land & Residential | C71: 13 | D71: 23 | E71: =SUM(C71:D71) -> 36 | G71: Multi-family | H71: =E74 -> 8608
B72: Lodging | C72: 5 | D72: 217 | E72: =SUM(C72:D72) -> 222 | G72: Office | H72: =E75+E73 -> 1123
B73: Medical Office | C73: 32 | D73: 246 | E73: =SUM(C73:D73) -> 278 | G73: Retail | H73: =E76 -> 977
B74: Multifamily | C74: 2367 | D74: 6241 | E74: =SUM(C74:D74) -> 8608 | G74: Other | H74: =SUM(E77:E81,E69,E71) -> 2227
B75: Office | C75: — | D75: 845 | E75: =SUM(C75:D75) -> 845 | G75: Total CRE | H75: =SUM(H69:H74) -> 13948
B76: Retail | C76: 62 | D76: 915 | E76: =SUM(C76:D76) -> 977
B77: Self Storage | C77: 8 | D77: 387 | E77: =SUM(C77:D77) -> 395
B78: Senior Housing | C78: 135 | D78: 620 | E78: =SUM(C78:D78) -> 755
B79: Skilled Nursing | C79: — | D79: 419 | E79: =SUM(C79:D79) -> 419
B80: Student Housing | C80: 50 | D80: 135 | E80: =SUM(C80:D80) -> 185
B81: Other | C81: — | D81: 295 | E81: =SUM(C81:D81) -> 295
B82: Total CRE | C82: =SUM(C69:C81) -> 2803 | D82: =SUM(D69:D81) -> 11145 | E82: =SUM(E69:E81) -> 13948

Sheet KEY LLM API
B2: 4Q24 AI API Script
B15: Correct
B17: CRE Property Type | C17: Loan Amount
B18: Data Center | C18: 152
B19: Diversified | C19: 135
B20: Industrial | C20: 733
B21: Land & Residential | C21: 48
B22: Lodging | C22: 234
B23: Medical Office | C23: 271
B24: Multifamily | C24: 8010
B25: Office | C25: 738
B26: Retail | C26: 880
B27: Self Storage | C27: 360
B28: Senior Housing | C28: 593
B29: Skilled Nursing | C29: 392
... B32: Total CRE | C32: 13004
B34: CRE Property Type | C34: Loan Amount | E34: CRE Property Type | F34: Loan Amount | H34: =B34=E34 -> TRUE | I34: =C34=F34 -> TRUE
B35: Multi-family | C35: =C24 -> 8010 | E35: Multi-family | F35: 8010 | H35: =B35=E35 -> TRUE | I35: =C35=F35 -> TRUE
B36: Office | C36: =C25+C23 -> 1009 | E36: Office | F36: 1009 | H36: =B36=E36 -> TRUE | I36: =C36=F36 -> TRUE
B37: Industrial | C37: =C20 -> 733 | E37: Industrial | F37: 733 | H37: =B37=E37 -> TRUE | I37: =C37=F37 -> TRUE
B38: Retail | C38: =C26 -> 880 | E38: Retail | F38: 880 | H38: =B38=E38 -> TRUE | I38: =C38=F38 -> TRUE
B39: Lodging | C39: =C22 -> 234 | E39: Lodging | F39: 234 | H39: =B39=E39 -> TRUE | I39: =C39=F39 -> TRUE
B40: Other | C40: =SUM(C27:C31,C19,C21,C18) -> 2138 | E40: Other | F40: 2138 | H40: =B40=E40 -> TRUE | I40: =C40=F40 -> TRUE
B41: Total CRE | C41: =SUM(C35:C40) -> 13004 | E41: Total CRE | F41: =SUM(F35:F40) -> 13004 | H41: =B41=E41 -> TRUE | I41: =C41=F41 -> TRUE
E43: Accuracy | F43: =16/16 -> 1
B46: 3Q24 AI API Script
B61: Correct
B63: CRE Property Type | C63: Loan Amount
B64: Diversified | C64: 136
B65: Industrial | C65: 763
B66: Land & Residential | C66: 41
B67: Lodging | C67: 226
B68: Medical Office | C68: 278
B69: Multifamily | C69: 8387
B70: Office | C70: 752
B71: Retail | C71: 889
B72: Self Storage | C72: 386
B73: Senior Housing | C73: 644
B74: Skilled Nursing | C74: 338
B75: Student Housing | C75: 205
... B77: Total CRE | C77: 13322
B79: CRE Property Type | C79: Loan Amount | E79: CRE Property Type | F79: Loan Amount | H79: =B79=E79 -> TRUE | I79: =C79=F79 -> TRUE
B80: Multi-family | C80: =C69 -> 8387 | E80: Multi-family | F80: 8387 | H80: =B80=E80 -> TRUE | I80: =C80=F80 -> TRUE
B81: Office | C81: =C70+C68 -> 1030 | E81: Office | F81: 1030 | H81: =B81=E81 -> TRUE | I81: =C81=F81 -> TRUE
B82: Industrial | C82: =C65 -> 763 | E82: Industrial | F82: 763 | H82: =B82=E82 -> TRUE | I82: =C82=F82 -> TRUE
B83: Retail | C83: =C71 -> 889 | E83: Retail | F83: 889 | H83: =B83=E83 -> TRUE | I83: =C83=F83 -> TRUE
B84: Lodging | C84: =C67 -> 226 | E84: Lodging | F84: 226 | H84: =B84=E84 -> TRUE | I84: =C84=F84 -> TRUE
B85: Other | C85: =SUM(C72:C76,C64,C66) -> 2027 | E85: Other | F85: 2027 | H85: =B85=E85 -> TRUE | I85: =C85=F85 -> TRUE
B86: Total CRE | C86: =SUM(C80:C85) -> 13322 | E86: Total CRE | F86: =SUM(F80:F85) -> 13322 | H86: =B86=E86 -> TRUE | I86: =C86=F86 -> TRUE
E88: Accuracy | F88: =16/16 -> 1
B90: 2Q24 AI API Script
B112: Correct
B114: CRE Property Type | C114: Loan Amount
B115: Diversified | C115: 143
B116: Industrial | C116: 779
B117: Land & Residential | C117: 38
B118: Lodging | C118: 214
B119: Medical Office | C119: 275
B120: Multifamily | C120: 8576
B121: Office | C121: 773
B122: Retail | C122: 902
B123: Self Storage | C123: 382
B124: Senior Housing | C124: 667
B125: Skilled Nursing | C125: 483
B126: Student Housing | C126: 185
B127: Other | C127: 298
B128: Total CRE | C128: =SUM(C115:C127) -> 13715
B130: CRE Property Type | C130: Loan Amount | E130: CRE Property Type | F130: Loan Amount | H130: =B130=E130 -> TRUE | I130: =C130=F130 -> TRUE
B131: Multi-family | C131: =C120 -> 8576 | E131: Multi-family | F131: 8676 | H131: =B131=E131 -> TRUE | I131: =C131=F131 -> FALSE
B132: Office | C132: =C121+C119 -> 1048 | E132: Office | F132: 1048 | H132: =B132=E132 -> TRUE | I132: =C132=F132 -> TRUE
B133: Industrial | C133: =C116 -> 779 | E133: Industrial | F133: 779 | H133: =B133=E133 -> TRUE | I133: =C133=F133 -> TRUE
B134: Retail | C134: =C122 -> 902 | E134: Retail | F134: 902 | H134: =B134=E134 -> TRUE | I134: =C134=F134 -> TRUE
B135: Lodging | C135: =C118 -> 214 | E135: Lodging | F135: 214 | H135: =B135=E135 -> TRUE | I135: =C135=F135 -> TRUE
B136: Other | C136: =SUM(C123:C127,C115,C117) -> 2196 | E136: Other | F136: 2096 | H136: =B136=E136 -> TRUE | I136: =C136=F136 -> FALSE
B137: Total CRE | C137: =SUM(C131:C136) -> 13715 | E137: Total CRE | F137: =SUM(F131:F136) -> 13715 | H137: =B137=E137 -> TRUE | I137: =C137=F137 -> TRUE
E139: Accuracy | F139: =14/16 -> 0.875
B141: 1Q24 AI API Script
B163: Correct
B165: CRE Property Type | C165: Loan Amount
B166: Diversified | C166: 142
B167: Industrial | C167: 791
B168: Land & Residential | C168: 36
B169: Lodging | C169: 222
B170: Medical Office | C170: 278
B171: Multifamily | C171: 8608
B172: Office | C172: 845
B173: Retail | C173: 977
B174: Self Storage | C174: 395
B175: Senior Housing | C175: 755
B176: Skilled Nursing | C176: 419
B177: Student Housing | C177: 185
B178: Other | C178: 295
B179: Total CRE | C179: =SUM(C166:C178) -> 13948
B181: CRE Property Type | C181: Loan Amount | E181: CRE Property Type | F181: Loan Amount | H181: =B181=E181 -> TRUE | I181: =C181=F181 -> TRUE
B182: Multi-family | C182: =C171 -> 8608 | E182: Multi-family | F182: 8608 | H182: =B182=E182 -> TRUE | I182: =C182=F182 -> TRUE
B183: Office | C183: =C172+C170 -> 1123 | E183: Office | F183: 845 | H183: =B183=E183 -> TRUE | I183: =C183=F183 -> FALSE
B184: Industrial | C184: =C167 -> 791 | E184: Industrial | F184: 791 | H184: =B184=E184 -> TRUE | I184: =C184=F184 -> TRUE
B185: Retail | C185: =C173 -> 977 | E185: Retail | F185: 957 | H185: =B185=E185 -> TRUE | I185: =C185=F185 -> FALSE
B186: Lodging | C186: =C169 -> 222 | E186: Lodging | F186: 222 | H186: =B186=E186 -> TRUE | I186: =C186=F186 -> TRUE
B187: Other | C187: =SUM(C174:C178,C166,C168) -> 2227 | E187: Other | F187: 3231 | H187: =B187=E187 -> TRUE | I187: =C187=F187 -> FALSE
...

Sheet KEY Script
B2: Script 4Q24 (10-Q) | K2: Script 3Q24 (10-Q)
B13: Script 2Q24 (10-Q) | K13: Script 1Q24 (10-Q)

Sheet HBAN

Sheet HBAN Manual
A3: 4Q24 | B3: CRE Property Type | C3: Loan Amount | E3: Ticker | F3: Quarter | G3: CRE Property Type | H3: Loan Amount | I3: Unit | J3: Currency | K3: Category
B4: Multi-family | C4: 4426 | E4: HBAN | F4: 4Q24 | G4: Multi-family | H4: =C4 -> 4426 | I4: mn | J4: USD | K4: CRE
B5: Industrial | C5: 1604 | E5: HBAN | F5: 4Q24 | G5: Industrial | H5: =C5 -> 1604 | I5: mn | J5: USD | K5: CRE
B6: Office | C6: 1559 | E6: HBAN | F6: 4Q24 | G6: Office | H6: =C6 -> 1559 | I6: mn | J6: USD | K6: CRE
B7: Retail | C7: 1477 | E7: HBAN | F7: 4Q24 | G7: Retail | H7: =C7 -> 1477 | I7: mn | J7: USD | K7: CRE
B8: Lodging | C8: 817 | E8: HBAN | F8: 4Q24 | G8: Lodging | H8: =C8 -> 817 | I8: mn | J8: USD | K8: CRE
B9: Other | C9: 1195 | E9: HBAN | F9: 4Q24 | G9: Other | H9: =C9 -> 1195 | I9: mn | J9: USD | K9: CRE
B10: Total CRE | C10: =SUM(C4:C9) -> 11078 | E10: HBAN | F10: 4Q24 | G10: Total CRE | H10: =SUM(H4:H9) -> 11078 | I10: mn | J10: USD | K10: CRE
A14: 3Q24 | B14: CRE Property Type | C14: Loan Amount | E14: Ticker | F14: Quarter | G14: CRE Property Type | H14: Loan Amount | I14: Unit | J14: Currency | K14: Category
B15: Multi-family | C15: 4524 | E15: HBAN | F15: 3Q24 | G15: Multi-family | H15: =C15 -> 4524 | I15: mn | J15: USD | K15: CRE
B16: Industrial | C16: 1954 | E16: HBAN | F16: 3Q24 | G16: Industrial | H16: =C16 -> 1954 | I16: mn | J16: USD | K16: CRE
B17: Office | C17: 1601 | E17: HBAN | F17: 3Q24 | G17: Office | H17: =C17 -> 1601 | I17: mn | J17: USD | K17: CRE
B18: Retail | C18: 1580 | E18: HBAN | F18: 3Q24 | G18: Retail | H18: =C18 -> 1580 | I18: mn | J18: USD | K18: CRE
B19: Lodging | C19: 853 | E19: HBAN | F19: 3Q24 | G19: Lodging | H19: =C19 -> 853 | I19: mn | J19: USD | K19: CRE
B20: Other | C20: 1031 | E20: HBAN | F20: 3Q24 | G20: Other | H20: =C20 -> 1031 | I20: mn | J20: USD | K20: CRE
B21: Total CRE | C21: =SUM(C15:C20) -> 11543 | E21: HBAN | F21: 3Q24 | G21: Total CRE | H21: =SUM(H15:H20) -> 11543 | I21: mn | J21: USD | K21: CRE
A26: 2Q24 | B26: CRE Property Type | C26: Loan Amount | E26: Ticker | F26: Quarter | G26: CRE Property Type | H26: Loan Amount | I26: Unit | J26: Currency | K26: Category
B27: Multi-family | C27: 4628 | E27: HBAN | F27: 2Q24 | G27: Multi-family | H27: =C27 -> 4628 | I27: mn | J27: USD | K27: CRE
B28: Industrial | C28: 1979 | E28: HBAN | F28: 2Q24 | G28: Industrial | H28: =C28 -> 1979 | I28: mn | J28: USD | K28: CRE
B29: Office | C29: 1706 | E29: HBAN | F29: 2Q24 | G29: Office | H29: =C29 -> 1706 | I29: mn | J29: USD | K29: CRE
B30: Retail | C30: 1606 | E30: HBAN | F30: 2Q24 | G30: Retail | H30: =C30 -> 1606 | I30: mn | J30: USD | K30: CRE
B31: Lodging | C31: 904 | E31: HBAN | F31: 2Q24 | G31: Lodging | H31: =C31 -> 904 | I31: mn | J31: USD | K31: CRE
B32: Other | C32: 1110 | E32: HBAN | F32: 2Q24 | G32: Other | H32: =C32 -> 1110 | I32: mn | J32: USD | K32: CRE
B33: Total CRE | C33: =SUM(C27:C32) -> 11933 | E33: HBAN | F33: 2Q24 | G33: Total CRE | H33: =SUM(H27:H32) -> 11933 | I33: mn | J33: USD | K33: CRE
A37: 1Q24 | B37: CRE Property Type | C37: Loan Amount | E37: Ticker | F37: Quarter | G37: CRE Property Type | H37: Loan Amount | I37: Unit | J37: Currency | K37: Category
B38: Multi-family | C38: 4692 | E38: HBAN | F38: 1Q24 | G38: Multi-family | H38: =C38 -> 4692 | I38: mn | J38: USD | K38: CRE
B39: Industrial | C39: 2007 | E39: HBAN | F39: 1Q24 | G39: Industrial | H39: =C39 -> 2007 | I39: mn | J39: USD | K39: CRE
B40: Office | C40: 1766 | E40: HBAN | F40: 1Q24 | G40: Office | H40: =C40 -> 1766 | I40: mn | J40: USD | K40: CRE
B41: Retail | C41: 1692 | E41: HBAN | F41: 1Q24 | G41: Retail | H41: =C41 -> 1692 | I41: mn | J41: USD | K41: CRE
B42: Lodging | C42: 946 | E42: HBAN | F42: 1Q24 | G42: Lodging | H42: =C42 -> 946 | I42: mn | J42: USD | K42: CRE
B43: Other | C43: 1239 | E43: HBAN | F43: 1Q24 | G43: Other | H43: =C43 -> 1239 | I43: mn | J43: USD | K43: CRE
B44: Total CRE | C44: =SUM(C38:C43) -> 12342 | E44: HBAN | F44: 1Q24 | G44: Total CRE | H44: =SUM(H38:H43) -> 12342 | I44: mn | J44: USD | K44: CRE

Sheet HBAN LLM API
B2: 4Q24 AI API Script
B14: Correct | E14: LLM
B16: CRE Property Type | C16: Loan Amount | E16: CRE Property Type | F16: Loan Amount | H16: =B16=E16 -> TRUE | I16: =C16=F16 -> TRUE
B17: Multi-family | C17: 4.4 | E17: Multi-family | F17: 4.4 | H17: =B17=E17 -> TRUE | I17: =C17=F17 -> TRUE
B18: Industrial | C18: 1.6 | E18: Industrial | F18: 1.6 | H18: =B18=E18 -> TRUE | I18: =C18=F18 -> TRUE
B19: Office | C19: 1.6 | E19: Office | F19: 1.6 | H19: =B19=E19 -> TRUE | I19: =C19=F19 -> TRUE
B20: Retail | C20: 1.5 | E20: Retail | F20: 1.5 | H20: =B20=E20 -> TRUE | I20: =C20=F20 -> TRUE
B21: Lodging | C21: 0.8 | E21: Lodging | F21: 0.8 | H21: =B21=E21 -> TRUE | I21: =C21=F21 -> TRUE
B22: Other | C22: 1.2 | E22: Other | F22: 1.2 | H22: =B22=E22 -> TRUE | I22: =C22=F22 -> TRUE
B23: Total CRE | C23: =SUM(C17:C22) -> 11.1 | E23: Total CRE | F23: =SUM(F17:F22) -> 11.1 | H23: =B23=E23 -> TRUE | I23: =C23=F23 -> TRUE
E25: Accuracy | F25: =16/16 -> 1
B27: 3Q24 AI API Script
B40: Correct | E40: LLM
B42: CRE Property Type | C42: Loan Amount | E42: CRE Property Type | F42: Loan Amount | H42: =B42=E42 -> TRUE | I42: =C42=F42 -> TRUE
B43: Multi-family | C43: 4.5 | E43: Multi-family | F43: 4.5 | H43: =B43=E43 -> TRUE | I43: =C43=F43 -> TRUE
B44: Industrial | C44: 2 | E44: Industrial | F44: 2 | H44: =B44=E44 -> TRUE | I44: =C44=F44 -> TRUE
B45: Office | C45: 1.6 | E45: Office | F45: 1.6 | H45: =B45=E45 -> TRUE | I45: =C45=F45 -> TRUE
B46: Retail | C46: 1.6 | E46: Retail | F46: 1.6 | H46: =B46=E46 -> TRUE | I46: =C46=F46 -> TRUE
B47: Lodging | C47: 0.9 | E47: Lodging | F47: 0.9 | H47: =B47=E47 -> TRUE | I47: =C47=F47 -> TRUE
B48: Other | C48: 0.9 | E48: Other | F48: 0.9 | H48: =B48=E48 -> TRUE | I48: =C48=F48 -> TRUE
B49: Total CRE | C49: =SUM(C43:C48) -> 11.5 | E49: Total CRE | F49: 11.5 | H49: =B49=E49 -> TRUE | I49: =C49=F49 -> TRUE
E51: Accuracy | F51: =16/16 -> 1
B53: 2Q24 AI API Script
B65: Correct | E65: LLM
B67: CRE Property Type | C67: Loan Amount | E67: CRE Property Type | F67: Loan Amount | H67: =B67=E67 -> TRUE | I67: =C67=F67 -> TRUE
B68: Multi-family | C68: 4.6 | E68: Multi-family | F68: 4.6 | H68: =B68=E68 -> TRUE | I68: =C68=F68 -> TRUE
B69: Industrial | C69: 2 | E69: Industrial | F69: 2 | H69: =B69=E69 -> TRUE | I69: =C69=F69 -> TRUE
B70: Office | C70: 1.7 | E70: Office | F70: 1.7 | H70: =B70=E70 -> TRUE | I70: =C70=F70 -> TRUE
B71: Retail | C71: 1.6 | E71: Retail | F71: 1.6 | H71: =B71=E71 -> TRUE | I71: =C71=F71 -> TRUE
B72: Lodging | C72: 0.9 | E72: Lodging | F72: 0.9 | H72: =B72=E72 -> TRUE | I72: =C72=F72 -> TRUE
B73: Other | C73: 1.1 | E73: Other | F73: 1.1 | H73: =B73=E73 -> TRUE | I73: =C73=F73 -> TRUE
B74: Total CRE | C74: =SUM(C68:C73) -> 11.9 | E74: Total CRE | F74: =SUM(F68:F73) -> 11.9 | H74: =B74=E74 -> TRUE | I74: =C74=F74 -> TRUE
E76: Accuracy | F76: =16/16 -> 1
B79: 1Q24 AI API Script
B92: Correct | E92: LLM
B93: CRE Property Type | C93: Loan Amount | E93: CRE Property Type | F93: Loan Amount | H93: =B93=E93 -> TRUE | I93: =C93=F93 -> TRUE
B94: Multi-family | C94: 4.7 | E94: Multi-family | F94: 4.7 | H94: =B94=E94 -> TRUE | I94: =C94=F94 -> TRUE
B95: Industrial | C95: 2 | E95: Industrial | F95: 2 | H95: =B95=E95 -> TRUE | I95: =C95=F95 -> TRUE
B96: Office | C96: 1.8 | E96: Office | F96: 1.8 | H96: =B96=E96 -> TRUE | I96: =C96=F96 -> TRUE
B97: Retail | C97: 1.7 | E97: Retail | F97: 1.7 | H97: =B97=E97 -> TRUE | I97: =C97=F97 -> TRUE
B98: Lodging | C98: 0.9 | E98: Lodging | F98: 0.9 | H98: =B98=E98 -> TRUE | I98: =C98=F98 -> TRUE
B99: Other | C99: 1.2 | E99: Other | F99: 1.2 | H99: =B99=E99 -> TRUE | I99: =C99=F99 -> TRUE
B100: Total CRE | C100: =SUM(C94:C99) -> 12.3 | E100: Total CRE | F100: =SUM(F94:F99) -> 12.3 | H100: =B100=E100 -> TRUE | I100: =C100=F100 -> TRUE
E102: Accuracy | F102: =16/16 -> 1

Sheet HBAN Script
B2: Script 4Q24 (10-Q) | K2: Script 3Q24 (10-Q)
B13: Script 2Q24 (10-Q) | K13: Script 1Q24 (10-Q)

Sheet CFG

Sheet CFG Manual
A2: 4Q24 | B2: Manual 4Q24 (10-Q)
B4: CRE Property Type | C4: Loan Amount | E4: CRE Property Type | F4: Loan Amount | H4: Ticker | I4: Quarter | J4: CRE Property Type | K4: Loan Amount | L4: Unit | M4: Currency | N4: Category
B5: Multi-family | C5: 9791 | E5: Multi-family | F5: =C5 -> 9791 | H5: CFG | I5: 4Q24 | J5: Multi-family | K5: =F5 -> 9791 | L5: mn | M5: USD | N5: CRE
B6: Office | E6: Office | F6: =SUM(C7:C8) -> 5065 | H6: CFG | I6: 4Q24 | J6: Office | K6: =F6 -> 5065 | L6: mn | M6: USD | N6: CRE
B7: Credit tenant lease and life sciences | C7: 2135 | E7: Retail | F7: =C9 -> 2940 | H7: CFG | I7: 4Q24 | J7: Retail | K7: =F7 -> 2940 | L7: mn | M7: USD | N7: CRE
B8: Other general office | C8: 2930 | E8: Industrial | F8: =C10 -> 3575 | H8: CFG | I8: 4Q24 | J8: Industrial | K8: =F8 -> 3575 | L8: mn | M8: USD | N8: CRE
B9: Retail | C9: 2940 | E9: Lodging | F9: =C13 -> 418 | H9: CFG | I9: 4Q24 | J9: Lodging | K9: =F9 -> 418 | L9: mn | M9: USD | N9: CRE
B10: Industrial | C10: 3575 | E10: Other | F10: =SUM(C14,C11:C12) -> 5436 | H10: CFG | I10: 4Q24 | J10: Other | K10: =F10 -> 5436 | L10: mn | M10: USD | N10: CRE
B11: Co-op | C11: 1802 | E11: Total CRE | F11: =SUM(F5:F10) -> 27225 | H11: CFG | I11: 4Q24 | J11: Total CRE | K11: =SUM(K5:K10) -> 27225 | L11: mn | M11: USD | N11: CRE
B12: Data center | C12: 1024
B13: Hospitality | C13: 418
B14: Other | C14: 2610
B15: Total CRE | C15: =SUM(C5:C14) -> 27225
A22: 3Q24 | B22: CRE Property Type | C22: Loan Amount | E22: CRE Property Type | F22: Loan Amount | H22: Ticker | I22: Quarter | J22: CRE Property Type | K22: Loan Amount | L22: Unit | M22: Currency | N22: Category
B23: Multi-family | C23: 9952 | E23: Multi-family | F23: =C23 -> 9952 | H23: CFG | I23: 3Q24 | J23: Multi-family | K23: 9952 | L23: mn | M23: USD | N23: CRE
B24: Office | E24: Office | F24: =SUM(C25:C26) -> 5376 | H24: CFG | I24: 3Q24 | J24: Office | K24: 5376 | L24: mn | M24: USD | N24: CRE
B25: Credit tenant | C25: 2220 | E25: Retail | F25: =C27 -> 2987 | H25: CFG | I25: 3Q24 | J25: Retail | K25: 2987 | L25: mn | M25: USD | N25: CRE
B26: Other Office | C26: 3156 | E26: Industrial | F26: =C28 -> 3744 | H26: CFG | I26: 3Q24 | J26: Industrial | K26: 3744 | L26: mn | M26: USD | N26: CRE
B27: Retail | C27: 2987 | E27: Lodging | F27: =C31 -> 423 | H27: CFG | I27: 3Q24 | J27: Lodging | K27: 423 | L27: mn | M27: USD | N27: CRE
B28: Industrial | C28: 3744 | E28: Other | F28: =SUM(C32,C29:C30) -> 5501 | H28: CFG | I28: 3Q24 | J28: Other | K28: 5501 | L28: mn | M28: USD | N28: CRE
B29: Co-op | C29: 1807 | E29: Total CRE | F29: =SUM(F23:F28) -> 27983 | H29: CFG | I29: 3Q24 | J29: Total CRE | K29: 27983 | L29: mn | M29: USD | N29: CRE
B30: Data center | C30: 991
B31: Hospitality | C31: 423
B32: Other | C32: 2703
B33: Total CRE | C33: =SUM(C23:C32) -> 27983
A37: 2Q24 | B37: CRE Property Type | C37: Loan Amount | E37: CRE Property Type | F37: Loan Amount | H37: Ticker | I37: Quarter | J37: CRE Property Type | K37: Loan Amount | L37: Unit | M37: Currency | N37: Category
B38: Multi-family | C38: 9689 | E38: Multi-family | F38: =C38 -> 9689 | H38: CFG | I38: 2Q24 | J38: Multi-family | K38: =F38 -> 9689 | L38: mn | M38: USD | N38: CRE
B39: Office | E39: Office | F39: =SUM(C40:C41) -> 5626 | H39: CFG | I39: 2Q24 | J39: Office | K39: =F39 -> 5626 | L39: mn | M39: USD | N39: CRE
B40: e | C40: 2303 | E40: Retail | F40: =C42 -> 3322 | H40: CFG | I40: 2Q24 | J40: Retail | K40: =F40 -> 3322 | L40: mn | M40: USD | N40: CRE
B41: Other general office | C41: 3323 | E41: Industrial | F41: =C43 -> 3689 | H41: CFG | I41: 2Q24 | J41: Industrial | K41: =F41 -> 3689 | L41: mn | M41: USD | N41: CRE
B42: Retail | C42: 3322 | E42: Lodging | F42: =C46 -> 425 | H42: CFG | I42: 2Q24 | J42: Lodging | K42: =F42 -> 425 | L42: mn | M42: USD | N42: CRE
B43: Industrial | C43: 3689 | E43: Other | F43: =SUM(C47,C44:C45) -> 5560 | H43: CFG | I43: 2Q24 | J43: Other | K43: =F43 -> 5560 | L43: mn | M43: USD | N43: CRE
B44: Co-op | C44: 1810 | E44: Total CRE | F44: =SUM(F38:F43) -> 28311 | H44: CFG | I44: 2Q24 | J44: Total CRE | K44: =SUM(K38:K43) -> 28311 | L44: mn | M44: USD | N44: CRE
B45: Data center | C45: 679
B46: Hospitality | C46: 425
B47: Other | C47: 3071
B48: Total CRE | C48: =SUM(C38:C47) -> 28311
A53: 1Q24 | B53: CRE Property Type | C53: Loan Amount | E53: CRE Property Type | F53: Loan Amount | H53: Ticker | I53: Quarter | J53: CRE Property Type | K53: Loan Amount | L53: Unit | M53: Currency | N53: Category
B54: Multi-family | C54: 9491 | E54: Multi-family | F54: =C54 -> 9491 | H54: CFG | I54: 1Q24 | J54: Multi-family | K54: =F54 -> 9491 | L54: mn | M54: USD | N54: CRE
B55: Office | E55: Office | F55: =SUM(C56:C57) -> 5708 | H55: CFG | I55: 1Q24 | J55: Office | K55: =F55 -> 5708 | L55: mn | M55: USD | N55: CRE
B56: Credit tenant lease and life sciences | C56: 2265 | E56: Retail | F56: =C58 -> 3376 | H56: CFG | I56: 1Q24 | J56: Retail | K56: =F56 -> 3376 | L56: mn | M56: USD | N56: CRE
B57: Other general office | C57: 3443 | E57: Industrial | F57: =C59 -> 4079 | H57: CFG | I57: 1Q24 | J57: Industrial | K57: =F57 -> 4079 | L57: mn | M57: USD | N57: CRE
B58: Retail | C58: 3376 | E58: Lodging | F58: =C62 -> 552 | H58: CFG | I58: 1Q24 | J58: Lodging | K58: =F58 -> 552 | L58: mn | M58: USD | N58: CRE
B59: Industrial | C59: 4079 | E59: Other | F59: =SUM(C63,C60:C61) -> 5666 | H59: CFG | I59: 1Q24 | J59: Other | K59: =F59 -> 5666 | L59: mn | M59: USD | N59: CRE
B60: Co-op | C60: 1816 | E60: Total CRE | F60: =SUM(F54:F59) -> 28872 | H60: CFG | I60: 1Q24 | J60: Total CRE | K60: =SUM(K54:K59) -> 28872 | L60: mn | M60: USD | N60: CRE
B61: Data center | C61: 722
B62: Hospitality | C62: 552
B63: Other | C63: 3128
B64: Total CRE | C64: =SUM(C54:C63) -> 28872

Sheet CFG LLM API
B2: 4Q24 AI API Script
B13: Correct | E13: LLM
B15: CRE Property Type | C15: Loan Amount | E15: CRE Property Type | F15: Loan Amount | H15: =B15=E15 -> TRUE | I15: =C15=F15 -> TRUE
B16: Multi-family | C16: 9.8 | E16: Multi-family | F16: 9.8 | H16: =B16=E16 -> TRUE | I16: =C16=F16 -> TRUE
B17: Office | C17: 5.1 | E17: Office | F17: 5.1 | H17: =B17=E17 -> TRUE | I17: =C17=F17 -> TRUE
B18: Industrial | C18: 3.6 | E18: Industrial | F18: 3.6 | H18: =B18=E18 -> TRUE | I18: =C18=F18 -> TRUE
B19: Retail | C19: 2.9 | E19: Retail | F19: 2.9 | H19: =B19=E19 -> TRUE | I19: =C19=F19 -> TRUE
B20: Lodging | C20: 0.4 | E20: Lodging | F20: 0.4 | H20: =B20=E20 -> TRUE | I20: =C20=F20 -> TRUE
B21: Other | C21: =2.6+1.8+1 -> 5.4 | E21: Other | F21: 5.4 | H21: =B21=E21 -> TRUE | I21: =C21=F21 -> TRUE
B22: Total CRE | C22: =SUM(C16:C21) -> 27.2 | E22: Total CRE | F22: =SUM(F16:F21) -> 27.2 | H22: =B22=E22 -> TRUE | I22: =C22=F22 -> TRUE
E24: Accuracy | F24: =16/16 -> 1
B26: 3Q24 AI API Script
B39: Correct | E39: LLM
B41: CRE Property Type | C41: Loan Amount | E41: CRE Property Type | F41: Loan Amount | H41: =B41=E41 -> TRUE | I41: =C41=F41 -> TRUE
B42: Multi-family | C42: 10 | E42: Multi-family | F42: 10 | H42: =B42=E42 -> TRUE | I42: =C42=F42 -> TRUE
B43: Office | C43: 5.4 | E43: Office | F43: 5.4 | H43: =B43=E43 -> TRUE | I43: =C43=F43 -> TRUE
B44: Industrial | C44: 3.7 | E44: Industrial | F44: 3.7 | H44: =B44=E44 -> TRUE | I44: =C44=F44 -> TRUE
B45: Retail | C45: 3 | E45: Retail | F45: 3 | H45: =B45=E45 -> TRUE | I45: =C45=F45 -> TRUE
B46: Lodging | C46: 0.4 | E46: Lodging | F46: 0.4 | H46: =B46=E46 -> TRUE | I46: =C46=F46 -> TRUE
B47: Other | C47: =2.7+1.8+1 -> 5.5 | E47: Other | F47: 5.5 | H47: =B47=E47 -> TRUE | I47: =C47=F47 -> TRUE
B48: Total CRE | C48: =SUM(C42:C47) -> 28 | E48: Total CRE | F48: =SUM(F42:F47) -> 28 | H48: =B48=E48 -> TRUE | I48: =C48=F48 -> TRUE
E50: Accuracy | F50: =16/16 -> 1
B52: 2Q24 AI API Script
B64: Correct | E64: LLM
B66: CRE Property Type | C66: Loan Amount | E66: CRE Property Type | F66: Loan Amount | H66: =B66=E66 -> TRUE | I66: =C66=F66 -> TRUE
B67: Multi-family | C67: 9.7 | E67: Multi-family | F67: 9.7 | H67: =B67=E67 -> TRUE | I67: =C67=F67 -> TRUE
B68: Office | C68: =2.3+3.3 -> 5.6 | E68: Office | F68: 5.6 | H68: =B68=E68 -> TRUE | I68: =C68=F68 -> TRUE
B69: Industrial | C69: 3.7 | E69: Industrial | F69: 3.7 | H69: =B69=E69 -> TRUE | I69: =C69=F69 -> TRUE
B70: Retail | C70: 3.3 | E70: Retail | F70: 3.3 | H70: =B70=E70 -> TRUE | I70: =C70=F70 -> TRUE
B71: Lodging | C71: 0.4 | E71: Lodging | F71: 0.4 | H71: =B71=E71 -> TRUE | I71: =C71=F71 -> TRUE
B72: Other | C72: =1.8+0.7+3.1 -> 5.6 | E72: Other | F72: =3.1+1.8+0.7 -> 5.6 | H72: =B72=E72 -> TRUE | I72: =C72=F72 -> TRUE
B73: Total CRE | C73: =SUM(C67:C72) -> 28.3 | E73: Total CRE | F73: =SUM(F67:F72) -> 28.3 | H73: =B73=E73 -> TRUE | I73: =C73=F73 -> TRUE
E75: Accuracy | F75: =16/16 -> 1
B77: 1Q24 AI API Script
B89: Correct | E89: LLM
B91: CRE Property Type | C91: Loan Amount | E91: CRE Property Type | F91: Loan Amount | H91: =B91=E91 -> TRUE | I91: =C91=F91 -> TRUE
B92: Multi-family | C92: 9.5 | E92: Multi-family | F92: 9.5 | H92: =B92=E92 -> TRUE | I92: =C92=F92 -> TRUE
B93: Office | C93: =2.3+3.4 -> 5.7 | E93: Office | F93: 5.7 | H93: =B93=E93 -> TRUE | I93: =C93=F93 -> TRUE
B94: Industrial | C94: 4.1 | E94: Industrial | F94: 4.1 | H94: =B94=E94 -> TRUE | I94: =C94=F94 -> TRUE
B95: Retail | C95: 3.4 | E95: Retail | F95: 3.4 | H95: =B95=E95 -> TRUE | I95: =C95=F95 -> TRUE
B96: Lodging | C96: 0.6 | E96: Lodging | F96: 0.6 | H96: =B96=E96 -> TRUE | I96: =C96=F96 -> TRUE
B97: Other | C97: =3.1+1.8+0.7 -> 5.6 | E97: Other | F97: 5.6 | H97: =B97=E97 -> TRUE | I97: =C97=F97 -> TRUE
B98: Total CRE | C98: =SUM(C92:C97) -> 28.9 | E98: Total CRE | F98: =SUM(F92:F97) -> 28.9 | H98: =B98=E98 -> TRUE | I98: =C98=F98 -> TRUE
E100: Accuracy | F100: =16/16 -> 1

Sheet CFG Script
B2: Script 4Q24 (10-Q) | K2: Script 3Q24 (10-Q)
B12: Script 2Q24 (10-Q) | K12: Script 1Q24 (10-Q)

Sheet SNV

Sheet SNV Manual
A2: 4Q24
B11: CRE Property Type | C11: Loan Amount | E11: CRE Property Type | F11: Loan Amount | H11: Ticker | I11: Quarter | J11: CRE Property Type | K11: Loan Amount | L11: Unit | M11: Currency | N11: Category
B12: Multi-family | C12: 4185.545 | E12: Multi-family | F12: =C12 -> 4185.545 | H12: SNV | I12: 2Q24 | J12: Multi-family | K12: =F12 -> 4185.545 | L12: mn | M12: USD | N12: CRE
B13: Hotels | C13: 1769.384 | E13: Lodging | F13: =C13 -> 1769.384 | H13: SNV | I13: 2Q24 | J13: Lodging | K13: =F13 -> 1769.384 | L13: mn | M13: USD | N13: CRE
B14: Office buildings | C14: 1743.329 | E14: Office | F14: =C14 -> 1743.329 | H14: SNV | I14: 2Q24 | J14: Office | K14: =F14 -> 1743.329 | L14: mn | M14: USD | N14: CRE
B15: Shopping centers | C15: 1273.439 | E15: Retail | F15: =C15 -> 1273.439 | H15: SNV | I15: 2Q24 | J15: Retail | K15: =F15 -> 1273.439 | L15: mn | M15: USD | N15: CRE
B16: Warehouses | C16: 846.025 | E16: Industrial | F16: =C16 -> 846.025 | H16: SNV | I16: 2Q24 | J16: Industrial | K16: =F16 -> 846.025 | L16: mn | M16: USD | N16: CRE
B17: Other investment property | C17: 1363.482 | E17: Residential | F17: =C19 -> 545.918 | H17: SNV | I17: 2Q24 | J17: Other | K17: =F18 -> 1650.979 | L17: mn | M17: USD | N17: CRE
B18: Total Investment CRE | C18: =SUM(C12:C17) -> 11181.204 | E18: Other | F18: =SUM(C17,C20) -> 1650.979 | H18: SNV | I18: 2Q24 | J18: Residential | K18: =F17 -> 545.918 | L18: mn | M18: USD | N18: CRE
B19: Residential | C19: 545.918 | E19: Total CRE | F19: =SUM(F12:F18) -> 12014.619 | H19: SNV | I19: 2Q24 | J19: Total CRE | K19: =SUM(K12:K18) -> 12014.619 | L19: mn | M19: USD | N19: CRE
B20: Land & Development | C20: 287.497
B21: Total CRE | C21: =SUM(C18:C20) -> 12014.619
A25: 3Q24
B34: CRE Property Type | C34: Loan Amount | E34: CRE Property Type | F34: Loan Amount | H34: Ticker | I34: Quarter | J34: CRE Property Type | K34: Loan Amount | L34: Unit | M34: Currency | N34: Category
B35: Multi-family | C35: 4379.459 | E35: Multi-family | F35: 4379.459 | H35: SNV | I35: 3Q24 | J35: Multi-family | K35: 4379.459 | L35: mn | M35: USD | N35: CRE
B36: Lodging | C36: 1738.068 | E36: Lodging | F36: 1738.068 | H36: SNV | I36: 3Q24 | J36: Lodging | K36: 1738.068 | L36: mn | M36: USD | N36: CRE
B37: Office | C37: 1778.698 | E37: Office | F37: 1778.698 | H37: SNV | I37: 3Q24 | J37: Office | K37: 1778.698 | L37: mn | M37: USD | N37: CRE
B38: Retail | C38: 1260.46 | E38: Retail | F38: 1260.46 | H38: SNV | I38: 3Q24 | J38: Retail | K38: 1260.46 | L38: mn | M38: USD | N38: CRE
B39: Industrial | C39: 837.145 | E39: Industrial | F39: 837.145 | H39: SNV | I39: 3Q24 | J39: Industrial | K39: 837.145 | L39: mn | M39: USD | N39: CRE
B40: Other | C40: 1352.719 | E40: Residential | F40: 528.13 | H40: SNV | I40: 3Q24 | J40: Other | K40: 1655.524 | L40: mn | M40: USD | N40: CRE
B41: Total Investment CRE | C41: =SUM(C35:C40) -> 11346.549 | E41: Other | F41: =C40+C43 -> 1655.524 | H41: SNV | I41: 3Q24 | J41: Residential | K41: 528 | L41: mn | M41: USD | N41: CRE
B42: Residential | C42: 528.13 | E42: Total CRE | F42: =SUM(F35:F41) -> 12177.484 | H42: SNV | I42: 3Q24 | J42: Total CRE | K42: =SUM(K35:K41) -> 12177.354 | L42: mn | M42: USD | N42: CRE
B43: Land & Development | C43: 302.805
B44: Total CRE | C44: =SUM(C41:C43) -> 12177.484
A47: 2Q24
B55: CRE Property Type | C55: Loan Amount | E55: CRE Property Type | F55: Loan Amount | H55: Ticker | I55: Quarter | J55: CRE Property Type | K55: Loan Amount | L55: Unit | M55: Currency | N55: Category
B56: Multi-Family | C56: 4288.436 | E56: Multi-family | F56: =C56 -> 4288.436 | H56: SNV | I56: 2Q24 | J56: Multi-family | K56: =F56 -> 4288.436 | L56: mn | M56: USD | N56: CRE
B57: Hotels | C57: 1802.076 | E57: Lodging | F57: =C57 -> 1802.076 | H57: SNV | I57: 2Q24 | J57: Lodging | K57: =F57 -> 1802.076 | L57: mn | M57: USD | N57: CRE
B58: Office Buildings | C58: 1801.945 | E58: Office | F58: =C58 -> 1801.945 | H58: SNV | I58: 2Q24 | J58: Office | K58: =F58 -> 1801.945 | L58: mn | M58: USD | N58: CRE
B59: Shopping Centers | C59: 1298.967 | E59: Retail | F59: =C59 -> 1298.967 | H59: SNV | I59: 2Q24 | J59: Retail | K59: =F59 -> 1298.967 | L59: mn | M59: USD | N59: CRE
B60: Warehouses | C60: 865.359 | E60: Industrial | F60: =C60 -> 865.359 | H60: SNV | I60: 2Q24 | J60: Industrial | K60: =F60 -> 865.359 | L60: mn | M60: USD | N60: CRE
B61: Other investment property | C61: 1271.266 | E61: Residential | F61: =C63 -> 552.547 | H61: SNV | I61: 2Q24 | J61: Other | K61: =F62 -> 1606.157 | L61: mn | M61: USD | N61: CRE
B62: Total Investment CRE | C62: =SUM(C56:C61) -> 11328.049 | E62: Other | F62: =SUM(C61,C64) -> 1606.157 | H62: SNV | I62: 2Q24 | J62: Residential | K62: =F61 -> 552.547 | L62: mn | M62: USD | N62: CRE
B63: Residential | C63: 552.547 | E63: Total CRE | F63: =SUM(F56:F62) -> 12215.487 | H63: SNV | I63: 2Q24 | J63: Total CRE | K63: =SUM(K56:K62) -> 12215.487 | L63: mn | M63: USD | N63: CRE
B64: Land & Development | C64: 334.891
B65: Total CRE | C65: =SUM(C62:C64) -> 12215.487
A68: 1Q24
B79: CRE Property Type | C79: Loan Amount | E79: CRE Property Type | F79: Loan Amount | H79: Ticker | I79: Quarter | J79: CRE Property Type | K79: Loan Amount | L79: Unit | M79: Currency | N79: Category
B80: Multi-Family | C80: 4199.435 | E80: Multi-family | F80: =C80 -> 4199.435 | H80: SNV | I80: 1Q24 | J80: Multi-family | K80: =F80 -> 4199.435 | L80: mn | M80: USD | N80: CRE
B81: Hotels | C81: 1790.505 | E81: Lodging | F81: =C81 -> 1790.505 | H81: SNV | I81: 1Q24 | J81: Lodging | K81: =F81 -> 1790.505 | L81: mn | M81: USD | N81: CRE
B82: Office Buildings | C82: 1852.208 | E82: Office | F82: =C82 -> 1852.208 | H82: SNV | I82: 1Q24 | J82: Office | K82: =F82 -> 1852.208 | L82: mn | M82: USD | N82: CRE
B83: Shopping Centers | C83: 1302.754 | E83: Retail | F83: =C83 -> 1302.754 | H83: SNV | I83: 1Q24 | J83: Retail | K83: =F83 -> 1302.754 | L83: mn | M83: USD | N83: CRE
B84: Warehouses | C84: 871.662 | E84: Industrial | F84: =C84 -> 871.662 | H84: SNV | I84: 1Q24 | J84: Industrial | K84: =F84 -> 871.662 | L84: mn | M84: USD | N84: CRE
B85: Other investment property | C85: 1294.317 | E85: Residential | F85: =C87 -> 580.138 | H85: SNV | I85: 1Q24 | J85: Other | K85: =F86 -> 1597.317 | L85: mn | M85: USD | N85: CRE
B86: Total Investment CRE | C86: =SUM(C80:C85) -> 11310.881 | E86: Other | F86: =SUM(C85,C88) -> 1597.317 | H86: SNV | I86: 1Q24 | J86: Residential | K86: =F85 -> 580.138 | L86: mn | M86: USD | N86: CRE
B87: Residential | C87: 580.138 | E87: Total CRE | F87: =SUM(F80:F86) -> 12194.019 | H87: SNV | I87: 1Q24 | J87: Total CRE | K87: =SUM(K80:K86) -> 12194.019 | L87: mn | M87: USD | N87: CRE
B88: Land & Development | C88: 303
B89: Total CRE | C89: =SUM(C86:C88) -> 12194.019

Sheet SNV LLM API
B2: 4Q24 AI API Script
B22: Correct | E22: LLM
B24: CRE Property Type | C24: Loan Amount | E24: CRE Property Type | F24: Loan Amount | H24: =B24=E24 -> TRUE | I24: =C24=F24 -> TRUE
B25: Office | C25: 1743 | E25: Office | F25: 1743 | H25: =B25=E25 -> TRUE | I25: =C25=F25 -> TRUE
B26: Multi-family | C26: 4186 | E26: Multi-family | F26: 4186 | H26: =B26=E26 -> TRUE | I26: =C26=F26 -> TRUE
B27: Retail | C27: 1273 | E27: Retail | F27: 1273 | H27: =B27=E27 -> TRUE | I27: =C27=F27 -> TRUE
B28: Lodging | C28: 1769 | E28: Lodging | F28: 1769 | H28: =B28=E28 -> TRUE | I28: =C28=F28 -> TRUE
B29: Other | C29: =1363+287 -> 1650 | E29: Other | F29: 1650 | H29: =B29=E29 -> TRUE | I29: =C29=F29 -> TRUE
B30: Industrial | C30: 846 | E30: Industrial | F30: 846 | H30: =B30=E30 -> TRUE | I30: =C30=F30 -> TRUE
B31: Residential | C31: 546 | E31: Residential | F31: 546 | H31: =B31=E31 -> TRUE | I31: =C31=F31 -> TRUE
B32: Total CRE | C32: =SUM(C25:C31) -> 12013 | E32: Total CRE | F32: =SUM(F25:F31) -> 12013 | H32: =B32=E32 -> TRUE | I32: =C32=F32 -> TRUE
E34: Accuracy | F34: =18/18 -> 1
B36: 3Q24 AI API Script
B58: Correct | E58: LLM
B60: CRE Property Type | C60: Loan Amount | E60: CRE Property Type | F60: Loan Amount | H60: =B60=E60 -> TRUE | I60: =C60=F60 -> TRUE
B61: Office | C61: 1779 | E61: Office | F61: 1779 | H61: =B61=E61 -> TRUE | I61: =C61=F61 -> TRUE
B62: Multi-family | C62: 4379 | E62: Multi-family | F62: 4379 | H62: =B62=E62 -> TRUE | I62: =C62=F62 -> TRUE
B63: Retail | C63: 1260 | E63: Retail | F63: 1260 | H63: =B63=E63 -> TRUE | I63: =C63=F63 -> TRUE
B64: Hotels | C64: 1738 | E64: Hotels | F64: 1738 | H64: =B64=E64 -> TRUE | I64: =C64=F64 -> TRUE
B65: Other | C65: =1353+303 -> 1656 | E65: Other | F65: 1656 | H65: =B65=E65 -> TRUE | I65: =C65=F65 -> TRUE
B66: Industrial | C66: 837 | E66: Industrial | F66: 837 | H66: =B66=E66 -> TRUE | I66: =C66=F66 -> TRUE
B67: Residential | C67: 528 | E67: Residential | F67: 528 | H67: =B67=E67 -> TRUE | I67: =C67=F67 -> TRUE
B68: Total CRE | C68: =SUM(C61:C67) -> 12177 | E68: Total CRE | F68: =SUM(F61:F67) -> 12177 | H68: =B68=E68 -> TRUE | I68: =C68=F68 -> TRUE
E70: Accuracy | F70: =18/18 -> 1
B72: 2Q24 AI API Script
B92: Correct | E92: LLM
B94: CRE Property Type | C94: Loan Amount | E94: CRE Property Type | F94: Loan Amount | H94: =B94=E94 -> TRUE | I94: =C94=F94 -> TRUE
B95: Office | C95: 1802 | E95: Office | F95: 1802 | H95: =B95=E95 -> TRUE | I95: =C95=F95 -> TRUE
B96: Multi-family | C96: 4288 | E96: Multi-family | F96: 4288 | H96: =B96=E96 -> TRUE | I96: =C96=F96 -> TRUE
B97: Retail | C97: 1299 | E97: Retail | F97: 1299 | H97: =B97=E97 -> TRUE | I97: =C97=F97 -> TRUE
B98: Lodging | C98: 1802 | E98: Lodging | F98: 1802 | H98: =B98=E98 -> TRUE | I98: =C98=F98 -> TRUE
B99: Other | C99: =1271+335 -> 1606 | E99: Other | F99: 1606 | H99: =B99=E99 -> TRUE | I99: =C99=F99 -> TRUE
B100: Industrial | C100: 865 | E100: Industrial | F100: 865 | H100: =B100=E100 -> TRUE | I100: =C100=F100 -> TRUE
B101: Residential | C101: 553 | E101: Residential | F101: 553 | H101: =B101=E101 -> TRUE | I101: =C101=F101 -> TRUE
B102: Total CRE | C102: =SUM(C95:C101) -> 12215 | E102: Total CRE | F102: =SUM(F95:F101) -> 12215 | H102: =B102=E102 -> TRUE | I102: =C102=F102 -> TRUE
E104: Accuracy | F104: =18/18 -> 1
B106: 1Q24 AI API Script
B127: Correct | E127: LLM
B129: CRE Property Type | C129: Loan Amount | E129: CRE Property Type | F129: Loan Amount | H129: =B129=E129 -> TRUE | I129: =C129=F129 -> TRUE
B130: Office | C130: 1852 | E130: Office | F130: 1852 | H130: =B130=E130 -> TRUE | I130: =C130=F130 -> TRUE
B131: Multi-family | C131: 4199 | E131: Multi-family | F131: 4199 | H131: =B131=E131 -> TRUE | I131: =C131=F131 -> TRUE
B132: Retail | C132: 1303 | E132: Retail | F132: 1303 | H132: =B132=E132 -> TRUE | I132: =C132=F132 -> TRUE
B133: Lodging | C133: 1791 | E133: Lodging | F133: 1791 | H133: =B133=E133 -> TRUE | I133: =C133=F133 -> TRUE
B134: Other | C134: =1294+303 -> 1597 | E134: Other | F134: =1294+303 -> 1597 | H134: =B134=E134 -> TRUE | I134: =C134=F134 -> TRUE
B135: Industrial | C135: 872 | E135: Industrial | F135: 872 | H135: =B135=E135 -> TRUE | I135: =C135=F135 -> TRUE
B136: Residential | C136: 580 | E136: Residential | F136: 580 | H136: =B136=E136 -> TRUE | I136: =C136=F136 -> TRUE
B137: Total CRE | C137: =SUM(C130:C136) -> 12194 | E137: Total CRE | F137: =SUM(F130:F136) -> 12194 | H137: =B137=E137 -> TRUE | I137: =C137=F137 -> TRUE
E139: Accuracy | F139: =18/18 -> 1

Sheet SNV Script
B2: Script 4Q24 (10-Q) | K2: Script 3Q24 (10-Q)
B13: Script 2Q24 (10-Q) | K13: Script 1Q24 (10-Q)

Sheet FCNCA

Sheet FCNCA Manual
A2: 4Q24 | B2: CRE Property Type | C2: Loan Amount | E2: CRE Property Type | F2: Loan Amount | H2: Ticker | I2: Quarter | J2: CRE Property Type | K2: Loan Amount | L2: Unit | M2: Currency | N2: Category
B3: Multi-Family | C3: 5713 | E3: Multi-family | F3: =C3 -> 5713 | H3: FCNCA | I3: 4Q24 | J3: Multi-family | K3: =F3 -> 5713 | L3: mn | M3: USD | N3: CRE
B4: Medical Office | C4: 3707 | E4: Office | F4: =C4+C6 -> 6183 | H4: FCNCA | I4: 4Q24 | J4: Office | K4: =F4 -> 6183 | L4: mn | M4: USD | N4: CRE
B5: Industrial/Warehouse | C5: 3604 | E5: Industrial | F5: =C5 -> 3604 | H5: FCNCA | I5: 4Q24 | J5: Industrial | K5: =F5 -> 3604 | L5: mn | M5: USD | N5: CRE
B6: General Office | C6: 2476 | E6: Retail | F6: =C7 -> 1995 | H6: FCNCA | I6: 4Q24 | J6: Retail | K6: =F6 -> 1995 | L6: mn | M6: USD | N6: CRE
B7: Retail | C7: 1995 | E7: Lodging | F7: =C8 -> 876 | H7: FCNCA | I7: 4Q24 | J7: Lodging | K7: =F7 -> 876 | L7: mn | M7: USD | N7: CRE
B8: Hotel/Motel | C8: 876 | E8: Other | F8: =C9 -> 4546 | H8: FCNCA | I8: 4Q24 | J8: Other | K8: =F8 -> 4546 | L8: mn | M8: USD | N8: CRE
B9: Other | C9: 4546 | E9: Total CRE | F9: =SUM(F3:F8) -> 22917 | H9: FCNCA | I9: 4Q24 | J9: Total CRE | K9: =SUM(K3:K8) -> 22917 | L9: mn | M9: USD | N9: CRE
B10: Total CRE | C10: =SUM(C3:C9) -> 22917
A22: 3Q24 | B22: CRE Property Type | C22: Loan Amount | E22: CRE Property Type | F22: Loan Amount | H22: Ticker | I22: Quarter | J22: CRE Property Type | K22: Loan Amount | L22: Unit | M22: Currency | N22: Category
B23: Multi-family | C23: 5715 | E23: Multi-family | F23: 5715 | H23: FCNCA | I23: 3Q24 | J23: Multi-family | K23: =F23 -> 5715 | L23: mn | M23: USD | N23: CRE
B24: Medical Office | C24: 3704 | E24: Office | F24: =SUM(C24:C25) -> 6240 | H24: FCNCA | I24: 3Q24 | J24: Office | K24: =F24 -> 6240 | L24: mn | M24: USD | N24: CRE
B25: General Office | C25: 2536 | E25: Industrial | F25: 3544 | H25: FCNCA | I25: 3Q24 | J25: Industrial | K25: =F25 -> 3544 | L25: mn | M25: USD | N25: CRE
B26: Industrial | C26: 3544 | E26: Retail | F26: 1959 | H26: FCNCA | I26: 3Q24 | J26: Retail | K26: =F26 -> 1959 | L26: mn | M26: USD | N26: CRE
B27: Retail | C27: 1959 | E27: Lodging | F27: 860 | H27: FCNCA | I27: 3Q24 | J27: Lodging | K27: =F27 -> 860 | L27: mn | M27: USD | N27: CRE
B28: Lodging | C28: 860 | E28: Other | F28: 4371 | H28: FCNCA | I28: 3Q24 | J28: Other | K28: =F28 -> 4371 | L28: mn | M28: USD | N28: CRE
B29: Other | C29: 4371 | E29: Total CRE | F29: 22689 | H29: FCNCA | I29: 3Q24 | J29: Total CRE | K29: =SUM(K23:K28) -> 22689 | L29: mn | M29: USD | N29: CRE
B30: Total CRE | C30: =SUM(C23:C29) -> 22689
A43: 2Q24 | B43: CRE Property Type | C43: Loan Amount | E43: CRE Property Type | F43: Loan Amount | H43: Ticker | I43: Quarter | J43: CRE Property Type | K43: Loan Amount | L43: Unit | M43: Currency | N43: Category
B44: Multi-Family | C44: 5538 | E44: Multi-family | F44: =C44 -> 5538 | H44: FCNCA | I44: 3Q24 | J44: Multi-family | K44: =F44 -> 5538 | L44: mn | M44: USD | N44: CRE
B45: Medical Office | C45: 3598 | E45: Office | F45: =C45+C47 -> 6281 | H45: FCNCA | I45: 3Q24 | J45: Office | K45: =F45 -> 6281 | L45: mn | M45: USD | N45: CRE
B46: Industrial / Warehouse | C46: 3296 | E46: Industrial | F46: =C46 -> 3296 | H46: FCNCA | I46: 3Q24 | J46: Industrial | K46: =F46 -> 3296 | L46: mn | M46: USD | N46: CRE
B47: General Office | C47: 2683 | E47: Retail | F47: =C48 -> 1949 | H47: FCNCA | I47: 3Q24 | J47: Retail | K47: =F47 -> 1949 | L47: mn | M47: USD | N47: CRE
B48: Retail | C48: 1949 | E48: Lodging | F48: =C49 -> 778 | H48: FCNCA | I48: 3Q24 | J48: Lodging | K48: =F48 -> 778 | L48: mn | M48: USD | N48: CRE
B49: Hotel / Motel | C49: 778 | E49: Other | F49: =C50 -> 3974 | H49: FCNCA | I49: 3Q24 | J49: Other | K49: =F49 -> 3974 | L49: mn | M49: USD | N49: CRE
B50: Other | C50: 3974 | E50: Total CRE | F50: =SUM(F44:F49) -> 21816 | H50: FCNCA | I50: 3Q24 | J50: Total CRE | K50: =SUM(K44:K49) -> 21816 | L50: mn | M50: USD | N50: CRE
B51: Total CRE | C51: =SUM(C44:C50) -> 21816
A65: 1Q24 | B65: CRE Property Type | C65: Loan Amount | E65: CRE Property Type | F65: Loan Amount | H65: Ticker | I65: Quarter | J65: CRE Property Type | K65: Loan Amount | L65: Unit | M65: Currency | N65: Category
B66: Multi-Family | C66: 5341 | E66: Multi-family | F66: =C66 -> 5341 | H66: FCNCA | I66: 1Q24 | J66: Multi-family | K66: =F66 -> 5341 | L66: mn | M66: USD | N66: CRE
B67: Medical Office | C67: 3443 | E67: Office | F67: =SUM(C67:C68) -> 6195 | H67: FCNCA | I67: 1Q24 | J67: Office | K67: =F67 -> 6195 | L67: mn | M67: USD | N67: CRE
B68: General Office | C68: 2752 | E68: Industrial | F68: =C69 -> 3121 | H68: FCNCA | I68: 1Q24 | J68: Industrial | K68: =F68 -> 3121 | L68: mn | M68: USD | N68: CRE
B69: Industrial / Warehouse | C69: 3121 | E69: Retail | F69: =C70 -> 1955 | H69: FCNCA | I69: 1Q24 | J69: Retail | K69: =F69 -> 1955 | L69: mn | M69: USD | N69: CRE
B70: Retail | C70: 1955 | E70: Lodging | F70: =C71 -> 818 | H70: FCNCA | I70: 1Q24 | J70: Lodging | K70: =F70 -> 818 | L70: mn | M70: USD | N70: CRE
B71: Hotel/Motel | C71: 818 | E71: Other | F71: =C72 -> 3706 | H71: FCNCA | I71: 1Q24 | J71: Other | K71: =F71 -> 3706 | L71: mn | M71: USD | N71: CRE
B72: Other | C72: 3706 | E72: Total CRE | F72: =SUM(F66:F71) -> 21136 | H72: FCNCA | I72: 1Q24 | J72: Total CRE | K72: =SUM(K66:K71) -> 21136 | L72: mn | M72: USD | N72: CRE
B73: Total CRE | C73: =SUM(C66:C72) -> 21136

Sheet FCNCA LLM API
B2: 4Q24 AI API Script
B14: Correct | C14: 1000 | E14: LLM
B16: CRE Property Type | C16: Loan Amount | E16: CRE Property Type | F16: Loan Amount | H16: =B16=E16 -> TRUE | I16: =C16=F16 -> TRUE
B17: Multi-family | C17: 5.7 | E17: Multi-family | F17: 5.7 | H17: =B17=E17 -> TRUE | I17: =C17=F17 -> TRUE
B18: Office | C18: =3.7+2.5 -> 6.2 | E18: Office | F18: 6.2 | H18: =B18=E18 -> TRUE | I18: =C18=F18 -> TRUE
B19: Industrial | C19: 3.6 | E19: Industrial | F19: 3.6 | H19: =B19=E19 -> TRUE | I19: =C19=F19 -> TRUE
B20: Retail | C20: 2 | E20: Retail | F20: 2 | H20: =B20=E20 -> TRUE | I20: =C20=F20 -> TRUE
B21: Lodging | C21: 0.9 | E21: Lodging | F21: 0.9 | H21: =B21=E21 -> TRUE | I21: =C21=F21 -> TRUE
B22: Other | C22: 4.5 | E22: Other | F22: 4.5 | H22: =B22=E22 -> TRUE | I22: =C22=F22 -> TRUE
B23: Total CRE | C23: =SUM(C17:C22) -> 22.9 | E23: Total CRE | F23: =SUM(F17:F22) -> 22.9
E25: Accuracy | F25: =18/18 -> 1
B27: 3Q24 AI API Script
B38: Correct | E38: LLM
B40: CRE Property Type | C40: Loan Amount | E40: CRE Property Type | F40: Loan Amount | H40: =B40=E40 -> TRUE | I40: =C40=F40 -> TRUE
B41: Multi-family | C41: 5.7 | E41: Multi-family | F41: 5.7 | H41: =B41=E41 -> TRUE | I41: =C41=F41 -> TRUE
B42: Office | C42: =3.7+2.5 -> 6.2 | E42: Office | F42: 6.2 | H42: =B42=E42 -> TRUE | I42: =C42=F42 -> TRUE
B43: Industrial | C43: 3.5 | E43: Industrial | F43: 3.5 | H43: =B43=E43 -> TRUE | I43: =C43=F43 -> TRUE
B44: Retail | C44: 2 | E44: Retail | F44: 2 | H44: =B44=E44 -> TRUE | I44: =C44=F44 -> TRUE
B45: Lodging | C45: 0.9 | E45: Lodging | F45: 0.9 | H45: =B45=E45 -> TRUE | I45: =C45=F45 -> TRUE
B46: Other | C46: 4.4 | E46: Other | F46: 4.4 | H46: =B46=E46 -> TRUE | I46: =C46=F46 -> TRUE
B47: Total CRE | C47: 22.7 | E47: Total CRE | F47: =SUM(F41:F46) -> 22.7 | H47: =B47=E47 -> TRUE | I47: =C47=F47 -> TRUE
E49: Accuracy | F49: =16/16 -> 1
B52: 2Q24 AI API Script
B64: Correct | C64: 1000 | E64: LLM
B66: CRE Property Type | C66: Loan Amount | E66: CRE Property Type | F66: Loan Amount | H66: =B66=E66 -> TRUE | I66: =C66=F66 -> TRUE
B67: Multi-family | C67: 5.5 | E67: Multi-family | F67: 5.5 | H67: =B67=E67 -> TRUE | I67: =C67=F67 -> TRUE
B68: Office | C68: =3.6+2.7 -> 6.3 | E68: Office | F68: 6.3 | H68: =B68=E68 -> TRUE | I68: =C68=F68 -> TRUE
B69: Industrial | C69: 3.3 | E69: Industrial | F69: 3.3 | H69: =B69=E69 -> TRUE | I69: =C69=F69 -> TRUE
B70: Retail | C70: 1.9 | E70: Retail | F70: 1.9 | H70: =B70=E70 -> TRUE | I70: =C70=F70 -> TRUE
B71: Lodging | C71: 0.8 | E71: Lodging | F71: 0.8 | H71: =B71=E71 -> TRUE | I71: =C71=F71 -> TRUE
B72: Other | C72: 4 | E72: Other | F72: 4 | H72: =B72=E72 -> TRUE | I72: =C72=F72 -> TRUE
B73: Total CRE | C73: =SUM(C67:C72) -> 21.8 | E73: Total CRE | F73: =SUM(F67:F72) -> 21.8
E75: Accuracy | F75: =18/18 -> 1
B77: 1Q24 AI API Script
B88: Correct | C88: 1000 | E88: LLM
B90: CRE Property Type | C90: Loan Amount | E90: CRE Property Type | F90: Loan Amount | H90: =B90=E90 -> TRUE | I90: =C90=F90 -> TRUE
B91: Multi-family | C91: 5.3 | E91: Multi-family | F91: 5.3 | H91: =B91=E91 -> TRUE | I91: =C91=F91 -> TRUE
B92: Office | C92: =3.4+2.8 -> 6.2 | E92: Office | F92: 6.2 | H92: =B92=E92 -> TRUE | I92: =C92=F92 -> TRUE
B93: Industrial | C93: 3.1 | E93: Industrial | F93: 3.1 | H93: =B93=E93 -> TRUE | I93: =C93=F93 -> TRUE
B94: Retail | C94: 2 | E94: Retail | F94: 2 | H94: =B94=E94 -> TRUE | I94: =C94=F94 -> TRUE
B95: Lodging | C95: 0.8 | E95: Lodging | F95: 0.8 | H95: =B95=E95 -> TRUE | I95: =C95=F95 -> TRUE
B96: Other | C96: 3.7 | E96: Other | F96: 3.7 | H96: =B96=E96 -> TRUE | I96: =C96=F96 -> TRUE
B97: Total CRE | C97: =SUM(C91:C96) -> 21.1 | E97: Total CRE | F97: =SUM(F91:F96) -> 21.1
E99: Accuracy | F99: =18/18 -> 1

Sheet FCNCA Script 
B2: Script 4Q24 (10-Q) | K2: Script 3Q24 (10-Q)
K12: Script 1Q24 (10-Q)

Sheet PNC

Sheet PNC Manual
A4: 4Q24 | B4: CRE Property Type | C4: Loan Amount | E4: CRE Property Type | F4: Loan Amount | H4: Ticker | I4: Quarter | J4: CRE Property Type | K4: Loan Amount | L4: Unit | M4: Currency | N4: Category
B5: Multifamily | C5: 16089 | E5: Multi-family | F5: =C5 -> 16089 | H5: PNC | I5: 4Q24 | J5: Multi-family | K5: =F5 -> 16089 | L5: mn | M5: USD | N5: CRE
B6: Office | C6: 6707 | E6: Office | F6: =C6 -> 6707 | H6: PNC | I6: 4Q24 | J6: Office | K6: =F6 -> 6707 | L6: mn | M6: USD | N6: CRE
B7: Industrial/warehouse | C7: 3911 | E7: Industrial | F7: =C7 -> 3911 | H7: PNC | I7: 4Q24 | J7: Industrial | K7: =F7 -> 3911 | L7: mn | M7: USD | N7: CRE
B8: Retail | C8: 2090 | E8: Retail | F8: =C8 -> 2090 | H8: PNC | I8: 4Q24 | J8: Retail | K8: =F8 -> 2090 | L8: mn | M8: USD | N8: CRE
B9: Seniors housing | C9: 1731 | E9: Lodging | F9: =C10 -> 1567 | H9: PNC | I9: 4Q24 | J9: Lodging | K9: =F9 -> 1567 | L9: mn | M9: USD | N9: CRE
B10: Hotel/motel | C10: 1567 | E10: Mixed-use | F10: =C11 -> 336 | H10: PNC | I10: 4Q24 | J10: Mixed-use | K10: =F10 -> 336 | L10: mn | M10: USD | N10: CRE
B11: Mixed use | C11: 336 | E11: Other | F11: =C12+C9 -> 2919 | H11: PNC | I11: 4Q24 | J11: Other | K11: =F11 -> 2919 | L11: mn | M11: USD | N11: CRE
B12: Other | C12: 1188 | E12: Total CRE | F12: =SUM(F5:F11) -> 33619 | H12: PNC | I12: 4Q24 | J12: Total CRE | K12: =SUM(K5:K11) -> 33619 | L12: mn | M12: USD | N12: CRE
B13: Total CRE | C13: =SUM(C5:C12) -> 33619
A25: 3Q24 | B25: CRE Property Type | C25: Loan Amount | E25: CRE Property Type | F25: Loan Amount | H25: Ticker | I25: Quarter | J25: CRE Property Type | K25: Loan Amount | L25: Unit | M25: Currency | N25: Category
B26: Multi-family | C26: 16678 | E26: Multi-family | F26: 16678 | H26: PNC | I26: 3Q24 | J26: Multi-family | K26: 16678 | L26: mn | M26: USD | N26: CRE
B27: Office | C27: 7225 | E27: Office | F27: 7225 | H27: PNC | I27: 3Q24 | J27: Office | K27: 7225 | L27: mn | M27: USD | N27: CRE
B28: Industrial | C28: 3990 | E28: Industrial | F28: 3990 | H28: PNC | I28: 3Q24 | J28: Industrial | K28: 3990 | L28: mn | M28: USD | N28: CRE
B29: Retail | C29: 2174 | E29: Retail | F29: 2174 | H29: PNC | I29: 3Q24 | J29: Retail | K29: 2174 | L29: mn | M29: USD | N29: CRE
B30: Senior Housing | C30: 1776 | E30: Lodging | F30: 1696 | H30: PNC | I30: 3Q24 | J30: Lodging | K30: 1696 | L30: mn | M30: USD | N30: CRE
B31: Lodging | C31: 1696 | E31: Mixed-use | F31: 348 | H31: PNC | I31: 3Q24 | J31: Mixed-use | K31: 348 | L31: mn | M31: USD | N31: CRE
B32: Mixed-use | C32: 348 | E32: Other | F32: =C33+C30 -> 2993 | H32: PNC | I32: 3Q24 | J32: Other | K32: 2993 | L32: mn | M32: USD | N32: CRE
B33: Other | C33: 1217 | E33: Total CRE | F33: =SUM(F26:F32) -> 35104 | H33: PNC | I33: 3Q24 | J33: Total CRE | K33: 35104 | L33: mn | M33: USD | N33: CRE
A45: 2Q24 | B45: CRE Property Type | C45: Loan Amount | E45: CRE Property Type | F45: Loan Amount | H45: Ticker | I45: Quarter | J45: CRE Property Type | K45: Loan Amount | L45: Unit | M45: Currency | N45: Category
B46: Multifamily | C46: 16453 | E46: Multi-family | F46: =C46 -> 16453 | H46: PNC | I46: 2Q24 | J46: Multi-family | K46: =F46 -> 16453 | L46: mn | M46: USD | N46: CRE
B47: Office | C47: 7498 | E47: Office | F47: =C47 -> 7498 | H47: PNC | I47: 2Q24 | J47: Office | K47: =F47 -> 7498 | L47: mn | M47: USD | N47: CRE
B48: Industrial/warehouse | C48: 4110 | E48: Industrial | F48: =C48 -> 4110 | H48: PNC | I48: 2Q24 | J48: Industrial | K48: =F48 -> 4110 | L48: mn | M48: USD | N48: CRE
B49: Retail | C49: 2238 | E49: Retail | F49: =C49 -> 2238 | H49: PNC | I49: 2Q24 | J49: Retail | K49: =F49 -> 2238 | L49: mn | M49: USD | N49: CRE
B50: Seniors housing | C50: 1862 | E50: Lodging | F50: =C51 -> 1709 | H50: PNC | I50: 2Q24 | J50: Lodging | K50: =F50 -> 1709 | L50: mn | M50: USD | N50: CRE
B51: Hotel/motel | C51: 1709 | E51: Mixed-use | F51: =C52 -> 387 | H51: PNC | I51: 2Q24 | J51: Mixed-use | K51: =F51 -> 387 | L51: mn | M51: USD | N51: CRE
B52: Mixed use | C52: 387 | E52: Other | F52: =C53+C50 -> 3103 | H52: PNC | I52: 2Q24 | J52: Other | K52: =F52 -> 3103 | L52: mn | M52: USD | N52: CRE
B53: Other | C53: 1241 | E53: Total CRE | F53: =SUM(F46:F52) -> 35498 | H53: PNC | I53: 2Q24 | J53: Total CRE | K53: =SUM(K46:K52) -> 35498 | L53: mn | M53: USD | N53: CRE
B54: Total CRE | C54: =SUM(C46:C53) -> 35498
A63: 1Q24 | B63: CRE Property Type | C63: Loan Amount | E63: CRE Property Type | F63: Loan Amount | H63: Ticker | I63: Quarter | J63: CRE Property Type | K63: Loan Amount | L63: Unit | M63: Currency | N63: Category
B64: Multifamily | C64: 16058 | E64: Multi-family | F64: =C64 -> 16058 | H64: PNC | I64: 1Q24 | J64: Multi-family | K64: =F64 -> 16058 | L64: mn | M64: USD | N64: CRE
B65: Office | C65: 7803 | E65: Office | F65: =C65 -> 7803 | H65: PNC | I65: 1Q24 | J65: Office | K65: =F65 -> 7803 | L65: mn | M65: USD | N65: CRE
B66: Industrial/warehouse | C66: 4116 | E66: Industrial | F66: =C66 -> 4116 | H66: PNC | I66: 1Q24 | J66: Industrial | K66: =F66 -> 4116 | L66: mn | M66: USD | N66: CRE
B67: Retail | C67: 2335 | E67: Retail | F67: =C67 -> 2335 | H67: PNC | I67: 1Q24 | J67: Retail | K67: =F67 -> 2335 | L67: mn | M67: USD | N67: CRE
B68: Seniors housing | C68: 1834 | E68: Lodging | F68: =C69 -> 1811 | H68: PNC | I68: 1Q24 | J68: Lodging | K68: =F68 -> 1811 | L68: mn | M68: USD | N68: CRE
B69: Hotel/motel | C69: 1811 | E69: Mixed-use | F69: =C70 -> 388 | H69: PNC | I69: 1Q24 | J69: Mixed-use | K69: =F69 -> 388 | L69: mn | M69: USD | N69: CRE
B70: Mixed use | C70: 388 | E70: Other | F70: =C71+C68 -> 3080 | H70: PNC | I70: 1Q24 | J70: Other | K70: =F70 -> 3080 | L70: mn | M70: USD | N70: CRE
B71: Other | C71: 1246 | E71: Total CRE | F71: =SUM(F64:F70) -> 35591 | H71: PNC | I71: 1Q24 | J71: Total CRE | K71: =SUM(K64:K70) -> 35591 | L71: mn | M71: USD | N71: CRE
B72: Total CRE | C72: =SUM(C64:C71) -> 35591

Sheet PNC LLM API
B1: 4Q24 AI API Script
B21: Correct | E21: LLM
B23: CRE Property Type | C23: Loan Amount | E23: CRE Property Type | F23: Loan Amount
B24: Multi-family | C24: 16.1 | E24: Multi-family | F24: 16.1 | H24: =B24=E24 -> TRUE | I24: =C24=F24 -> TRUE
B25: Office | C25: 6.7 | E25: Office | F25: 6.7 | H25: =B25=E25 -> TRUE | I25: =C25=F25 -> TRUE
B26: Industrial | C26: 3.9 | E26: Industrial | F26: 3.9 | H26: =B26=E26 -> TRUE | I26: =C26=F26 -> TRUE
B27: Retail | C27: 2.1 | E27: Retail | F27: 2.1 | H27: =B27=E27 -> TRUE | I27: =C27=F27 -> TRUE
B28: Lodging | C28: 1.6 | E28: Lodging | F28: 1.6 | H28: =B28=E28 -> TRUE | I28: =C28=F28 -> TRUE
B29: Mixed-use | C29: 0.3 | E29: Mixed-use | F29: 0.3 | H29: =B29=E29 -> TRUE | I29: =C29=F29 -> TRUE
B30: Other | C30: =1.7+1.2 -> 2.9 | E30: Other | F30: 4.6 | H30: =B30=E30 -> TRUE | I30: =C30=F30 -> FALSE
B31: Total CRE | C31: =SUM(C24:C30) -> 33.6 | E31: Total CRE | F31: 33.6 | H31: =B31=E31 -> TRUE | I31: =C31=F31 -> TRUE
E33: Accuracy | F33: =13/14 -> 0.92857143
B34: 3Q24 AI API Script
B46: Correct | E46: LLM
B48: CRE Property Type | C48: Loan Amount | E48: CRE Property Type | F48: Loan Amount
B49: Multi-family | C49: 16.7 | E49: Multi-family | F49: 16.7 | H49: =B49=E49 -> TRUE | I49: =C49=F49 -> TRUE
B50: Office | C50: 7.2 | E50: Office | F50: 7.2 | H50: =B50=E50 -> TRUE | I50: =C50=F50 -> TRUE
B51: Industrial | C51: 4 | E51: Industrial | F51: 4 | H51: =B51=E51 -> TRUE | I51: =C51=F51 -> TRUE
B52: Retail | C52: 2.2 | E52: Retail | F52: 2.2 | H52: =B52=E52 -> TRUE | I52: =C52=F52 -> TRUE
B53: Lodging | C53: 1.7 | E53: Lodging | F53: 1.7 | H53: =B53=E53 -> TRUE | I53: =C53=F53 -> TRUE
B54: Mixed-use | C54: 0.3 | E54: Mixed-use | F54: 0.3 | H54: =B54=E54 -> TRUE | I54: =C54=F54 -> TRUE
B55: Other | C55: 3 | E55: Other | F55: 3 | H55: =B55=E55 -> TRUE | I55: =C55=F55 -> TRUE
B56: Total CRE | C56: =SUM(C49:C55) -> 35.1 | E56: Total CRE | F56: =SUM(F49:F55) -> 35.1 | H56: =B56=E56 -> TRUE | I56: =C56=F56 -> TRUE
E58: Accuracy | F58: =14/14 -> 1
B59: 2Q24 AI API Script
B71: Correct | E71: LLM
B73: CRE Property Type | C73: Loan Amount | E73: CRE Property Type | F73: Loan Amount
B74: Multi-family | C74: 16.5 | E74: Multi-family | F74: 16.5 | H74: =B74=E74 -> TRUE | I74: =C74=F74 -> TRUE
B75: Office | C75: 7.5 | E75: Office | F75: 7.5 | H75: =B75=E75 -> TRUE | I75: =C75=F75 -> TRUE
B76: Industrial | C76: 4.1 | E76: Industrial | F76: 4.1 | H76: =B76=E76 -> TRUE | I76: =C76=F76 -> TRUE
B77: Retail | C77: 2.2 | E77: Retail | F77: 2.2 | H77: =B77=E77 -> TRUE | I77: =C77=F77 -> TRUE
B78: Lodging | C78: 1.7 | E78: Lodging | F78: 1.7 | H78: =B78=E78 -> TRUE | I78: =C78=F78 -> TRUE
B79: Mixed-use | C79: 0.4 | E79: Mixed-use | F79: 0.4 | H79: =B79=E79 -> TRUE | I79: =C79=F79 -> TRUE
B80: Other | C80: 3.1 | E80: Other | F80: 3.1 | H80: =B80=E80 -> TRUE | I80: =C80=F80 -> TRUE
B81: Total CRE | C81: =SUM(C74:C80) -> 35.5 | E81: Total CRE | F81: =SUM(F74:F80) -> 35.5 | H81: =B81=E81 -> TRUE | I81: =C81=F81 -> TRUE
E83: Accuracy | F83: =14/14 -> 1
B85: 1Q24 AI API Script
B107: Correct | E107: LLM
B109: CRE Property Type | C109: Loan Amount | E109: CRE Property Type | F109: Loan Amount
B110: Multi-family | C110: 16.1 | E110: Multi-family | F110: 16.1 | H110: =B110=E110 -> TRUE | I110: =C110=F110 -> TRUE
B111: Office | C111: 7.8 | E111: Office | F111: 7.8 | H111: =B111=E111 -> TRUE | I111: =C111=F111 -> TRUE
B112: Industrial | C112: 4.1 | E112: Industrial | F112: 4.1 | H112: =B112=E112 -> TRUE | I112: =C112=F112 -> TRUE
B113: Retail | C113: 2.3 | E113: Retail | F113: 2.3 | H113: =B113=E113 -> TRUE | I113: =C113=F113 -> TRUE
B114: Lodging | C114: 1.8 | E114: Lodging | F114: 1.8 | H114: =B114=E114 -> TRUE | I114: =C114=F114 -> TRUE
B115: Mixed-use | C115: 0.4 | E115: Mixed-use | F115: 0.4 | H115: =B115=E115 -> TRUE | I115: =C115=F115 -> TRUE
B116: Other | C116: =1.2+1.8 -> 3 | E116: Other | F116: 4.8 | H116: =B116=E116 -> TRUE | I116: =C116=F116 -> FALSE
B117: Total CRE | C117: =SUM(C110:C116) -> 35.5 | E117: Total CRE | F117: 35.5 | H117: =B117=E117 -> TRUE | I117: =C117=F117 -> TRUE
E119: Accuracy | F119: =13/14 -> 0.92857143

Sheet PNC Script 
B2: Script 4Q24 (10-Q) | K2: Script 3Q24 (10-Q)
B14: Script 2Q24 (10-Q) | K14: Script 1Q24 (10-Q)

Sheet RF

Sheet RF Manual
A2: 4Q24 | B2: CRE Property Type | C2: Loan Amount | E2: CRE Property Type | F2: Loan Amount | H2: Ticker | I2: Quarter | J2: CRE Property Type | K2: Loan Amount | L2: Unit | M2: Currency | N2: Category
B3: Residential homebuilders | C3: 1081 | E3: Residential | F3: =C9+C3 -> 1136 | H3: RF | I3: 4Q24 | J3: Residential | K3: =F3 -> 1136 | L3: mn | M3: USD | N3: CRE
B4: Apartments | C4: 4371 | E4: Multi-family | F4: =C4 -> 4371 | H4: RF | I4: 4Q24 | J4: Multi-family | K4: =F4 -> 4371 | L4: mn | M4: USD | N4: CRE
B5: Industrial | C5: 2287 | E5: Industrial | F5: =C5 -> 2287 | H5: RF | I5: 4Q24 | J5: Industrial | K5: =F5 -> 2287 | L5: mn | M5: USD | N5: CRE
B6: Data center | C6: 332 | E6: Office | F6: =C8 -> 1473 | H6: RF | I6: 4Q24 | J6: Office | K6: =F6 -> 1473 | L6: mn | M6: USD | N6: CRE
B7: Diversified | C7: 1740 | E7: Retail | F7: =C10 -> 1458 | H7: RF | I7: 4Q24 | J7: Retail | K7: =F7 -> 1458 | L7: mn | M7: USD | N7: CRE
B8: Business offices | C8: 1473 | E8: Lodging | F8: =C12 -> 785 | H8: RF | I8: 4Q24 | J8: Lodging | K8: =F8 -> 785 | L8: mn | M8: USD | N8: CRE
B9: Residential land | C9: 55 | E9: Other | F9: =SUM(C11,C13:C15,C6:C7) -> 3776 | H9: RF | I9: 4Q24 | J9: Other | K9: =F9 -> 3776 | L9: mn | M9: USD | N9: CRE
B10: Retail | C10: 1458 | E10: Total CRE | F10: =SUM(F3:F9) -> 15286 | H10: RF | I10: 4Q24 | J10: Total CRE | K10: =SUM(K3:K9) -> 15286 | L10: mn | M10: USD | N10: CRE
B11: Healthcare | C11: 1129
B12: Hotel | C12: 785
B13: Commercial land | C13: 19
B14: Self Storage | C14: 296
B15: Other | C15: 260
B16: Total CRE | C16: =SUM(C3:C15) -> 15286
A21: 3Q24 | B21: CRE Property Type | C21: Loan Amount | E21: CRE Property Type | F21: Loan Amount | H21: Ticker | I21: Quarter | J21: CRE Property Type | K21: Loan Amount | L21: Unit | M21: Currency | N21: Category
B22: Residential homebuilders | C22: 1166 | E22: Residential | F22: =C22+C28 -> 1233 | H22: RF | I22: 3Q24 | J22: Residential | K22: 1233 | L22: mn | M22: USD | N22: CRE
B23: Apartments | C23: 4243 | E23: Multi-family | F23: =C23 -> 4243 | H23: RF | I23: 3Q24 | J23: Multi-family | K23: 4243 | L23: mn | M23: USD | N23: CRE
B24: Industrial | C24: 2233 | E24: Industrial | F24: =C24 -> 2233 | H24: RF | I24: 3Q24 | J24: Industrial | K24: 2233 | L24: mn | M24: USD | N24: CRE
B25: Data center | C25: 406 | E25: Office | F25: =C27 -> 1555 | H25: RF | I25: 3Q24 | J25: Office | K25: 1555 | L25: mn | M25: USD | N25: CRE
B26: Diversified | C26: 1871 | E26: Retail | F26: =C29 -> 1369 | H26: RF | I26: 3Q24 | J26: Retail | K26: 1369 | L26: mn | M26: USD | N26: CRE
B27: Business offices | C27: 1555 | E27: Lodging | F27: =C31 -> 798 | H27: RF | I27: 3Q24 | J27: Lodging | K27: 798 | L27: mn | M27: USD | N27: CRE
B28: Residential land | C28: 67 | E28: Other | F28: =SUM(C25:C26,C30,C32:C34) -> 3999 | H28: RF | I28: 3Q24 | J28: Other | K28: 3999 | L28: mn | M28: USD | N28: CRE
B29: Retail | C29: 1369 | E29: Total CRE | F29: =SUM(F22:F28) -> 15430 | H29: RF | I29: 3Q24 | J29: Total CRE | K29: 15430 | L29: mn | M29: USD | N29: CRE
B30: Healthcare | C30: 1168
B31: Hotel | C31: 798
B32: Commercial land | C32: 19
B33: Self storage | C33: 272
B34: Other | C34: 263
B35: Total CRE | C35: =SUM(C22:C34) -> 15430
A40: 2Q24 | B40: CRE Property Type | C40: Loan Amount | E40: CRE Property Type | F40: Loan Amount | H40: Ticker | I40: Quarter | J40: CRE Property Type | K40: Loan Amount | L40: Unit | M40: Currency | N40: Category
B41: Residential homebuilders | C41: 1128 | E41: Residential | F41: =C47+C41 -> 1207 | H41: RF | I41: 2Q24 | J41: Residential | K41: =F41 -> 1207 | L41: mn | M41: USD | N41: CRE
B42: Apartments | C42: 4279 | E42: Multi-family | F42: =C42 -> 4279 | H42: RF | I42: 2Q24 | J42: Multi-family | K42: =F42 -> 4279 | L42: mn | M42: USD | N42: CRE
B43: Industrial | C43: 2210 | E43: Industrial | F43: =C43 -> 2210 | H43: RF | I43: 2Q24 | J43: Industrial | K43: =F43 -> 2210 | L43: mn | M43: USD | N43: CRE
B44: Data center | C44: 329 | E44: Office | F44: =C46 -> 1574 | H44: RF | I44: 2Q24 | J44: Office | K44: =F44 -> 1574 | L44: mn | M44: USD | N44: CRE
B45: Diversified | C45: 1890 | E45: Retail | F45: =C48 -> 1382 | H45: RF | I45: 2Q24 | J45: Retail | K45: =F45 -> 1382 | L45: mn | M45: USD | N45: CRE
B46: Business offices | C46: 1574 | E46: Lodging | F46: =C50 -> 806 | H46: RF | I46: 2Q24 | J46: Lodging | K46: =F46 -> 806 | L46: mn | M46: USD | N46: CRE
B47: Residential land | C47: 79 | E47: Other | F47: =SUM(C49,C51:C52,C44:C45) -> 4102 | H47: RF | I47: 2Q24 | J47: Other | K47: =F47 -> 4102 | L47: mn | M47: USD | N47: CRE
B48: Retail | C48: 1382 | E48: Total CRE | F48: =SUM(F41:F47) -> 15560 | H48: RF | I48: 2Q24 | J48: Total CRE | K48: =SUM(K41:K47) -> 15560 | L48: mn | M48: USD | N48: CRE
B49: Healthcare | C49: 1273
B50: Hotel | C50: 806
B51: Commercial land | C51: 13
B52: Other | C52: 597
B53: Total | C53: =SUM(C41:C52) -> 15560
A57: 1Q24 | B57: CRE Property Type | C57: Loan Amount | E57: CRE Property Type | F57: Loan Amount | H57: Ticker | I57: Quarter | J57: CRE Property Type | K57: Loan Amount | L57: Unit | M57: Currency | N57: Category
B58: Residential homebuilders | C58: 992 | E58: Residential | F58: =C64+C58 -> 1085 | H58: RF | I58: 1Q24 | J58: Residential | K58: =F58 -> 1085 | L58: mn | M58: USD | N58: CRE
B59: Apartments | C59: 4052 | E59: Multi-family | F59: =C59 -> 4052 | H59: RF | I59: 1Q24 | J59: Multi-family | K59: =F59 -> 4052 | L59: mn | M59: USD | N59: CRE
B60: Industrial | C60: 2229 | E60: Industrial | F60: =C60 -> 2229 | H60: RF | I60: 1Q24 | J60: Industrial | K60: =F60 -> 2229 | L60: mn | M60: USD | N60: CRE
B61: Data center | C61: 314 | E61: Office | F61: =C63 -> 1504 | H61: RF | I61: 1Q24 | J61: Office | K61: =F61 -> 1504 | L61: mn | M61: USD | N61: CRE
B62: Diversified | C62: 2034 | E62: Retail | F62: =C65 -> 1396 | H62: RF | I62: 1Q24 | J62: Retail | K62: =F62 -> 1396 | L62: mn | M62: USD | N62: CRE
B63: Business offices | C63: 1504 | E63: Lodging | F63: =C67 -> 785 | H63: RF | I63: 1Q24 | J63: Lodging | K63: =F63 -> 785 | L63: mn | M63: USD | N63: CRE
B64: Residential land | C64: 93 | E64: Other | F64: =SUM(C66,C68:C69,C61:C62) -> 4311 | H64: RF | I64: 1Q24 | J64: Other | K64: =F64 -> 4311 | L64: mn | M64: USD | N64: CRE
B65: Retail | C65: 1396 | E65: Total CRE | F65: =SUM(F58:F64) -> 15362 | H65: RF | I65: 1Q24 | J65: Total CRE | K65: =SUM(K58:K64) -> 15362 | L65: mn | M65: USD | N65: CRE
B66: Healthcare | C66: 1382
B67: Hotel | C67: 785
B68: Commercial land | C68: 17
B69: Other | C69: 564
B70: Total | C70: =SUM(C58:C69) -> 15362

Sheet RF LLM API
A1: 4Q24
B2: Correct | C2: 15.3
B4: CRE Property Type | C4: Percentage
B5: Residential homebuilders | C5: 0.071
B6: Apartments | C6: 0.286
B7: Industrial | C7: 0.15
B8: Data center | C8: 0.022
B9: Diversified | C9: 0.114
B10: Business offices | C10: 0.096
B11: Residential land | C11: 0.004
B12: Retail | C12: 0.095
B13: Healthcare | C13: 0.074
B14: Hotel | C14: 0.051
B15: Commercial land | C15: 0.001
B16: Self storage | C16: 0.019
B17: Other | C17: 0.017
B18: Total CRE | C18: =SUM(C5:C17) -> 1
B29: Correct | F29: LLM
B31: CRE Property Type | C31: Percentage | D31: Loan Amount | F31: CRE Property Type | G31: Loan Amount | I31: =B31=F31 -> TRUE | J31: =D31=G31 -> TRUE
B32: Multi-family | C32: =C6 -> 0.286 | D32: =$C$2*C32*1000 -> 4375.8 | F32: Multi-family | G32: 4375 | I32: =B32=F32 -> TRUE | J32: TRUE
B33: Industrial | C33: =C7 -> 0.15 | D33: =$C$2*C33*1000 -> 2295 | F33: Industrial | G33: 2295 | I33: =B33=F33 -> TRUE | J33: =D33=G33 -> TRUE
B34: Retail | C34: =C12 -> 0.095 | D34: =$C$2*C34*1000 -> 1453.5 | F34: Retail | G34: 1453 | I34: =B34=F34 -> TRUE | J34: TRUE
B35: Lodging | C35: =C14 -> 0.051 | D35: =$C$2*C35*1000 -> 780.3 | F35: Lodging | G35: 780 | I35: =B35=F35 -> TRUE | J35: TRUE
B36: Office | C36: =C10 -> 0.096 | D36: =$C$2*C36*1000 -> 1468.8 | F36: Office | G36: 1468 | I36: =B36=F36 -> TRUE | J36: TRUE
B37: Residential | C37: =C11+C5 -> 0.075 | D37: =$C$2*C37*1000 -> 1147.5 | F37: Residential | G37: 1147 | I37: =B37=F37 -> TRUE | J37: TRUE
B38: Other | C38: =SUM(C15:C17,C13,C8:C9) -> 0.247 | D38: =$C$2*C38*1000 -> 3779.1 | F38: Other | G38: 3779 | I38: =B38=F38 -> TRUE | J38: TRUE
B39: Total CRE | C39: =SUM(C32:C38) -> 1 | D39: =SUM(D32:D38) -> 15300 | F39: Total CRE | G39: 15300 | I39: =B39=F39 -> TRUE | J39: =D39=G39 -> TRUE
B41: Accuracy | C41: =18/18 -> 1
A43: 3Q24
B44: Correct | C44: 15.4
B46: CRE Property Type | C46: Percentage
B47: Residential homebuilders | C47: 0.075
B48: Apartments | C48: 0.275
B49: Industrial | C49: 0.145
B50: Data center | C50: 0.026
B51: Diversified | C51: 0.121
B52: Business offices | C52: 0.101
B53: Residential land | C53: 0.004
B54: Retail | C54: 0.089
B55: Healthcare | C55: 0.076
B56: Hotel | C56: 0.052
B57: Commercial land | C57: 0.001
B58: Self storage | C58: 0.018
B59: Other | C59: 0.017
B60: Total CRE | C60: =SUM(C47:C59) -> 1
B68: Correct | F68: LLM
B70: CRE Property Type | C70: Percentage | D70: Loan Amount | F70: CRE Property Type | G70: Loan Amount | I70: =B70=F70 -> TRUE | J70: =D70=G70 -> TRUE
B71: Multi-family | C71: =C48 -> 0.275 | D71: =$C$44*C71*1000 -> 4235 | F71: Multi-family | G71: 4235 | I71: =B71=F71 -> TRUE | J71: =D71=G71 -> TRUE
B72: Industrial | C72: =C49 -> 0.145 | D72: =$C$44*C72*1000 -> 2233 | F72: Industrial | G72: 2233 | I72: =B72=F72 -> TRUE | J72: =D72=G72 -> TRUE
B73: Retail | C73: =C54 -> 0.089 | D73: =$C$44*C73*1000 -> 1370.6 | F73: Retail | G73: 1371 | I73: =B73=F73 -> TRUE | J73: TRUE
B74: Lodging | C74: =C56 -> 0.052 | D74: =$C$44*C74*1000 -> 800.8 | F74: Lodging | G74: 801 | I74: =B74=F74 -> TRUE | J74: TRUE
B75: Office | C75: =C52 -> 0.101 | D75: =$C$44*C75*1000 -> 1555.4 | F75: Office | G75: 1555 | I75: =B75=F75 -> TRUE | J75: TRUE
B76: Residential | C76: =C53+C47 -> 0.079 | D76: =$C$44*C76*1000 -> 1216.6 | F76: Residential | G76: 1189 | I76: =B76=F76 -> TRUE | J76: =D76=G76 -> FALSE
B77: Other | C77: =SUM(C57:C59,C55,C50:C51) -> 0.259 | D77: =$C$44*C77*1000 -> 3988.6 | F77: Other | G77: 4013 | I77: =B77=F77 -> TRUE | J77: =D77=G77 -> FALSE
B78: Total CRE | C78: =SUM(C71:C77) -> 1 | D78: =SUM(D71:D77) -> 15400 | F78: Total CRE | G78: 15400 | I78: =B78=F78 -> TRUE | J78: =D78=G78 -> TRUE
B80: Accuracy | C80: =16/18 -> 0.88888889
A82: 2Q24
B83: Correct | C83: 15.6
B85: CRE Property Type | C85: Percentage
B86: Residential homebuilders | C86: 0.072
B87: Apartments | C87: 0.275
B88: Industrial | C88: 0.142
B89: Data center | C89: 0.021
B90: Diversified | C90: 0.122
B91: Business offices | C91: 0.101
B92: Residential land | C92: 0.005
B93: Retail | C93: 0.089
B94: Healthcare | C94: 0.082
B95: Hotel | C95: 0.052
B96: Commercial land | C96: 0.001
B97: Other | C97: 0.038
B98: Total CRE | C98: =SUM(C86:C97) -> 1
B105: Correct | F105: LLM
B107: CRE Property Type | C107: Percentage | D107: Loan Amount | F107: CRE Property Type | G107: Loan Amount | I107: =B107=F107 -> TRUE | J107: =D107=G107 -> TRUE
B108: Multi-family | C108: =C87 -> 0.275 | D108: =$C$83*C108*1000 -> 4290 | F108: Multi-family | G108: 4292 | I108: =B108=F108 -> TRUE | J108: =D108=G108 -> FALSE
B109: Industrial | C109: =C88 -> 0.142 | D109: =$C$83*C109*1000 -> 2215.2 | F109: Industrial | G109: 2212 | I109: =B109=F109 -> TRUE | J109: =D109=G109 -> FALSE
B110: Retail | C110: =C93 -> 0.089 | D110: =$C$83*C110*1000 -> 1388.4 | F110: Retail | G110: 1388 | I110: =B110=F110 -> TRUE | J110: TRUE
B111: Lodging | C111: =C95 -> 0.052 | D111: =$C$83*C111*1000 -> 811.2 | F111: Lodging | G111: 811 | I111: =B111=F111 -> TRUE | J111: TRUE
B112: Office | C112: =C91 -> 0.101 | D112: =$C$83*C112*1000 -> 1575.6 | F112: Office | G112: 1575 | I112: =B112=F112 -> TRUE | J112: TRUE
B113: Residential | C113: =C92+C86 -> 0.077 | D113: =$C$83*C113*1000 -> 1201.2 | F113: Residential | G113: 1158 | I113: =B113=F113 -> TRUE | J113: =D113=G113 -> FALSE
B114: Other | C114: =SUM(C96:C97,C94,C89:C90) -> 0.264 | D114: =$C$83*C114*1000 -> 4118.4 | F114: Other | G114: 2461 | I114: =B114=F114 -> TRUE | J114: =D114=G114 -> FALSE
B115: Total CRE | C115: =SUM(C108:C114) -> 1 | D115: =SUM(D108:D114) -> 15600 | F115: Total CRE | G115: 15600 | I115: =B115=F115 -> TRUE | J115: =D115=G115 -> TRUE
B117: Accuracy | C117: =14/18 -> 0.77777778
A119: 1Q24
B120: Correct | C120: 15.4
B122: CRE Property Type | C122: Percentage
B123: Residential homebuilders | C123: 0.065
B124: Apartments | C124: 0.264
B125: Industrial | C125: 0.145
B126: Data center | C126: 0.02
B127: Diversified | C127: 0.132
B128: Business offices | C128: 0.098
B129: Residential land | C129: 0.006
B130: Retail | C130: 0.091
B131: Healthcare | C131: 0.09
B132: Hotel | C132: 0.051
B133: Commercial land | C133: 0.001
B134: Other | C134: 0.037
B135: Total CRE | C135: =SUM(C123:C134) -> 1
B141: Correct | F141: LLM
...

Sheet RF Script
B2: Script 4Q24 (10-Q) | K2: Script 3Q24 (10-Q)
B14: Script 2Q24 (10-Q) | K14: Script 1Q24 (10-Q)

Sheet LLM Interface Prompts

Sheet BAC LLM Interface
B2: Write Seconds | C2: LLM (4Q24)
B3: =175/250*60 -> 42 | C3: Convert Prompt | D3: Please convert the attached pie chart of a commercial real estate (CRE) portfolio into a table by property type with its amount and percentage values, and include a total row.
B4: =(215/250)*60 -> 51.6 | C4: Correct Prompt | D4: There is an error in the table. The $13.2 and 20% values should be associated the "Other" property type and the $0.90 and 1% values should be associated with the "Residential" property type. Please revise the table.
B5: =276/250*60 -> 66.24 | C5: Clean Prompt | D5: Please create a new table using the "Property Type" and "Amount" columns. First rename them "CRE Property Type" and "Loan Amount", then add "Ticker" and "Quarter" columns to the left of these columns, and each row should include "BAC" under "Ticker" and "4Q24" under "Quarter"
B6: =236/250*60 -> 56.64 | C6: Clean Prompt | D6: Now add "Unit", "Currency", and "Category" columns to the right of the "CRE Property Type" and "Loan Amount" columns, and each row should include "bn", "USD", and "CRE" under the "Unit", "Currency", and "Category" columns, respectively.
B7: =155/250*60 -> 37.2 | C7: Clean Prompt | D7: Include the original "Total" row but rename it to "Total CRE" and populate the empty cells in this row with the same values from prior rows in each column.
B8: =228/250*60 -> 54.72 | C8: Clean Prompt | D8: In the "CRE Property Type" column, rename "Industrial / Warehouse" to "Industrial", "Multi-family rental" to "Multi-family", "Shopping centers / Retail" to "Retail", "Hotel / Motels" to "Lodging", and "Multi-use" to "Mixed-use".
P11: Correct | S11: LLM
P12: Property Type | Q12: Amount ($bn) | S12: Property Type | T12: Amount ($bn) | V12: =P12=S12 -> TRUE | W12: =Q12=T12 -> TRUE
P13: Office | Q13: 15.1 | S13: Office | T13: 15.1 | V13: =P13=S13 -> TRUE | W13: =Q13=T13 -> TRUE
P14: Industrial | Q14: 13.2 | S14: Industrial | T14: 13.2 | V14: =P14=S14 -> TRUE | W14: =Q14=T14 -> TRUE
P15: Multi-family | Q15: 11 | S15: Multi-family | T15: 11 | V15: =P15=S15 -> TRUE | W15: =Q15=T15 -> TRUE
P16: Retail | Q16: 5.6 | S16: Retail | T16: 5.6 | V16: =P16=S16 -> TRUE | W16: =Q16=T16 -> TRUE
P17: Lodging | Q17: 4.7 | S17: Lodging | T17: 4.7 | V17: =P17=S17 -> TRUE | W17: =Q17=T17 -> TRUE
P18: Mixed-use | Q18: 2.2 | S18: Mixed-use | T18: 2.2 | V18: =P18=S18 -> TRUE | W18: =Q18=T18 -> TRUE
P19: Residential | Q19: 0.9 | S19: Residential | T19: 13.2 | V19: =P19=S19 -> TRUE | W19: =Q19=T19 -> FALSE
P20: Other | Q20: 13.2 | S20: Other | T20: 0.9 | V20: =P20=S20 -> TRUE | W20: =Q20=T20 -> FALSE
P21: Total | Q21: =SUM(Q13:Q20) -> 65.9 | S21: Total | T21: 66
S23: Accuracy | T23: =18/20 -> 0.9
B31: Write Seconds | C31: LLM (3Q24)
B32: 28 | C32: Convert Prompt | D32: Please convert the attached pie chart of a commercial real estate (CRE) portfolio into a table by property type with its amount and percentage values, and include a total row.
B33: 32 | C33: Correct Prompt | D33: There is an error in the table. The $14.2 and 21% values should be associated the "Other" property type and the $0.70 and 1% values should be associated with the "Residential" property type. Please revise the table.
B34: 45 | C34: Clean Prompt | D34: Please create a new table using the "Property Type" and "Amount" columns. First rename them "CRE Property Type" and "Loan Amount", then add "Ticker" and "Quarter" columns to the left of these columns, and each row should include "BAC" under "Ticker" and "3Q24" under "Quarter"
B35: 42 | C35: Clean Prompt | D35: Now add "Unit", "Currency", and "Category" columns to the right of the "CRE Property Type" and "Loan Amount" columns, and each row should include "bn", "USD", and "CRE" under the "Unit", "Currency", and "Category" columns, respectively.
B36: 22 | C36: Clean Prompt | D36: Include the original "Total" row but rename it to "Total CRE" and populate the empty cells in this row with the same values from prior rows in each column.
B37: 50 | C37: Clean Prompt | D37: In the "CRE Property Type" column, rename "Industrial / Warehouse" to "Industrial", "Multi-family rental" to "Multi-family", "Shopping centers / Retail" to "Retail", "Hotel / Motels" to "Lodging", and "Multi-use" to "Mixed-use".
P40: Correct | S40: LLM
P41: Property Type | Q41: Amount ($bn) | S41: Property Type | T41: Amount ($bn) | V41: =P41=S41 -> TRUE | W41: =Q41=T41 -> TRUE
P42: Office | Q42: 15.8 | S42: Office | T42: 15.8 | V42: =P42=S42 -> TRUE | W42: =Q42=T42 -> TRUE
P43: Industrial | Q43: 13.9 | S43: Industrial | T43: 13.9 | V43: =P43=S43 -> TRUE | W43: =Q43=T43 -> TRUE
P44: Multi-family | Q44: 11.7 | S44: Multi-family | T44: 11.7 | V44: =P44=S44 -> TRUE | W44: =Q44=T44 -> TRUE
P45: Retail | Q45: 5.4 | S45: Retail | T45: 5.4 | V45: =P45=S45 -> TRUE | W45: =Q45=T45 -> TRUE
P46: Lodging | Q46: 4.7 | S46: Lodging | T46: 4.7 | V46: =P46=S46 -> TRUE | W46: =Q46=T46 -> TRUE
P47: Multi-use | Q47: 2.1 | S47: Multi-use | T47: 2.1 | V47: =P47=S47 -> TRUE | W47: =Q47=T47 -> TRUE
P48: Residential | Q48: 0.7 | S48: Residential | T48: 14.2 | V48: =P48=S48 -> TRUE | W48: =Q48=T48 -> FALSE
P49: Other | Q49: 14.2 | S49: Other | T49: 0.7 | V49: =P49=S49 -> TRUE | W49: =Q49=T49 -> FALSE
P50: Total | Q50: =SUM(Q42:Q49) -> 68.5 | S50: Total | T50: 68
S52: Accuracy | T52: =18/20 -> 0.9
B62: Write Seconds | C62: LLM (2Q24)
B63: 28 | C63: Convert Prompt | D63: Please convert the attached pie chart of a commercial real estate (CRE) portfolio into a table by property type with its amount and percentage values, and include a total row.
B64: 45 | C64: Clean Prompt | D64: Please create a new table using the "Property Type" and "Amount" columns. First rename them "CRE Property Type" and "Loan Amount", then add "Ticker" and "Quarter" columns to the left of these columns, and each row should include "BAC" under "Ticker" and "2Q24" under "Quarter"
B65: 42 | C65: Clean Prompt | D65: Now add "Unit", "Currency", and "Category" columns to the right of the "CRE Property Type" and "Loan Amount" columns, and each row should include "bn", "USD", and "CRE" under the "Unit", "Currency", and "Category" columns, respectively.
B66: 22 | C66: Clean Prompt | D66: Include the original "Total" row but rename it to "Total CRE" and populate the empty cells in this row with the same values from prior rows in each column.
B67: 50 | C67: Clean Prompt | D67: In the "CRE Property Type" column, rename "Industrial / Warehouse" to "Industrial", "Multi-family rental" to "Multi-family", "Shopping centers / Retail" to "Retail", "Hotel / Motels" to "Lodging", and "Multi-use" to "Mixed-use".
P71: Correct | S71: LLM
P72: Property Type | Q72: Amount ($bn) | S72: Property Type | T72: Amount ($bn)
P73: Office | Q73: 16.3 | S73: Office | T73: 16.3 | V73: =P73=S73 -> TRUE | W73: =Q73=T73 -> TRUE
P74: Industrial | Q74: 14.7 | S74: Industrial | T74: 14.7 | V74: =P74=S74 -> TRUE | W74: =Q74=T74 -> TRUE
P75: Multi-family | Q75: 11.6 | S75: Multi-family | T75: 11.6 | V75: =P75=S75 -> TRUE | W75: =Q75=T75 -> TRUE
P76: Retail | Q76: 5.6 | S76: Retail | T76: 5.6 | V76: =P76=S76 -> TRUE | W76: =Q76=T76 -> TRUE
P77: Lodging | Q77: 5.1 | S77: Lodging | T77: 5.1 | V77: =P77=S77 -> TRUE | W77: =Q77=T77 -> TRUE
P78: Multi-use | Q78: 2.1 | S78: Multi-use | T78: 2.1 | V78: =P78=S78 -> TRUE | W78: =Q78=T78 -> TRUE
P79: Residential | Q79: 0.8 | S79: Residential | T79: 0.8 | V79: =P79=S79 -> TRUE | W79: =Q79=T79 -> TRUE
P80: Other | Q80: 14.1 | S80: Other | T80: 14.1 | V80: =P80=S80 -> TRUE | W80: =Q80=T80 -> TRUE
P81: Total | Q81: =SUM(Q73:Q80) -> 70.3 | S81: Total | T81: =SUM(T73:T80) -> 70.3 | V81: =P81=S81 -> TRUE | W81: =Q81=T81 -> TRUE
S83: Accuracy | T83: =30/30 -> 1
B90: Write Seconds | C90: LLM (1Q24)
B91: 28 | C91: Convert Prompt | D91: Please convert the attached pie chart of a commercial real estate (CRE) portfolio into a table by property type with its amount and percentage values, and include a total row.
B92: 45 | C92: Clean Prompt | D92: Please create a new table using the "Property Type" and "Amount" columns. First rename them "CRE Property Type" and "Loan Amount", then add "Ticker" and "Quarter" columns to the left of these columns, and each row should include "BAC" under "Ticker" and "1Q24" under "Quarter" columns.
B93: 42 | C93: Clean Prompt | D93: Now add "Unit", "Currency", and "Category" columns to the right of the "CRE Property Type" and "Loan Amount" columns, and each row should include "bn", "USD", and "CRE" under the "Unit", "Currency", and "Category" columns, respectively.
B94: 22 | C94: Clean Prompt | D94: Include the original "Total" row but rename it to "Total CRE" and populate the empty cells in this row with the same values from prior rows in each column.
B95: 50 | C95: Clean Prompt | D95: In the "CRE Property Type" column, rename "Industrial / Warehouse" to "Industrial", "Multi-family rental" to "Multi-family", "Shopping centers / Retail" to "Retail", "Hotel / Motels" to "Lodging", and "Multi-use" to "Mixed-use".
P96: Correct | S96: LLM
P97: Property Type | Q97: Amount ($bn) | S97: Property Type | T97: Amount ($bn)
P98: Office | Q98: 17.4 | S98: Office | T98: 17.4 | V98: =P98=S98 -> TRUE | W98: =Q98=T98 -> TRUE
P99: Industrial | Q99: 14.6 | S99: Industrial | T99: 14.6 | V99: =P99=S99 -> TRUE | W99: =Q99=T99 -> TRUE
P100: Multi-family | Q100: 11.4 | S100: Multi-family | T100: 11.4 | V100: =P100=S100 -> TRUE | W100: =Q100=T100 -> TRUE
P101: Retail | Q101: 5.7 | S101: Retail | T101: 5.7 | V101: =P101=S101 -> TRUE | W101: =Q101=T101 -> TRUE
P102: Lodging | Q102: 5.4 | S102: Lodging | T102: 5.4 | V102: =P102=S102 -> TRUE | W102: =Q102=T102 -> TRUE
P103: Multi-use | Q103: 2.5 | S103: Multi-use | T103: 2.5 | V103: =P103=S103 -> TRUE | W103: =Q103=T103 -> TRUE
P104: Residential | Q104: 0.7 | S104: Residential | T104: 0.7 | V104: =P104=S104 -> TRUE | W104: =Q104=T104 -> TRUE
P105: Other | Q105: 13.8 | S105: Other | T105: 13.8 | V105: =P105=S105 -> TRUE | W105: =Q105=T105 -> TRUE
P106: Total | Q106: 72 | S106: Total | T106: 72 | V106: =P106=S106 -> TRUE | W106: =Q106=T106 -> TRUE
S109: Accuracy | T109: =30/30 -> 1

Sheet JPM LLM Interface
A2: Write Seconds | B2: LLM 3Q24 (10-Q)
A3: =200/250*60 -> 48 | B3: Convert Prompt | C3: Please convert the attached image containing data on a commercial real estate portfolio into a table with only the property type rows, the credit exposure and % drawn columns, and include a total row.
A4: =224/250*60 -> 53.76 | B4: Standardization Prompt | C4: Use the table to create a new one that takes the product between the "Credit Exposure" and "% Drawn" columns in a new column. Do not show decimals and the "Total CRE" row should sum the calculated values from the prior rows.
A5: =167/250*60 -> 40.08 | B5: Standardization Prompt | C5: Revise the table to combine "Other Income Producing Properties" and "Services and Non Income Producing" property types into an "Other" row with the combined sum value.
A6: =225/250*60 -> 54 | B6: Clean Prompt | C6: Please create a new table using only the "Property Type" and "Credit Exposure Drawn ($M)" columns. Then add "Ticker" and "Quarter" columns to the left of these columns, and each row should include "JPM" under "Ticker" and "3Q24" under "Quarter".
A7: =235/250*60 -> 56.4 | B7: Clean Prompt | C7: Now add "Unit", "Currency", and "Category" columns to the right of the "CRE Property Type" and "Loan Amount" columns, and each row should include "mn", "USD", and "CRE" under the "Unit", "Currency", and "Category" columns, respectively.
A8: =108/250*60 -> 25.92 | B8: Clean Prompt | C8: Rename "Total Real Estate Exposure" to "Total CRE" and rename "Credit Exposure Drawn ($M)" to "Loan Amount".
B10: EXTRACTION
B12: Correct | F12: LLM
B14: CRE Property Type | C14: Loan Amount | D14: % Drawn | F14: CRE Property Type | G14: Loan Amount | H14: % Drawn | I14: =B14=F14 -> TRUE | J14: =C14=G14 -> TRUE | K14: =D14=H14 -> TRUE
B15: Multi-family | C15: 125410 | D15: 0.91 | F15: Multi-family | G15: 125410 | H15: 0.91 | I15: =B15=F15 -> TRUE | J15: =C15=G15 -> TRUE | K15: =D15=H15 -> TRUE
B16: Industrial | C16: 19282 | D16: 0.74 | F16: Industrial | G16: 19282 | H16: 0.74 | I16: =B16=F16 -> TRUE | J16: =C16=G16 -> TRUE | K16: =D16=H16 -> TRUE
B17: Office | C17: 16926 | D17: 0.81 | F17: Office | G17: 16926 | H17: 0.81 | I17: =B17=F17 -> TRUE | J17: =C17=G17 -> TRUE | K17: =D17=H17 -> TRUE
B18: Other Income Producing Properties | C18: 15011 | D18: 0.67 | F18: Other Income Producing Properties | G18: 15011 | H18: 0.67 | I18: =B18=F18 -> TRUE | J18: =C18=G18 -> TRUE | K18: =D18=H18 -> TRUE
B19: Services and Non Income Producing | C19: 14557 | D19: 0.51 | F19: Services and Non Income Producing | G19: 14557 | H19: 0.51 | I19: =B19=F19 -> TRUE | J19: =C19=G19 -> TRUE | K19: =D19=H19 -> TRUE
B20: Retail | C20: 12841 | D20: 0.69 | F20: Retail | G20: 12841 | H20: 0.69 | I20: =B20=F20 -> TRUE | J20: =C20=G20 -> TRUE | K20: =D20=H20 -> TRUE
