Workbook

Sheet Summary
E2: Cumulative Extraction Summary by Method
F4: Excel (Advanced) | G4: LLM API (exc build) | H4: Python Script (exc build) | K4: Standardize Goal:
E5: Ticker | F5: Manual | G5: Supplement | H5: 10-Q | V5: Scroll
E6: AVB | F6: =H23 -> 372 | G6: =N23 -> 242 | H6: =S23 -> 112.33333 | V6: Right
E7: CCI | F7: =H36 -> 448 | G7: =N36 -> 423 | H7: =S36 -> 103 | V7: for
E8: AMT | F8: =H51 -> 444 | G8: =N51 -> 459.66667 | H8: =S51 -> 165 | V8: Charts
E9: PLD | F9: =H68 -> 560 | G9: =N68 -> 431 | H9: =S68 -> 396.08
E10: WELL | F10: =H84 -> 432 | G10: =N84 -> 282.33333 | H10: =S84 -> 174.72
E12: Average | F12: =AVERAGE(F6:F10) -> 451.2 | G12: =AVERAGE(G6:G10) -> 367.6 | H12: =AVERAGE(H6:H10) -> 190.22667
E13: Efficency | G13: =($F$12-G12)/$F$12*1 -> 0.18528369 | H13: =($F$12-H12)/$F$12*1 -> 0.57839835
H14: =H13-G13 -> 0.39311466
AJ15: Cumulative Time (10-Q) | AX15: Cumulative Time (Presentation)
E16: Advanced Excel Manual Benchmark (10-Q) | J16: LLM API (Presentation) | P16: Python Modules (10-Q) | V16: Time Savings | AJ16: (Python Modules vs Advanced Excel) | AX16: (LLM API vs Advanced Excel) | BL16: Script Construct | BO16: LLM API Construct
E17: (time measured in seconds) | J17: (time measured in seconds) | P17: (time measured in seconds) | BL17: Breakeven | BO17: Breakeven
B18: Ticker | C18: Quarter | E18: Extraction | F18: Standardization | G18: Database Format | H18: Total | J18: Construct Extraction | K18: Adjustment | L18: Execute | M18: Accuracy | N18: Total | P18: Construct Extraction | Q18: Adjustment | R18: Execute | S18: Total | U18: Date | V18: LLM API | W18: Python Modules | AJ18: Advanced Excel | AK18: Python Modules | AM18: Delta | AN18: Efficiency % | AX18: Advanced Excel | AY18: LLM API | BA18: Delta | BB18: Efficiency %
B19: AVB | C19: 4Q24 | E19: 28 | F19: =66-E19 -> 38 | G19: =93-SUM(E19:F19) -> 27 | H19: =SUM(E19:G19) -> 93 | K19: 47 | L19: 18 | M19: ='AVB LLM API'!L20 -> 1 | N19: =SUM(K19:L19) -> 65 | Q19: 11 | R19: 7 | S19: =SUM(Q19:R19) -> 18 | U19: 45657 | V19: =H19-N19 -> 28 | W19: =H19-S19 -> 75 | AI19: 45657 | AJ19: =H19+H20+H21+H22 -> 372 | AK19: =S19+S20+S21+S22 -> 112.33333 | AM19: =AK19-AJ19 -> -259.66667 | AN19: =(-AM19/AJ19) -> 0.69802867 | AW19: 45657 | AX19: =AJ19 -> 372 | AY19: =N19+N20+N21+N22 -> 242 | BA19: =AY19-AX19 -> -130 | BB19: =(-BA19/AX19) -> 0.34946237 | BJ19: =B19 -> AVB | BK19: 45657 | BL19: =H19-S19 -> 75 | BO19: =H19-N19 -> 28
A20: Base | B20: AVB | C20: 3Q24 | E20: 28 | F20: =66-E20 -> 38 | G20: =93-SUM(E20:F20) -> 27 | H20: =SUM(E20:G20) -> 93 | J20: =3619/250*60 -> 868.56 | K20: 0 | L20: 24 | M20: ='AVB LLM API'!L40 -> 0.96153846 | N20: =L20+AVERAGE(K19,K21:K22) -> 64 | P20: =2496/250*60 -> 599.04 | Q20: 0 | R20: 10 | S20: =R20+AVERAGE(Q19,Q21:Q22) -> 29.333333 | U20: 45565 | V20: =H20-N20 -> 29 | W20: =H20-S20 -> 63.666667 | AI20: 45565 | AJ20: =H20+H21+H22 -> 279 | AK20: =S20+S21+S22 -> 94.333333 | AM20: =AK20-AJ20 -> -184.66667 | AN20: =(-AM20/AJ20) -> 0.66188769 | AW20: 45565 | AX20: =AJ20 -> 279 | AY20: =N20+N21+N22 -> 177 | BA20: =AY20-AX20 -> -102 | BB20: =(-BA20/AX20) -> 0.3655914 | BJ20: =B20 -> AVB | BK20: 45565 | BL20: =H20-(R20+AVERAGE(Q19,Q21:Q22)) -> 63.666667 | BO20: =H20-(L20+AVERAGE(K19,K21:K22)) -> 29
B21: AVB | C21: 2Q24 | E21: 28 | F21: =66-E21 -> 38 | G21: =93-SUM(E21:F21) -> 27 | H21: =SUM(E21:G21) -> 93 | K21: 38 | L21: 20 | M21: ='AVB LLM API'!L58 -> 1 | N21: =SUM(K21:L21) -> 58 | Q21: 32 | R21: 8 | S21: =SUM(Q21:R21) -> 40 | U21: 45473 | V21: =H21-N21 -> 35 | W21: =H21-S21 -> 53 | AI21: 45473 | AJ21: =H21+H22 -> 186 | AK21: =S21+S22 -> 65 | AM21: =AK21-AJ21 -> -121 | AN21: =(-AM21/AJ21) -> 0.65053763 | AW21: 45473 | AX21: =AJ21 -> 186 | AY21: =N21+N22 -> 113 | BA21: =AY21-AX21 -> -73 | BB21: =(-BA21/AX21) -> 0.39247312 | BJ21: =B21 -> AVB | BK21: 45473 | BL21: =H21-S21 -> 53 | BO21: =H21-N21 -> 35
B22: AVB | C22: 1Q24 | E22: 28 | F22: =66-E22 -> 38 | G22: =93-SUM(E22:F22) -> 27 | H22: =SUM(E22:G22) -> 93 | K22: 35 | L22: 20 | M22: ='AVB LLM API'!L76 -> 1 | N22: =SUM(K22:L22) -> 55 | Q22: 15 | R22: 10 | S22: =SUM(Q22:R22) -> 25 | U22: 45382 | V22: =H22-N22 -> 38 | W22: =H22-S22 -> 68 | AI22: 45382 | AJ22: =H22 -> 93 | AK22: =S22 -> 25 | AM22: =AK22-AJ22 -> -68 | AN22: =(-AM22/AJ22) -> 0.7311828 | AW22: 45382 | AX22: =AJ22 -> 93 | AY22: =N22 -> 55 | BA22: =AY22-AX22 -> -38 | BB22: =(-BA22/AX22) -> 0.40860215 | BJ22: =B22 -> AVB | BK22: 45382 | BL22: =H22-S22 -> 68 | BO22: =H22-N22 -> 38
B23: Total | G23: Cumulative Total | H23: =SUM(H19:H22) -> 372 | L23: Cumulative Total | N23: =SUM(N19:N22) -> 242 | R23: Cumulative Total | S23: =SUM(S19:S22) -> 112.33333 | U23: Total | V23: =SUM(V19:V22) -> 130 | W23: =SUM(W19:W22) -> 259.66667 | BK23: Quarter Breakeven | BL23: =P20/AVERAGE(BL19:BM22) -> 9.2278306 | BO23: =J20/AVERAGE(BO19:BP22) -> 26.724923
L24: Cumulative Efficiency % | N24: =(($H23-N23)/$H23)*1 -> 0.34946237 | R24: Cumulative Efficiency % | S24: =(($H23-S23)/$H23)*1 -> 0.69802867
L25: Average Accuracy | M25: =AVERAGE(M19:M22) -> 0.99038462
K26: =SUM(K19:K22) -> 120 | L26: =SUM(L19:L22) -> 82
E29: Advanced Excel Manual Benchmark (10-Q) | J29: LLM API (Presentation) | P29: Python Modules (10-Q)
E30: (time measured in seconds) | J30: (time measured in seconds) | P30: (time measured in seconds)
B31: Ticker | C31: Quarter | E31: Extraction | F31: Standardization | G31: Database Format | H31: Total | J31: Construct Extraction | K31: Adjustment | L31: Execute | M31: Accuracy | N31: Total | P31: Construct Extraction | Q31: Adjustment | R31: Execute | S31: Total | U31: Date | V31: LLM API | W31: Python Modules | AJ31: Advanced Excel | AK31: Python Modules | AM31: Delta | AN31: Efficiency % | AX31: Advanced Excel | AY31: LLM API | BA31: Delta | BB31: Efficiency %
B32: CCI | C32: 4Q24 | E32: 25 | F32: 59 | G32: 28 | H32: =SUM(E32:G32) -> 112 | K32: 62 | L32: 46 | M32: ='CCI LLM API'!H26 -> 0.92105263 | N32: =SUM(K32:L32) -> 108 | Q32: 22 | R32: 8 | S32: =SUM(Q32:R32) -> 30 | U32: 45657 | V32: =H32-N32 -> 4 | W32: =H32-S32 -> 82 | AI32: 45657 | AJ32: =H32+H33+H34+H35 -> 448 | AK32: =S32+S33+S34+S35 -> 103 | AM32: =AK32-AJ32 -> -345 | AN32: =(-AM32/AJ32) -> 0.77008929 | AW32: 45657 | AX32: =AJ32 -> 448 | AY32: =N32+N33+N34+N35 -> 423 | BA32: =AY32-AX32 -> -25 | BB32: =(-BA32/AX32) -> 0.055803571 | BJ32: =B32 -> CCI | BK32: 45657 | BL32: =H32-S32 -> 82 | BO32: =H32-N32 -> 4
A33: Base | B33: CCI | C33: 3Q24 | E33: 25 | F33: 59 | G33: 28 | H33: =SUM(E33:G33) -> 112 | J33: =5674/250*60 -> 1361.76 | K33: 0 | L33: 39 | M33: ='CCI LLM API'!H50 -> 0.73684211 | N33: =L33+AVERAGE(K32,K34:K35) -> 99 | P33: =2639/250*60 -> 633.36 | Q33: 0 | R33: 6 | S33: =R33+AVERAGE(Q32,Q34:Q35) -> 24 | U33: 45565 | V33: =H33-N33 -> 13 | W33: =H33-S33 -> 88 | AI33: 45565 | AJ33: =H33+H34+H35 -> 336 | AK33: =S33+S34+S35 -> 73 | AM33: =AK33-AJ33 -> -263 | AN33: =(-AM33/AJ33) -> 0.7827381 | AW33: 45565 | AX33: =AJ33 -> 336 | AY33: =N33+N34+N35 -> 315 | BA33: =AY33-AX33 -> -21 | BB33: =(-BA33/AX33) -> 0.0625 | BJ33: =B33 -> CCI | BK33: 45565 | BL33: =H33-(R33+AVERAGE(Q32,Q34:Q35)) -> 88 | BO33: =H33-(L33+AVERAGE(K32,K34:K35)) -> 13
B34: CCI | C34: 2Q24 | E34: 25 | F34: 59 | G34: 28 | H34: =SUM(E34:G34) -> 112 | K34: =73 -> 73 | L34: 44 | M34: ='CCI LLM API'!H77 -> 0.85 | N34: =SUM(K34:L34) -> 117 | Q34: 15 | R34: 7 | S34: =SUM(Q34:R34) -> 22 | U34: 45473 | V34: =H34-N34 -> -5 | W34: =H34-S34 -> 90 | AI34: 45473 | AJ34: =H34+H35 -> 224 | AK34: =S34+S35 -> 49 | AM34: =AK34-AJ34 -> -175 | AN34: =(-AM34/AJ34) -> 0.78125 | AW34: 45473 | AX34: =AJ34 -> 224 | AY34: =N34+N35 -> 216 | BA34: =AY34-AX34 -> -8 | BB34: =(-BA34/AX34) -> 0.035714286 | BJ34: =B34 -> CCI | BK34: 45473 | BL34: =H34-S34 -> 90 | BO34: =H34-N34 -> -5
B35: CCI | C35: 1Q24 | E35: 25 | F35: 59 | G35: 28 | H35: =SUM(E35:G35) -> 112 | K35: 45 | L35: 54 | M35: ='CCI LLM API'!H103 -> 0.9 | N35: =SUM(K35:L35) -> 99 | Q35: 17 | R35: 10 | S35: =SUM(Q35:R35) -> 27 | U35: 45382 | V35: =H35-N35 -> 13 | W35: =H35-S35 -> 85 | AI35: 45382 | AJ35: =H35 -> 112 | AK35: =S35 -> 27 | AM35: =AK35-AJ35 -> -85 | AN35: =(-AM35/AJ35) -> 0.75892857 | AW35: 45382 | AX35: =AJ35 -> 112 | AY35: =N35 -> 99 | BA35: =AY35-AX35 -> -13 | BB35: =(-BA35/AX35) -> 0.11607143 | BJ35: =B35 -> CCI | BK35: 45382 | BL35: =H35-S35 -> 85 | BO35: =H35-N35 -> 13
G36: Cumulative Total | H36: =SUM(H32:H35) -> 448 | L36: Cumulative Total | N36: =SUM(N32:N35) -> 423 | R36: Cumulative Total | S36: =SUM(S32:S35) -> 103 | U36: Total | V36: =SUM(V32:V35) -> 25 | W36: =SUM(W32:W35) -> 345 | BK36: Quarter Breakeven | BL36: =P33/AVERAGE(BL32:BM35) -> 7.3433043 | BO36: =J33/AVERAGE(BO32:BP35) -> 217.8816
L37: Cumulative Efficiency % | N37: =(($H36-N36)/$H36)*1 -> 0.055803571 | R37: Cumulative Efficiency % | S37: =(($H36-S36)/$H36)*1 -> 0.77008929
L38: Average Accuracy | M38: =AVERAGE(M32:M35) -> 0.85197368
K39: =SUM(K32:K35) -> 180 | L39: =SUM(L32:L35) -> 183
E44: Advanced Excel Manual Benchmark (10-Q) | J44: LLM API (Presentation) | P44: Python Modules (10-Q)
E45: (time measured in seconds) | J45: (time measured in seconds) | P45: (time measured in seconds)
B46: Ticker | C46: Quarter | E46: Extraction | F46: Standardization | G46: Database Format | H46: Total | J46: Construct Extraction | K46: Adjustment | L46: Execute | M46: Accuracy | N46: Total | P46: Construct Extraction | Q46: Adjustment | R46: Execute | S46: Total | U46: Date | V46: LLM API | W46: Python Modules | AJ46: Advanced Excel | AK46: Python Modules | AM46: Delta | AN46: Efficiency % | AX46: Advanced Excel | AY46: LLM API | BA46: Delta | BB46: Efficiency %
B47: AMT | C47: 4Q24 | E47: 55 | F47: 31 | G47: 25 | H47: =SUM(E47:G47) -> 111 | K47: 92 | L47: 20 | M47: ='AMT LLM API'!G23 -> 1 | N47: =SUM(K47:L47) -> 112 | Q47: 21 | R47: 20 | S47: =SUM(Q47:R47) -> 41 | U47: 45657 | V47: =H47-N47 -> -1 | W47: =H47-S47 -> 70 | AI47: 45657 | AJ47: =H47+H48+H49+H50 -> 444 | AK47: =S47+S48+S49+S50 -> 165 | AM47: =AK47-AJ47 -> -279 | AN47: =(-AM47/AJ47) -> 0.62837838 | AW47: 45657 | AX47: =AJ47 -> 444 | AY47: =N47+N48+N49+N50 -> 459.66667 | BA47: =AY47-AX47 -> 15.666667 | BB47: =(-BA47/AX47) -> -0.035285285 | BJ47: =B47 -> AMT | BK47: 45657 | BL47: =H47-S47 -> 70 | BO47: =H47-N47 -> -1
A48: Base | B48: AMT | C48: 3Q24 | E48: 55 | F48: 31 | G48: 25 | H48: =SUM(E48:G48) -> 111 | J48: =4812/250*60 -> 1154.88 | K48: 0 | L48: 32 | M48: ='AMT LLM API'!G43 -> 1 | N48: =L48+AVERAGE(K47,K49:K50) -> 120.66667 | P48: =3929/250*60 -> 942.96 | Q48: 0 | R48: 19 | S48: =R48+AVERAGE(Q47,Q49:Q50) -> 41 | U48: 45565 | V48: =H48-N48 -> -9.6666667 | W48: =H48-S48 -> 70 | AI48: 45565 | AJ48: =H48+H49+H50 -> 333 | AK48: =S48+S49+S50 -> 124 | AM48: =AK48-AJ48 -> -209 | AN48: =(-AM48/AJ48) -> 0.62762763 | AW48: 45565 | AX48: =AJ48 -> 333 | AY48: =N48+N49+N50 -> 347.66667 | BA48: =AY48-AX48 -> 14.666667 | BB48: =(-BA48/AX48) -> -0.044044044 | BJ48: =B48 -> AMT | BK48: 45565 | BL48: =H48-(R48+AVERAGE(Q47,Q49:Q50)) -> 70 | BO48: =H48-(L48+AVERAGE(K47,K49:K50)) -> -9.6666667
B49: AMT | C49: 2Q24 | E49: 55 | F49: 31 | G49: 25 | H49: =SUM(E49:G49) -> 111 | K49: 88 | L49: 31 | M49: ='AMT LLM API'!G63 -> 1 | N49: =SUM(K49:L49) -> 119 | Q49: 22 | R49: 20 | S49: =SUM(Q49:R49) -> 42 | U49: 45473 | V49: =H49-N49 -> -8 | W49: =H49-S49 -> 69 | AI49: 45473 | AJ49: =H49+H50 -> 222 | AK49: =S49+S50 -> 83 | AM49: =AK49-AJ49 -> -139 | AN49: =(-AM49/AJ49) -> 0.62612613 | AW49: 45473 | AX49: =AJ49 -> 222 | AY49: =N49+N50 -> 227 | BA49: =AY49-AX49 -> 5 | BB49: =(-BA49/AX49) -> -0.022522523 | BJ49: =B49 -> AMT | BK49: 45473 | BL49: =H49-S49 -> 69 | BO49: =H49-N49 -> -8
B50: AMT | C50: 1Q24 | E50: 55 | F50: 31 | G50: 25 | H50: =SUM(E50:G50) -> 111 | K50: 86 | L50: 22 | M50: ='AMT LLM API'!G85 -> 0.96875 | N50: =SUM(K50:L50) -> 108 | Q50: 23 | R50: 18 | S50: =SUM(Q50:R50) -> 41 | U50: 45382 | V50: =H50-N50 -> 3 | W50: =H50-S50 -> 70 | AI50: 45382 | AJ50: =H50 -> 111 | AK50: =S50 -> 41 | AM50: =AK50-AJ50 -> -70 | AN50: =(-AM50/AJ50) -> 0.63063063 | AW50: 45382 | AX50: =AJ50 -> 111 | AY50: =N50 -> 108 | BA50: =AY50-AX50 -> -3 | BB50: =(-BA50/AX50) -> 0.027027027 | BJ50: =B50 -> AMT | BK50: 45382 | BL50: =H50-S50 -> 70 | BO50: =H50-N50 -> 3
G51: Cumulative Total | H51: =SUM(H47:H50) -> 444 | L51: Cumulative Total | N51: =SUM(N47:N50) -> 459.66667 | R51: Cumulative Total | S51: =SUM(S47:S50) -> 165 | U51: Total | V51: =SUM(V47:V50) -> -15.666667 | W51: =SUM(W47:W50) -> 279 | BK51: Quarter Breakeven | BL51: =P48/AVERAGE(BL47:BM50) -> 13.51914 | BO51: =J48/AVERAGE(BO47:BP50) -> -294.86298
L52: Cumulative Efficiency % | N52: =(($H51-N51)/$H51)*1 -> -0.035285285 | R52: Cumulative Efficiency % | S52: =(($H51-S51)/$H51)*1 -> 0.62837838
L53: Average Accuracy | M53: =AVERAGE(M47:M50) -> 0.9921875
K54: =SUM(K47:K50) -> 266 | L54: =SUM(L47:L50) -> 105
E61: Advanced Excel Manual Benchmark (10-Q) | J61: LLM API (Presentation) | P61: Python Modules (10-Q)
E62: (time measured in seconds) | J62: (time measured in seconds) | P62: (time measured in seconds)
B63: Ticker | C63: Quarter | E63: Extraction | F63: Standardization | G63: Database Format | H63: Total | J63: Construct Extraction | K63: Adjustment | L63: Execute | M63: Accuracy | N63: Total | P63: Construct Extraction | Q63: Adjustment | R63: Execute | S63: Total | U63: Date | V63: LLM API | W63: Python Modules | AJ63: Advanced Excel | AK63: Python Modules | AM63: Delta | AN63: Efficiency % | AX63: Advanced Excel | AY63: LLM API | BA63: Delta | BB63: Efficiency %
B64: PLD | C64: 4Q24 | E64: 66 | F64: 41 | G64: 33 | H64: =SUM(E64:G64) -> 140 | K64: 83 | L64: 29 | M64: ='PLD LLM API'!H21 -> 0.78571429 | N64: =SUM(K64:L64) -> 112 | Q64: 31 | R64: 15 | S64: =SUM(Q64:R64) -> 46 | U64: 45657 | V64: =H64-N64 -> 28 | W64: =H64-S64 -> 94 | AI64: 45657 | AJ64: =H64+H65+H66+H67 -> 560 | AK64: =S64+S65+S66+S67 -> 396.08 | AM64: =AK64-AJ64 -> -163.92 | AN64: =(-AM64/AJ64) -> 0.29271429 | AW64: 45657 | AX64: =AJ64 -> 560 | AY64: =N64+N65+N66+N67 -> 431 | BA64: =AY64-AX64 -> -129 | BB64: =(-BA64/AX64) -> 0.23035714 | BJ64: =B64 -> PLD | BK64: 45657 | BL64: =H64-S64 -> 94 | BO64: =H64-N64 -> 28
B65: PLD | C65: 3Q24 | E65: 66 | F65: 41 | G65: 33 | H65: =SUM(E65:G65) -> 140 | K65: 73 | L65: 35 | M65: ='PLD LLM API'!H40 -> 0.78571429 | N65: =SUM(K65:L65) -> 108 | Q65: =769/250*60+8 -> 192.56 | R65: 13 | S65: =SUM(Q65:R65) -> 205.56 | U65: 45565 | V65: =H65-N65 -> 32 | W65: =H65-S65 -> -65.56 | AI65: 45565 | AJ65: =H65+H66+H67 -> 420 | AK65: =S65+S66+S67 -> 350.08 | AM65: =AK65-AJ65 -> -69.92 | AN65: =(-AM65/AJ65) -> 0.16647619 | AW65: 45565 | AX65: =AJ65 -> 420 | AY65: =N65+N66+N67 -> 319 | BA65: =AY65-AX65 -> -101 | BB65: =(-BA65/AX65) -> 0.24047619 | BJ65: =B65 -> PLD | BK65: 45565 | BL65: =H65-(R65+AVERAGE(Q64,Q66:Q67)) -> 106.66667 | BO65: =H65-(L65+AVERAGE(K64,K66:K67)) -> 52.333333
A66: Base | B66: PLD | C66: 2Q24 | E66: 66 | F66: 41 | G66: 33 | H66: =SUM(E66:G66) -> 140 | J66: =5132/250*60 -> 1231.68 | K66: 0 | L66: 30 | M66: ='PLD LLM API'!H61 -> 0.85714286 | N66: =L66+AVERAGE(K64:K65,K67) -> 107 | P66: =2732/250*60 -> 655.68 | Q66: 0 | R66: 14 | S66: =R66+AVERAGE(Q64:Q65,Q67) -> 98.52 | U66: 45473 | V66: =H66-N66 -> 33 | W66: =H66-S66 -> 41.48 | AI66: 45473 | AJ66: =H66+H67 -> 280 | AK66: =S66+S67 -> 144.52 | AM66: =AK66-AJ66 -> -135.48 | AN66: =(-AM66/AJ66) -> 0.48385714 | AW66: 45473 | AX66: =AJ66 -> 280 | AY66: =N66+N67 -> 211 | BA66: =AY66-AX66 -> -69 | BB66: =(-BA66/AX66) -> 0.24642857 | BJ66: =B66 -> PLD | BK66: 45473 | BL66: =H66-S66 -> 41.48 | BO66: =H66-N66 -> 33
B67: PLD | C67: 1Q24 | E67: 66 | F67: 41 | G67: 33 | H67: =SUM(E67:G67) -> 140 | K67: 75 | L67: 29 | M67: ='PLD LLM API'!H81 -> 0.78571429 | N67: =SUM(K67:L67) -> 104 | Q67: 30 | R67: 16 | S67: =SUM(Q67:R67) -> 46 | U67: 45382 | V67: =H67-N67 -> 36 | W67: =H67-S67 -> 94 | AI67: 45382 | AJ67: =H67 -> 140 | AK67: =S67 -> 46 | AM67: =AK67-AJ67 -> -94 | AN67: =(-AM67/AJ67) -> 0.67142857 | AW67: 45382 | AX67: =AJ67 -> 140 | AY67: =N67 -> 104 | BA67: =AY67-AX67 -> -36 | BB67: =(-BA67/AX67) -> 0.25714286 | BJ67: =B67 -> PLD | BK67: 45382 | BL67: =H67-S67 -> 94 | BO67: =H67-N67 -> 36
G68: Cumulative Total | H68: =SUM(H64:H67) -> 560 | L68: Cumulative Total | N68: =SUM(N64:N67) -> 431 | R68: Cumulative Total | S68: =SUM(S64:S67) -> 396.08 | U68: Total | V68: =SUM(V64:V67) -> 129 | W68: =SUM(W64:W67) -> 163.92 | BK68: Quarter Breakeven | BL68: =P65/AVERAGE(BL64:BM67) -> 0 | BO68: =J65/AVERAGE(BO64:BP67) -> 0
L69: Cumulative Efficiency % | N69: =(($H68-N68)/$H68)*1 -> 0.23035714 | R69: Cumulative Efficiency % | S69: =(($H68-S68)/$H68)*1 -> 0.29271429
L70: Average Accuracy | M70: =AVERAGE(M64:M67) -> 0.80357143
K71: =SUM(K64:K67) -> 231 | L71: =SUM(L64:L67) -> 123
E77: Advanced Excel Manual Benchmark (10-Q) | J77: LLM API (Presentation) | P77: Python Modules (10-Q)
E78: (time measured in seconds) | J78: (time measured in seconds) | P78: (time measured in seconds)
B79: Ticker | C79: Quarter | E79: Extraction | F79: Standardization | G79: Database Format | H79: Total | J79: Construct Extraction | K79: Adjustment | L79: Execute | M79: Accuracy | N79: Total | P79: Construct Extraction | Q79: Adjustment | R79: Execute | S79: Total | U79: Date | V79: LLM API | W79: Python Modules | AJ79: Advanced Excel | AK79: Python Modules | AM79: Delta | AN79: Efficiency % | AX79: Advanced Excel | AY79: LLM API | BA79: Delta | BB79: Efficiency %
B80: WELL | C80: 4Q24 | E80: 35 | F80: 40 | G80: 33 | H80: =SUM(E80:G80) -> 108 | K80: 61 | L80: 33 | M80: ='WELL LLM API'!M18 -> 1 | N80: =SUM(K80:L80) -> 94 | Q80: 10 | R80: 12 | S80: =SUM(Q80:R80) -> 22 | U80: 45657 | V80: =H80-N80 -> 14 | W80: =H80-S80 -> 86 | AI80: 45657 | AJ80: =H80+H81+H82+H83 -> 432 | AK80: =S80+S81+S82+S83 -> 174.72 | AM80: =AK80-AJ80 -> -257.28 | AN80: =(-AM80/AJ80) -> 0.59555556 | AW80: 45657 | AX80: =AJ80 -> 432 | AY80: =N80+N81+N82+N83 -> 282.33333 | BA80: =AY80-AX80 -> -149.66667 | BB80: =(-BA80/AX80) -> 0.34645062 | BJ80: =B80 -> WELL | BK80: 45657 | BL80: =H80-S80 -> 86 | BO80: =H80-N80 -> 14
A81: Base | B81: WELL | C81: 3Q24 | E81: 35 | F81: 40 | G81: 33 | H81: =SUM(E81:G81) -> 108 | J81: =4897/250*60 -> 1175.28 | K81: 0 | L81: 28 | M81: ='WELL LLM API'!M34 -> 1 | N81: =L81+AVERAGE(K80,K82:K83) -> 68.333333 | P81: =2757/250*60 -> 661.68 | Q81: 0 | R81: 10 | S81: =R81+AVERAGE(Q80,Q82:Q83) -> 44.68 | U81: 45565 | V81: =H81-N81 -> 39.666667 | W81: =H81-S81 -> 63.32 | AI81: 45565 | AJ81: =H81+H82+H83 -> 324 | AK81: =S81+S82+S83 -> 152.72 | AM81: =AK81-AJ81 -> -171.28 | AN81: =(-AM81/AJ81) -> 0.52864198 | AW81: 45565 | AX81: =AJ81 -> 324 | AY81: =N81+N82+N83 -> 188.33333 | BA81: =AY81-AX81 -> -135.66667 | BB81: =(-BA81/AX81) -> 0.41872428 | BJ81: =B81 -> WELL | BK81: 45565 | BL81: =H81-(R81+AVERAGE(Q80,Q82:Q83)) -> 63.32 | BO81: =H81-(L81+AVERAGE(K80,K82:K83)) -> 39.666667
B82: WELL | C82: 2Q24 | E82: 35 | F82: 40 | G82: 33 | H82: =SUM(E82:G82) -> 108 | K82: 30 | L82: 35 | M82: ='WELL LLM API'!M50 -> 1 | N82: =SUM(K82:L82) -> 65 | Q82: =296/250*60+9 -> 80.04 | R82: 7 | S82: =SUM(Q82:R82) -> 87.04 | U82: 45473 | V82: =H82-N82 -> 43 | W82: =H82-S82 -> 20.96 | AI82: 45473 | AJ82: =H82+H83 -> 216 | AK82: =S82+S83 -> 108.04 | AM82: =AK82-AJ82 -> -107.96 | AN82: =(-AM82/AJ82) -> 0.49981481 | AW82: 45473 | AX82: =AJ82 -> 216 | AY82: =N82+N83 -> 120 | BA82: =AY82-AX82 -> -96 | BB82: =(-BA82/AX82) -> 0.44444444 | BJ82: =B82 -> WELL | BK82: 45473 | BL82: =H82-S82 -> 20.96 | BO82: =H82-N82 -> 43
B83: WELL | C83: 1Q24 | E83: 35 | F83: 40 | G83: 33 | H83: =SUM(E83:G83) -> 108 | K83: 30 | L83: 25 | M83: ='WELL LLM API'!M66 -> 1 | N83: =SUM(K83:L83) -> 55 | Q83: 14 | R83: 7 | S83: =SUM(Q83:R83) -> 21 | U83: 45382 | V83: =H83-N83 -> 53 | W83: =H83-S83 -> 87 | AI83: 45382 | AJ83: =H83 -> 108 | AK83: =S83 -> 21 | AM83: =AK83-AJ83 -> -87 | AN83: =(-AM83/AJ83) -> 0.80555556 | AW83: 45382 | AX83: =AJ83 -> 108 | AY83: =N83 -> 55 | BA83: =AY83-AX83 -> -53 | BB83: =(-BA83/AX83) -> 0.49074074 | BJ83: =B83 -> WELL | BK83: 45382 | BL83: =H83-S83 -> 87 | BO83: =H83-N83 -> 53
G84: Cumulative Total | H84: =SUM(H80:H83) -> 432 | L84: Cumulative Total | N84: =SUM(N80:N83) -> 282.33333 | R84: Cumulative Total | S84: =SUM(S80:S83) -> 174.72 | U84: Total | V84: =SUM(V80:V83) -> 149.66667 | W84: =SUM(W80:W83) -> 257.28 | BK84: Quarter Breakeven | BL84: =P81/AVERAGE(BL80:BM83) -> 10.287313 | BO84: =J81/AVERAGE(BO80:BP83) -> 31.410601
L85: Cumulative Efficiency % | N85: =(($H84-N84)/$H84)*1 -> 0.34645062 | R85: Cumulative Efficiency % | S85: =(($H84-S84)/$H84)*1 -> 0.59555556
L86: Average Accuracy | M86: =AVERAGE(M80:M83) -> 1
K87: =SUM(K80:K83) -> 121 | L87: =SUM(L80:L83) -> 121
I89: Average Adjustment Time (15 quarters) | K89: =AVERAGE(K82:K83,K80,K67,K64:K65,K49:K50,K47,K34:K35,K32,K21:K22,K19) -> 61.2 | Q89: =AVERAGE(Q82:Q83,Q80,Q67,Q64:Q65,Q49:Q50,Q47,Q34:Q35,Q32,Q21:Q22,Q19) -> 35.706667
I90: Average Execution Time (20 quarters) | L90: =AVERAGE(L80:L83,L64:L67,L47:L50,L32:L35,L19:L22) -> 30.7 | R90: =AVERAGE(R80:R83,R64:R67,R47:R50,R32:R35,R19:R22) -> 11.85

Sheet WELL

Sheet WELL Manual
B1: 1000
A2: 4Q24 | B2: Year | C2: Unsecured Debt | P2: Ticker | Q2: Quarter | R2: Unsecured Debt | S2: Amount | T2: Unit | U2: Currency | V2: Category
B3: 2025 | C3: 1260 | P3: WELL | Q3: 4Q24 | R3: Near-Term | S3: =SUM(C3:C7) -> 8400.465 | T3: mn | U3: USD | V3: Unsecured Debt
B4: 2026 | C4: 700 | P4: WELL | Q4: 4Q24 | R4: Medium-Term | S4: =SUM(C8:C11) -> 3150 | T4: mn | U4: USD | V4: Unsecured Debt
B5: 2027 | C5: 1881.865 | P5: WELL | Q5: 4Q24 | R5: Long-Term | S5: =SUM(C12:C13) -> 1776 | T5: mn | U5: USD | V5: Unsecured Debt
B6: 2028 | C6: 2473.6 | P6: WELL | Q6: 4Q24 | R6: Total Unsecured | S6: =SUM(S3:S5) -> 13326.465 | T6: mn | U6: USD | V6: Unsecured Debt
B7: 2029 | C7: 2085
B8: 2030 | C8: 750
B9: 2031 | C9: 1350
B10: 2032 | C10: 1050
B11: 2033 | C11: —
B12: 2034 | C12: 626
B13: Thereafter | C13: 1150
B14: Total | C14: =SUM(C3:C13) -> 13326.465
B16: 1000
A17: 3Q24 | B17: Year | C17: Unsecured Debt | P17: Ticker | Q17: Quarter | R17: Unsecured Debt | S17: Amount | T17: Unit | U17: Currency | V17: Category
B18: 2024 | C18: — | P18: WELL | Q18: 4Q24 | R18: Near-Term | S18: =SUM(C18:C23) -> 8473.835 | T18: mn | U18: USD | V18: Unsecured Debt
B19: 2025 | C19: 1260 | P19: WELL | Q19: 4Q24 | R19: Medium-Term | S19: =SUM(C24:C27) -> 3150 | T19: mn | U19: USD | V19: Unsecured Debt
B20: 2026 | C20: 700 | P20: WELL | Q20: 4Q24 | R20: Long-Term | S20: =SUM(C28) -> 1819.9 | T20: mn | U20: USD | V20: Unsecured Debt
B21: 2027 | C21: 1906.945 | P21: WELL | Q21: 4Q24 | R21: Total Unsecured | S21: =SUM(S18:S20) -> 13443.735 | T21: mn | U21: USD | V21: Unsecured Debt
B22: 2028 | C22: 2521.89
B23: 2029 | C23: 2085
B24: 2030 | C24: 750
B25: 2031 | C25: 1350
B26: 2032 | C26: 1050
B27: 2033 | C27: —
B28: Thereafter | C28: 1819.9
B29: Total | C29: =SUM(C18:C28) -> 13443.735
B31: 1000
A32: 2Q24 | B32: Year | C32: Unsecured Debt | P32: Ticker | Q32: Quarter | R32: Unsecured Debt | S32: Amount | T32: Unit | U32: Currency | V32: Category
B33: 2024 | C33: — | P33: WELL | Q33: 4Q24 | R33: Near-Term | S33: =SUM(C33:C38) -> 7392.129 | T33: mn | U33: USD | V33: Unsecured Debt
B34: 2025 | C34: 1260 | P34: WELL | Q34: 4Q24 | R34: Medium-Term | S34: =SUM(C39:C42) -> 3150 | T34: mn | U34: USD | V34: Unsecured Debt
B35: 2026 | C35: 700 | P35: WELL | Q35: 4Q24 | R35: Long-Term | S35: =SUM(C43) -> 1782 | T35: mn | U35: USD | V35: Unsecured Debt
B36: 2027 | C36: 1901.929 | P36: WELL | Q36: 4Q24 | R36: Total Unsecured | S36: =SUM(S33:S35) -> 12324.129 | T36: mn | U36: USD | V36: Unsecured Debt
B37: 2028 | C37: 2480.2
B38: 2029 | C38: 1050
B39: 2030 | C39: 750
B40: 2031 | C40: 1350
B41: 2032 | C41: 1050
B42: 2033 | C42: —
B43: Thereafter | C43: 1782
B44: Total | C44: =SUM(C33:C43) -> 12324.129
B46: 1000
A47: 1Q24 | B47: Year | C47: Unsecured Debt | P47: Ticker | Q47: Quarter | R47: Unsecured Debt | S47: Amount | T47: Unit | U47: Currency | V47: Category
B48: 2024 | C48: — | P48: WELL | Q48: 4Q24 | R48: Near-Term | S48: =SUM(C48:C53) -> 7396.239 | T48: mn | U48: USD | V48: Unsecured Debt
B49: 2025 | C49: 1260 | P49: WELL | Q49: 4Q24 | R49: Medium-Term | S49: =SUM(C54:C57) -> 3150 | T49: mn | U49: USD | V49: Unsecured Debt
B50: 2026 | C50: 700 | P50: WELL | Q50: 4Q24 | R50: Long-Term | S50: =SUM(C58) -> 1781.85 | T50: mn | U50: USD | V50: Unsecured Debt
B51: 2027 | C51: 1906.204 | P51: WELL | Q51: 4Q24 | R51: Total Unsecured | S51: =SUM(S48:S50) -> 12328.089 | T51: mn | U51: USD | V51: Unsecured Debt
B52: 2028 | C52: 2480.035
B53: 2029 | C53: 1050
B54: 2030 | C54: 750
B55: 2031 | C55: 1350
B56: 2032 | C56: 1050
B57: 2033 | C57: —
B58: Thereafter | C58: 1781.85
B59: Total | C59: =SUM(C48:C58) -> 12328.089

Sheet WELL LLM API
A2: OpenAI | B2: Debt Partition
I3: Correct | L3: LLM
A5: 4Q24 | I5: Year | J5: Unsecured Debt | L5: Year | M5: Unsecured Debt | O5: =I5=L5 -> TRUE | P5: =J5=M5 -> TRUE | R5: Ticker | S5: Quarter | T5: Unsecured Debt | U5: Amount | V5: Unit | W5: Currency | X5: Category
I6: 2025 | J6: 1260 | L6: 2025 | M6: 1260 | O6: =I6=L6 -> TRUE | P6: =J6=M6 -> TRUE | R6: WELL | S6: 4Q24 | T6: Near-Term | U6: =SUM(J6:J10) -> 8401 | V6: mn | W6: USD | X6: Unsecured Debt
I7: 2026 | J7: 700 | L7: 2026 | M7: 700 | O7: =I7=L7 -> TRUE | P7: =J7=M7 -> TRUE | R7: WELL | S7: 4Q24 | T7: Medium-Term | U7: =SUM(J11:J13) -> 3150 | V7: mn | W7: USD | X7: Unsecured Debt
I8: 2027 | J8: 1882 | L8: 2027 | M8: 1882 | O8: =I8=L8 -> TRUE | P8: =J8=M8 -> TRUE | R8: WELL | S8: 4Q24 | T8: Long-Term | U8: =SUM(J14:J15) -> 1776 | V8: mn | W8: USD | X8: Unsecured Debt
I9: 2028 | J9: 2474 | L9: 2028 | M9: 2474 | O9: =I9=L9 -> TRUE | P9: =J9=M9 -> TRUE | R9: WELL | S9: 4Q24 | T9: Total Unsecured | U9: =SUM(U6:U8) -> 13327 | V9: mn | W9: USD | X9: Unsecured Debt
I10: 2029 | J10: 2085 | L10: 2029 | M10: 2085 | O10: =I10=L10 -> TRUE | P10: =J10=M10 -> TRUE
I11: 2030 | J11: 750 | L11: 2030 | M11: 750 | O11: =I11=L11 -> TRUE | P11: =J11=M11 -> TRUE
I12: 2031 | J12: 1350 | L12: 2031 | M12: 1350 | O12: =I12=L12 -> TRUE | P12: =J12=M12 -> TRUE
I13: 2032 | J13: 1050 | L13: 2032 | M13: 1050 | O13: =I13=L13 -> TRUE | P13: =J13=M13 -> TRUE
I14: 2034 | J14: 626 | L14: 2034 | M14: 626 | O14: =I14=L14 -> TRUE | P14: =J14=M14 -> TRUE
I15: Thereafter | J15: 1150 | L15: Thereafter | M15: 1150 | O15: =I15=L15 -> TRUE | P15: =J15=M15 -> TRUE
I16: Total | J16: =SUM(J6:J15) -> 13327 | L16: Total | M16: =SUM(M6:M15) -> 13327 | O16: =I16=L16 -> TRUE | P16: =J16=M16 -> TRUE
L18: Accuracy | M18: 1
I20: Correct | L20: LLM
A22: 3Q24 | I22: Year | J22: Unsecured Debt | L22: Year | M22: Unsecured Debt | O22: =I22=L22 -> TRUE | P22: =J22=M22 -> TRUE | R22: Ticker | S22: Quarter | T22: Unsecured Debt | U22: Amount | V22: Unit | W22: Currency | X22: Category
I23: 2025 | J23: 1260 | L23: 2025 | M23: 1260 | O23: =I23=L23 -> TRUE | P23: =J23=M23 -> TRUE | R23: WELL | S23: 3Q24 | T23: Near-Term | U23: =SUM(J23:J27) -> 8474 | V23: mn | W23: USD | X23: Unsecured Debt
I24: 2026 | J24: 700 | L24: 2026 | M24: 700 | O24: =I24=L24 -> TRUE | P24: =J24=M24 -> TRUE | R24: WELL | S24: 3Q24 | T24: Medium-Term | U24: =SUM(J28:J30) -> 3150 | V24: mn | W24: USD | X24: Unsecured Debt
I25: 2027 | J25: 1907 | L25: 2027 | M25: 1907 | O25: =I25=L25 -> TRUE | P25: =J25=M25 -> TRUE | R25: WELL | S25: 3Q24 | T25: Long-Term | U25: =J31 -> 1820 | V25: mn | W25: USD | X25: Unsecured Debt
I26: 2028 | J26: 2522 | L26: 2028 | M26: 2522 | O26: =I26=L26 -> TRUE | P26: =J26=M26 -> TRUE | R26: WELL | S26: 3Q24 | T26: Total Unsecured | U26: =SUM(U23:U25) -> 13444 | V26: mn | W26: USD | X26: Unsecured Debt
I27: 2029 | J27: 2085 | L27: 2029 | M27: 2085 | O27: =I27=L27 -> TRUE | P27: =J27=M27 -> TRUE
I28: 2030 | J28: 750 | L28: 2030 | M28: 750 | O28: =I28=L28 -> TRUE | P28: =J28=M28 -> TRUE
I29: 2031 | J29: 1350 | L29: 2031 | M29: 1350 | O29: =I29=L29 -> TRUE | P29: =J29=M29 -> TRUE
I30: 2032 | J30: 1050 | L30: 2032 | M30: 1050 | O30: =I30=L30 -> TRUE | P30: =J30=M30 -> TRUE
I31: Thereafter | J31: 1820 | L31: Thereafter | M31: 1820 | O31: =I31=L31 -> TRUE | P31: =J31=M31 -> TRUE
I32: Total | J32: =SUM(J23:J31) -> 13444 | L32: Total | M32: =SUM(M23:M31) -> 13444 | O32: =I32=L32 -> TRUE | P32: =J32=M32 -> TRUE
L34: Accuracy | M34: 1
I36: Correct | L36: LLM
A38: 2Q24 | I38: Year | J38: Unsecured Debt | L38: Year | M38: Unsecured Debt | O38: =I38=L38 -> TRUE | P38: =J38=M38 -> TRUE | R38: Ticker | S38: Quarter | T38: Unsecured Debt | U38: Amount | V38: Unit | W38: Currency | X38: Category
I39: 2025 | J39: 1260 | L39: 2025 | M39: 1260 | O39: =I39=L39 -> TRUE | P39: =J39=M39 -> TRUE | R39: WELL | S39: 2Q24 | T39: Near-Term | U39: =SUM(J39:J43) -> 7392 | V39: mn | W39: USD | X39: Unsecured Debt
I40: 2026 | J40: 700 | L40: 2026 | M40: 700 | O40: =I40=L40 -> TRUE | P40: =J40=M40 -> TRUE | R40: WELL | S40: 2Q24 | T40: Medium-Term | U40: =SUM(J44:J46) -> 3150 | V40: mn | W40: USD | X40: Unsecured Debt
I41: 2027 | J41: 1902 | L41: 2027 | M41: 1902 | O41: =I41=L41 -> TRUE | P41: =J41=M41 -> TRUE | R41: WELL | S41: 2Q24 | T41: Long-Term | U41: =J47 -> 1782 | V41: mn | W41: USD | X41: Unsecured Debt
I42: 2028 | J42: 2480 | L42: 2028 | M42: 2480 | O42: =I42=L42 -> TRUE | P42: =J42=M42 -> TRUE | R42: WELL | S42: 2Q24 | T42: Total Unsecured | U42: =SUM(U39:U41) -> 12324 | V42: mn | W42: USD | X42: Unsecured Debt
I43: 2029 | J43: 1050 | L43: 2029 | M43: 1050 | O43: =I43=L43 -> TRUE | P43: =J43=M43 -> TRUE
I44: 2030 | J44: 750 | L44: 2030 | M44: 750 | O44: =I44=L44 -> TRUE | P44: =J44=M44 -> TRUE
I45: 2031 | J45: 1350 | L45: 2031 | M45: 1350 | O45: =I45=L45 -> TRUE | P45: =J45=M45 -> TRUE
I46: 2032 | J46: 1050 | L46: 2032 | M46: 1050 | O46: =I46=L46 -> TRUE | P46: =J46=M46 -> TRUE
I47: Thereafter | J47: 1782 | L47: Thereafter | M47: 1782 | O47: =I47=L47 -> TRUE | P47: =J47=M47 -> TRUE
I48: Total | J48: =SUM(J39:J47) -> 12324 | L48: Total | M48: =SUM(M39:M47) -> 12324 | O48: =I48=L48 -> TRUE | P48: =J48=M48 -> TRUE
L50: Accuracy | M50: 1
I52: Correct | L52: LLM
A54: 1Q24 | I54: Year | J54: Unsecured Debt | L54: Year | M54: Unsecured Debt | O54: =I54=L54 -> TRUE | P54: =J54=M54 -> TRUE | R54: Ticker | S54: Quarter | T54: Unsecured Debt | U54: Amount | V54: Unit | W54: Currency | X54: Category
I55: 2025 | J55: 1260 | L55: 2025 | M55: 1260 | O55: =I55=L55 -> TRUE | P55: =J55=M55 -> TRUE | R55: WELL | S55: 1Q24 | T55: Near-Term | U55: =SUM(J55:J59) -> 7396 | V55: mn | W55: USD | X55: Unsecured Debt
I56: 2026 | J56: 700 | L56: 2026 | M56: 700 | O56: =I56=L56 -> TRUE | P56: =J56=M56 -> TRUE | R56: WELL | S56: 1Q24 | T56: Medium-Term | U56: =SUM(J60:J62) -> 3150 | V56: mn | W56: USD | X56: Unsecured Debt
I57: 2027 | J57: 1906 | L57: 2027 | M57: 1906 | O57: =I57=L57 -> TRUE | P57: =J57=M57 -> TRUE | R57: WELL | S57: 1Q24 | T57: Long-Term | U57: =J63 -> 1782 | V57: mn | W57: USD | X57: Unsecured Debt
I58: 2028 | J58: 2480 | L58: 2028 | M58: 2480 | O58: =I58=L58 -> TRUE | P58: =J58=M58 -> TRUE | R58: WELL | S58: 1Q24 | T58: Total Unsecured | U58: =SUM(U55:U57) -> 12328 | V58: mn | W58: USD | X58: Unsecured Debt
I59: 2029 | J59: 1050 | L59: 2029 | M59: 1050 | O59: =I59=L59 -> TRUE | P59: =J59=M59 -> TRUE
I60: 2030 | J60: 750 | L60: 2030 | M60: 750 | O60: =I60=L60 -> TRUE | P60: =J60=M60 -> TRUE
I61: 2031 | J61: 1350 | L61: 2031 | M61: 1350 | O61: =I61=L61 -> TRUE | P61: =J61=M61 -> TRUE
I62: 2032 | J62: 1050 | L62: 2032 | M62: 1050 | O62: =I62=L62 -> TRUE | P62: =J62=M62 -> TRUE
I63: Thereafter | J63: 1782 | L63: Thereafter | M63: 1782 | O63: =I63=L63 -> TRUE | P63: =J63=M63 -> TRUE
I64: Total | J64: =SUM(J55:J63) -> 12328 | L64: Total | M64: =SUM(M55:M63) -> 12328 | O64: =I64=L64 -> TRUE | P64: =J64=M64 -> TRUE
L66: Accuracy | M66: 1

Sheet WELL Script
A2: 4Q24
R5: Year | S5: Unsecured Debt | U5: Ticker | V5: Quarter | W5: Unsecured Debt | X5: Amount | Y5: Unit | Z5: Currency | AA5: Category
R6: 2025 | S6: 1260 | U6: WELL | V6: 4Q24 | W6: Near-Term | X6: =SUM(S6:S10) -> 8401 | Y6: mn | Z6: USD | AA6: Unsecured Debt
R7: 2026 | S7: 700 | U7: WELL | V7: 4Q24 | W7: Long-Term | X7: =S11 -> 4926 | Y7: mn | Z7: USD | AA7: Unsecured Debt
R8: 2027 | S8: 1882 | U8: WELL | V8: 4Q24 | W8: Total Unsecured | X8: =SUM(X6:X7) -> 13327 | Y8: mn | Z8: USD | AA8: Unsecured Debt
R9: 2028 | S9: 2474
R10: 2029 | S10: 2085
R11: Thereafter | S11: 4926
R12: Total | S12: =SUM(S6:S11) -> 13327
A19: 3Q24 | B19: (Thereafter includes maturities in 2029)
R21: Year | S21: Unsecured Debt | U21: Ticker | V21: Quarter | W21: Unsecured Debt | X21: Amount | Y21: Unit | Z21: Currency | AA21: Category
R22: 2024 | S22: — | U22: WELL | V22: 3Q24 | W22: Near-Term | X22: =SUM(S22:S26) -> 6388.835 | Y22: mn | Z22: USD | AA22: Unsecured Debt
R23: 2025 | S23: 1260 | U23: WELL | V23: 3Q24 | W23: Long-Term | X23: =S27 -> 7054.9 | Y23: mn | Z23: USD | AA23: Unsecured Debt
R24: 2026 | S24: 700 | U24: WELL | V24: 3Q24 | W24: Total Unsecured | X24: =SUM(X22:X23) -> 13443.735 | Y24: mn | Z24: USD | AA24: Unsecured Debt
R25: 2027 | S25: 1906.945
R26: 2028 | S26: 2521.89
R27: Thereafter | S27: 7054.9
R28: Total | S28: =SUM(S22:S27) -> 13443.735
A36: 2Q24 | B36: (Thereafter includes maturities in 2029)
R37: Year | S37: Unsecured Debt | U37: Ticker | V37: Quarter | W37: Unsecured Debt | X37: Amount | Y37: Unit | Z37: Currency | AA37: Category
R38: 2024 | S38: — | U38: WELL | V38: 2Q24 | W38: Near-Term | X38: =SUM(S38:S42) -> 6342 | Y38: mn | Z38: USD | AA38: Unsecured Debt
R39: 2025 | S39: 1260 | U39: WELL | V39: 2Q24 | W39: Long-Term | X39: =S43 -> 5982 | Y39: mn | Z39: USD | AA39: Unsecured Debt
R40: 2026 | S40: 700 | U40: WELL | V40: 2Q24 | W40: Total Unsecured | X40: =SUM(X38:X39) -> 12324 | Y40: mn | Z40: USD | AA40: Unsecured Debt
R41: 2027 | S41: 1902
R42: 2028 | S42: 2480
R43: Thereafter | S43: 5982
R44: Total | S44: =SUM(S38:S43) -> 12324
A52: 1Q24 | B52: (Thereafter includes maturities in 2029)
R54: Year | S54: Unsecured Debt | U54: Ticker | V54: Quarter | W54: Unsecured Debt | X54: Amount | Y54: Unit | Z54: Currency | AA54: Category
R55: 2024 | S55: — | U55: WELL | V55: 1Q24 | W55: Near-Term | X55: =SUM(S55:S59) -> 6346 | Y55: mn | Z55: USD | AA55: Unsecured Debt
R56: 2025 | S56: 1260 | U56: WELL | V56: 1Q24 | W56: Long-Term | X56: =S60 -> 5982 | Y56: mn | Z56: USD | AA56: Unsecured Debt
R57: 2026 | S57: 700 | U57: WELL | V57: 1Q24 | W57: Total Unsecured | X57: =SUM(X55:X56) -> 12328 | Y57: mn | Z57: USD | AA57: Unsecured Debt
R58: 2027 | S58: 1906
R59: 2028 | S59: 2480
R60: Thereafter | S60: 5982
R61: Total | S61: =SUM(S55:S60) -> 12328

Sheet PLD

Sheet PLD Manual
B1: 1000
A2: 4Q24 | B2: Year | C2: Total | D2: Secured Debt | E2: Unsecured Debt | G2: Senior | H2: Facilities & Commercial Paper | I2: Other | K2: Ticker | L2: Quarter | M2: Unsecured Debt | N2: Amount | O2: Unit | P2: Currency | Q2: Category
B3: 2025 | C3: 205.559 | D3: 173.389 | E3: =C3-D3 -> 32.17 | G3: 31.856 | H3: – | I3: 0.314 | K3: PLD | L3: 4Q24 | M3: Near-Term | N3: =SUM(E3:E7) -> 10281.179 | O3: mn | P3: USD | Q3: Unsecured Debt | S3: (2024 - 2029 maturities)
B4: 2026 | C4: 2111.021 | D4: 45.542 | E4: =C4-D4 -> 2065.479 | G4: 1284.618 | H4: – | I4: 780.861 | K4: PLD | L4: 4Q24 | M4: Medium-Term | N4: =SUM(E8:E11) -> 9094.555 | O4: mn | P4: USD | Q4: Unsecured Debt | S4: (2030 - 2033 maturities)
B5: 2027 | C5: 2319.219 | D5: 4.156 | E5: =C5-D5 -> 2315.063 | G5: 1898.055 | H5: 162.632 | I5: 254.376 | K5: PLD | L5: 4Q24 | M5: Long-Term | N5: =SUM(E12:E14) -> 11761.953 | O5: mn | P5: USD | Q5: Unsecured Debt | S5: Thereafter
B6: 2028 | C6: 2678.378 | D6: 3.041 | E6: =C6-D6 -> 2675.337 | G6: 2518.708 | H6: 62.334 | I6: 94.295 | K6: PLD | L6: 4Q24 | M6: Total Unsecured | N6: =SUM(N3:N5) -> 31137.687 | O6: mn | P6: USD | Q6: Unsecured Debt
B7: 2029 | C7: 3196.321 | D7: 3.191 | E7: =C7-D7 -> 3193.13 | G7: 3193.13 | H7: – | I7: –
B8: 2030 | C8: 2801.382 | D8: 3.345 | E8: =C8-D8 -> 2798.037 | G8: 2766.181 | H8: – | I8: 31.856
B9: 2031 | C9: 2138.161 | D9: 17.607 | E9: =C9-D9 -> 2120.554 | G9: 1993.129 | H9: – | I9: 127.425
B10: 2032 | C10: 1771.313 | D10: 18.715 | E10: =C10-D10 -> 1752.598 | G10: 1561.46 | H10: – | I10: 191.138
B11: 2033 | C11: 2466.602 | D11: 43.236 | E11: =C11-D11 -> 2423.366 | G11: 2256.856 | H11: – | I11: 166.51
B12: 2034 | C12: 3270.229 | D12: 0 | E12: =C12-D12 -> 3270.229 | G12: 2900.57 | H12: – | I12: 369.659
B13: 2035 | C13: 1771.343 | D13: 0 | E13: =C13-D13 -> 1771.343 | G13: 1771.343 | H13: – | I13: –
B14: Thereafter | C14: 6720.381 | D14: 0 | E14: =C14-D14 -> 6720.381 | G14: 6720.381 | H14: – | I14: –
B15: Total | C15: =SUM(C3:C14) -> 31449.909 | D15: =SUM(D3:D14) -> 312.222 | E15: =SUM(E3:E14) -> 31137.687 | G15: =SUM(G3:G14) -> 28896.287 | H15: =SUM(H3:H14) -> 224.966 | I15: =SUM(I3:I14) -> 2016.434
G16: =SUM(G15:I15) -> 31137.687 | H16: Check
B18: 1000
A19: 3Q24 | B19: Year | C19: Total | D19: Secured Debt | E19: Unsecured Debt | G19: Senior | H19: Facilities & Commercial Paper | I19: Other | K19: Ticker | L19: Quarter | M19: Unsecured Debt | N19: Amount | O19: Unit | P19: Currency | Q19: Category
B20: 2024 | C20: 1.962 | D20: 1.962 | E20: =C20-D20 -> 0 | G20: – | H20: – | I20: – | K20: PLD | L20: 3Q24 | M20: Near-Term | N20: =SUM(E20:E25) -> 11160.291 | O20: mn | P20: USD | Q20: Unsecured Debt | S20: (2024 - 2029 maturities)
B21: 2025 | C21: 215.388 | D21: 179.938 | E21: =C21-D21 -> 35.45 | G21: 35.027 | H21: – | I21: 0.423 | K21: PLD | L21: 3Q24 | M21: Medium-Term | N21: =SUM(E26:E29) -> 9440.346 | O21: mn | P21: USD | Q21: Unsecured Debt | S21: (2030 - 2033 maturities)
B22: 2026 | C22: 2169.899 | D22: 3.98 | E22: =C22-D22 -> 2165.919 | G22: 1324.968 | H22: – | I22: 840.951 | K22: PLD | L22: 3Q24 | M22: Long-Term | N22: =SUM(E30:E31) -> 12004.618 | O22: mn | P22: USD | Q22: Unsecured Debt | S22: Thereafter
B23: 2027 | C23: 2239.442 | D23: 4.156 | E23: =C23-D23 -> 2235.286 | G23: 1962.895 | H23: 660.737 | I23: 272.391 | K23: PLD | L23: 3Q24 | M23: Total Unsecured | N23: =SUM(N20:N22) -> 32605.255 | O23: mn | P23: USD | Q23: Unsecured Debt
B24: 2028 | C24: 3361.812 | D24: 3.041 | E24: =C24-D24 -> 3358.771 | G24: 2594.354 | H24: – | I24: 103.68
B25: 2029 | C25: 3368.056 | D25: 3.191 | E25: =C25-D25 -> 3364.865 | G25: 3364.865 | H25: – | I25: –
B26: 2030 | C26: 2859.568 | D26: 3.345 | E26: =C26-D26 -> 2856.223 | G26: 2821.196 | H26: – | I26: 35.027
B27: 2031 | C27: 2237.168 | D27: 17.607 | E27: =C27-D27 -> 2219.561 | G27: 2079.453 | H27: – | I27: 140.108
B28: 2032 | C28: 1878.018 | D28: 18.715 | E28: =C28-D28 -> 1859.303 | G28: 1649.142 | H28: – | I28: 210.161
B29: 2033 | C29: 2548.495 | D29: 43.236 | E29: =C29-D29 -> 2505.259 | G29: 2322.789 | H29: – | I29: 182.47
B30: 2034 | C30: 3180.615 | D30: 0 | E30: =C30-D30 -> 3180.615 | G30: 3005.48 | H30: – | I30: 175.135
B31: Thereafter | C31: 8824.003 | D31: 0 | E31: =C31-D31 -> 8824.003 | G31: 8824.003 | H31: 0 | I31: –
B32: Total | C32: =SUM(C20:C31) -> 32884.426 | D32: =SUM(D20:D31) -> 279.171 | E32: =SUM(E20:E31) -> 32605.255 | G32: =SUM(G20:G31) -> 29984.172 | H32: =SUM(H20:H31) -> 660.737 | I32: =SUM(I20:I31) -> 1960.346
G33: =SUM(G32:I32) -> 32605.255 | H33: Check
B35: 1000
A36: 2Q24 | B36: Year | C36: Total | D36: Secured Debt | E36: Unsecured Debt | G36: Senior | H36: Facilities & Commercial Paper | I36: Other | K36: Ticker | L36: Quarter | M36: Unsecured Debt | N36: Amount | O36: Unit | P36: Currency | Q36: Category
B37: 2024 | C37: 4.113 | D37: 4.113 | E37: =C37-D37 -> 0 | G37: - | H37: - | I37: - | K37: PLD | L37: 2Q24 | M37: Near-Term | N37: =SUM(E37:E42) -> 10460.604 | O37: mn | P37: USD | Q37: Unsecured Debt | S37: (2024 - 2029 maturities)
B38: 2025 | C38: 216.507 | D38: 177.412 | E38: =C38-D38 -> 39.095 | G38: 31.13 | H38: 7.463 | I38: 0.502 | K38: PLD | L38: 2Q24 | M38: Medium-Term | N38: =SUM(E43:E46) -> 9185.281 | O38: mn | P38: USD | Q38: Unsecured Debt | S38: (2030 - 2033 maturities)
B39: 2026 | C39: 2074.996 | D39: 3.98 | E39: =C39-D39 -> 2071.016 | G39: 1300.418 | H39: - | I39: 770.598 | K39: PLD | L39: 2Q24 | M39: Long-Term | N39: =SUM(E47:E48) -> 10554.004 | O39: mn | P39: USD | Q39: Unsecured Debt | S39: Thereafter
B40: 2027 | C40: 2384.778 | D40: 4.156 | E40: =C40-D40 -> 2380.622 | G40: 1916.291 | H40: 201 | I40: 263.331 | K40: PLD | L40: 2Q24 | M40: Total Unsecured | N40: =SUM(N37:N39) -> 30199.889 | O40: mn | P40: USD | Q40: Unsecured Debt
B41: 2028 | C41: 2905.044 | D41: 3.041 | E41: =C41-D41 -> 2902.003 | G41: 2528.926 | H41: 280.932 | I41: 92.145
B42: 2029 | C42: 3071.059 | D42: 3.191 | E42: =C42-D42 -> 3067.868 | G42: 3067.868 | H42: - | I42: -
B43: 2030 | C43: 2818.105 | D43: 3.345 | E43: =C43-D43 -> 2814.76 | G43: 2783.63 | H43: - | I43: 31.13
B44: 2031 | C44: 2173.032 | D44: 17.607 | E44: =C44-D44 -> 2155.425 | G44: 2030.905 | H44: - | I44: 124.52
B45: 2032 | C45: 1789.443 | D45: 18.715 | E45: =C45-D45 -> 1770.728 | G45: 1583.948 | H45: - | I45: 186.78
B46: 2033 | C46: 2487.604 | D46: 43.236 | E46: =C46-D46 -> 2444.368 | G46: 2281.292 | H46: - | I46: 163.076
B47: 2034 | C47: 3097.3 | D47: 0 | E47: =C47-D47 -> 3097.3 | G47: 2941.65 | H47: - | I47: 155.65
B48: Thereafter | C48: 7456.704 | D48: 0 | E48: =C48-D48 -> 7456.704 | G48: 7456.704 | H48: - | I48: -
B49: Total | C49: =SUM(C37:C48) -> 30478.685 | D49: =SUM(D37:D48) -> 278.796 | E49: =SUM(E37:E48) -> 30199.889 | G49: =SUM(G37:G48) -> 27922.762 | H49: =SUM(H37:H48) -> 489.395 | I49: =SUM(I37:I48) -> 1787.732
G50: =SUM(G49:I49) -> 30199.889 | H50: Check
B57: 1000
A58: 1Q24 | B58: Year | C58: Total | D58: Secured Debt | E58: Unsecured Debt | G58: Senior | H58: Facilities & Commercial Paper | I58: Other | K58: Ticker | L58: Quarter | M58: Unsecured Debt | N58: Amount | O58: Unit | P58: Currency | Q58: Category
B59: 2024 | C59: 5.352 | D59: 5.352 | E59: =C59-D59 -> 0 | G59: - | H59: - | I59: - | K59: PLD | L59: 1Q24 | M59: Near-Term | N59: =SUM(E59:E64) -> 11111.091 | O59: mn | P59: USD | Q59: Unsecured Debt | S59: (2024 - 2029 maturities)
B60: 2025 | C60: 212.566 | D60: 178.913 | E60: =C60-D60 -> 33.653 | G60: 33.071 | H60: - | I60: 0.582 | K60: PLD | L60: 1Q24 | M60: Medium-Term | N60: =SUM(E65:E68) -> 9270.969 | O60: mn | P60: USD | Q60: Unsecured Debt | S60: (2030 - 2033 maturities)
B61: 2026 | C61: 2114.382 | D61: 3.98 | E61: =C61-D61 -> 2110.402 | G61: 1305.718 | H61: - | I61: 804.684 | K61: PLD | L61: 1Q24 | M61: Long-Term | N61: =SUM(E69:E70) -> 9478.451 | O61: mn | P61: USD | Q61: Unsecured Debt | S61: Thereafter
B62: 2027 | C62: 2532.539 | D62: 4.156 | E62: =C62-D62 -> 2528.383 | G62: 1930.348 | H62: 329.744 | I62: 268.291 | K62: PLD | L62: 1Q24 | M62: Total Unsecured | N62: =SUM(N59:N61) -> 29860.511 | O62: mn | P62: USD | Q62: Unsecured Debt
B63: 2028 | C63: 3356.351 | D63: 3.041 | E63: =C63-D63 -> 3353.31 | G63: 2553.897 | H63: 701.522 | I63: 97.891
B64: 2029 | C64: 3088.534 | D64: 3.191 | E64: =C64-D64 -> 3085.343 | G64: 3085.343 | H64: - | I64: -
B65: 2030 | C65: 2830.444 | D65: 3.345 | E65: =C65-D65 -> 2827.099 | G65: 2794.028 | H65: - | I65: 33.071
B66: 2031 | C66: 2196.322 | D66: 17.607 | E66: =C66-D66 -> 2178.715 | G66: 2046.43 | H66: - | I66: 132.285
B67: 2032 | C67: 1821.787 | D67: 18.715 | E67: =C67-D67 -> 1803.072 | G67: 1604.644 | H67: - | I67: 198.428
B68: 2033 | C68: 2505.319 | D68: 43.236 | E68: =C68-D68 -> 2462.083 | G68: 2289.211 | H68: - | I68: 172.872
B69: 2034 | C69: 2393.896 | D69: 0 | E69: =C69-D69 -> 2393.896 | G69: 2360.825 | H69: - | I69: 33.071
B70: Thereafter | C70: 7084.555 | D70: 0 | E70: =C70-D70 -> 7084.555 | G70: 7084.555 | H70: - | I70: -
B71: Total | C71: =SUM(C59:C70) -> 30142.047 | D71: =SUM(D59:D70) -> 281.536 | E71: =SUM(E59:E70) -> 29860.511 | G71: =SUM(G59:G70) -> 27088.07 | H71: =SUM(H59:H70) -> 1031.266 | I71: =SUM(I59:I70) -> 1741.175
G72: =SUM(G71:I71) -> 29860.511 | H72: Check

Sheet PLD LLM API
A2: OpenAI | B2: Debt Partition
G4: Correct | J4: LLM
A5: 4Q24
G6: Year | H6: Unsecured Debt | J6: Year | K6: Unsecured Debt | M6: =G6=J6 -> TRUE | N6: =H6=K6 -> TRUE
G7: 2025 | H7: 32 | J7: 2025 | K7: 32 | M7: =G7=J7 -> TRUE | N7: =H7=K7 -> TRUE
G8: 2026 | H8: 2065 | J8: 2026 | K8: 2065 | M8: =G8=J8 -> TRUE | N8: =H8=K8 -> TRUE
G9: 2027 | H9: 2315 | J9: 2027 | K9: 2315 | M9: =G9=J9 -> TRUE | N9: =H9=K9 -> TRUE
G10: 2028 | H10: 2675 | J10: 2028 | K10: 2675 | M10: =G10=J10 -> TRUE | N10: =H10=K10 -> TRUE
G11: 2029 | H11: 3193 | J11: 2029 | K11: 3193 | M11: =G11=J11 -> TRUE | N11: =H11=K11 -> TRUE
G12: 2030 | H12: 2798 | J12: 2030 | K12: 2798 | M12: =G12=J12 -> TRUE | N12: =H12=K12 -> TRUE
G13: 2031 | H13: 2121 | J13: 2031 | K13: 2792 | M13: =G13=J13 -> TRUE | N13: =H13=K13 -> FALSE | S13: Ticker | T13: Quarter | U13: Unsecured Debt | V13: Amount | W13: Unit | X13: Currency | Y13: Category
G14: 2032 | H14: 1753 | J14: 2032 | K14: 1460 | M14: =G14=J14 -> TRUE | N14: =H14=K14 -> FALSE | S14: PLD | T14: 4Q24 | U14: Near-Term | V14: =SUM(H7:H11) -> 10280 | W14: mn | X14: USD | Y14: Unsecured Debt
G15: 2033 | H15: 2423 | J15: 2033 | K15: 2222 | M15: =G15=J15 -> TRUE | N15: =H15=K15 -> FALSE | S15: PLD | T15: 4Q24 | U15: Medium-Term | V15: =SUM(H12:H15) -> 9095 | W15: mn | X15: USD | Y15: Unsecured Debt
G16: 2034 | H16: 3270 | J16: 2034 | K16: 2900 | M16: =G16=J16 -> TRUE | N16: =H16=K16 -> FALSE | S16: PLD | T16: 4Q24 | U16: Long-Term | V16: =SUM(H16:H18) -> 11761 | W16: mn | X16: USD | Y16: Unsecured Debt
G17: 2035 | H17: 1771 | J17: 2035 | K17: 1771 | M17: =G17=J17 -> TRUE | N17: =H17=K17 -> TRUE | S17: PLD | T17: 4Q24 | U17: Total Unsecured | V17: =SUM(V14:V16) -> 31136 | W17: mn | X17: USD | Y17: Unsecured Debt
G18: Thereafter | H18: 6720 | J18: Thereafter | K18: 7270 | M18: =G18=J18 -> TRUE | N18: =H18=K18 -> FALSE
G19: Total | H19: =SUM(H7:H18) -> 31136 | J19: Total | K19: 33493 | M19: =G19=J19 -> TRUE | N19: =H19=K19 -> FALSE
G21: Accuracy | H21: =22/28 -> 0.78571429
G23: Correct | J23: LLM
A24: 3Q24
G25: Year | H25: Unsecured Debt | J25: Year | K25: Unsecured Debt | M25: =G25=J25 -> TRUE | N25: =H25=K25 -> TRUE
G26: 2024 | H26: 0 | J26: 2024 | K26: 0 | M26: =G26=J26 -> TRUE | N26: =H26=K26 -> TRUE
G27: 2025 | H27: 35 | J27: 2025 | K27: 35 | M27: =G27=J27 -> TRUE | N27: =H27=K27 -> TRUE
G28: 2026 | H28: 2166 | J28: 2026 | K28: 2166 | M28: =G28=J28 -> TRUE | N28: =H28=K28 -> TRUE
G29: 2027 | H29: 2235 | J29: 2027 | K29: 2235 | M29: =G29=J29 -> TRUE | N29: =H29=K29 -> TRUE
G30: 2028 | H30: 3359 | J30: 2028 | K30: 3359 | M30: =G30=J30 -> TRUE | N30: =H30=K30 -> TRUE | S30: Ticker | T30: Quarter | U30: Unsecured Debt | V30: Amount | W30: Unit | X30: Currency | Y30: Category
G31: 2029 | H31: 3365 | J31: 2029 | K31: 3865 | M31: =G31=J31 -> TRUE | N31: =H31=K31 -> FALSE | S31: PLD | T31: 3Q24 | U31: Near-Term | V31: =SUM(H26:H31) -> 11160 | W31: mn | X31: USD | Y31: Unsecured Debt
G32: 2030 | H32: 2856 | J32: 2030 | K32: 2818 | M32: =G32=J32 -> TRUE | N32: =H32=K32 -> FALSE | S32: PLD | T32: 3Q24 | U32: Medium-Term | V32: =SUM(H32:H35) -> 9440 | W32: mn | X32: USD | Y32: Unsecured Debt
G33: 2031 | H33: 2220 | J33: 2031 | K33: 2220 | M33: =G33=J33 -> TRUE | N33: =H33=K33 -> TRUE | S33: PLD | T33: 3Q24 | U33: Long-Term | V33: =SUM(H36:H37) -> 12005 | W33: mn | X33: USD | Y33: Unsecured Debt
G34: 2032 | H34: 1859 | J34: 2032 | K34: 2862 | M34: =G34=J34 -> TRUE | N34: =H34=K34 -> FALSE | S34: PLD | T34: 3Q24 | U34: Total Unsecured | V34: =SUM(V31:V33) -> 32605 | W34: mn | X34: USD | Y34: Unsecured Debt
G35: 2033 | H35: 2505 | J35: 2033 | K35: 2505 | M35: =G35=J35 -> TRUE | N35: =H35=K35 -> TRUE
G36: 2034 | H36: 3181 | J36: 2034 | K36: 3004 | M36: =G36=J36 -> TRUE | N36: =H36=K36 -> FALSE
G37: Thereafter | H37: 8824 | J37: Thereafter | K37: 0 | M37: =G37=J37 -> TRUE | N37: =H37=K37 -> FALSE
G38: Total | H38: =SUM(H26:H37) -> 32605 | J38: Total | K38: 25069 | M38: =G38=J38 -> TRUE | N38: =H38=K38 -> FALSE
G40: Accuracy | H40: =22/28 -> 0.78571429
G43: Correct | J43: LLM
A44: 2Q24
G46: Year | H46: Unsecured Debt | J46: Year | K46: Unsecured Debt | M46: =G46=J46 -> TRUE | N46: =H46=K46 -> TRUE
G47: 2024 | H47: 0 | J47: 2024 | K47: 0 | M47: =G47=J47 -> TRUE | N47: =H47=K47 -> TRUE
G48: 2025 | H48: 39 | J48: 2025 | K48: 39 | M48: =G48=J48 -> TRUE | N48: =H48=K48 -> TRUE
G49: 2026 | H49: 2071 | J49: 2026 | K49: 2071 | M49: =G49=J49 -> TRUE | N49: =H49=K49 -> TRUE
G50: 2027 | H50: 2381 | J50: 2027 | K50: 2381 | M50: =G50=J50 -> TRUE | N50: =H50=K50 -> TRUE
G51: 2028 | H51: 2902 | J51: 2028 | K51: 2092 | M51: =G51=J51 -> TRUE | N51: =H51=K51 -> FALSE
G52: 2029 | H52: 3068 | J52: 2029 | K52: 3068 | M52: =G52=J52 -> TRUE | N52: =H52=K52 -> TRUE | S52: Ticker | T52: Quarter | U52: Unsecured Debt | V52: Amount | W52: Unit | X52: Currency | Y52: Category
G53: 2030 | H53: 2815 | J53: 2030 | K53: 2815 | M53: =G53=J53 -> TRUE | N53: =H53=K53 -> TRUE | S53: PLD | T53: 2Q24 | U53: Near-Term | V53: =SUM(H47:H52) -> 10461 | W53: mn | X53: USD | Y53: Unsecured Debt
G54: 2031 | H54: 2155 | J54: 2031 | K54: 2156 | M54: =G54=J54 -> TRUE | N54: =H54=K54 -> FALSE | S54: PLD | T54: 2Q24 | U54: Medium-Term | V54: =SUM(H53:H56) -> 9185 | W54: mn | X54: USD | Y54: Unsecured Debt
G55: 2032 | H55: 1771 | J55: 2032 | K55: 1771 | M55: =G55=J55 -> TRUE | N55: =H55=K55 -> TRUE | S55: PLD | T55: 2Q24 | U55: Long-Term | V55: =SUM(H57:H58) -> 10554 | W55: mn | X55: USD | Y55: Unsecured Debt
G56: 2033 | H56: 2444 | J56: 2033 | K56: 2444 | M56: =G56=J56 -> TRUE | N56: =H56=K56 -> TRUE | S56: PLD | T56: 2Q24 | U56: Total Unsecured | V56: =SUM(V53:V55) -> 30200 | W56: mn | X56: USD | Y56: Unsecured Debt
G57: 2034 | H57: 3097 | J57: 2034 | K57: 2942 | M57: =G57=J57 -> TRUE | N57: =H57=K57 -> FALSE
G58: Thereafter | H58: 7457 | J58: Thereafter | K58: 7457 | M58: =G58=J58 -> TRUE | N58: =H58=K58 -> TRUE
G59: Total | H59: =SUM(H48:H58) -> 30200 | J59: Total | K59: 29236 | M59: =G59=J59 -> TRUE | N59: =H59=K59 -> FALSE
G61: Accuracy | H61: =24/28 -> 0.85714286
G64: Correct | J64: LLM
A65: 1Q24
G66: Year | H66: Unsecured Debt | J66: Year | K66: Unsecured Debt | M66: =G66=J66 -> TRUE | N66: =H66=K66 -> TRUE
G67: 2024 | H67: 0 | J67: 2024 | K67: 0 | M67: =G67=J67 -> TRUE | N67: =H67=K67 -> TRUE
G68: 2025 | H68: 34 | J68: 2025 | K68: 34 | M68: =G68=J68 -> TRUE | N68: =H68=K68 -> TRUE
G69: 2026 | H69: 2110 | J69: 2026 | K69: 1931 | M69: =G69=J69 -> TRUE | N69: =H69=K69 -> FALSE
G70: 2027 | H70: 2528 | J70: 2027 | K70: 2528 | M70: =G70=J70 -> TRUE | N70: =H70=K70 -> TRUE
G71: 2028 | H71: 3353 | J71: 2028 | K71: 3350 | M71: =G71=J71 -> TRUE | N71: =H71=K71 -> FALSE
G72: 2029 | H72: 3085 | J72: 2029 | K72: 3085 | M72: =G72=J72 -> TRUE | N72: =H72=K72 -> TRUE | S72: Ticker | T72: Quarter | U72: Unsecured Debt | V72: Amount | W72: Unit | X72: Currency | Y72: Category
G73: 2030 | H73: 2827 | J73: 2030 | K73: 2831 | M73: =G73=J73 -> TRUE | N73: =H73=K73 -> FALSE | S73: PLD | T73: 1Q24 | U73: Near-Term | V73: =SUM(H67:H72) -> 11110 | W73: mn | X73: USD | Y73: Unsecured Debt
G74: 2031 | H74: 2179 | J74: 2031 | K74: 2029 | M74: =G74=J74 -> TRUE | N74: =H74=K74 -> FALSE | S74: PLD | T74: 1Q24 | U74: Medium-Term | V74: =SUM(H73:H76) -> 9271 | W74: mn | X74: USD | Y74: Unsecured Debt
G75: 2032 | H75: 1803 | J75: 2032 | K75: 1803 | M75: =G75=J75 -> TRUE | N75: =H75=K75 -> TRUE | S75: PLD | T75: 1Q24 | U75: Long-Term | V75: =SUM(H77:H78) -> 9479 | W75: mn | X75: USD | Y75: Unsecured Debt
G76: 2033 | H76: 2462 | J76: 2033 | K76: 2462 | M76: =G76=J76 -> TRUE | N76: =H76=K76 -> TRUE | S76: PLD | T76: 1Q24 | U76: Total Unsecured | V76: =SUM(V73:V75) -> 29860 | W76: mn | X76: USD | Y76: Unsecured Debt
G77: 2034 | H77: 2394 | J77: 2034 | K77: 2318 | M77: =G77=J77 -> TRUE | N77: =H77=K77 -> FALSE
G78: Thereafter | H78: 7085 | J78: Thereafter | K78: 7085 | M78: =G78=J78 -> TRUE | N78: =H78=K78 -> TRUE
G79: Total | H79: =SUM(H67:H78) -> 29860 | J79: Total | K79: =SUM(K67:K78) -> 29456 | M79: =G79=J79 -> TRUE | N79: =H79=K79 -> FALSE
G81: Accuracy | H81: =22/28 -> 0.78571429

Sheet PLD Script
B2: 4Q24
Z6: 1000
AA7: Secured Debt | AB7: Total Debt | AC7: Unsecured Debt | AE7: Ticker | AF7: Quarter | AG7: Unsecured Debt | AH7: Amount | AI7: Unit | AJ7: Currency | AK7: Category
Z8: 2024 | AA8: 173.389 | AB8: 514.223 | AC8: =AB8-AA8 -> 340.834 | AE8: PLD | AF8: 4Q24 | AG8: Near-Term | AH8: =SUM(AC8:AC12) -> 10281.179 | AI8: mn | AJ8: USD | AK8: Unsecured Debt
Z9: 2025 | AA9: 45.542 | AB9: 2173.492 | AC9: =AB9-AA9 -> 2127.95 | AE9: PLD | AF9: 4Q24 | AG9: Long-Term | AH9: =SUM(AC13) -> 20856.508 | AI9: mn | AJ9: USD | AK9: Unsecured Debt
Z10: 2026 | AA10: 4.156 | AB10: 2010.418 | AC10: =AB10-AA10 -> 2006.262 | AE10: PLD | AF10: 4Q24 | AG10: Total Unsecured | AH10: =SUM(AH8:AH9) -> 31137.687 | AI10: mn | AJ10: USD | AK10: Unsecured Debt
Z11: 2027 | AA11: 3.041 | AB11: 2616.044 | AC11: =AB11-AA11 -> 2613.003
Z12: 2028 | AA12: 3.191 | AB12: 3196.321 | AC12: =AB12-AA12 -> 3193.13
Z13: Thereafter | AA13: 82.903 | AB13: 20939.411 | AC13: =AB13-AA13 -> 20856.508
Z14: Total | AA14: =SUM(AA8:AA13) -> 312.222 | AB14: =SUM(AB8:AB13) -> 31449.909 | AC14: =SUM(AC8:AC13) -> 31137.687
B20: 3Q24 | C20: (Thereafter includes maturities in 2029)
Z25: 1000
AA26: Secured Debt | AB26: Total Debt | AC26: Unsecured Debt | AE26: Ticker | AF26: Quarter | AG26: Unsecured Debt | AH26: Amount | AI26: Unit | AJ26: Currency | AK26: Category
Z27: 2024 | AA27: 1.962 | AB27: 1.962 | AC27: =AB27-AA27 -> 0 | AE27: PLD | AF27: 3Q24 | AG27: Near-Term | AH27: =SUM(AC27:AC31) -> 7795.426 | AI27: mn | AJ27: USD | AK27: Unsecured Debt
Z28: 2025 | AA28: 179.938 | AB28: 540.089 | AC28: =AB28-AA28 -> 360.151 | AE28: PLD | AF28: 3Q24 | AG28: Long-Term | AH28: =SUM(AC32) -> 24809.829 | AI28: mn | AJ28: USD | AK28: Unsecured Debt
Z29: 2026 | AA29: 3.98 | AB29: 2067.15 | AC29: =AB29-AA29 -> 2063.17 | AE29: PLD | AF29: 3Q24 | AG29: Total Unsecured | AH29: =SUM(AH27:AH28) -> 32605.255 | AI29: mn | AJ29: USD | AK29: Unsecured Debt
Z30: 2027 | AA30: 4.156 | AB30: 2678.227 | AC30: =AB30-AA30 -> 2674.071
Z31: 2028 | AA31: 3.041 | AB31: 2701.075 | AC31: =AB31-AA31 -> 2698.034
Z32: Thereafter | AA32: 86.094 | AB32: 24895.923 | AC32: =AB32-AA32 -> 24809.829
Z33: Total | AA33: =SUM(AA27:AA32) -> 279.171 | AB33: =SUM(AB27:AB32) -> 32884.426 | AC33: =SUM(AC27:AC32) -> 32605.255
B37: 2Q24 | C37: (Thereafter includes maturities in 2029)
Z38: 1000
AA39: Secured Debt | AB39: Total Debt | AC39: Unsecured Debt | AE39: Ticker | AF39: Quarter | AG39: Unsecured Debt | AH39: Amount | AI39: Unit | AJ39: Currency | AK39: Category
Z40: 2024 | AA40: 4.113 | AB40: 105.14 | AC40: =AB40-AA40 -> 101.027 | AE40: PLD | AF40: 2Q24 | AG40: Near-Term | AH40: =SUM(AC40:AC44) -> 7392.736 | AI40: mn | AJ40: USD | AK40: Unsecured Debt
Z41: 2025 | AA41: 177.412 | AB41: 435.423 | AC41: =AB41-AA41 -> 258.011 | AE41: PLD | AF41: 2Q24 | AG41: Long-Term | AH41: =SUM(AC45) -> 22807.153 | AI41: mn | AJ41: USD | AK41: Unsecured Debt
Z42: 2026 | AA42: 3.98 | AB42: 2174.969 | AC42: =AB42-AA42 -> 2170.989 | AE42: PLD | AF42: 2Q24 | AG42: Total Unsecured | AH42: =SUM(AH40:AH41) -> 30199.889 | AI42: mn | AJ42: USD | AK42: Unsecured Debt
Z43: 2027 | AA43: 4.156 | AB43: 2245.794 | AC43: =AB43-AA43 -> 2241.638
Z44: 2028 | AA44: 3.041 | AB44: 2624.112 | AC44: =AB44-AA44 -> 2621.071
Z45: Thereafter | AA45: 86.094 | AB45: 22893.247 | AC45: =AB45-AA45 -> 22807.153
Z46: Total | AA46: =SUM(AA40:AA45) -> 278.796 | AB46: =SUM(AB40:AB45) -> 30478.685 | AC46: =SUM(AC40:AC45) -> 30199.889
B55: 1Q24 | C55: (Thereafter includes maturities in 2029)
Z58: 1000
AA59: Secured Debt | AB59: Total Debt | AC59: Unsecured Debt | AE59: Ticker | AF59: Quarter | AG59: Unsecured Debt | AH59: Amount | AI59: Unit | AJ59: Currency | AK59: Category
Z60: 2024 | AA60: 5.352 | AB60: 106.832 | AC60: =AB60-AA60 -> 101.48 | AE60: PLD | AF60: 1Q24 | AG60: Near-Term | AH60: =SUM(AC60:AC64) -> 8025.748 | AI60: mn | AJ60: USD | AK60: Unsecured Debt
Z61: 2025 | AA61: 178.913 | AB61: 433.62 | AC61: =AB61-AA61 -> 254.707 | AE61: PLD | AF61: 1Q24 | AG61: Long-Term | AH61: =SUM(AC65) -> 21834.763 | AI61: mn | AJ61: USD | AK61: Unsecured Debt
Z62: 2026 | AA62: 3.98 | AB62: 2342.646 | AC62: =AB62-AA62 -> 2338.666 | AE62: PLD | AF62: 1Q24 | AG62: Total Unsecured | AH62: =SUM(AH60:AH61) -> 29860.511 | AI62: mn | AJ62: USD | AK62: Unsecured Debt
Z63: 2027 | AA63: 4.156 | AB63: 2683.263 | AC63: =AB63-AA63 -> 2679.107
Z64: 2028 | AA64: 3.041 | AB64: 2654.829 | AC64: =AB64-AA64 -> 2651.788
Z65: Thereafter | AA65: 86.094 | AB65: 21920.857 | AC65: =AB65-AA65 -> 21834.763
Z66: Total | AA66: =SUM(AA60:AA65) -> 281.536 | AB66: =SUM(AB60:AB65) -> 30142.047 | AC66: =SUM(AC60:AC65) -> 29860.511

Sheet CCI

Sheet CCI Manual
B1: Debt Maturities from 10Q (supplement/presentation did not show unsecured vs secured composition)
A3: 4Q24 | B3: Year | C3: Unsecured debt | E3: Ticker | F3: Quarter | G3: Unsecured Debt | H3: Amount | I3: Unit | J3: Currency | K3: Category
B4: 2027 | C4: 1117 | E4: CCI | F4: 4Q24 | G4: Near-Term | H4: =SUM(C6:C19,C4) -> 11567 | I4: mn | J4: USD | K4: Unsecured Debt | M4: (2024 - 2029 maturities)
B5: Thereafter | C5: 1341 | E5: CCI | F5: 4Q24 | G5: Medium-Term | H5: =SUM(C20:C24) -> 4350 | I5: mn | J5: USD | K5: Unsecured Debt | M5: (2030 - 2033 maturities)
B6: 2025 | C6: 500 | E6: CCI | F6: 4Q24 | G6: Long-Term | H6: =SUM(C5,C25:C32) -> 6541 | I6: mn | J6: USD | K6: Unsecured Debt | M6: Thereafter
B7: 2026 | C7: 900 | E7: CCI | F7: 4Q24 | G7: Total Unsecured | H7: =SUM(H4:H6) -> 22458 | I7: mn | J7: USD | K7: Unsecured Debt
B8: 2026 | C8: 750
B9: 2026 | C9: 1000
B10: 2027 | C10: 750
B11: 2027 | C11: 500
B12: 2027 | C12: 1000
B13: 2028 | C13: 1000 | Q13: Year | R13: Unsecured Debt
B14: 2028 | C14: 1000 | Q14: 2027 | R14: =SUMIF($B$4:$B$33,$Q14,$C$4:$C$33) -> 3367
B15: 2028 | C15: 600 | Q15: 2025 | R15: =SUMIF($B$4:$B$33,$Q15,$C$4:$C$33) -> 500
B16: 2029 | C16: 600 | Q16: 2026 | R16: =SUMIF($B$4:$B$33,$Q16,$C$4:$C$33) -> 2650
B17: 2029 | C17: 750 | Q17: 2028 | R17: =SUMIF($B$4:$B$33,$Q17,$C$4:$C$33) -> 2600
B18: 2029 | C18: 550 | Q18: 2029 | R18: =SUMIF($B$4:$B$33,$Q18,$C$4:$C$33) -> 2450
B19: 2029 | C19: 550 | Q19: 2030 | R19: =SUMIF($B$4:$B$33,$Q19,$C$4:$C$33) -> 750
B20: 2030 | C20: 750 | Q20: 2031 | R20: =SUMIF($B$4:$B$33,$Q20,$C$4:$C$33) -> 2850
B21: 2031 | C21: 1100 | Q21: 2033 | R21: =SUMIF($B$4:$B$33,$Q21,$C$4:$C$33) -> 750
B22: 2031 | C22: 1000 | Q22: 2034 | R22: =SUMIF($B$4:$B$33,$Q22,$C$4:$C$33) -> 1450
B23: 2031 | C23: 750 | Q23: 2041 | R23: =SUMIF($B$4:$B$33,$Q23,$C$4:$C$33) -> 1250
B24: 2033 | C24: 750 | Q24: 2047 | R24: =SUMIF($B$4:$B$33,$Q24,$C$4:$C$33) -> 350
B25: 2034 | C25: 750 | Q25: 2049 | R25: =SUMIF($B$4:$B$33,$Q25,$C$4:$C$33) -> 750
... B27: 2041 | C27: 1250 | Q27: 2051 | R27: =SUMIF($B$4:$B$33,$Q27,$C$4:$C$33) -> 900
B28: 2047 | C28: 350 | Q28: Thereafter | R28: 1341
B29: 2049 | C29: 400 | Q29: Total Unsecured Debt | R29: =SUM(R14:R28) -> 22458
B30: 2049 | C30: 350 | Q30: Total Secured Debt | R30: 1782
B31: 2050 | C31: 500 | Q31: Total Debt | R31: =SUM(R29:R30) -> 24240
B32: 2051 | C32: 900
A34: 3Q24 | B34: Year | C34: Unsecured Debt | E34: Ticker | F34: Quarter | G34: Unsecured Debt | H34: Amount | I34: Unit | J34: Currency | K34: Category
B35: 2027 | C35: — | E35: CCI | F35: 3Q24 | G35: Near-Term | H35: =SUM(C38:C51,C36) -> 11582 | I35: mn | J35: USD | K35: Unsecured Debt | M35: (2024 - 2029 maturities)
B36: 2027 | C36: 1132 | E36: CCI | F36: 3Q24 | G36: Medium-Term | H36: =SUM(C52:C56) -> 4350 | I36: mn | J36: USD | K36: Unsecured Debt | M36: (2030 - 2033 maturities)
B37: Thereafter | C37: 1312 | E37: CCI | F37: 3Q24 | G37: Long-Term | H37: =SUM(C37,C57:C64) -> 6512 | I37: mn | J37: USD | K37: Unsecured Debt | M37: Thereafter
B38: 2025 | C38: 500 | E38: CCI | F38: 3Q24 | G38: Total Unsecured | H38: =SUM(H35:H37) -> 22444 | I38: mn | J38: USD | K38: Unsecured Debt
B39: 2026 | C39: 900
B40: 2026 | C40: 750
B41: 2026 | C41: 1000
B42: 2027 | C42: 750
B43: 2027 | C43: 500
B44: 2027 | C44: 1000
B45: 2028 | C45: 1000
B46: 2028 | C46: 1000 | Q46: Year | R46: Unsecured Debt
B47: 2028 | C47: 600 | Q47: 2027 | R47: =SUMIF($B$35:$B$64,$Q47,$C$35:$C$64) -> 3382
B48: 2029 | C48: 600 | Q48: 2025 | R48: =SUMIF($B$35:$B$64,$Q48,$C$35:$C$64) -> 500
B49: 2029 | C49: 750 | Q49: 2026 | R49: =SUMIF($B$35:$B$64,$Q49,$C$35:$C$64) -> 2650
B50: 2029 | C50: 550 | Q50: 2028 | R50: =SUMIF($B$35:$B$64,$Q50,$C$35:$C$64) -> 2600
B51: 2029 | C51: 550 | Q51: 2029 | R51: =SUMIF($B$35:$B$64,$Q51,$C$35:$C$64) -> 2450
B52: 2030 | C52: 750 | Q52: 2030 | R52: =SUMIF($B$35:$B$64,$Q52,$C$35:$C$64) -> 750
B53: 2031 | C53: 1100 | Q53: 2031 | R53: =SUMIF($B$35:$B$64,$Q53,$C$35:$C$64) -> 2850
B54: 2031 | C54: 1000 | Q54: 2033 | R54: =SUMIF($B$35:$B$64,$Q54,$C$35:$C$64) -> 750
B55: 2031 | C55: 750 | Q55: 2034 | R55: =SUMIF($B$35:$B$64,$Q55,$C$35:$C$64) -> 1450
B56: 2033 | C56: 750 | Q56: 2041 | R56: =SUMIF($B$35:$B$64,$Q56,$C$35:$C$64) -> 1250
B57: 2034 | C57: 750 | Q57: 2047 | R57: =SUMIF($B$35:$B$64,$Q57,$C$35:$C$64) -> 350
B58: 2034 | C58: 700 | Q58: 2049 | R58: =SUMIF($B$35:$B$64,$Q58,$C$35:$C$64) -> 750
... B60: 2047 | C60: 350 | Q60: 2051 | R60: =SUMIF($B$35:$B$64,$Q60,$C$35:$C$64) -> 900
B61: 2049 | C61: 400 | Q61: Thereafter | R61: 1312
B62: 2049 | C62: 350 | Q62: Total Unsecured Debt | R62: =SUM(R47:R61) -> 22444
B63: 2050 | C63: 500 | Q63: Total Secured Debt | R63: 1785
B64: 2051 | C64: 900 | Q64: Total Debt | R64: =SUM(R62:R63) -> 24229
A67: 2Q24 | B67: Year | C67: Unsecured Debt | E67: Ticker | F67: Quarter | G67: Unsecured Debt | H67: Amount | I67: Unit | J67: Currency | K67: Category
B68: 2027 | C68: — | E68: CCI | F68: 2Q24 | G68: Near-Term | H68: =SUM(C71:C84,C69) -> 11805 | I68: mn | J68: USD | K68: Unsecured Debt | M68: (2024 - 2029 maturities)
B69: 2027 | C69: 1155 | E69: CCI | F69: 2Q24 | G69: Medium-Term | H69: =SUM(C85:C89) -> 4350 | I69: mn | J69: USD | K69: Unsecured Debt | M69: (2030 - 2033 maturities)
B70: Thereafter | C70: 1438 | E70: CCI | F70: 2Q24 | G70: Long-Term | H70: =SUM(C70,C90:C96) -> 5938 | I70: mn | J70: USD | K70: Unsecured Debt | M70: Thereafter
B71: 2024 | C71: 750 | E71: CCI | F71: 2Q24 | G71: Total Unsecured | H71: =SUM(H68:H70) -> 22093 | I71: mn | J71: USD | K71: Unsecured Debt
B72: 2025 | C72: 500
B73: 2026 | C73: 900
B74: 2026 | C74: 750
B75: 2026 | C75: 1000
B76: 2027 | C76: 750
B77: 2027 | C77: 500
B78: 2027 | C78: 1000 | Q78: Year | R78: Unsecured Debt
B79: 2028 | C79: 1000 | Q79: 2027 | R79: =SUMIF($B$68:$B$96,$Q79,$C$68:$C$96) -> 3405
B80: 2028 | C80: 1000 | Q80: 2024 | R80: =SUMIF($B$68:$B$96,$Q80,$C$68:$C$96) -> 750
B81: 2028 | C81: 600 | Q81: 2025 | R81: =SUMIF($B$68:$B$96,$Q81,$C$68:$C$96) -> 500
B82: 2029 | C82: 600 | Q82: 2026 | R82: =SUMIF($B$68:$B$96,$Q82,$C$68:$C$96) -> 2650
B83: 2029 | C83: 750 | Q83: 2028 | R83: =SUMIF($B$68:$B$96,$Q83,$C$68:$C$96) -> 2600
B84: 2029 | C84: 550 | Q84: 2029 | R84: =SUMIF($B$68:$B$96,$Q84,$C$68:$C$96) -> 1900
B85: 2030 | C85: 750 | Q85: 2030 | R85: =SUMIF($B$68:$B$96,$Q85,$C$68:$C$96) -> 750
B86: 2031 | C86: 1100 | Q86: 2031 | R86: =SUMIF($B$68:$B$96,$Q86,$C$68:$C$96) -> 2850
B87: 2031 | C87: 1000 | Q87: 2033 | R87: =SUMIF($B$68:$B$96,$Q87,$C$68:$C$96) -> 750
B88: 2031 | C88: 750 | Q88: 2034 | R88: =SUMIF($B$68:$B$96,$Q88,$C$68:$C$96) -> 750
B89: 2033 | C89: 750 | Q89: 2041 | R89: =SUMIF($B$68:$B$96,$Q89,$C$68:$C$96) -> 1250
B90: 2034 | C90: 750 | Q90: 2047 | R90: =SUMIF($B$68:$B$96,$Q90,$C$68:$C$96) -> 350
... B93: 2049 | C93: 400 | Q93: 2051 | R93: =SUMIF($B$68:$B$96,$Q93,$C$68:$C$96) -> 900
B94: 2049 | C94: 350 | Q94: Thereafter | R94: 1438
B95: 2050 | C95: 500 | Q95: Total Unsecured Debt | R95: =SUM(R79:R94) -> 22093
B96: 2051 | C96: 900 | Q96: Total Secured Debt | R96: 1781
Q97: Total Debt | R97: =SUM(R95:R96) -> 23874
A99: 1Q24 | B99: Year | C99: Unsecured Debt | E99: Ticker | F99: Quarter | G99: Unsecured Debt | H99: Amount | I99: Unit | J99: Currency | K99: Category
B100: 2027 | C100: — | E100: CCI | F100: 1Q24 | G100: Near-Term | H100: =SUM(C103:C116,C101) -> 11812 | I100: mn | J100: USD | K100: Unsecured Debt | M100: (2024 - 2029 maturities)
B101: 2027 | C101: 1162 | E101: CCI | F101: 1Q24 | G101: Medium-Term | H101: =SUM(C117:C121) -> 4350 | I101: mn | J101: USD | K101: Unsecured Debt | M101: (2030 - 2033 maturities)
B102: Thereafter | C102: 1138 | E102: CCI | F102: 1Q24 | G102: Long-Term | H102: =SUM(C102,C122:C128) -> 5638 | I102: mn | J102: USD | K102: Unsecured Debt | M102: Thereafter
B103: 2024 | C103: 750 | E103: CCI | F103: 1Q24 | G103: Total Unsecured | H103: =SUM(H100:H102) -> 21800 | I103: mn | J103: USD | K103: Unsecured Debt
B104: 2025 | C104: 500
B105: 2026 | C105: 900
B106: 2026 | C106: 750
B107: 2026 | C107: 1000
B108: 2027 | C108: 750
B109: 2027 | C109: 500
...

Sheet CCI LLM API
A2: OpenAI | B2: Debt Partition
G4: Correct | J4: LLM
A5: 4Q24
G6: Year | H6: Unsecured Debt | J6: Year | K6: Unsecured Debt | M6: =G6=J6 -> TRUE | N6: =H6=K6 -> TRUE
G7: 2025 | H7: 500 | J7: 2025 | K7: 500 | M7: =G7=J7 -> TRUE | N7: =H7=K7 -> TRUE
G8: 2026 | H8: 2650 | J8: 2026 | K8: 2650 | M8: =G8=J8 -> TRUE | N8: =H8=K8 -> TRUE
G9: 2027 | H9: 3367 | J9: 2027 | K9: 3591 | M9: =G9=J9 -> TRUE | N9: =H9=K9 -> FALSE
G10: 2028 | H10: 2600 | J10: 2028 | K10: 2600 | M10: =G10=J10 -> TRUE | N10: =H10=K10 -> TRUE
G11: 2029 | H11: 2450 | J11: 2029 | K11: 1900 | M11: =G11=J11 -> TRUE | N11: =H11=K11 -> FALSE
G12: 2030 | H12: 750 | J12: 2030 | K12: 1300 | M12: =G12=J12 -> TRUE | N12: =H12=K12 -> FALSE
G13: 2031 | H13: 2850 | J13: 2031 | K13: 2850 | M13: =G13=J13 -> TRUE | N13: =H13=K13 -> TRUE
G14: 2033 | H14: 750 | J14: 2033 | K14: 750 | M14: =G14=J14 -> TRUE | N14: =H14=K14 -> TRUE
G15: 2034 | H15: 1450 | J15: 2034 | K15: 1450 | M15: =G15=J15 -> TRUE | N15: =H15=K15 -> TRUE
G16: 2041 | H16: 1250 | J16: 2041 | K16: 1250 | M16: =G16=J16 -> TRUE | N16: =H16=K16 -> TRUE
G17: 2047 | H17: 350 | J17: 2047 | K17: 350 | M17: =G17=J17 -> TRUE | N17: =H17=K17 -> TRUE
G18: 2049 | H18: 750 | J18: 2049 | K18: 750 | M18: =G18=J18 -> TRUE | N18: =H18=K18 -> TRUE
... G20: 2051 | H20: 900 | J20: 2051 | K20: 900 | M20: =G20=J20 -> TRUE | N20: =H20=K20 -> TRUE
G21: Thereafter | H21: 1341 | J21: Thereafter | K21: 1341 | M21: =G21=J21 -> TRUE | N21: =H21=K21 -> TRUE
G22: Total Unsecured Debt | H22: =SUM(H7:H21) -> 22458 | J22: Total Unsecured Debt | K22: 22458 | M22: =G22=J22 -> TRUE | N22: =H22=K22 -> TRUE
G23: Total Secured Debt | H23: 1782 | J23: Total Secured Debt | K23: 1782 | M23: =G23=J23 -> TRUE | N23: =H23=K23 -> TRUE
G24: Total Debt | H24: =SUM(H22:H23) -> 24240 | J24: Total Debt | K24: 24240 | M24: =G24=J24 -> TRUE | N24: =H24=K24 -> TRUE
G26: Accuracy | H26: =35/38 -> 0.92105263
G28: Correct | J28: LLM
A29: 3Q24
G30: Year | H30: Unsecured Debt | J30: Year | K30: Unsecured Debt | M30: =G30=J30 -> TRUE | N30: =H30=K30 -> TRUE
G31: 2025 | H31: 500 | J31: 2025 | K31: 500 | M31: =G31=J31 -> TRUE | N31: =H31=K31 -> TRUE
G32: 2026 | H32: 2650 | J32: 2026 | K32: 2650 | M32: =G32=J32 -> TRUE | N32: =H32=K32 -> TRUE
G33: 2027 | H33: 3382 | J33: 2027 | K33: 1500 | M33: =G33=J33 -> TRUE | N33: =H33=K33 -> FALSE
G34: 2028 | H34: 2600 | J34: 2028 | K34: 2350 | M34: =G34=J34 -> TRUE | N34: =H34=K34 -> FALSE
G35: 2029 | H35: 2450 | J35: 2029 | K35: 1100 | M35: =G35=J35 -> TRUE | N35: =H35=K35 -> FALSE
G36: 2030 | H36: 750 | J36: 2030 | K36: 750 | M36: =G36=J36 -> TRUE | N36: =H36=K36 -> TRUE
G37: 2031 | H37: 2850 | J37: 2031 | K37: 2850 | M37: =G37=J37 -> TRUE | N37: =H37=K37 -> TRUE
G38: 2033 | H38: 750 | J38: 2032 | M38: =G38=J38 -> FALSE | N38: =H38=K38 -> FALSE
G39: 2034 | H39: 1450 | J39: 2034 | K39: 750 | M39: =G39=J39 -> TRUE | N39: =H39=K39 -> FALSE
G40: 2041 | H40: 1250 | J40: 2040 | M40: =G40=J40 -> FALSE | N40: =H40=K40 -> FALSE
G41: 2047 | H41: 350 | J41: 2047 | K41: 350 | M41: =G41=J41 -> TRUE | N41: =H41=K41 -> TRUE
G42: 2049 | H42: 750 | J42: 2049 | K42: 1250 | M42: =G42=J42 -> TRUE | N42: =H42=K42 -> FALSE
G43: 2050 | H43: 500 | J43: 2050 | M43: =G43=J43 -> TRUE | N43: =H43=K43 -> FALSE
G44: 2051 | H44: 900 | J44: 2051 | K44: 900 | M44: =G44=J44 -> TRUE | N44: =H44=K44 -> TRUE
G45: Thereafter | H45: 1312 | J45: Thereafter | K45: 1312 | M45: =G45=J45 -> TRUE | N45: =H45=K45 -> TRUE
G46: Total Unsecured Debt | H46: =SUM(H31:H45) -> 22444 | J46: Total Unsecured Debt | K46: 22444 | M46: =G46=J46 -> TRUE | N46: =H46=K46 -> TRUE
G47: Total Secured Debt | H47: 1785 | J47: Total Secured Debt | K47: 1785 | M47: =G47=J47 -> TRUE | N47: =H47=K47 -> TRUE
G48: Total Debt | H48: =SUM(H46:H47) -> 24229 | J48: Total Debt | K48: 24229 | M48: =G48=J48 -> TRUE | N48: =H48=K48 -> TRUE
G50: Accuracy | H50: =(28)/38 -> 0.73684211
G53: Correct | J53: LLM
A54: 2Q24
G56: Year | H56: Unsecured Debt | J56: Year | K56: Unsecured Debt | M56: =G56=J56 -> TRUE | N56: =H56=K56 -> TRUE
G57: 2024 | H57: 750 | J57: 2024 | K57: 750 | M57: =G57=J57 -> TRUE | N57: =H57=K57 -> TRUE
G58: 2025 | H58: 500 | J58: 2025 | K58: 500 | M58: =G58=J58 -> TRUE | N58: =H58=K58 -> TRUE
G59: 2026 | H59: 2650 | J59: 2026 | K59: 2400 | M59: =G59=J59 -> TRUE | N59: =H59=K59 -> FALSE
G60: 2027 | H60: 3405 | J60: 2027 | K60: 1000 | M60: =G60=J60 -> TRUE | N60: =H60=K60 -> FALSE
G61: 2028 | H61: 2600 | J61: 2028 | K61: 3000 | M61: =G61=J61 -> TRUE | N61: =H61=K61 -> FALSE
G62: 2029 | H62: 1900 | J62: 2029 | K62: 1350 | M62: =G62=J62 -> TRUE | N62: =H62=K62 -> FALSE
G63: 2030 | H63: 750 | J63: 2030 | K63: 750 | M63: =G63=J63 -> TRUE | N63: =H63=K63 -> TRUE
G64: 2031 | H64: 2850 | J64: 2031 | K64: 2600 | M64: =G64=J64 -> TRUE | N64: =H64=K64 -> FALSE
G65: 2033 | H65: 750 | J65: 2033 | K65: 750 | M65: =G65=J65 -> TRUE | N65: =H65=K65 -> TRUE
G66: 2034 | H66: 750 | J66: 2034 | K66: 750 | M66: =G66=J66 -> TRUE | N66: =H66=K66 -> TRUE
G67: 2041 | H67: 1250 | J67: 2041 | K67: 1250 | M67: =G67=J67 -> TRUE | N67: =H67=K67 -> TRUE
G68: 2047 | H68: 350 | J68: 2047 | K68: 350 | M68: =G68=J68 -> TRUE | N68: =H68=K68 -> TRUE
... G71: 2051 | H71: 900 | J71: 2051 | K71: 900 | M71: =G71=J71 -> TRUE | N71: =H71=K71 -> TRUE
G72: Thereafter | H72: 1438 | J72: Thereafter | K72: 1438 | M72: =G72=J72 -> TRUE | N72: =H72=K72 -> TRUE
G73: Total Unsecured Debt | H73: =SUM(H57:H72) -> 22093 | J73: Total Unsecured Debt | K73: 22093 | M73: =G73=J73 -> TRUE | N73: =H73=K73 -> TRUE
G74: Total Secured Debt | H74: 1781 | J74: Total Secured Debt | K74: 1781 | M74: =G74=J74 -> TRUE | N74: =H74=K74 -> TRUE
G75: Total Debt | H75: =SUM(H73:H74) -> 23874 | J75: Total Debt | K75: 23874 | M75: =G75=J75 -> TRUE | N75: =H75=K75 -> TRUE
G77: Accuracy | H77: =34/40 -> 0.85
G80: Correct | J80: LLM
A81: 1Q24
G82: Year | H82: Unsecured Debt | J82: Year | K82: Unsecured Debt | M82: =G82=J82 -> TRUE | N82: =H82=K82 -> TRUE
G83: 2024 | H83: 750 | J83: 2024 | K83: 750 | M83: =G83=J83 -> TRUE | N83: =H83=K83 -> TRUE
G84: 2025 | H84: 500 | J84: 2025 | K84: 500 | M84: =G84=J84 -> TRUE | N84: =H84=K84 -> TRUE
G85: 2026 | H85: 2650 | J85: 2026 | K85: 2650 | M85: =G85=J85 -> TRUE | N85: =H85=K85 -> TRUE
G86: 2027 | H86: 3412 | J86: 2027 | K86: 3162 | M86: =G86=J86 -> TRUE | N86: =H86=K86 -> FALSE
G87: 2028 | H87: 2600 | J87: 2028 | K87: 1600 | M87: =G87=J87 -> TRUE | N87: =H87=K87 -> FALSE
G88: 2029 | H88: 1900 | J88: 2029 | K88: 2050 | M88: =G88=J88 -> TRUE | N88: =H88=K88 -> FALSE
G89: 2030 | H89: 750 | J89: 2030 | K89: 750 | M89: =G89=J89 -> TRUE | N89: =H89=K89 -> TRUE
G90: 2031 | H90: 2850 | J90: 2031 | K90: 2850 | M90: =G90=J90 -> TRUE | N90: =H90=K90 -> TRUE
G91: 2033 | H91: 750 | J91: 2033 | K91: 750 | M91: =G91=J91 -> TRUE | N91: =H91=K91 -> TRUE
G92: 2034 | H92: 750 | J92: 2034 | K92: 750 | M92: =G92=J92 -> TRUE | N92: =H92=K92 -> TRUE
G93: 2041 | H93: 1250 | J93: 2041 | K93: 1250 | M93: =G93=J93 -> TRUE | N93: =H93=K93 -> TRUE
G94: 2047 | H94: 350 | J94: 2047 | K94: 350 | M94: =G94=J94 -> TRUE | N94: =H94=K94 -> TRUE
... G97: 2051 | H97: 900 | J97: 2051 | K97: 900 | M97: =G97=J97 -> TRUE | N97: =H97=K97 -> TRUE
G98: Thereafter | H98: 1138 | J98: Thereafter | K98: 1138 | M98: =G98=J98 -> TRUE | N98: =H98=K98 -> TRUE
G99: Total Unsecured Debt | H99: =SUM(H83:H98) -> 21800 | J99: Total Unsecured Debt | K99: 21800 | M99: =G99=J99 -> TRUE | N99: =H99=K99 -> TRUE
G100: Total Secured Debt | H100: 1775 | J100: Total Secured Debt | K100: 1775 | M100: =G100=J100 -> TRUE | N100: =H100=K100 -> TRUE
G101: Total Debt | H101: =SUM(H99:H100) -> 23575 | J101: Total Debt | K101: 23575 | M101: =G101=J101 -> TRUE | N101: =H101=K101 -> TRUE
G103: Accuracy | H103: =36/40 -> 0.9

Sheet CCI Script
B2: 4Q24
X3: Check | AA3: Check
AD5: Ticker | AE5: Quarter | AF5: Unsecured Debt | AG5: Amount | AH5: Unit | AI5: Currency | AJ5: Category
X6: 2027 | Y6: 1117 | AA6: 2025 | AB6: =SUMIF($X$6:$X$34,$AA6,$Y$6:$Y$34) -> 499 | AD6: CCI | AE6: 4Q24 | AF6: Near-Term | AG6: =SUM(AB6:AB10) -> 11515 | AH6: mn | AI6: USD | AJ6: Unsecured Debt
X7: 2025 | Y7: 499 | AA7: 2026 | AB7: =SUMIF($X$6:$X$34,$AA7,$Y$6:$Y$34) -> 2645 | AD7: CCI | AE7: 4Q24 | AF7: Medium-Term | AG7: =SUM(AB11:AB13) -> 4313 | AH7: mn | AI7: USD | AJ7: Unsecured Debt
X8: 2026 | Y8: 899 | AA8: 2027 | AB8: =SUMIF($X$6:$X$34,$AA8,$Y$6:$Y$34) -> 3358 | AD8: CCI | AE8: 4Q24 | AF8: Long-Term | AG8: =SUM(AB14:AB20) -> 6475 | AH8: mn | AI8: USD | AJ8: Unsecured Debt
X9: 2026 | Y9: 749 | AA9: 2028 | AB9: =SUMIF($X$6:$X$34,$AA9,$Y$6:$Y$34) -> 2584 | AD9: CCI | AE9: 4Q24 | AF9: Total Unsecured | AG9: =SUM(AG6:AG8) -> 22303 | AH9: mn | AI9: USD | AJ9: Unsecured Debt
X10: 2026 | Y10: 997 | AA10: 2029 | AB10: =SUMIF($X$6:$X$34,$AA10,$Y$6:$Y$34) -> 2429
X11: 2027 | Y11: 498 | AA11: 2030 | AB11: =SUMIF($X$6:$X$34,$AA11,$Y$6:$Y$34) -> 742
X12: 2027 | Y12: 746 | AA12: 2031 | AB12: =SUMIF($X$6:$X$34,$AA12,$Y$6:$Y$34) -> 2828
X13: 2027 | Y13: 997 | AA13: 2033 | AB13: =SUMIF($X$6:$X$34,$AA13,$Y$6:$Y$34) -> 743
X14: 2028 | Y14: 993 | AA14: 2034 | AB14: =SUMIF($X$6:$X$34,$AA14,$Y$6:$Y$34) -> 1431
X15: 2028 | Y15: 996 | AA15: 2041 | AB15: =SUMIF($X$6:$X$34,$AA15,$Y$6:$Y$34) -> 1235
X16: 2028 | Y16: 595 | AA16: 2047 | AB16: =SUMIF($X$6:$X$34,$AA16,$Y$6:$Y$34) -> 345
X17: 2029 | Y17: 596 | AA17: 2049 | AB17: =SUMIF($X$6:$X$34,$AA17,$Y$6:$Y$34) -> 742
X18: 2029 | Y18: 742 | AA18: 2050 | AB18: =SUMIF($X$6:$X$34,$AA18,$Y$6:$Y$34) -> 490
X19: 2029 | Y19: 544 | AA19: 2051 | AB19: =SUMIF($X$6:$X$34,$AA19,$Y$6:$Y$34) -> 891
X20: 2029 | Y20: 547 | AA20: Thereafter | AB20: =SUMIF($X$6:$X$34,$AA20,$Y$6:$Y$34) -> 1341
X21: 2030 | Y21: 742 | AB21: =SUM(AB6:AB20) -> 22303
X22: 2031 | Y22: 1093
X23: 2031 | Y23: 991
X24: 2031 | Y24: 744
X25: 2033 | Y25: 743
X26: 2034 | Y26: 742
X27: 2034 | Y27: 689
X28: 2041 | Y28: 1235
X29: 2047 | Y29: 345
X30: 2049 | Y30: 396
X31: 2049 | Y31: 346
X32: 2050 | Y32: 490
X33: 2051 | Y33: 891
X34: Thereafter | Y34: 1341
Y35: =SUM(Y6:Y34) -> 22303
X39: Check | AA39: Check
B40: 3Q24 | AD40: Ticker | AE40: Quarter | AF40: Unsecured Debt | AG40: Amount | AH40: Unit | AI40: Currency | AJ40: Category
X41: 2027 | Y41: 1132 | AA41: 2025 | AB41: =SUMIF($X$41:$X$69,$AA41,$Y$41:$Y$69) -> 499 | AD41: CCI | AE41: 3Q24 | AF41: Near-Term | AG41: =SUM(AB41:AB45) -> 11526 | AH41: mn | AI41: USD | AJ41: Unsecured Debt
X42: 2025 | Y42: 499 | AA42: 2026 | AB42: =SUMIF($X$41:$X$69,$AA42,$Y$41:$Y$69) -> 2643 | AD42: CCI | AE42: 3Q24 | AF42: Medium-Term | AG42: =SUM(AB46:AB48) -> 4311 | AH42: mn | AI42: USD | AJ42: Unsecured Debt
X43: 2026 | Y43: 898 | AA43: 2027 | AB43: =SUMIF($X$41:$X$69,$AA43,$Y$41:$Y$69) -> 3372 | AD43: CCI | AE43: 3Q24 | AF43: Long-Term | AG43: =SUM(AB49:AB55) -> 6445 | AH43: mn | AI43: USD | AJ43: Unsecured Debt
X44: 2026 | Y44: 749 | AA44: 2028 | AB44: =SUMIF($X$41:$X$69,$AA44,$Y$41:$Y$69) -> 2584 | AD44: CCI | AE44: 3Q24 | AF44: Total Unsecured | AG44: =SUM(AG41:AG43) -> 22282 | AH44: mn | AI44: USD | AJ44: Unsecured Debt
X45: 2026 | Y45: 996 | AA45: 2029 | AB45: =SUMIF($X$41:$X$69,$AA45,$Y$41:$Y$69) -> 2428
X46: 2027 | Y46: 498 | AA46: 2030 | AB46: =SUMIF($X$41:$X$69,$AA46,$Y$41:$Y$69) -> 742
X47: 2027 | Y47: 745 | AA47: 2031 | AB47: =SUMIF($X$41:$X$69,$AA47,$Y$41:$Y$69) -> 2826
X48: 2027 | Y48: 997 | AA48: 2033 | AB48: =SUMIF($X$41:$X$69,$AA48,$Y$41:$Y$69) -> 743
X49: 2028 | Y49: 993 | AA49: 2034 | AB49: =SUMIF($X$41:$X$69,$AA49,$Y$41:$Y$69) -> 1431
X50: 2028 | Y50: 996 | AA50: 2041 | AB50: =SUMIF($X$41:$X$69,$AA50,$Y$41:$Y$69) -> 1235
X51: 2028 | Y51: 595 | AA51: 2047 | AB51: =SUMIF($X$41:$X$69,$AA51,$Y$41:$Y$69) -> 344
X52: 2029 | Y52: 596 | AA52: 2049 | AB52: =SUMIF($X$41:$X$69,$AA52,$Y$41:$Y$69) -> 742
X53: 2029 | Y53: 742 | AA53: 2050 | AB53: =SUMIF($X$41:$X$69,$AA53,$Y$41:$Y$69) -> 490
X54: 2029 | Y54: 543 | AA54: 2051 | AB54: =SUMIF($X$41:$X$69,$AA54,$Y$41:$Y$69) -> 891
X55: 2029 | Y55: 547 | AA55: Thereafter | AB55: =SUMIF($X$41:$X$69,$AA55,$Y$41:$Y$69) -> 1312
X56: 2030 | Y56: 742 | AB56: =SUM(AB41:AB55) -> 22282
X57: 2031 | Y57: 1092
X58: 2031 | Y58: 991
X59: 2031 | Y59: 743
X60: 2033 | Y60: 743
X61: 2034 | Y61: 742
X62: 2034 | Y62: 689
X63: 2041 | Y63: 1235
X64: 2047 | Y64: 344
X65: 2049 | Y65: 396
X66: 2049 | Y66: 346
X67: 2050 | Y67: 490
X68: 2051 | Y68: 891
X69: Thereafter | Y69: 1312
Y70: =SUM(Y41:Y69) -> 22282
B72: 2Q24
X73: Check | AA73: Check
AD74: Ticker | AE74: Quarter | AF74: Unsecured Debt | AG74: Amount | AH74: Unit | AI74: Currency | AJ74: Category
X75: 2024 | Y75: 750 | AA75: 2024 | AB75: =SUMIF($X$75:$X$102,$AA75,$Y$75:$Y$102) -> 750 | AD75: CCI | AE75: 2Q24 | AF75: Near-Term | AG75: =SUM(AB75:AB80) -> 11751 | AH75: mn | AI75: USD | AJ75: Unsecured Debt
X76: 2025 | Y76: 499 | AA76: 2025 | AB76: =SUMIF($X$75:$X$102,$AA76,$Y$75:$Y$102) -> 499 | AD76: CCI | AE76: 2Q24 | AF76: Medium-Term | AG76: =SUM(AB81:AB83) -> 4310 | AH76: mn | AI76: USD | AJ76: Unsecured Debt
X77: 2026 | Y77: 898 | AA77: 2026 | AB77: =SUMIF($X$75:$X$102,$AA77,$Y$75:$Y$102) -> 2642 | AD77: CCI | AE77: 2Q24 | AF77: Long-Term | AG77: =SUM(AB84:AB90) -> 5881 | AH77: mn | AI77: USD | AJ77: Unsecured Debt
X78: 2026 | Y78: 748 | AA78: 2027 | AB78: =SUMIF($X$75:$X$102,$AA78,$Y$75:$Y$102) -> 3395 | AD78: CCI | AE78: 2Q24 | AF78: Total Unsecured | AG78: =SUM(AG75:AG77) -> 21942 | AH78: mn | AI78: USD | AJ78: Unsecured Debt
X79: 2026 | Y79: 996 | AA79: 2028 | AB79: =SUMIF($X$75:$X$102,$AA79,$Y$75:$Y$102) -> 2582
X80: 2027 | Y80: 498 | AA80: 2029 | AB80: =SUMIF($X$75:$X$102,$AA80,$Y$75:$Y$102) -> 1883
X81: 2027 | Y81: 1155 | AA81: 2030 | AB81: =SUMIF($X$75:$X$102,$AA81,$Y$75:$Y$102) -> 741
X82: 2027 | Y82: 745 | AA82: 2031 | AB82: =SUMIF($X$75:$X$102,$AA82,$Y$75:$Y$102) -> 2826
X83: 2027 | Y83: 997 | AA83: 2033 | AB83: =SUMIF($X$75:$X$102,$AA83,$Y$75:$Y$102) -> 743
X84: 2028 | Y84: 992 | AA84: 2034 | AB84: =SUMIF($X$75:$X$102,$AA84,$Y$75:$Y$102) -> 742
X85: 2028 | Y85: 995 | AA85: 2041 | AB85: =SUMIF($X$75:$X$102,$AA85,$Y$75:$Y$102) -> 1235
X86: 2028 | Y86: 595 | AA86: 2047 | AB86: =SUMIF($X$75:$X$102,$AA86,$Y$75:$Y$102) -> 344
X87: 2029 | Y87: 596 | AA87: 2049 | AB87: =SUMIF($X$75:$X$102,$AA87,$Y$75:$Y$102) -> 742
X88: 2029 | Y88: 741 | AA88: 2050 | AB88: =SUMIF($X$75:$X$102,$AA88,$Y$75:$Y$102) -> 490
X89: 2029 | Y89: 546 | AA89: 2051 | AB89: =SUMIF($X$75:$X$102,$AA89,$Y$75:$Y$102) -> 890
X90: 2030 | Y90: 741 | AA90: Thereafter | AB90: =SUMIF($X$75:$X$102,$AA90,$Y$75:$Y$102) -> 1438
X91: 2031 | Y91: 1092 | AB91: =SUM(AB75:AB90) -> 21942
X92: 2031 | Y92: 991
X93: 2031 | Y93: 743
X94: 2033 | Y94: 743
X95: 2034 | Y95: 742
X96: 2041 | Y96: 1235
X97: 2047 | Y97: 344
X98: 2049 | Y98: 396
X99: 2049 | Y99: 346
X100: 2050 | Y100: 490
X101: 2051 | Y101: 890
X102: Thereafter | Y102: 1438
Y103: =SUM(Y75:Y102) -> 21942
B108: 1Q24 | X108: Check | AA108: Check
AD109: Ticker | AE109: Quarter | AF109: Unsecured Debt | AG109: Amount | AH109: Unit | AI109: Currency | AJ109: Category
X110: 2027 | Y110: 1162 | AA110: 2024 | AB110: =SUMIF($X$110:$X$136,$AA110,$Y$110:$Y$136) -> 750 | AD110: CCI | AE110: 1Q24 | AF110: Near-Term | AG110: =SUM(AB110:AB115) -> 11753 | AH110: mn | AI110: USD | AJ110: Unsecured Debt
...

Sheet AVB

Sheet AVB Manual
A2: 4Q24 | B2: Year | C2: Secured Debt | D2: Unsecured Debt | E2: Total | G2: Ticker | H2: Quarter | I2: Unsecured Debt | J2: Amount | K2: Unit | L2: Currency | M2: Category
B3: 2025 | C3: 11365 | D3: 825000 | E3: =SUM(C3:D3) -> 836365 | G3: AVB | H3: 4Q24 | I3: Near-term | J3: =SUM(D3:D7)/1000 -> 3300 | K3: mn | L3: USD | M3: Unsecured Debt | O3: (2024 - 2029 maturities)
B4: 2026 | C4: 11811 | D4: 775000 | E4: =SUM(C4:D4) -> 786811 | G4: AVB | H4: 4Q24 | I4: Medium-Term | J4: =SUM(D8:D11)/1000 -> 2750 | K4: mn | L4: USD | M4: Unsecured Debt | O4: (2030 - 2033 maturities)
B5: 2027 | C5: 250159 | D5: 400000 | E5: =SUM(C5:D5) -> 650159 | G5: AVB | H5: 4Q24 | I5: Long-term | J5: =(D13+D12)/1000 -> 1350 | K5: mn | L5: USD | M5: Unsecured Debt | O5: Thereafter
B6: 2028 | C6: 19002 | D6: 850000 | E6: =SUM(C6:D6) -> 869002 | G6: AVB | H6: 4Q24 | I6: Total Unsecured | J6: =SUM(J3:J5) -> 7400 | K6: mn | L6: USD | M6: Unsecured Debt
B7: 2029 | C7: 131561 | D7: 450000 | E7: =SUM(C7:D7) -> 581561
B8: 2030 | C8: 9000 | D8: 700000 | E8: =SUM(C8:D8) -> 709000
B9: 2031 | C9: 9600 | D9: 600000 | E9: =SUM(C9:D9) -> 609600
B10: 2032 | C10: 10400 | D10: 700000 | E10: =SUM(C10:D10) -> 710400
B11: 2033 | C11: 11900 | D11: 750000 | E11: =SUM(C11:D11) -> 761900
B12: 2034 | C12: 12800 | D12: 400000 | E12: =SUM(C12:D12) -> 412800
B13: Thereafter | C13: 256831 | D13: 950000 | E13: =SUM(C13:D13) -> 1206831
B14: Total | C14: =SUM(C3:C13) -> 734429 | D14: =SUM(D3:D13) -> 7400000 | E14: =SUM(E3:E13) -> 8134429
A16: 3Q24 | B16: Year | C16: Secured Debt | D16: Unsecured Debt | E16: Total | G16: Ticker | H16: Quarter | I16: Unsecured Debt | J16: Amount | K16: Unit | L16: Currency | M16: Category
B17: 2024 | C17: 461 | D17: 300000 | E17: =SUM(C17:D17) -> 300461 | G17: AVB | H17: 3Q24 | I17: Near-term | J17: =SUM(D17:D22)/1000 -> 3600 | K17: mn | L17: USD | M17: Unsecured Debt | O17: (2024 - 2029 maturities)
B18: 2025 | C18: 10765 | D18: 825000 | E18: =SUM(C18:D18) -> 835765 | G18: AVB | H18: 3Q24 | I18: Medium-Term | J18: =SUM(D23:D26)/1000 -> 2750 | K18: mn | L18: USD | M18: Unsecured Debt | O18: (2030 - 2033 maturities)
B19: 2026 | C19: 11811 | D19: 775000 | E19: =SUM(C19:D19) -> 786811 | G19: AVB | H19: 3Q24 | I19: Long-term | J19: =D27/1000 -> 1350 | K19: mn | L19: USD | M19: Unsecured Debt | O19: Thereafter
B20: 2027 | C20: 250159 | D20: 400000 | E20: =SUM(C20:D20) -> 650159 | G20: AVB | H20: 3Q24 | I20: Total Unsecured | J20: =SUM(J17:J19) -> 7700 | K20: mn | L20: USD | M20: Unsecured Debt
B21: 2028 | C21: 18902 | D21: 850000 | E21: =SUM(C21:D21) -> 868902
B22: 2029 | C22: 132661 | D22: 450000 | E22: =SUM(C22:D22) -> 582661
B23: 2030 | C23: 9100 | D23: 700000 | E23: =SUM(C23:D23) -> 709100
B24: 2031 | C24: 9700 | D24: 600000 | E24: =SUM(C24:D24) -> 609700
B25: 2032 | C25: 10400 | D25: 700000 | E25: =SUM(C25:D25) -> 710400
B26: 2033 | C26: 12000 | D26: 750000 | E26: =SUM(C26:D26) -> 762000
B27: Thereafter | C27: 268951 | D27: 1350000 | E27: =SUM(C27:D27) -> 1618951
B28: Total | C28: =SUM(C17:C27) -> 734910 | D28: =SUM(D17:D27) -> 7700000 | E28: =SUM(E17:E27) -> 8434910
A30: 2Q24 | B30: Year | C30: Secured Debt | D30: Unsecured Debt | E30: Total | G30: Ticker | H30: Quarter | I30: Unsecured Debt | J30: Amount | K30: Unit | L30: Currency | M30: Category
B31: 2024 | C31: 1612 | D31: 300000 | E31: =SUM(C31:D31) -> 301612 | G31: AVB | H31: 2Q24 | I31: Near-term | J31: =SUM(D31:D36)/1000 -> 3600 | K31: mn | L31: USD | M31: Unsecured Debt | O31: (2024 - 2029 maturities)
B32: 2025 | C32: 10765 | D32: 825000 | E32: =SUM(C32:D32) -> 835765 | G32: AVB | H32: 2Q24 | I32: Medium-Term | J32: =SUM(D37:D40)/1000 -> 2750 | K32: mn | L32: USD | M32: Unsecured Debt | O32: (2030 - 2033 maturities)
B33: 2026 | C33: 11811 | D33: 775000 | E33: =SUM(C33:D33) -> 786811 | G33: AVB | H33: 2Q24 | I33: Long-term | J33: =D41/1000 -> 1350 | K33: mn | L33: USD | M33: Unsecured Debt | O33: Thereafter
B34: 2027 | C34: 250159 | D34: 400000 | E34: =SUM(C34:D34) -> 650159 | G34: AVB | H34: 2Q24 | I34: Total Unsecured | J34: =SUM(J31:J33) -> 7700 | K34: mn | L34: USD | M34: Unsecured Debt
B35: 2028 | C35: 18902 | D35: 850000 | E35: =SUM(C35:D35) -> 868902
B36: 2029 | C36: 132661 | D36: 450000 | E36: =SUM(C36:D36) -> 582661
B37: 2030 | C37: 9100 | D37: 700000 | E37: =SUM(C37:D37) -> 709100
B38: 2031 | C38: 9700 | D38: 600000 | E38: =SUM(C38:D38) -> 609700
B39: 2032 | C39: 10400 | D39: 700000 | E39: =SUM(C39:D39) -> 710400
B40: 2033 | C40: 12000 | D40: 750000 | E40: =SUM(C40:D40) -> 762000
B41: Thereafter | C41: 268951 | D41: 1350000 | E41: =SUM(C41:D41) -> 1618951
B42: Total | C42: =SUM(C31:C41) -> 736061 | D42: =SUM(D31:D41) -> 7700000 | E42: =SUM(E31:E41) -> 8436061
A45: 1Q24 | B45: Year | C45: Secured Debt | D45: Unsecured Debt | E45: Total | G45: Ticker | H45: Quarter | I45: Unsecured Debt | J45: Amount | K45: Unit | L45: Currency | M45: Category
B46: 2024 | C46: 8793 | D46: 300000 | E46: =SUM(C46:D46) -> 308793 | G46: AVB | H46: 1Q24 | I46: Near-term | J46: =SUM(D46:D51)/1000 -> 3600 | K46: mn | L46: USD | M46: Unsecured Debt | O46: (2024 - 2029 maturities)
B47: 2025 | C47: 10765 | D47: 825000 | E47: =SUM(C47:D47) -> 835765 | G47: AVB | H47: 1Q24 | I47: Medium-Term | J47: =SUM(D52:D55)/1000 -> 2750 | K47: mn | L47: USD | M47: Unsecured Debt | O47: (2030 - 2033 maturities)
B48: 2026 | C48: 11811 | D48: 775000 | E48: =SUM(C48:D48) -> 786811 | G48: AVB | H48: 1Q24 | I48: Long-term | J48: =D56/1000 -> 950 | K48: mn | L48: USD | M48: Unsecured Debt | O48: Thereafter
B49: 2027 | C49: 250159 | D49: 400000 | E49: =SUM(C49:D49) -> 650159 | G49: AVB | H49: 1Q24 | I49: Total Unsecured | J49: =SUM(J46:J48) -> 7300 | K49: mn | L49: USD | M49: Unsecured Debt
B50: 2028 | C50: 18902 | D50: 850000 | E50: =SUM(C50:D50) -> 868902
B51: 2029 | C51: 132661 | D51: 450000 | E51: =SUM(C51:D51) -> 582661
B52: 2030 | C52: 9100 | D52: 700000 | E52: =SUM(C52:D52) -> 709100
B53: 2031 | C53: 9700 | D53: 600000 | E53: =SUM(C53:D53) -> 609700
B54: 2032 | C54: 10400 | D54: 700000 | E54: =SUM(C54:D54) -> 710400
B55: 2033 | C55: 12000 | D55: 750000 | E55: =SUM(C55:D55) -> 762000
B56: Thereafter | C56: 268951 | D56: 950000 | E56: =SUM(C56:D56) -> 1218951
B57: Total | C57: =SUM(C46:C56) -> 743242 | D57: =SUM(D46:D56) -> 7300000 | E57: =SUM(E46:E56) -> 8043242

Sheet AVB LLM API
A2: OpenAI | B2: Debt Partition
H4: Correct | K4: LLM
A5: 4Q24
H6: Year | I6: Unsecured Debt | K6: Year | L6: Unsecured Debt | N6: =H6=K6 -> TRUE | O6: =I6=L6 -> TRUE
H7: 2025 | I7: 825 | K7: 2025 | L7: 825 | N7: =H7=K7 -> TRUE | O7: =I7=L7 -> TRUE
H8: 2026 | I8: 775 | K8: 2026 | L8: 775 | N8: =H8=K8 -> TRUE | O8: =I8=L8 -> TRUE
H9: 2027 | I9: 400 | K9: 2027 | L9: 400 | N9: =H9=K9 -> TRUE | O9: =I9=L9 -> TRUE
H10: 2028 | I10: 850 | K10: 2028 | L10: 850 | N10: =H10=K10 -> TRUE | O10: =I10=L10 -> TRUE
H11: 2029 | I11: 450 | K11: 2029 | L11: 450 | N11: =H11=K11 -> TRUE | O11: =I11=L11 -> TRUE
H12: 2030 | I12: 700 | K12: 2030 | L12: 700 | N12: =H12=K12 -> TRUE | O12: =I12=L12 -> TRUE
H13: 2031 | I13: 600 | K13: 2031 | L13: 600 | N13: =H13=K13 -> TRUE | O13: =I13=L13 -> TRUE
H14: 2032 | I14: 700 | K14: 2032 | L14: 700 | N14: =H14=K14 -> TRUE | O14: =I14=L14 -> TRUE
H15: 2033 | I15: 750 | K15: 2033 | L15: 750 | N15: =H15=K15 -> TRUE | O15: =I15=L15 -> TRUE
H16: 2034 | I16: 400 | K16: 2034 | L16: 400 | N16: =H16=K16 -> TRUE | O16: =I16=L16 -> TRUE
H17: Thereafter | I17: 950 | K17: Thereafter | L17: 950 | N17: =H17=K17 -> TRUE | O17: =I17=L17 -> TRUE
H18: Total | I18: =SUM(I7:I17) -> 7400 | K18: Total | L18: =SUM(L7:L17) -> 7400 | N18: =H18=K18 -> TRUE | O18: =I18=L18 -> TRUE
K20: Accuracy | L20: =26/26 -> 1
H24: Correct | K24: LLM
A25: 3Q24
H26: Year | I26: Unsecured Debt | K26: Year | L26: Unsecured Debt | N26: =H26=K26 -> TRUE | O26: =I26=L26 -> TRUE
H27: 2024 | I27: 300 | K27: 2024 | L27: 300 | N27: =H27=K27 -> TRUE | O27: =I27=L27 -> TRUE
H28: 2025 | I28: 825 | K28: 2025 | L28: 825 | N28: =H28=K28 -> TRUE | O28: =I28=L28 -> TRUE
H29: 2026 | I29: 775 | K29: 2026 | L29: 775 | N29: =H29=K29 -> TRUE | O29: =I29=L29 -> TRUE
H30: 2027 | I30: 400 | K30: 2027 | L30: 400 | N30: =H30=K30 -> TRUE | O30: =I30=L30 -> TRUE
H31: 2028 | I31: 850 | K31: 2028 | L31: 850 | N31: =H31=K31 -> TRUE | O31: =I31=L31 -> TRUE
H32: 2029 | I32: 450 | K32: 2029 | L32: 450 | N32: =H32=K32 -> TRUE | O32: =I32=L32 -> TRUE
H33: 2030 | I33: 700 | K33: 2030 | L33: 900 | N33: =H33=K33 -> TRUE | O33: =I33=L33 -> FALSE
H34: 2031 | I34: 600 | K34: 2031 | L34: 600 | N34: =H34=K34 -> TRUE | O34: =I34=L34 -> TRUE
H35: 2032 | I35: 700 | K35: 2032 | L35: 700 | N35: =H35=K35 -> TRUE | O35: =I35=L35 -> TRUE
H36: 2033 | I36: 750 | K36: 2033 | L36: 750 | N36: =H36=K36 -> TRUE | O36: =I36=L36 -> TRUE
H37: Thereafter | I37: 1350 | K37: Thereafter | L37: 1350 | N37: =H37=K37 -> TRUE | O37: =I37=L37 -> TRUE
H38: Total | I38: =SUM(I27:I37) -> 7700 | K38: Total | L38: 7700 | N38: =H38=K38 -> TRUE | O38: =I38=L38 -> TRUE
K40: Accuracy | L40: =25/26 -> 0.96153846
H42: Correct | K42: LLM
A43: 2Q24
H44: Year | I44: Unsecured Debt | K44: Year | L44: Unsecured Debt | N44: =H44=K44 -> TRUE | O44: =I44=L44 -> TRUE
H45: 2024 | I45: 300 | K45: 2024 | L45: 300 | N45: =H45=K45 -> TRUE | O45: =I45=L45 -> TRUE
H46: 2025 | I46: 825 | K46: 2025 | L46: 825 | N46: =H46=K46 -> TRUE | O46: =I46=L46 -> TRUE
H47: 2026 | I47: 775 | K47: 2026 | L47: 775 | N47: =H47=K47 -> TRUE | O47: =I47=L47 -> TRUE
H48: 2027 | I48: 400 | K48: 2027 | L48: 400 | N48: =H48=K48 -> TRUE | O48: =I48=L48 -> TRUE
H49: 2028 | I49: 850 | K49: 2028 | L49: 850 | N49: =H49=K49 -> TRUE | O49: =I49=L49 -> TRUE
H50: 2029 | I50: 450 | K50: 2029 | L50: 450 | N50: =H50=K50 -> TRUE | O50: =I50=L50 -> TRUE
H51: 2030 | I51: 700 | K51: 2030 | L51: 700 | N51: =H51=K51 -> TRUE | O51: =I51=L51 -> TRUE
H52: 2031 | I52: 600 | K52: 2031 | L52: 600 | N52: =H52=K52 -> TRUE | O52: =I52=L52 -> TRUE
H53: 2032 | I53: 700 | K53: 2032 | L53: 700 | N53: =H53=K53 -> TRUE | O53: =I53=L53 -> TRUE
H54: 2033 | I54: 750 | K54: 2033 | L54: 750 | N54: =H54=K54 -> TRUE | O54: =I54=L54 -> TRUE
H55: Thereafter | I55: 1350 | K55: Thereafter | L55: 1350 | N55: =H55=K55 -> TRUE | O55: =I55=L55 -> TRUE
H56: Total | I56: =SUM(I45:I55) -> 7700 | K56: Total | L56: =SUM(L45:L55) -> 7700 | N56: =H56=K56 -> TRUE | O56: =I56=L56 -> TRUE
K58: Accuracy | L58: =26/26 -> 1
H60: Correct | K60: LLM
A61: 1Q24
H62: Year | I62: Unsecured Debt | K62: Year | L62: Unsecured Debt | N62: =H62=K62 -> TRUE | O62: =I62=L62 -> TRUE
H63: 2024 | I63: 300 | K63: 2024 | L63: 300 | N63: =H63=K63 -> TRUE | O63: =I63=L63 -> TRUE
H64: 2025 | I64: 825 | K64: 2025 | L64: 825 | N64: =H64=K64 -> TRUE | O64: =I64=L64 -> TRUE
H65: 2026 | I65: 775 | K65: 2026 | L65: 775 | N65: =H65=K65 -> TRUE | O65: =I65=L65 -> TRUE
H66: 2027 | I66: 400 | K66: 2027 | L66: 400 | N66: =H66=K66 -> TRUE | O66: =I66=L66 -> TRUE
H67: 2028 | I67: 850 | K67: 2028 | L67: 850 | N67: =H67=K67 -> TRUE | O67: =I67=L67 -> TRUE
H68: 2029 | I68: 450 | K68: 2029 | L68: 450 | N68: =H68=K68 -> TRUE | O68: =I68=L68 -> TRUE
H69: 2030 | I69: 700 | K69: 2030 | L69: 700 | N69: =H69=K69 -> TRUE | O69: =I69=L69 -> TRUE
H70: 2031 | I70: 600 | K70: 2031 | L70: 600 | N70: =H70=K70 -> TRUE | O70: =I70=L70 -> TRUE
H71: 2032 | I71: 700 | K71: 2032 | L71: 700 | N71: =H71=K71 -> TRUE | O71: =I71=L71 -> TRUE
H72: 2033 | I72: 750 | K72: 2033 | L72: 750 | N72: =H72=K72 -> TRUE | O72: =I72=L72 -> TRUE
H73: Thereafter | I73: 950 | K73: Thereafter | L73: 950 | N73: =H73=K73 -> TRUE | O73: =I73=L73 -> TRUE
H74: Total | I74: =SUM(I63:I73) -> 7300 | K74: Total | L74: =SUM(L63:L73) -> 7300 | N74: =H74=K74 -> TRUE | O74: =I74=L74 -> TRUE
K76: Accuracy | L76: =26/26 -> 1

Sheet AVB Script
B2: 4Q24
B25: 3Q24
B48: 2Q24
B71: 1Q24

Sheet AMT

Sheet AMT Manual
A2: 4Q24 | B2: Year | C2: Unsecured Debt | E2: Ticker | F2: Quarter | G2: Unsecured Debt | H2: Amount | I2: Unit | J2: Currency | K2: Category
B3: 2025 | C3: 3168 | E3: AMT | F3: 4Q24 | G3: Near-term | H3: =SUM(C3:C7) -> 18853 | I3: mn | J3: USD | K3: Unsecured Debt | M3: (2024 - 2029 maturities)
B4: 2026 | C4: 3318 | E4: AMT | F4: 4Q24 | G4: Medium-Term | H4: =SUM(C8:C11) -> 10094 | I4: mn | J4: USD | K4: Unsecured Debt | M4: (2030 - 2033 maturities)
B5: 2027 | C5: 4465 | E5: AMT | F5: 4Q24 | G5: Long-term | H5: =SUM(C12:C16) -> 4468 | I5: mn | J5: USD | K5: Unsecured Debt | M5: Thereafter
B6: 2028 | C6: 4226 | E6: AMT | F6: 4Q24 | G6: Total Unsecured | H6: =SUM(H3:H5) -> 33415 | I6: mn | J6: USD | K6: Unsecured Debt
B7: 2029 | C7: 3676 | H7: =H6-C17 -> 0
B8: 2030 | C8: 3935
B9: 2031 | C9: 1918
B10: 2032 | C10: 1323
B11: 2033 | C11: 2918
B12: 2034 | C12: 1168
B13: 2035 | C13: 600
B14: 2049 | C14: 600
B15: 2050 | C15: 1050
B16: 2051 | C16: 1050
B17: Total | C17: =SUM(C3:C16) -> 33415
A22: 3Q24 | B22: Year | C22: Unsecured Debt | E22: Ticker | F22: Quarter | G22: Unsecured Debt | H22: Amount | I22: Unit | J22: Currency | K22: Category
B23: 2025 | C23: 3207 | E23: AMT | F23: 3Q24 | G23: Near-term | H23: =SUM(C23:C27) -> 19194 | I23: mn | J23: USD | K23: Unsecured Debt | M23: (2024 - 2029 maturities)
B24: 2026 | C24: 3357 | E24: AMT | F24: 3Q24 | G24: Medium-Term | H24: =SUM(C28:C31) -> 9701 | I24: mn | J24: USD | K24: Unsecured Debt | M24: (2030 - 2033 maturities)
B25: 2027 | C25: 4610 | E25: AMT | F25: 3Q24 | G25: Long-term | H25: =SUM(C32:C35) -> 3907 | I25: mn | J25: USD | K25: Unsecured Debt | M25: Thereafter
B26: 2028 | C26: 4285 | E26: AMT | F26: 3Q24 | G26: Total Unsecured | H26: =SUM(H23:H25) -> 32802 | I26: mn | J26: USD | K26: Unsecured Debt
B27: 2029 | C27: 3735 | H27: =H26-C36 -> 0
B28: 2030 | C28: 3413
B29: 2031 | C29: 1957
B30: 2032 | C30: 1374
B31: 2033 | C31: 2957
B32: 2034 | C32: 1207
B33: 2049 | C33: 600
B34: 2050 | C34: 1050
B35: 2051 | C35: 1050
B36: Total | C36: =SUM(C23:C35) -> 32802
A42: 2Q24 | B42: Year | C42: Unsecured Debt | E42: Ticker | F42: Quarter | G42: Unsecured Debt | H42: Amount | I42: Unit | J42: Currency | K42: Category
B43: 2025 | C43: 3186 | E43: AMT | F43: 2Q24 | G43: Near-term | H43: =SUM(C43:C47) -> 19012 | I43: mn | J43: USD | K43: Unsecured Debt | M43: (2024 - 2029 maturities)
B44: 2026 | C44: 3336 | E44: AMT | F44: 2Q24 | G44: Medium-Term | H44: =SUM(C48:C51) -> 9589 | I44: mn | J44: USD | K44: Unsecured Debt | M44: (2030 - 2033 maturities)
B45: 2027 | C45: 4532 | E45: AMT | F45: 2Q24 | G45: Long-term | H45: =SUM(C52:C55) -> 3886 | I45: mn | J45: USD | K45: Unsecured Debt | M45: Thereafter
B46: 2028 | C46: 4254 | E46: AMT | F46: 2Q24 | G46: Total Unsecured | H46: =SUM(H43:H45) -> 32487 | I46: mn | J46: USD | K46: Unsecured Debt
B47: 2029 | C47: 3704 | H47: =H46-C56 -> 0
B48: 2030 | C48: 3371
B49: 2031 | C49: 1936
B50: 2032 | C50: 1346
B51: 2033 | C51: 2936
B52: 2034 | C52: 1186
B53: 2049 | C53: 600
B54: 2050 | C54: 1050
B55: 2051 | C55: 1050
B56: Total | C56: =SUM(C43:C55) -> 32487
A63: 1Q24 | B63: Year | C63: Unsecured Debt | E63: Ticker | F63: Quarter | G63: Unsecured Debt | H63: Amount | I63: Unit | J63: Currency | K63: Category
B64: 2024 | C64: 650 | E64: AMT | F64: 1Q24 | G64: Near-term | H64: =SUM(C64:C69) -> 19692 | I64: mn | J64: USD | K64: Unsecured Debt | M64: (2024 - 2029 maturities)
B65: 2025 | C65: 3189 | E65: AMT | F65: 1Q24 | G65: Medium-Term | H65: =SUM(C70:C73) -> 9068 | I65: mn | J65: USD | K65: Unsecured Debt | M65: (2030 - 2033 maturities)
B66: 2026 | C66: 3339 | E66: AMT | F66: 1Q24 | G66: Long-term | H66: =SUM(C74:C77) -> 3350 | I66: mn | J66: USD | K66: Unsecured Debt | M66: Thereafter
B67: 2027 | C67: 4546 | E67: AMT | F67: 1Q24 | G67: Total Unsecured | H67: =SUM(H64:H66) -> 32110 | I67: mn | J67: USD | K67: Unsecured Debt
B68: 2028 | C68: 4259 | H68: =H67-C78 -> 0
B69: 2029 | C69: 3709
B70: 2030 | C70: 2839
B71: 2031 | C71: 1939
B72: 2032 | C72: 1351
B73: 2033 | C73: 2939
B74: 2034 | C74: 650
B75: 2049 | C75: 600
B76: 2050 | C76: 1050
B77: 2051 | C77: 1050
B78: Total | C78: =SUM(C64:C77) -> 32110

Sheet AMT LLM API
A2: OpenAI | B2: Debt Partition
F4: Correct | I4: LLM
A5: 4Q24
F6: Year | G6: Unsecured Debt | I6: Year | J6: Unsecured Debt | L6: =F6=I6 -> TRUE | M6: =G6=J6 -> TRUE
F7: 2025 | G7: 3168 | I7: 2025 | J7: 3168 | L7: =F7=I7 -> TRUE | M7: =G7=J7 -> TRUE
F8: 2026 | G8: 3318 | I8: 2026 | J8: 3318 | L8: =F8=I8 -> TRUE | M8: =G8=J8 -> TRUE
F9: 2027 | G9: 4465 | I9: 2027 | J9: 4465 | L9: =F9=I9 -> TRUE | M9: =G9=J9 -> TRUE
F10: 2028 | G10: 4226 | I10: 2028 | J10: 4226 | L10: =F10=I10 -> TRUE | M10: =G10=J10 -> TRUE
F11: 2029 | G11: 3676 | I11: 2029 | J11: 3676 | L11: =F11=I11 -> TRUE | M11: =G11=J11 -> TRUE
F12: 2030 | G12: 3935 | I12: 2030 | J12: 3935 | L12: =F12=I12 -> TRUE | M12: =G12=J12 -> TRUE
F13: 2031 | G13: 1918 | I13: 2031 | J13: 1918 | L13: =F13=I13 -> TRUE | M13: =G13=J13 -> TRUE
F14: 2032 | G14: 1323 | I14: 2032 | J14: 1323 | L14: =F14=I14 -> TRUE | M14: =G14=J14 -> TRUE
F15: 2033 | G15: 2918 | I15: 2033 | J15: 2918 | L15: =F15=I15 -> TRUE | M15: =G15=J15 -> TRUE
F16: 2034 | G16: 1168 | I16: 2034 | J16: 1168 | L16: =F16=I16 -> TRUE | M16: =G16=J16 -> TRUE
F17: 2035 | G17: 600 | I17: 2035 | J17: 600 | L17: =F17=I17 -> TRUE | M17: =G17=J17 -> TRUE
F18: 2049 | G18: 600 | I18: 2049 | J18: 600 | L18: =F18=I18 -> TRUE | M18: =G18=J18 -> TRUE
... F20: 2051 | G20: 1050 | I20: 2051 | J20: 1050 | L20: =F20=I20 -> TRUE | M20: =G20=J20 -> TRUE
F21: Total | G21: =SUM(G7:G20) -> 33415 | I21: Total | J21: =SUM(J7:J20) -> 33415 | L21: =F21=I21 -> TRUE | M21: =G21=J21 -> TRUE
F23: Accuracy | G23: 1
F25: Correct | I25: LLM
A26: 3Q24
F27: Year | G27: Unsecured Debt | I27: Year | J27: Unsecured Debt | L27: =F27=I27 -> TRUE | M27: =G27=J27 -> TRUE
F28: 2025 | G28: 3207 | I28: 2025 | J28: 3207 | L28: =F28=I28 -> TRUE | M28: =G28=J28 -> TRUE
F29: 2026 | G29: 3357 | I29: 2026 | J29: 3357 | L29: =F29=I29 -> TRUE | M29: =G29=J29 -> TRUE
F30: 2027 | G30: 4610 | I30: 2027 | J30: 4610 | L30: =F30=I30 -> TRUE | M30: =G30=J30 -> TRUE
F31: 2028 | G31: 4285 | I31: 2028 | J31: 4285 | L31: =F31=I31 -> TRUE | M31: =G31=J31 -> TRUE
F32: 2029 | G32: 3735 | I32: 2029 | J32: 3735 | L32: =F32=I32 -> TRUE | M32: =G32=J32 -> TRUE
F33: 2030 | G33: 3413 | I33: 2030 | J33: 3413 | L33: =F33=I33 -> TRUE | M33: =G33=J33 -> TRUE
F34: 2031 | G34: 1957 | I34: 2031 | J34: 1957 | L34: =F34=I34 -> TRUE | M34: =G34=J34 -> TRUE
F35: 2032 | G35: 1374 | I35: 2032 | J35: 1374 | L35: =F35=I35 -> TRUE | M35: =G35=J35 -> TRUE
F36: 2033 | G36: 2957 | I36: 2033 | J36: 2957 | L36: =F36=I36 -> TRUE | M36: =G36=J36 -> TRUE
F37: 2034 | G37: 1207 | I37: 2034 | J37: 1207 | L37: =F37=I37 -> TRUE | M37: =G37=J37 -> TRUE
F38: 2049 | G38: 600 | I38: 2049 | J38: 600 | L38: =F38=I38 -> TRUE | M38: =G38=J38 -> TRUE
F39: 2050 | G39: 1050 | I39: 2050 | J39: 1050 | L39: =F39=I39 -> TRUE | M39: =G39=J39 -> TRUE
F40: 2051 | G40: 1050 | I40: 2051 | J40: 1050 | L40: =F40=I40 -> TRUE | M40: =G40=J40 -> TRUE
F41: Total | G41: =SUM(G28:G40) -> 32802 | I41: Total | J41: 32802 | L41: =F41=I41 -> TRUE | M41: =G41=J41 -> TRUE
F43: Accuracy | G43: 1
F45: Correct | I45: LLM
A46: 2Q24
F47: Year | G47: Unsecured Debt | I47: Year | J47: Unsecured Debt | L47: =F47=I47 -> TRUE | M47: =G47=J47 -> TRUE
F48: 2025 | G48: 3186 | I48: 2025 | J48: 3186 | L48: =F48=I48 -> TRUE | M48: =G48=J48 -> TRUE
F49: 2026 | G49: 3336 | I49: 2026 | J49: 3336 | L49: =F49=I49 -> TRUE | M49: =G49=J49 -> TRUE
F50: 2027 | G50: 4532 | I50: 2027 | J50: 4532 | L50: =F50=I50 -> TRUE | M50: =G50=J50 -> TRUE
F51: 2028 | G51: 4254 | I51: 2028 | J51: 4254 | L51: =F51=I51 -> TRUE | M51: =G51=J51 -> TRUE
F52: 2029 | G52: 3704 | I52: 2029 | J52: 3704 | L52: =F52=I52 -> TRUE | M52: =G52=J52 -> TRUE
F53: 2030 | G53: 3371 | I53: 2030 | J53: 3371 | L53: =F53=I53 -> TRUE | M53: =G53=J53 -> TRUE
F54: 2031 | G54: 1936 | I54: 2031 | J54: 1936 | L54: =F54=I54 -> TRUE | M54: =G54=J54 -> TRUE
F55: 2032 | G55: 1346 | I55: 2032 | J55: 1346 | L55: =F55=I55 -> TRUE | M55: =G55=J55 -> TRUE
F56: 2033 | G56: 2936 | I56: 2033 | J56: 2936 | L56: =F56=I56 -> TRUE | M56: =G56=J56 -> TRUE
F57: 2034 | G57: 1186 | I57: 2034 | J57: 1186 | L57: =F57=I57 -> TRUE | M57: =G57=J57 -> TRUE
F58: 2049 | G58: 600 | I58: 2049 | J58: 600 | L58: =F58=I58 -> TRUE | M58: =G58=J58 -> TRUE
F59: 2050 | G59: 1050 | I59: 2050 | J59: 1050 | L59: =F59=I59 -> TRUE | M59: =G59=J59 -> TRUE
F60: 2051 | G60: 1050 | I60: 2051 | J60: 1050 | L60: =F60=I60 -> TRUE | M60: =G60=J60 -> TRUE
F61: Total | G61: =SUM(G48:G60) -> 32487 | I61: Total | J61: =SUM(J48:J60) -> 32487 | L61: =F61=I61 -> TRUE | M61: =G61=J61 -> TRUE
F63: Accuracy | G63: 1
F65: Correct | I65: LLM
A67: 1Q24
F68: Year | G68: Unsecured Debt | I68: Year | J68: Unsecured Debt | L68: =F68=I68 -> TRUE | M68: =G68=J68 -> TRUE
F69: 2024 | G69: 650 | I69: 2024 | J69: 650 | L69: =F69=I69 -> TRUE | M69: =G69=J69 -> TRUE
F70: 2025 | G70: 3189 | I70: 2025 | J70: 3189 | L70: =F70=I70 -> TRUE | M70: =G70=J70 -> TRUE
F71: 2026 | G71: 3339 | I71: 2026 | J71: 3339 | L71: =F71=I71 -> TRUE | M71: =G71=J71 -> TRUE
F72: 2027 | G72: 4546 | I72: 2027 | J72: 4546 | L72: =F72=I72 -> TRUE | M72: =G72=J72 -> TRUE
F73: 2028 | G73: 4259 | I73: 2028 | J73: 4259 | L73: =F73=I73 -> TRUE | M73: =G73=J73 -> TRUE
F74: 2029 | G74: 3709 | I74: 2029 | J74: 3709 | L74: =F74=I74 -> TRUE | M74: =G74=J74 -> TRUE
F75: 2030 | G75: 2839 | I75: 2030 | J75: 2839 | L75: =F75=I75 -> TRUE | M75: =G75=J75 -> TRUE
F76: 2031 | G76: 1939 | I76: 2031 | J76: 1939 | L76: =F76=I76 -> TRUE | M76: =G76=J76 -> TRUE
F77: 2032 | G77: 1351 | I77: 2032 | J77: 1351 | L77: =F77=I77 -> TRUE | M77: =G77=J77 -> TRUE
F78: 2033 | G78: 2939 | I78: 2033 | J78: 2939 | L78: =F78=I78 -> TRUE | M78: =G78=J78 -> TRUE
F79: 2034 | G79: 650 | I79: 2034 | J79: 650 | L79: =F79=I79 -> TRUE | M79: =G79=J79 -> TRUE
F80: 2049 | G80: 600 | I80: 2049 | J80: 600 | L80: =F80=I80 -> TRUE | M80: =G80=J80 -> TRUE
... F82: 2051 | G82: 1050 | I82: 2051 | J82: 1050 | L82: =F82=I82 -> TRUE | M82: =G82=J82 -> TRUE
F83: Total | G83: =SUM(G69:G82) -> 32110 | I83: Total | J83: 31110 | L83: =F83=I83 -> TRUE | M83: =G83=J83 -> FALSE
F85: Accuracy | G85: =31/32 -> 0.96875

Sheet AMT Script
B2: 4Q24 | S2: Unsecured Debt ($mn) | T2: Date | U2: Year | W2: Year | X2: Unsecured Debt | Y2: Other Debt | Z2: Total Debt
S3: 650 | T3: 45672 | U3: =YEAR(T3) -> 2025 | W3: 2025 | X3: =SUMIF($U$3:$U$50,$W3,$S$3:$S$50) -> 3165.7 | Y3: 997.9 | Z3: =Y6+X17 -> 34174.9
S4: 749.7 | T4: 45731 | U4: =YEAR(T4) -> 2025 | W4: 2026 | X4: =SUMIF($U$3:$U$50,$W4,$S$3:$S$50) -> 3308.2
S5: 517.3 | T5: 45751 | U5: =YEAR(T5) -> 2025 | W5: 2027 | X5: =SUMIF($U$3:$U$50,$W5,$S$3:$S$50) -> 4449.2
S6: 749.4 | T6: 45809 | U6: =YEAR(T6) -> 2025 | W6: 2028 | X6: =SUMIF($U$3:$U$50,$W6,$S$3:$S$50) -> 4202.2 | Y6: =SUM(Y3:Y5) -> 997.9
S7: 499.3 | T7: 45915 | U7: =YEAR(T7) -> 2025 | W7: 2029 | X7: =SUMIF($U$3:$U$50,$W7,$S$3:$S$50) -> 3652
S8: 499.3 | T8: 46068 | U8: =YEAR(T8) -> 2026 | W8: 2030 | X8: =SUMIF($U$3:$U$50,$W8,$S$3:$S$50) -> 3902.2
S9: 698.5 | T9: 46127 | U9: =YEAR(T9) -> 2026 | W9: 2031 | X9: =SUMIF($U$3:$U$50,$W9,$S$3:$S$50) -> 1900.9
S10: 516.4 | T10: 46164 | U10: =YEAR(T10) -> 2026 | W10: 2032 | X10: =SUMIF($U$3:$U$50,$W10,$S$3:$S$50) -> 1311.3
S11: 597.4 | T11: 46280 | U11: =YEAR(T11) -> 2026 | W11: 2033 | X11: =SUMIF($U$3:$U$50,$W11,$S$3:$S$50) -> 2887.1
S12: 996.6 | T12: 46310 | U12: =YEAR(T12) -> 2026 | W12: 2034 | X12: =SUMIF($U$3:$U$50,$W12,$S$3:$S$50) -> 1151.1
S13: 399.3 | T13: 46402 | U13: =YEAR(T13) -> 2027 | W13: 2035 | X13: =SUMIF($U$3:$U$50,$W13,$S$3:$S$50) -> 591.9
S14: 748 | T14: 46402 | U14: =YEAR(T14) -> 2027 | W14: 2049 | X14: =SUMIF($U$3:$U$50,$W14,$S$3:$S$50) -> 592.6
S15: 774.1 | T15: 46402 | U15: =YEAR(T15) -> 2027 | W15: 2050 | X15: =SUMIF($U$3:$U$50,$W15,$S$3:$S$50) -> 1038.8
S16: 515 | T16: 46433 | U16: =YEAR(T16) -> 2027 | W16: 2051 | X16: =SUMIF($U$3:$U$50,$W16,$S$3:$S$50) -> 1023.8
S17: 646.4 | T17: 46461 | U17: =YEAR(T17) -> 2027 | W17: Total | X17: =SUM(X3:X16) -> 33177
S18: 618.5 | T18: 46523 | U18: =YEAR(T18) -> 2027
S19: 747.9 | T19: 46583 | U19: =YEAR(T19) -> 2027 | W19: Delta to presentation number may be due to exchange
S20: 697 | T20: 46767 | U20: =YEAR(T20) -> 2028 | W20: rate impact on EUR denominated senior unsecured debt
S21: 772.6 | T21: 46767 | U21: =YEAR(T21) -> 2028
S22: 647.8 | T22: 46783 | U22: =YEAR(T22) -> 2028
S23: 695 | T23: 46827 | U23: =YEAR(T23) -> 2028
S24: 645.2 | T24: 46949 | U24: =YEAR(T24) -> 2028
S25: 744.6 | T25: 47072 | U25: =YEAR(T25) -> 2028
S26: 643.7 | T26: 47164 | U26: =YEAR(T26) -> 2029
S27: 594.8 | T27: 47192 | U27: =YEAR(T27) -> 2029
S28: 773 | T28: 47259 | U28: =YEAR(T28) -> 2029
B29: Ticker | C29: Quarter | D29: Unsecured Debt | E29: Amount | F29: Unit | G29: Currency | H29: Category | S29: 1640.5 | T29: 47345 | U29: =YEAR(T29) -> 2029
B30: AMT | C30: 4Q24 | D30: Near-term | E30: =SUM(X3:X7) -> 18777.3 | F30: mn | G30: USD | H30: Unsecured Debt | S30: 745.1 | T30: 47498 | U30: =YEAR(T30) -> 2030
B31: AMT | C31: 4Q24 | D31: Medium-Term | E31: =SUM(X8:X11) -> 10001.5 | F31: mn | G31: USD | H31: Unsecured Debt | S31: 593.2 | T31: 47514 | U31: =YEAR(T31) -> 2030
B32: AMT | C32: 4Q24 | D32: Long-term | E32: =SUM(X12:X16) -> 4398.2 | F32: mn | G32: USD | H32: Unsecured Debt | S32: 512.9 | T32: 47619 | U32: =YEAR(T32) -> 2030
B33: AMT | C33: 4Q24 | D33: Total Unsecured | E33: =SUM(E30:E32) -> 33177 | F33: mn | G33: USD | H33: Unsecured Debt | S33: 744.1 | T33: 47649 | U33: =YEAR(T33) -> 2030
S34: 512.6 | T34: 47761 | U34: =YEAR(T34) -> 2030
S35: 794.3 | T35: 47771 | U35: =YEAR(T35) -> 2030
S36: 695.6 | T36: 47953 | U36: =YEAR(T36) -> 2031
S37: 511.7 | T37: 47984 | U37: =YEAR(T37) -> 2031
S38: 693.6 | T38: 48106 | U38: =YEAR(T38) -> 2031
S39: 667.6 | T39: 48228 | U39: =YEAR(T39) -> 2032
S40: 643.7 | T40: 48288 | U40: =YEAR(T40) -> 2032
S41: 791.4 | T41: 48653 | U41: =YEAR(T41) -> 2033
S42: 512.1 | T42: 48720 | U42: =YEAR(T42) -> 2033
S43: 841.4 | T43: 48775 | U43: =YEAR(T43) -> 2033
S44: 742.2 | T44: 48898 | U44: =YEAR(T44) -> 2033
S45: 640.6 | T45: 48990 | U45: =YEAR(T45) -> 2034
... S50: 1023.8 | T50: 55168 | U50: =YEAR(T50) -> 2051
S51: =SUM(S3:S50) -> 33177
B54: 3Q24
S55: Unsecured Debt ($mn) | T55: Date | U55: Year | W55: Year | X55: Unsecured Debt | Y55: Other Debt | Z55: Total Debt
S56: 649.6 | T56: 45672 | U56: =YEAR(T56) -> 2025 | W56: 2025 | X56: =SUMIF($U$56:$U$101,W56,$S$56:$S$101) -> 3203.1 | Y56: 140 | Z56: =Y59+X69 -> 34772.1
S57: 749.4 | T57: 45731 | U57: =YEAR(T57) -> 2025 | W57: 2026 | X57: =SUMIF($U$56:$U$101,W57,$S$56:$S$101) -> 3345.6 | Y57: 997.7
S58: 556 | T58: 45751 | U58: =YEAR(T58) -> 2025 | W58: 2027 | X58: =SUMIF($U$56:$U$101,W58,$S$56:$S$101) -> 4592 | Y58: 1068
S59: 749.1 | T59: 45809 | U59: =YEAR(T59) -> 2025 | W59: 2028 | X59: =SUMIF($U$56:$U$101,W59,$S$56:$S$101) -> 4259 | Y59: =SUM(Y56:Y58) -> 2205.7
S60: 499 | T60: 45915 | U60: =YEAR(T60) -> 2025 | W60: 2029 | X60: =SUMIF($U$56:$U$101,W60,$S$56:$S$101) -> 3709.3
S61: 499.2 | T61: 46068 | U61: =YEAR(T61) -> 2026 | W61: 2030 | X61: =SUMIF($U$56:$U$101,W61,$S$56:$S$101) -> 3385.9
S62: 698.2 | T62: 46127 | U62: =YEAR(T62) -> 2026 | W62: 2031 | X62: =SUMIF($U$56:$U$101,W62,$S$56:$S$101) -> 1939.5
S63: 555.1 | T63: 46164 | U63: =YEAR(T63) -> 2026 | W63: 2032 | X63: =SUMIF($U$56:$U$101,W63,$S$56:$S$101) -> 1361.7
S64: 597 | T64: 46280 | U64: =YEAR(T64) -> 2026 | W64: 2033 | X64: =SUMIF($U$56:$U$101,W64,$S$56:$S$101) -> 2925.4
S65: 996.1 | T65: 46310 | U65: =YEAR(T65) -> 2026 | W65: 2034 | X65: =SUMIF($U$56:$U$101,W65,$S$56:$S$101) -> 1189.9
S66: 399.2 | T66: 46402 | U66: =YEAR(T66) -> 2027 | W66: 2049 | X66: =SUMIF($U$56:$U$101,W66,$S$56:$S$101) -> 592.6
S67: 747.7 | T67: 46402 | U67: =YEAR(T67) -> 2027 | W67: 2050 | X67: =SUMIF($U$56:$U$101,W67,$S$56:$S$101) -> 1038.8
S68: 832.4 | T68: 46402 | U68: =YEAR(T68) -> 2027 | W68: 2051 | X68: =SUMIF($U$56:$U$101,W68,$S$56:$S$101) -> 1023.6
S69: 553.9 | T69: 46433 | U69: =YEAR(T69) -> 2027 | W69: Total | X69: =SUM(X56:X68) -> 32566.4
S70: 646 | T70: 46461 | U70: =YEAR(T70) -> 2027
S71: 665.1 | T71: 46523 | U71: =YEAR(T71) -> 2027 | W71: Delta to presentation number may be due to exchange
S72: 747.7 | T72: 46583 | U72: =YEAR(T72) -> 2027 | W72: rate impact on EUR denominated senior unsecured debt
S73: 696.7 | T73: 46767 | U73: =YEAR(T73) -> 2028
S74: 830.9 | T74: 46767 | U74: =YEAR(T74) -> 2028
S75: 647.6 | T75: 46783 | U75: =YEAR(T75) -> 2028
S76: 694.7 | T76: 46827 | U76: =YEAR(T76) -> 2028
S77: 644.8 | T77: 46949 | U77: =YEAR(T77) -> 2028
S78: 744.3 | T78: 47072 | U78: =YEAR(T78) -> 2028
S79: 643.4 | T79: 47164 | U79: =YEAR(T79) -> 2029
S80: 594.5 | T80: 47192 | U80: =YEAR(T80) -> 2029
B81: Ticker | C81: Quarter | D81: Unsecured Debt | E81: Amount | F81: Unit | G81: Currency | H81: Category | S81: 831.4 | T81: 47259 | U81: =YEAR(T81) -> 2029
B82: AMT | C82: 3Q24 | D82: Near-term | E82: =SUM(X56:X60) -> 19109 | F82: mn | G82: USD | H82: Unsecured Debt | S82: 1640 | T82: 47345 | U82: =YEAR(T82) -> 2029
B83: AMT | C83: 3Q24 | D83: Medium-Term | E83: =SUM(X61:X64) -> 9612.5 | F83: mn | G83: USD | H83: Unsecured Debt | S83: 744.9 | T83: 47498 | U83: =YEAR(T83) -> 2030
B84: AMT | C84: 3Q24 | D84: Long-term | E84: =SUM(X65:X68) -> 3844.9 | F84: mn | G84: USD | H84: Unsecured Debt | S84: 551.7 | T84: 47619 | U84: =YEAR(T84) -> 2030
B85: AMT | C85: 3Q24 | D85: Total Unsecured | E85: =SUM(E82:E84) -> 32566.4 | F85: mn | G85: USD | H85: Unsecured Debt | S85: 743.9 | T85: 47649 | U85: =YEAR(T85) -> 2030
S86: 551.4 | T86: 47761 | U86: =YEAR(T86) -> 2030
S87: 794 | T87: 47771 | U87: =YEAR(T87) -> 2030
S88: 695.5 | T88: 47953 | U88: =YEAR(T88) -> 2031
S89: 550.6 | T89: 47984 | U89: =YEAR(T89) -> 2031
S90: 693.4 | T90: 48106 | U90: =YEAR(T90) -> 2031
S91: 718.2 | T91: 48228 | U91: =YEAR(T91) -> 2032
S92: 643.5 | T92: 48288 | U92: =YEAR(T92) -> 2032
S93: 791.2 | T93: 48653 | U93: =YEAR(T93) -> 2033
S94: 551 | T94: 48720 | U94: =YEAR(T94) -> 2033
S95: 841.2 | T95: 48775 | U95: =YEAR(T95) -> 2033
S96: 742 | T96: 48898 | U96: =YEAR(T96) -> 2033
S97: 640.4 | T97: 48990 | U97: =YEAR(T97) -> 2034
... S101: 1023.6 | T101: 55168 | U101: =YEAR(T101) -> 2051
S102: =SUM(S56:S101) -> 32566.4
S107: Unsecured Debt ($mn) | T107: Date | U107: Year | W107: Year | X107: Unsecured Debt | Y107: Other Debt | Z107: Total Debt
B108: 2Q24 | S108: 649.1 | T108: 45672 | U108: =YEAR(T108) -> 2025 | W108: 2025 | X108: =SUMIF($U$108:$U$153,$W108,$S$108:$S$153) -> 3180.3 | Y108: 1170 | Z108: =Y111+X121 -> 36520.2
S109: 749.1 | T109: 45731 | U109: =YEAR(T109) -> 2025 | W109: 2026 | X109: =SUMIF($U$108:$U$153,$W109,$S$108:$S$153) -> 3323.1 | Y109: 997.4
S110: 534.6 | T110: 45751 | U110: =YEAR(T110) -> 2025 | W110: 2027 | X110: =SUMIF($U$108:$U$153,$W110,$S$108:$S$153) -> 4512.4 | Y110: 2113.4
S111: 748.7 | T111: 45809 | U111: =YEAR(T111) -> 2025 | W111: 2028 | X111: =SUMIF($U$108:$U$153,$W111,$S$108:$S$153) -> 4225.8 | Y111: =SUM(Y108:Y110) -> 4280.8
S112: 498.8 | T112: 45915 | U112: =YEAR(T112) -> 2025 | W112: 2029 | X112: =SUMIF($U$108:$U$153,$W112,$S$108:$S$153) -> 3676.4
S113: 499 | T113: 46068 | U113: =YEAR(T113) -> 2026 | W113: 2030 | X113: =SUMIF($U$108:$U$153,$W113,$S$108:$S$153) -> 3342.9
S114: 698 | T114: 46127 | U114: =YEAR(T114) -> 2026 | W114: 2031 | X114: =SUMIF($U$108:$U$153,$W114,$S$108:$S$153) -> 1917.7
...

Sheet EBITDA Check
A2: EDGAR API | B2: Standardized EBITDA
A4: AVB | B4: Quarter | C4: Line Item | D4: Net Income | E4: Interest Expense | F4: Tax Expense | G4: D&A Expense | H4: EBITDA | I4: Units | K4: Check | L4: EBITDA
A5: 10K Check | B5: 2024 | C5: EBITDA | D5: 1082.175 | E5: 226.589 | F5: 0.445 | G5: 846.853 | H5: =SUM(D5:G5) -> 2156.062 | I5: mn | K5: FY24 | L5: =H5 -> 2156.062
A6: 10Q Check | B6: 3Q24 | C6: EBITDA | D6: 372.519 | E6: 55.769 | F6: 0.782 | G6: 212.122 | H6: =SUM(D6:G6) -> 641.192 | I6: mn | K6: 4Q24 | L6: =L5-SUM(L7:L9) -> 556.354
A7: 10Q Check | B7: 2Q24 | C7: EBITDA | D7: 254.007 | E7: 57.078 | F7: -0.062 | G7: 206.923 | H7: =SUM(D7:G7) -> 517.946 | I7: mn | K7: 3Q24 | L7: =H6 -> 641.192
A8: 10Q Check | B8: 1Q24 | C8: EBITDA | D8: 173.557 | E8: 54.766 | F8: -0.022 | G8: 212.269 | H8: =SUM(D8:G8) -> 440.57 | I8: mn | K8: 2Q24 | L8: =H7 -> 517.946
K9: 1Q24 | L9: =H8 -> 440.57
A22: CCI | B22: Quarter / FY | C22: Line Item | D22: Net Income | E22: Interest Expense | F22: Tax Expense | G22: D&A Expense | H22: EBITDA | I22: Units | K22: Check | L22: EBITDA
A23: 10K Check | B23: 2024 | C23: EBITDA | D23: =-3903 -> -3903 | E23: 932 | F23: 24 | G23: 1738 | H23: =SUM(D23:G23) -> -1209 | I23: mn | K23: FY24 | L23: =H23 -> -1209
A24: 10Q Check | B24: 3Q24 | C24: EBITDA | D24: 303 | E24: 236 | F24: 5 | G24: 432 | H24: =SUM(D24:G24) -> 976 | I24: mn | K24: 4Q24 | L24: =L23-SUM(L25:L27) -> -4086
A25: 10Q Check | B25: 2Q24 | C25: EBITDA | D25: 251 | E25: 230 | F25: 7 | G25: 430 | H25: =SUM(D25:G25) -> 918 | I25: mn | K25: 3Q24 | L25: =H24 -> 976
A26: 10Q Check | B26: 1Q24 | C26: EBITDA | D26: 311 | E26: 226 | F26: 7 | G26: 439 | H26: =SUM(D26:G26) -> 983 | I26: mn | K26: 2Q24 | L26: =H25 -> 918
K27: 1Q24 | L27: =H26 -> 983
A41: AMT | B41: Quarter / FY | C41: Line Item | D41: Net Income | E41: Interest Expense | F41: Tax Expense | G41: D&A Expense | H41: EBITDA | I41: Units | K41: Check | L41: EBITDA
A42: 10K Check | B42: 2024 | C42: EBITDA | D42: 2280.2 | E42: 1404.5 | F42: 366.3 | G42: 2028.8 | H42: =SUM(D42:G42) -> 6079.8 | I42: mn | K42: FY24 | L42: =H42 -> 6079.8
A43: 10Q Check | B43: 3Q24 | C43: EBITDA | D43: -780.4 | E43: 356.8 | F43: 122.4 | G43: 498.5 | H43: =SUM(D43:G43) -> 197.3 | I43: mn | K43: 4Q24 | L43: =L42-SUM(L44:L46) -> 1980.6
A44: 10Q Check | B44: 2Q24 | C44: EBITDA | D44: 908.4 | E44: 365.4 | F44: 120 | G44: 561.7 | H44: =SUM(D44:G44) -> 1955.5 | I44: mn | K44: 3Q24 | L44: =H43 -> 197.3
A45: 10Q Check | B45: 1Q24 | C45: EBITDA | D45: 921 | E45: 367 | F45: 109 | G45: 549.4 | H45: =SUM(D45:G45) -> 1946.4 | I45: mn | K45: 2Q24 | L45: =H44 -> 1955.5
K46: 1Q24 | L46: =H45 -> 1946.4
A60: PLD | B60: Quarter / FY | C60: Line Item | D60: Net Income | E60: Interest Expense | F60: Tax Expense | G60: D&A Expense | H60: EBITDA | I60: Units | K60: Check | L60: EBITDA
A61: 10K Check | B61: 2024 | C61: EBITDA | D61: 3947.935 | E61: 863.932 | F61: 166.943 | G61: 2580.519 | H61: =SUM(D61:G61) -> 7559.329 | I61: mn | K61: FY24 | L61: =H61 -> 7559.329
A62: 10Q Check | B62: 3Q24 | C62: EBITDA | D62: 1063.415 | E62: 230.113 | F62: 4.214 | G62: 649.265 | H62: =SUM(D62:G62) -> 1947.007 | I62: mn | K62: 4Q24 | L62: =L61-SUM(L63:L65) -> 2317.758
A63: 10Q Check | B63: 2Q24 | C63: EBITDA | D63: 911.501 | E63: 208.267 | F63: 43.059 | G63: 637.305 | H63: =SUM(D63:G63) -> 1800.132 | I63: mn | K63: 3Q24 | L63: =H62 -> 1947.007
A64: 10Q Check | B64: 1Q24 | C64: EBITDA | D64: 630.807 | E64: 193.32 | F64: 32.8 | G64: 637.505 | H64: =SUM(D64:G64) -> 1494.432 | I64: mn | K64: 2Q24 | L64: =H63 -> 1800.132
K65: 1Q24 | L65: =H64 -> 1494.432
A78: WELL | B78: Quarter / FY | C78: Line Item | D78: Net Income | E78: Interest Expense | F78: Tax Expense | G78: D&A Expense | H78: EBITDA | I78: Units | K78: Check | L78: EBITDA
A79: 10K Check | B79: 2024 | C79: EBITDA | D79: 972.857 | E79: 574.261 | F79: 2.7 | G79: 1632.093 | H79: =SUM(D79:G79) -> 3181.911 | I79: mn | K79: FY24 | L79: =H79 -> 3181.911
A80: 10Q Check | B80: 3Q24 | C80: EBITDA | D80: 456.8 | E80: 139.05 | F80: -4.706 | G80: 403.779 | H80: =SUM(D80:G80) -> 994.923 | I80: mn | K80: 4Q24 | L80: =L79-SUM(L81:L83) -> 758.742
A81: 10Q Check | B81: 2Q24 | C81: EBITDA | D81: 260.67 | E81: 133.424 | F81: 1.101 | G81: 382.045 | H81: =SUM(D81:G81) -> 777.24 | I81: mn | K81: 3Q24 | L81: =H80 -> 994.923
A82: 10Q Check | B82: 1Q24 | C82: EBITDA | D82: 131.634 | E82: 147.318 | F82: 6.191 | G82: 365.863 | H82: =SUM(D82:G82) -> 651.006 | I82: mn | K82: 2Q24 | L82: =H81 -> 777.24
K83: 1Q24 | L83: =H82 -> 651.006
